Workbook

Sheet Form responses 1
A1: Timestamp | B1: Date | C1: Time | D1: Type Of Meeting | E1: Name of Restaurant ? | F1: Seating Capacity | G1: AOV | H1: POS | I1: Daily Revenue? | J1: Kind of Restaurant | K1: Restaurant Live on | L1: Claimed Margins (Competition) | M1: Expected Margins (Caps) | N1: No.of Branches? | O1: Type of Ownership | P1: GST | Q1: FSSAI | R1: Labour License | S1: Google Map Business link | T1: Restaurant ID | U1: Name (POC-1) | V1: Contact Number (POC-1) | W1: Email- ID (POC-1) | X1: Name (POC-2) | Y1: Contact Number (POC-2) | Z1: Email- ID (POC-2) | AA1: Do you want to Submit Documents | AB1: FSSAI Number | AC1: FSSAI 2 | AD1: GST Number | AE1: GST 2 | AF1: PAN Number | AG1: PAN Card | AH1: Labour License Number | AI1: Labour License 2 | AJ1: Menu (Image) | AK1: Bank Account Proof | AL1: Account Number | AM1: IFSC | AN1: Name on Bank Account | AO1: Owner Name | AP1: Owner Contact Number | AQ1: Owner Email address | AR1: Legal Entity Name | AS1: Onboarding Done | AT1: Remarks(Comments) | AU1: Follow Up Meeting Required? | AV1: Meeting agenda for follow up | AW1: Points to be prepared | AX1: Meeting Date | AY1: Meeting Time | AZ1: Email address | BA1: Cold Walk/ Scheduled | BB1: POC Available | BC1: Manager Name | BD1: Manager Contact Details | BE1: Manager Email ID | BF1: Manager Contact Number | BG1: Manager Email ID 2 | BH1: Caps Magin % | BI1: Additional 2% Distance Margin | BJ1: Restaurant Open Time | BK1: Restaurant Close Time | BL1: Daily Online Orders | BM1: Restaurant Address | BN1: Cluster | BO1: Name of Restaurant Walk | BP1: Name of Restaurant | BQ1: Name of Ra | BR1: Restaurant Name Concat
A4: 46056.702 | B4: 44577 | C4: 0.42430556 | D4: Growth Meeting | T4: 5823694 | U4: sandeep | V4: 916679555 | W4: parul986@gmail | X4: amit | Y4: 7896541232 | Z4: parul@gmail | AA4: Yes | AB4: 3589795 | AC4: https://drive.google.com/open?id=1K2GAYdf9j8OoeRQJN7a2rrWNqrJv-Yr8 | AD4: 6954865895 | AE4: https://drive.google.com/open?id=1Xrc3uPOk64pgUM1gMvRHq-hhYc6pYKJT | AF4: 685654hgu | AG4: https://drive.google.com/open?id=1P8o5u-wkGayDLIcyTArlaMzpPcBL8IP1 | AH4: 5484581245 | AI4: https://drive.google.com/open?id=1zOmxq565qkkMqqCAFCaCRWzjb7i60OTF | AJ4: https://drive.google.com/open?id=1qsXvdJuct7_aToPR8ThIMJcmid9TRtyr | AL4: 54946489461649 | AM4: 949464bguhb | AN4: icici | AO4: jihughyfu | AP4: 64946165597 | AQ4: jhgyfyf2@GMAIL,COM | AR4: HVTFUGYFYGJH | AS4: Yes | AU4: Yes | AV4: Document Collection | AW4: KBUHIH | AX4: 35098 | AY4: 0.42430556 | AZ4: TEST | BR4: =Concatenate(BQ4,BP4,BO4,E4,T4) -> 5823694
A5: 46056.798 | B5: 46056 | C5: 0.66666667 | D5: Intro Meeting | E5: Bhuvan’s Kitchen | F5: 85 | G5: 250 | H5: OrderMatic | I5: 50000 | J5: Tier-2 (AOV <400) | K5: None | L5: 28 | M5: 20 | N5: 1 | O5: Prop | P5: Yes | Q5: Active | R5: Not Applied | S5: https://maps.app.goo.gl/QukQHejyepep1eaLA?g_st=ic | U5: Rama Rao | V5: 9030611616 | W5: Bhuvan’skitchen25@gmail.com | AA5: Yes | AB5: 20251226108111377 | AC5: https://drive.google.com/open?id=1zQ8cp3_66Bhden1m6eXDLNsshBt8JXb3 | AL5: 50200102000231 | AM5: HDFC0010090 | AN5: HDFC Bank | AO5: Rama Rao | AP5: 9030611616 | AQ5: bhuvanskitchen25@gmail.com | AR5: Bhuvan’s Kitchen | AS5: Yes | AT5: Res has been onboarded | AU5: No | AZ5: manasa.chigurupati@capsdelivery.com | BR5: =Concatenate(BQ5,BP5,BO5,E5,T5) -> Bhuvan’s Kitchen
A6: 46056.803 | B6: 46056 | C6: 0.64583333 | D6: Follow up | T6: 12345578 | U6: Mohammed Amir | V6: 9949814600 | W6: na | AA6: No | AU6: Yes | AV6: Contract Signing | AX6: 46057 | AY6: 0.45833333 | AZ6: sumadhur.mummadi@capsdelivery.com | BR6: =Concatenate(BQ6,BP6,BO6,E6,T6) -> 12345578
A7: 46057.379 | B7: 46056 | C7: 0.75 | D7: Intro Meeting | E7: Bhojanams & Birynis | F7: 30 | G7: 500 | H7: NA | I7: 24 | J7: Tier-2 (AOV <400) | K7: Zomato | N7: 1 | O7: Prop | P7: Yes | Q7: Active | R7: Yes | S7: yes | U7: Shesha sai | V7: 9052592437 | W7: sheshasai@gmail.com | AA7: Yes | AB7: 13619013001993 | AC7: https://drive.google.com/open?id=1jDd9udZkiYFM95E6qDnBXxB9dZAPA3Q6 | AD7: 36AAHFi2620K1ZF | AE7: https://drive.google.com/open?id=1wmAzfgRO6AUexNEcncft5vbltGIV8av4 | AK7: https://drive.google.com/open?id=13qbsLsi98K74BchvdcD_7-swJp4EtkeO | AL7: 10192341683 | AM7: IDFB00B0231 | AN7: IDFC | AO7: SHESHA SAI | AP7: 9052592437 | AR7: INVENCES FOODS | AS7: Yes | AT7: PARTNER ON BOARDED | AU7: No | AV7: Document Collection | AX7: 46056 | AY7: 0.84722222 | AZ7: chanakya.inugala@capsdelivery.com | BR7: =Concatenate(BQ7,BP7,BO7,E7,T7) -> Bhojanams & Birynis
A8: 46057.397 | B8: 46055 | C8: 0.23958333 | D8: Intro Meeting | E8: Sunrise Business Hotel | F8: 100 | G8: 300 | H8: Own | I8: 50000 | J8: Tier-2 (AOV <400) | K8: Swiggy, Zomato | N8: 1 | O8: Partnership | P8: Yes | Q8: Active | R8: Yes | S8: https://maps.app.goo.gl/U96V4tJ8v4oih7cF9 | U8: Venkat Lingam | V8: 8989873636 | W8: bowlrise.srnagar@gmail.com | AA8: Yes | AB8: 23625030001500 | AC8: https://drive.google.com/open?id=1p7jWoaNGA48ZsmXz8piawFvDD6h8MZPo | AD8: 36ACHFA3021A1Z7 | AE8: https://drive.google.com/open?id=1hZ4_XJa0ar_5viyQyWSwjO63ut7o3QIh | AF8: AWNPV9668G | AG8: https://drive.google.com/open?id=11LbxcMTLS62PuKE6EHwzu8WdUemKU5ba | AK8: https://drive.google.com/open?id=1LV1wXeDgKShlIJHBUn--Sn9J2gR1xgxD | AL8: 803705000004 | AM8: ICIC0008037 | AN8: ICICI BANK | AO8: VENKAT LINGAM | AP8: 8989873636 | AQ8: BOWLRISE.SRNAGAR@GMAIL.COM | AR8: AARAV SUNRISE HOSPITALITES | AS8: Yes | AT8: They got impress with our application take away point | AU8: No | AV8: Document Collection | AX8: 46056 | AY8: 0.23958333 | AZ8: parthive.maganti@capsdelivery.com | BR8: =Concatenate(BQ8,BP8,BO8,E8,T8) -> Sunrise Business Hotel
A9: 46057.408 | B9: 46056 | C9: 0.75 | D9: Intro Meeting | E9: ZYROS BIRYANI HOUSE | F9: 8 | G9: 300 | H9: YES | I9: 60000 | J9: Tier-2 (AOV <400) | K9: Swiggy, Zomato | L9: 22 | M9: 18 | N9: 1 | O9: Prop | P9: Yes | Q9: Active | R9: Not Applied | S9: https://www.google.com/maps/place/17%C2%B027'04.3%22N+78%C2%B023'30.1%22E/@17.4512028,78.389128,17z/data=!3m1!4b1!4m4!3m3!8m2!3d17.4512028!4d78.3917029?hl=en&entry=ttu&g_ep=EgoyMDI2MDIwMS4wIKXMDSoKLDEwMDc5MjA2OUgBUAM%3D | U9: NATVA SANTOSH KUMAR | V9: 6302181276 | W9: nsantosh086@gmail.com | X9: NA | AA9: Yes | AB9: 13625010001295 | AC9: https://drive.google.com/open?id=19PGovlvYadreb67eUHeNKzrktgJO-8bX | AD9: 36BQBPK2933A1ZD | AE9: https://drive.google.com/open?id=1xkvSfuIbWsf_ar7Z_3_MFx49cCnJTGSd | AJ9: https://drive.google.com/open?id=1zs5LVtkzfw6Ig4tlx1lPWSn0Lm-7bwoP | AK9: https://drive.google.com/open?id=12sEwp13vy0B0IOgjOaR48di8G3M0dgC6 | AL9: 6450935473 | AM9: KKBK0000561 | AO9: NATVA SANTOSH KUMAR | AP9: 6302181276 | AQ9: nsantosh086@gmail.com | AR9: NATVA SANTOSH KUMAR | AS9: Yes | AT9: ONBOARDED | AU9: No | AZ9: moin.khan@capsdelivery.com | BR9: =Concatenate(BQ9,BP9,BO9,E9,T9) -> ZYROS BIRYANI HOUSE
A10: 46057.417 | B10: 46055 | C10: 0.125 | D10: Intro Meeting | E10: Slice of Spice | F10: 150 | G10: 5000 | H10: own software | I10: 120000 | J10: Tier-1(AOV>400) | K10: None | N10: 15 | O10: Partnership | P10: Yes | Q10: Active | R10: Yes | S10: 2-52/1/3, Hitech City Rd, Phase 2, Kavuri Hills, Madhapur, Hyderabad, Telangana 500081 | U10: Venkat Lingam | V10: 888655996 | W10: bowlrise.srnagar@gmail.com | AA10: Yes | AB10: 23625032003555 | AC10: https://drive.google.com/open?id=1O-A-ESorVgS21JbM9bD4LsPgYXHMCp0d | AD10: 36AAKFE8997J1ZI | AE10: https://drive.google.com/open?id=15R5f8q3so1Ik7UrWJk_3rCjAQY8sBEFO | AF10: AAKFE8997J | AG10: https://drive.google.com/open?id=1r4LwvkbszhmmgLl56dsxPyTtENCSry3W | AJ10: https://drive.google.com/open?id=1kddVXBDtmyxBYZuEGyQzheu06kPD2YCr | AK10: https://drive.google.com/open?id=1HMbFf9NKxwpNmJpRUAoeT4JSbWFH_gsM | AL10: 112005003328 | AM10: ICIC0001120 | AN10: EASTIN HOTELS AND RESORTS | AO10: VAMSI | AP10: 9014707850 | AQ10: info@eastinhotel.com | AS10: Yes | AT10: Onboarded | AU10: No | AZ10: nitya.akshara@capsdelivery.com | BR10: =Concatenate(BQ10,BP10,BO10,E10,T10) -> Slice of Spice
A11: 46057.975 | B11: 46057 | C11: 0.91111111 | D11: Intro Meeting | E11: ROLO BAKERS | F11: 20 | G11: 250 | H11: PET POOJA | I11: 25000 | J11: Tier-2 (AOV <400) | K11: Swiggy, Zomato | L11: 15 | M11: 18 | N11: 1 | O11: Partnership | P11: Yes | Q11: Active | R11: No | S11: google.com/maps?q=17.440473,78.3934188&z=17&hl=en | U11: GM RAGHAVENDRA | V11: 9963968917 | W11: NA | AA11: Yes | AB11: 23624032003815 | AC11: https://drive.google.com/open?id=16IQXYD4HTTgs7GCdBU6iPTmSXHfWlbQY | AD11: 36ABJFR8448R1Z2 | AE11: https://drive.google.com/open?id=1QyRpGDX2lP1lX3GoLj4kqxGuQ7cNxZ5q | AF11: ABJFR8448R | AG11: https://drive.google.com/open?id=1wLa_Pt-AJbdtSV0NDD93Cgm0a-yocPNO | AO11: GM RAGHAVENDRA | AP11: 9963968917 | AR11: ROLO ONE BAKERS | AS11: Yes | AT11: ONBOARDED | AU11: No | AZ11: moin.khan@capsdelivery.com | BR11: =Concatenate(BQ11,BP11,BO11,E11,T11) -> ROLO BAKERS
A12: 46057.988 | B12: 46057 | C12: 0.93333333 | D12: Intro Meeting | E12: rayalseema spice restaurant | F12: 40 | G12: 300 | H12: PET POOJA | I12: 21000 | J12: Tier-2 (AOV <400) | K12: Swiggy, Zomato | L12: 20 | M12: 18 | N12: 1 | O12: Prop | P12: Yes | Q12: Active | R12: No | S12: https://www.google.com/maps/place/Rayalaseema+Spice+Restaurant/@17.4463018,78.3898889,17z/data=!3m1!4b1!4m6!3m5!1s0x3bcb91140c324827:0xb8961b47ea2ebc6a!8m2!3d17.4463018!4d78.3924638!16s%2Fg%2F11ks1mwcz0?entry=ttu&g_ep=EgoyMDI2MDIwMS4wIKXMDSoKLDEwMDc5MjA2OUgBUAM%3D | U12: narapu reddy | V12: 6301782448 | W12: rayalseemaspice@gmail.com | AA12: Yes | AB12: 13623013001342 | AC12: https://drive.google.com/open?id=12A0pBqsWeMNRgfr4-RewydCYL1MhGFzW | AD12: 36BDMPC6430Q1Z4 | AE12: https://drive.google.com/open?id=1w2-0S2iGSW_hsqhFAKZANxRRUo2t8rGA | AF12: BDMPC6430Q | AG12: https://drive.google.com/open?id=1pP1p8yHifkOvlMj3fFQXJ-_zZU02HhTR | AK12: https://drive.google.com/open?id=1B_C4vy9xoX9tPLwjSW2tR-EM6ekXOlYl | AL12: 20100061259823 | AM12: BDBL0002722 | AN12: BANDHAN BANK | AO12: POKURI PRATHYUSHA | AP12: 6301782448 | AR12: POKURI PRATHYUSHA | AS12: Yes | AT12: ONBOARDED | AU12: No | AZ12: moin.khan@capsdelivery.com | BR12: =Concatenate(BQ12,BP12,BO12,E12,T12) -> rayalseema spice restaurant
A13: 46057.997 | B13: 46057 | C13: 0.94722222 | D13: Intro Meeting | E13: alankrutha multicuisine restaurant | F13: 20 | G13: 300 | H13: PETPOOJA | I13: 24000 | J13: Tier-2 (AOV <400) | K13: Swiggy, Zomato | L13: 20 | M13: 18 | N13: 1 | O13: Prop | P13: No | Q13: Active | R13: No | S13: https://www.google.com/maps/place/Alankrutha+Restaurant/@17.44665,78.3922746,3a,75y,90t/data=!3m8!1e2!3m6!1sAF1QipN-ydSRKlr93jgWDRaakYdE5oV8xhAkUs2hDWna!2e10!3e12!6shttps:%2F%2Flh3.googleusercontent.com%2Fp%2FAF1QipN-ydSRKlr93jgWDRaakYdE5oV8xhAkUs2hDWna%3Dw203-h114-k-no!7i1920!8i1080!4m7!3m6!1s0x3bcb9100076d4f83:0x7e07d0c42ed99066!8m2!3d17.4466622!4d78.3923727!10e5!16s%2Fg%2F11m6k7vc6z?entry=ttu&g_ep=EgoyMDI2MDIwMS4wIKXMDSoKLDEwMDc5MjA2OUgBUAM%3D | U13: AKASH | V13: 8341514984 | W13: cakash121@gmail.com | AA13: Yes | AB13: 23625028001267 | AC13: https://drive.google.com/open?id=1yUrIaR5y55zD2nSA-kJ0RTpJklMZhyOE | AD13: na | AF13: AOXPC9349D | AG13: https://drive.google.com/open?id=1lHnQS6jFD0j-ODzzm6ncc6Fds_MkMTOj | AK13: https://drive.google.com/open?id=1xJurv609CUKpePCGd0rcMOwYy6MJKEto | AL13: 6598200001283 | AM13: BARB0DBMDHP | AN13: BANK OF BARODA | AO13: ALANKRUTHA RESTAURANT | AP13: 8341514984 | AQ13: cakash121@gmail.com | AR13: ALANKRUTHA MULTICUSINE RESTAURANT | AS13: Yes | AT13: ONBOARDED | AU13: No | AZ13: moin.khan@capsdelivery.com | BR13: =Concatenate(BQ13,BP13,BO13,E13,T13) -> alankrutha multicuisine restaurant
A14: 46058.414 | B14: 46057 | C14: 0.625 | D14: Intro Meeting | E14: GUNTUR MESS | F14: 20 | G14: 200 | H14: NA | I14: 10000 | J14: Tier-3 ( AOV<200 ) | K14: Zomato | N14: 1 | O14: Prop | P14: No | Q14: Active | R14: Yes | S14: YES | U14: SHIVA | V14: 9391167117 | W14: shiva@gmail.com | AA14: Yes | AS14: Yes | AT14: on boarded waiting for documents | AU14: No | AV14: Document Collection | AZ14: chanakya.inugala@capsdelivery.com | BR14: =Concatenate(BQ14,BP14,BO14,E14,T14) -> GUNTUR MESS
A15: 46058.833 | B15: 46058 | C15: 0.625 | D15: Intro Meeting | E15: Bihar Dhaba | F15: 30 | G15: 200 | H15: NA | I15: 15000 | J15: Tier-3 ( AOV<200 ) | K15: Swiggy, Zomato | L15: 22 | M15: 22 | N15: 1 | O15: Prop | P15: Yes | Q15: Active | R15: Yes | S15: yes | U15: prajwah kumar | V15: 9441674841 | W15: na | AA15: No | AT15: onboarded waiting for documets | AU15: No | AV15: Document Collection | AX15: 46059 | AY15: 0.625 | AZ15: chanakya.inugala@capsdelivery.com | BR15: =Concatenate(BQ15,BP15,BO15,E15,T15) -> Bihar Dhaba
A16: 46058.837 | B16: 46058 | C16: 0.81180556 | D16: Intro Meeting | E16: hunan chinese cusine | F16: 20 | G16: 200 | H16: NO POS | I16: 12000 | J16: Tier-2 (AOV <400) | K16: Swiggy, Zomato | L16: 18 | M16: 20 | N16: 1 | O16: Prop | P16: No | Q16: Active | R16: No | S16: https://www.google.com/maps/place/Hunan+Chinese+Cuisine/@17.4478451,78.3885023,17z/data=!3m1!4b1!4m6!3m5!1s0x3bcb91b50352f21f:0xee872dfeab40a154!8m2!3d17.4478451!4d78.3885023!16s%2Fg%2F11vxjzpgh9?hl=en&entry=ttu&g_ep=EgoyMDI2MDIwMS4wIKXMDSoKLDEwMDc5MjA2OUgBUAM%3D | U16: RAVI | V16: 7396735758 | W16: thehumanspice@gmail.com | X16: NA | Z16: NA | AA16: Yes | AB16: 23625032004054 | AC16: https://drive.google.com/open?id=1eq2DvTRrEKjx7F39onOqBAWekTlxGmlf | AD16: NA | AK16: https://drive.google.com/open?id=1EM4vsraBCi3CmJzJUZ8gpuR8XRGBOcDh | AL16: 1548257253 | AN16: HUNAN CHINESE CUSINE | AO16: RAVI | AP16: 7396735758 | AQ16: thehumanspice@gmail.com | AR16: Ravi | AS16: Yes | AT16: onboarded | AU16: No | AZ16: moin.khan@capsdelivery.com | BR16: =Concatenate(BQ16,BP16,BO16,E16,T16) -> hunan chinese cusine
A17: 46059.177 | B17: 46058 | C17: 0.73263889 | D17: Growth Meeting | T17: Krishna teeram | U17: Suresh | V17: 9985609966 | W17: krishnateeram2025@gmail.com | AA17: No | AT17: Onboarding done but Adhar and pan details didnt recevied at. | AU17: No | AV17: Need to receive some of the documents | AZ17: greeshma.vanneldas@capsdelivery.com | BR17: =Concatenate(BQ17,BP17,BO17,E17,T17) -> Krishna teeram
A18: 46059.179 | B18: 46058 | C18: 0.625 | D18: Growth Meeting | T18: Ahaladha kitchen | U18: Naveen | V18: 8555086883 | W18: didnt recevied | AA18: No | AT18: Onboarding done | AU18: No | AV18: Onboarding done. | AZ18: greeshma.vanneldas@capsdelivery.com | BR18: =Concatenate(BQ18,BP18,BO18,E18,T18) -> Ahaladha kitchen
A19: 46059.184 | B19: 46058 | C19: 0.79166667 | D19: Intro Meeting | E19: Rameshwaram cafe | F19: 80 | G19: 1 | H19: intro meeting not done | I19: 1 | J19: Tier-2 (AOV <400) | K19: Swiggy, Zomato | N19: 1 | O19: Intro meet not done because owner will be available after 19:00pm | P19: Yes | Q19: Active | R19: Not Applied | S19: 72, Capital Pk Rd, beside Jain Sadguru Capital Park, Cyber Hills Colony, VIP Hills, Silicon Valley, Madhapur, Serilingampalle (M), Hyderabad, Telangana 500081 | U19: no details | V19: no details | W19: no details | AA19: No | AU19: Yes | AV19: Met the front office team, | AZ19: greeshma.vanneldas@capsdelivery.com | BR19: =Concatenate(BQ19,BP19,BO19,E19,T19) -> Rameshwaram cafe
A20: 46059.334 | B20: 46058 | C20: 0.66666667 | D20: Intro Meeting | E20: Hamara Adda | F20: 30 | G20: 1 | H20: 1 | I20: 1 | J20: Tier-1(AOV>400) | K20: Swiggy, Zomato | N20: 1 | O20: Didnt meet the client,got the niumber of the owner | P20: Yes | Q20: Active | R20: Not Applied | S20: G-02, Ground Floor, Silicon Towers, Image Gardens Road, Madhapur, Hyderabad | U20: owner | V20: 8712220229 | W20: didnt received | AA20: No | AU20: Yes | AV20: To explain about our platform | AZ20: greeshma.vanneldas@capsdelivery.com | BR20: =Concatenate(BQ20,BP20,BO20,E20,T20) -> Hamara Adda
A21: 46059.336 | B21: 46058 | C21: 0.54166667 | D21: Follow up | T21: Delicia | U21: Vishwa | V21: 8522886035 | W21: didnt provided | AA21: No | AU21: Yes | AV21: Manager need to discuss with owner and he will get up to us,but I will follow up. | AZ21: greeshma.vanneldas@capsdelivery.com | BR21: =Concatenate(BQ21,BP21,BO21,E21,T21) -> Delicia
A22: 46059.34 | B22: 46058 | C22: 0.5 | D22: Follow up | T22: Palapitta Ruchulu | U22: didnt mention | V22: 7032682089 | W22: didnt got mail | AA22: No | AU22: Yes | AV22: Owner was busy during lunch and he said to follow up on monday | AZ22: greeshma.vanneldas@capsdelivery.com | BR22: =Concatenate(BQ22,BP22,BO22,E22,T22) -> Palapitta Ruchulu
A23: 46059.386 | B23: 46058 | C23: 0.75 | D23: Follow up | T23: lucky restaurant | U23: khasim | V23: 9849108337 | W23: na | AA23: No | AU23: Yes | AV23: Meeting with different POC | AX23: 46059 | AY23: 0.625 | AZ23: moin.khan@capsdelivery.com | BR23: =Concatenate(BQ23,BP23,BO23,E23,T23) -> lucky restaurant
A24: 46059.39 | B24: 46058 | C24: 0.66666667 | D24: Intro Meeting | E24: kiss me mandi | F24: 50 | G24: 300 | H24: na | I24: 15000 | J24: Tier-3 ( AOV<200 ) | K24: Swiggy | L24: 22 | M24: 20 | N24: 3 | O24: Prop | P24: Yes | Q24: Active | R24: Yes | S24: yes | U24: syed Aman | V24: 9866174396 | W24: NA | AA24: No | AU24: Yes | AV24: Contract Signing | AW24: NA | AX24: 46059 | AY24: 0.58333333 | AZ24: chanakya.inugala@capsdelivery.com | BR24: =Concatenate(BQ24,BP24,BO24,E24,T24) -> kiss me mandi
A25: 46059.394 | B25: 46058 | C25: 0.625 | D25: Intro Meeting | E25: Girl Friend Mandi | F25: 40 | G25: 300 | H25: na | I25: 30000 | J25: Tier-3 ( AOV<200 ) | K25: Swiggy, Zomato | L25: 22 | M25: 20 | N25: 2 | O25: Prop | P25: Yes | Q25: Active | R25: Yes | S25: NA | U25: shiek Nazeer | V25: 8886904546 | W25: na | AA25: No | AU25: Yes | AV25: Contract Signing | AX25: 46062 | AY25: 0.54166667 | AZ25: chanakya.inugala@capsdelivery.com | BR25: =Concatenate(BQ25,BP25,BO25,E25,T25) -> Girl Friend Mandi
A26: 46059.394 | B26: 46057 | C26: 0.50902778 | D26: Intro Meeting | E26: Shree Balaji Tiffin Center | F26: 60 | G26: 90 | H26: Mobile Software | I26: 16000 | J26: Tier-3 ( AOV<200 ) | K26: Swiggy, Zomato | L26: 22 | M26: 22 | N26: 1 | O26: Prop | P26: No | Q26: Active | R26: No | S26: https://maps.app.goo.gl/7YMoNqTWQYbg4jmu7 | U26: B.Raja Yeshwanth Kumar | V26: 9705812524 | W26: NA | AA26: Yes | AB26: 23625034003143 | AC26: https://drive.google.com/open?id=1FDLfrP2vE0w4X7UHEaSFNcpu27KdfG4j | AF26: AIOPB0243L | AG26: https://drive.google.com/open?id=1-S0Ms1yARTteTRwzAtfYIosgIvtAoKrD | AO26: B RAJA YESHWANTH KUMAR | AP26: 9705812524 | AR26: SHREE BALAJI TIFFIN CENTER | AS26: Yes | AT26: Onboarding is Done | AU26: No | AV26: NA | AZ26: ankitha.baske@capsdelivery.com | BR26: =Concatenate(BQ26,BP26,BO26,E26,T26) -> Shree Balaji Tiffin Center
A27: 46059.397 | B27: 46058 | C27: 0.625 | D27: Intro Meeting | E27: President Dhaba | F27: 50 | G27: 250 | H27: Nikhil | I27: 15000 | J27: Tier-2 (AOV <400) | K27: Swiggy, Zomato | L27: 22 | M27: 22 | N27: 2 | O27: Prop | P27: Yes | Q27: Active | R27: Yes | S27: yes | U27: Nikhil | V27: 7799956667 | W27: na | AA27: No | AU27: Yes | AV27: Meeting with different POC | AX27: 46062 | AY27: 0.625 | AZ27: chanakya.inugala@capsdelivery.com | BR27: =Concatenate(BQ27,BP27,BO27,E27,T27) -> President Dhaba
A28: 46059.397 | B28: 46058 | C28: 0.75 | D28: Intro Meeting | E28: lucky multicusine restaurant | F28: 200 | G28: 300 | H28: pet pooja | I28: 90000 | J28: Tier-2 (AOV <400) | K28: Swiggy, Zomato | L28: 15 | M28: 15 | N28: 1 | O28: Prop | P28: Yes | Q28: Active | R28: No | S28: https://www.google.com/maps/place/lucky+multi+cuisine+restaurant+madhapur/data=!4m2!3m1!1s0x3bcb915eea8173fb:0x9c806787d3a94d48?sa=X&ved=1t:242&ictx=111 | U28: Mansoor | V28: 9676213874 | W28: ya6822534@gmail.com | AA28: Yes | AB28: 13622013001491 | AC28: https://drive.google.com/open?id=1M7jn0BGrwdxzFH55n7AA8m6MyWVZRx1z | AD28: 36AAJFL6331Q1ZQ | AE28: https://drive.google.com/open?id=19lSB9R9cl_cCitMQsEsLggwyE9tp94F1 | AF28: AAJFL6331Q | AG28: https://drive.google.com/open?id=1NsZ5WcHnZIPbzaY8z4g91aZM_fe2ibN8 | AL28: 50200064899781 | AM28: HDFC0004277 | AN28: LUCKY MULTI CUISINE RESTAURANT | AO28: MANSOOR | AP28: 9676213874 | AQ28: ya6822534@gmail.com | AR28: LUCKY MULTI CUISINE RESTAURANT | AS28: Yes | AT28: ONBOARDED | AU28: No | AZ28: moin.khan@capsdelivery.com | BR28: =Concatenate(BQ28,BP28,BO28,E28,T28) -> lucky multicusine restaurant
A29: 46059.4 | B29: 46058 | C29: 0.75 | D29: Follow up | T29: godavari restaurant | U29: satya | V29: 9553119997 | W29: na | AA29: No | AU29: Yes | AV29: Meeting with different POC | AX29: 46059 | AY29: 0.54166667 | AZ29: moin.khan@capsdelivery.com | BR29: =Concatenate(BQ29,BP29,BO29,E29,T29) -> godavari restaurant
A30: 46059.401 | B30: 46058 | C30: 0.75 | D30: Follow up | T30: frozen bottles | U30: bhanu | V30: 8309230685 | W30: na | AA30: No | AU30: Yes | AV30: Meeting with different POC | AW30: interface about the AAP | AX30: 46059 | AY30: 0.58333333 | AZ30: moin.khan@capsdelivery.com | BR30: =Concatenate(BQ30,BP30,BO30,E30,T30) -> frozen bottles
A31: 46059.402 | B31: 46058 | C31: 0.66666667 | D31: Intro Meeting | E31: Adhirath | F31: 25 | G31: 200 | H31: na | I31: 20000 | J31: Tier-2 (AOV <400) | K31: Zomato | N31: 1 | O31: Prop | P31: Yes | Q31: Active | R31: Yes | S31: na | U31: Mukesh | V31: na | W31: na | AA31: No | AU31: Yes | AV31: Meeting with different POC | AX31: 46063 | AY31: 0.66666667 | AZ31: chanakya.inugala@capsdelivery.com | BR31: =Concatenate(BQ31,BP31,BO31,E31,T31) -> Adhirath
A32: 46059.403 | B32: 46058 | C32: 0.75 | D32: Follow up | T32: minyu | U32: ajay | V32: 7799223445 | W32: na | AA32: No | AU32: Yes | AV32: Meeting with different POC | AX32: 46059 | AY32: 0.625 | AZ32: moin.khan@capsdelivery.com | BR32: =Concatenate(BQ32,BP32,BO32,E32,T32) -> minyu
A33: 46059.404 | B33: 46058 | C33: 0.75 | D33: Follow up | T33: hyderabad host | U33: HARI | V33: 9849991664 | W33: NA | AA33: No | AU33: Yes | AV33: Meeting with different POC | AX33: 46059 | AY33: 0.625 | AZ33: moin.khan@capsdelivery.com | BR33: =Concatenate(BQ33,BP33,BO33,E33,T33) -> hyderabad host
A34: 46059.405 | B34: 46056 | C34: 0.68888889 | D34: Intro Meeting | E34: BIRYANI N BIRYANI | F34: 150 | G34: 150 | H34: NA | I34: 12000 | J34: Tier-3 ( AOV<200 ) | K34: Swiggy, Zomato | L34: 22 | M34: 22 | N34: 1 | O34: Partnership | P34: No | Q34: Active | R34: No | S34: https://maps.app.goo.gl/bVjfB92p6JmtmXyu9 | U34: Uttam Kumar | V34: 9010022093 | W34: NA | AA34: Yes | AB34: 23625030002129 | AC34: https://drive.google.com/open?id=1uEv1SbghR4V6SRNuV_W5cWmXTxOGaOTk | AO34: Uttam Kumar | AP34: 9010022093 | AR34: BIRYANI N BIRYANI | AS34: Yes | AU34: Yes | AV34: Document Collection | AZ34: ankitha.baske@capsdelivery.com | BR34: =Concatenate(BQ34,BP34,BO34,E34,T34) -> BIRYANI N BIRYANI
A35: 46059.406 | B35: 46058 | C35: 0.625 | D35: Intro Meeting | E35: Mehfil | F35: 70 | G35: 300 | H35: na | I35: 200000 | J35: Tier-2 (AOV <400) | K35: Swiggy, Zomato | L35: 22 | M35: 19 | N35: 10 | O35: Prop | P35: Yes | Q35: Active | R35: Yes | S35: yes | U35: Masood | V35: na | W35: na | AA35: No | AU35: Yes | AV35: Meeting with different POC | AW35: na | AX35: 46062 | AY35: 0.5 | AZ35: chanakya.inugala@capsdelivery.com | BR35: =Concatenate(BQ35,BP35,BO35,E35,T35) -> Mehfil
A36: 46059.406 | B36: 46058 | C36: 0.83333333 | D36: Follow up | T36: king mandi | U36: kavi raj | V36: 9059787788 | W36: NA | AA36: No | AU36: Yes | AV36: Meeting with different POC | AX36: 46059 | AY36: 0.79166667 | AZ36: moin.khan@capsdelivery.com | BR36: =Concatenate(BQ36,BP36,BO36,E36,T36) -> king mandi
A37: 46059.412 | B37: 46056 | C37: 0.54166667 | D37: Intro Meeting | E37: AL RAWAF HOME MADE DISHES | F37: 1 | G37: 300 | H37: Mobile Application | I37: 10000 | J37: Cloud Kitchen | K37: Swiggy | L37: 22 | M37: 22 | N37: 1 | O37: Prop | P37: No | Q37: Active | R37: No | S37: https://maps.app.goo.gl/3NoTX3DyLcp6bSMX7 | U37: ASFIYA SULTANA | V37: 9502632532 | W37: NA | AA37: Yes | AB37: 23625030004336 | AC37: https://drive.google.com/open?id=1jlS2uzGgdXIiBFtKTniOqZcQQP1Def9B | AF37: QGEPS7989L | AG37: https://drive.google.com/open?id=14vl9WR1NycmF9z9tVJiiS1sjEI4BpUgn | AS37: Yes | AT37: Onboarding Completed | AU37: No | AZ37: ankitha.baske@capsdelivery.com | BR37: =Concatenate(BQ37,BP37,BO37,E37,T37) -> AL RAWAF HOME MADE DISHES
A38: 46059.424 | B38: 46057 | C38: 0.57361111 | D38: Intro Meeting | E38: Govinda's Resturant | F38: 25 | G38: 400 | H38: Peta Puja | I38: 10000 | J38: Tier-2 (AOV <400) | K38: Swiggy, Zomato | L38: 21 | M38: 21 | N38: 2 | O38: Trust | P38: No | Q38: Active | R38: No | S38: https://maps.app.goo.gl/2zVYUFdRf5UbswRq8 | U38: Harish Dhas | V38: 9964818700 | W38: NA | AA38: Yes | AB38: 13622015000429 | AC38: https://drive.google.com/open?id=1XHti40Q6rcjbNTd4338mnP-gp5zYiTTo | AD38: 36AAAT10017P3ZM | AE38: https://drive.google.com/open?id=1wfQiIC4z7mrMJ5O4AxkRDuixJ2qPRhk2 | AF38: AAATI0017P | AG38: https://drive.google.com/open?id=1i3JNiPqA3bg9GskvIiKQOkcygNvWSwFo | AJ38: https://drive.google.com/open?id=1DMx_aqiNEP9UWnIpWFPjhq9IVflDo6wh | AK38: https://drive.google.com/open?id=1-_wWaTH5f5gEAIqiuRyYQXb_tpy1C51V | AO38: Harish Dhas | AP38: 9964818700 | AS38: Yes | AT38: Onboarding Completed | AU38: No | AZ38: ankitha.baske@capsdelivery.com | BR38: =Concatenate(BQ38,BP38,BO38,E38,T38) -> Govinda's Resturant
A39: 46059.426 | B39: 46175 | C39: 0.5625 | D39: Intro Meeting | E39: KNOX | F39: 200 | G39: 500 | H39: - | I39: 1 | J39: Tier-1(AOV>400) | K39: Swiggy, Zomato | L39: 22 | M39: 20 | N39: 1 | O39: Prop | P39: Yes | Q39: Active | R39: Yes | S39: NA | U39: Das | V39: 7842264138 | W39: - | AA39: No | AU39: Yes | AV39: Document Collection | AX39: 46059 | AY39: 0.5625 | AZ39: manasa.chigurupati@capsdelivery.com | BR39: =Concatenate(BQ39,BP39,BO39,E39,T39) -> KNOX
A40: 46059.43 | B40: 46055 | C40: 0.60416667 | D40: Intro Meeting | E40: NEW FARMAISH RESTAURANT | F40: 50 | G40: 300 | H40: NA | I40: 10000 | J40: Tier-3 ( AOV<200 ) | K40: Zomato | L40: 22 | M40: 22 | N40: 1 | O40: Prop | P40: No | Q40: Active | R40: No | S40: https://maps.app.goo.gl/Aiiv6UZV7TLfDBn47 | U40: SYED AMEER HUSSAIN | V40: 9742645678 | W40: NA | AA40: Yes | AB40: 23622028000187 | AC40: https://drive.google.com/open?id=1GwUWxdepNWvDVaZTDr0zsGPPIuKR_QoL | AD40: NA | AF40: BJVPS7089G | AG40: https://drive.google.com/open?id=1Uop_OL_J095nxx7Re4m3p62_DS8J7Cai | AO40: SYED | AP40: 9742645678 | AS40: Yes | AT40: Onboarding Completed | AU40: No | AZ40: ankitha.baske@capsdelivery.com | BR40: =Concatenate(BQ40,BP40,BO40,E40,T40) -> NEW FARMAISH RESTAURANT
A41: 46059.431 | B41: 46059 | C41: 0.47916667 | D41: Follow up | T41: Bahar Biryani | U41: Bodh | V41: 8978216439 | W41: NA | Z41: NA | AA41: No | AU41: Yes | AV41: Meeting with different POC | AW41: Comiision | AX41: 46059 | AY41: 0.47916667 | AZ41: akhila.narra@capsdelivery.com | BR41: =Concatenate(BQ41,BP41,BO41,E41,T41) -> Bahar Biryani
A42: 46059.431 | B42: 46059 | C42: 0.60416667 | D42: Intro Meeting | E42: Zythum | F42: 300 | G42: 1000 | H42: - | I42: 1 | J42: Tier-1(AOV>400) | K42: Swiggy, Zomato | L42: 22 | M42: 20 | N42: 1 | O42: Prop | P42: Yes | Q42: Active | R42: No | S42: - | U42: Bhargav | V42: 8019447999 | W42: - | AA42: No | AU42: Yes | AV42: Document Collection | AZ42: manasa.chigurupati@capsdelivery.com | BR42: =Concatenate(BQ42,BP42,BO42,E42,T42) -> Zythum
A43: 46059.434 | B43: 46059 | C43: 0.52083333 | D43: Follow up | T43: Singha Dhaba | U43: Surendar Singh | V43: 9848814600 | W43: NA | X43: Jaspreet Singh | Y43: 9848444396 | Z43: NA | AA43: No | AU43: Yes | AV43: Contract Signing | AW43: NA | AX43: 46059 | AY43: 0.52083333 | AZ43: akhila.narra@capsdelivery.com | BR43: =Concatenate(BQ43,BP43,BO43,E43,T43) -> Singha Dhaba
A44: 46059.542 | B44: 46059 | C44: 0.45486111 | D44: Intro Meeting | E44: Ohri's Cake Nation | F44: 150 | G44: 600 | H44: Brain power | I44: 15000 | J44: Tier-1(AOV>400) | K44: Swiggy, Zomato | L44: 17 | M44: 10 | N44: 11 | O44: Prop | P44: Yes | Q44: Active | R44: Yes | S44: na | U44: Ravi Kanth | V44: 6309794222 | W44: - | AA44: No | AU44: Yes | AV44: Document Collection | AW44: documents collection | AX44: 46069 | AY44: 0.45833333 | AZ44: manasa.chigurupati@capsdelivery.com | BR44: =Concatenate(BQ44,BP44,BO44,E44,T44) -> Ohri's Cake Nation
A45: 46059.586 | B45: 46059 | C45: 0.58333333 | D45: Intro Meeting | E45: KNOX | F45: 320 | G45: 450 | H45: pet pooja | I45: 20000 | J45: Tier-1(AOV>400) | K45: Swiggy, Zomato | L45: 20 | M45: 20 | N45: 1 | O45: Prop | P45: Yes | Q45: Active | R45: Yes | S45: - | U45: Jashwanth | V45: 9100007676 | W45: knowclubandkitchen@gmail.com | AA45: No | AU45: Yes | AV45: Document Collection | AW45: commissions & documents signs | AX45: 46064 | AY45: 0.39583333 | AZ45: manasa.chigurupati@capsdelivery.com | BR45: =Concatenate(BQ45,BP45,BO45,E45,T45) -> KNOX
A46: 46059.667 | B46: 46059 | C46: 0.66666667 | D46: Intro Meeting | E46: Zythum | F46: 400 | G46: 500 | H46: explorates | I46: 100000 | J46: Tier-1(AOV>400) | K46: Swiggy, Zomato | L46: 20 | M46: 20 | N46: 1 | O46: PVT | P46: Yes | Q46: Active | R46: Yes | S46: - | U46: BHURDHABAN | V46: 8249132908 | W46: - | AA46: No | AU46: Yes | AV46: Negotiation | AW46: Commissions, documents collections, Competrtiors | AX46: 46063 | AY46: 0.70833333 | AZ46: manasa.chigurupati@capsdelivery.com | BR46: =Concatenate(BQ46,BP46,BO46,E46,T46) -> Zythum
A47: 46059.709 | B47: 46059 | C47: 0.64930556 | D47: Intro Meeting | E47: Naseeb Cafe | F47: 25 | G47: 250 | H47: NA | I47: 8000 | J47: Tier-3 ( AOV<200 ) | K47: Zomato | L47: 22 | M47: 22 | N47: 1 | O47: Prop | P47: No | Q47: Active | R47: No | S47: https://maps.app.goo.gl/gbPqgYV9ZsUP1gDc8 | U47: Khuddus Hussian | V47: 9182466676 | W47: khuddushussian7@gmail.com | AA47: Yes | AB47: 30260206123260477 | AC47: https://drive.google.com/open?id=1hhJ4HCs3cnLc731dz0ty_EzVSMGi6q8m | AF47: AZCPH8455M | AG47: https://drive.google.com/open?id=14IVRIxSnIQQt6lva1v7ExVvqU4V4bM6l | AK47: https://drive.google.com/open?id=1HoToRS41uHrqu_gErmgajRS9Q13SKrzV | AL47: 37947443400 | AM47: SBIN0005322 | AN47: State Bank Of India | AO47: Quddus Hussain | AP47: 9182466676 | AQ47: khuddushussian7@gmail.com | AR47: Naseeb Cafe | AS47: Yes | AT47: Onboarding Done | AU47: No | AZ47: ankitha.baske@capsdelivery.com | BR47: =Concatenate(BQ47,BP47,BO47,E47,T47) -> Naseeb Cafe
A48: 46059.715 | B48: 46059 | C48: 0.67152778 | D48: Intro Meeting | E48: Sri Balaji Family Dhaba | F48: 60 | G48: 200 | H48: Na | I48: 9000 | J48: Tier-3 ( AOV<200 ) | K48: Swiggy, Zomato | L48: 22 | M48: 22 | N48: 1 | O48: Prop | P48: No | Q48: Active | R48: No | S48: https://maps.app.goo.gl/CYfpD7HuaPaEeArM6 | U48: Rihaan | V48: 04023536061 | W48: bidhaniyasony@gmail.com | AA48: Yes | AB48: 13620011000085 | AC48: https://drive.google.com/open?id=1aZgR-8WQbSPhz8kdHLDR2naTnc3fOi42 | AF48: MMLPS4120E | AG48: https://drive.google.com/open?id=1TGEb0yhwAAch3o-uj61e77IJ76PBiiNm | AK48: https://drive.google.com/open?id=1FHEOkgoHN1uVC9-OPnLYD4xoB1lkx6FT | AL48: 02711500006880 | AM48: DCBL0000027 | AN48: DCB Bank Limited | AO48: B SONI | AP48: 9010022093 | AQ48: bidhaniyasony@gmail.com | AR48: Sri Balaji Family Dhaba | AS48: Yes | AT48: Onboarding Completed | AU48: No | AZ48: ankitha.baske@capsdelivery.com | BR48: =Concatenate(BQ48,BP48,BO48,E48,T48) -> Sri Balaji Family Dhaba
A49: 46059.717 | B49: 46059 | C49: 0.70833333 | D49: Intro Meeting | E49: 10th street coffee | F49: 15 | G49: 300 | H49: - | I49: 15000 | J49: Tier-2 (AOV <400) | K49: None | L49: 1 | N49: 1 | O49: Prop | P49: Yes | Q49: Active | R49: Yes | S49: - | U49: Prathap | V49: 9063906004 | W49: - | AA49: No | AU49: Yes | AV49: Negotiation | AW49: commissions, demo | AX49: 46082 | AY49: 0.70833333 | AZ49: manasa.chigurupati@capsdelivery.com | BR49: =Concatenate(BQ49,BP49,BO49,E49,T49) -> 10th street coffee
A50: 46059.754 | B50: 46059 | C50: 0.75 | D50: Intro Meeting | E50: Mujataba Grills | F50: 200 | G50: 300 | H50: Rista | I50: 20000 | J50: Tier-2 (AOV <400) | K50: Swiggy, Zomato | L50: 20 | M50: 18 | N50: 1 | O50: Prop | P50: Yes | Q50: Active | R50: No | S50: - | U50: AFROZE | V50: 9032417871 | W50: - | AA50: No | AU50: Yes | AV50: Document Collection | AW50: NA | AX50: 46063 | AY50: 0.75 | AZ50: manasa.chigurupati@capsdelivery.com | BR50: =Concatenate(BQ50,BP50,BO50,E50,T50) -> Mujataba Grills
A51: 46060.65 | B51: 46062 | C51: 0.125 | D51: Follow up | T51: Minerva Blue fox hotel | U51: Hamzad ali | V51: 9030266975 | W51: Na | AA51: No | AU51: Yes | AV51: Negotiation | AW51: Meetings are with HOD's at minerva group of hotels | AX51: 46062 | AY51: 0.125 | AZ51: parthive.maganti@capsdelivery.com | BR51: =Concatenate(BQ51,BP51,BO51,E51,T51) -> Minerva Blue fox hotel
A52: 46060.65 | B52: 46062 | C52: 0.52083333 | D52: Follow up | T52: Rayalasema Ruchulu | U52: 99590 20310 | V52: 99590 20310 | W52: NA | X52: NA | Y52: 9959020310 | Z52: NA | AA52: No | AU52: Yes | AV52: Meeting with different POC | AW52: Need discuss how are Planning the things What our Vision from merchant Pointnof View | AX52: 46061 | AY52: 0.52083333 | AZ52: akhila.narra@capsdelivery.com | BR52: =Concatenate(BQ52,BP52,BO52,E52,T52) -> Rayalasema Ruchulu
A53: 46060.654 | B53: 46062 | C53: 0.041666667 | D53: Follow up | T53: Ahara Tiffins | U53: Venu | V53: 9493106693 | W53: Na | AA53: No | AU53: Yes | AV53: Contract Signing | AW53: Na | AX53: 46062 | AY53: 0.54166667 | AZ53: parthive.maganti@capsdelivery.com | BR53: =Concatenate(BQ53,BP53,BO53,E53,T53) -> Ahara Tiffins
A54: 46060.657 | B54: 46059 | C54: 0.64583333 | D54: Intro Meeting | E54: Samastha Tiffins | F54: 90 | G54: 120 | H54: N/a | I54: 30000 | J54: Tier-3 ( AOV<200 ) | K54: Swiggy, Zomato | L54: 28 | M54: 17 | N54: 1 | O54: Partnership | P54: No | Q54: Active | R54: Yes | S54: https://share.google/2dLN0NYKphOuVkK3U | U54: Harsha | V54: 9704204592 | W54: Na | AA54: No | AU54: Yes | AV54: Contract Signing | AW54: Na | AX54: 46062 | AY54: 0.625 | AZ54: parthive.maganti@capsdelivery.com | BR54: =Concatenate(BQ54,BP54,BO54,E54,T54) -> Samastha Tiffins
A55: 46060.667 | B55: 46059 | C55: 0.64583333 | D55: Intro Meeting | E55: Mokshi kitchens | F55: 90 | G55: 150 | H55: Na | I55: 50000 | J55: Tier-3 ( AOV<200 ) | K55: Swiggy, Zomato | L55: 30 | M55: 17 | N55: 1 | O55: Partnership | P55: No | Q55: Active | R55: Yes | S55: https://maps.app.goo.gl/avzks9t6kSFWe88o8 | U55: Harsha | V55: 9604204592 | W55: Na | AA55: No | AU55: Yes | AV55: Contract Signing | AW55: Na | AX55: 46062 | AY55: 0.64583333 | AZ55: parthive.maganti@capsdelivery.com | BR55: =Concatenate(BQ55,BP55,BO55,E55,T55) -> Mokshi kitchens
A56: 46060.677 | B56: 46059 | C56: 0.60416667 | D56: Intro Meeting | E56: Exotic Shawarma | F56: 60 | G56: 160 | H56: Petpooja | I56: 40000 | J56: Tier-3 ( AOV<200 ) | K56: Swiggy, Zomato | L56: 28 | M56: 17 | N56: 1 | O56: Partnership | P56: No | Q56: Active | R56: Yes | S56: https://share.google/tMU7i0NamuInUBqVj | U56: Vinesh Reddy | V56: 8500703171 | W56: Na | AA56: No | AU56: Yes | AV56: Contract Signing | AW56: Na | AX56: 46062 | AY56: 0.41666667 | AZ56: parthive.maganti@capsdelivery.com | BR56: =Concatenate(BQ56,BP56,BO56,E56,T56) -> Exotic Shawarma
A57: 46060.686 | B57: 46059 | C57: 0.41666667 | D57: Intro Meeting | E57: Sri Sai Swetha foods | F57: 100 | G57: 200 | H57: Na | I57: 50000 | J57: Tier-3 ( AOV<200 ) | K57: Swiggy, Zomato | L57: 28 | M57: 17 | N57: 1 | O57: Prop | P57: Yes | Q57: Active | R57: Yes | S57: https://share.google/tMU7i0NamuInUBqVj | U57: Praveen | V57: 9032460766 | W57: Na | AA57: No | AU57: Yes | AV57: Contract Signing | AW57: Na | AX57: 46062 | AY57: 0.4375 | AZ57: parthive.maganti@capsdelivery.com | BR57: =Concatenate(BQ57,BP57,BO57,E57,T57) -> Sri Sai Swetha foods
A58: 46061.732 | B58: 46055 | C58: 0.10416667 | D58: Intro Meeting | E58: JUS VOUS | F58: 50 | G58: 150 | H58: NA | I58: 5000 | J58: Tier-3 ( AOV<200 ) | K58: Zomato | L58: 22 | M58: 22 | N58: 1 | O58: Prop | P58: No | Q58: Active | R58: No | S58: NA | U58: SHABANA BEGUM | V58: 8121007155 | W58: NA | AA58: Yes | AB58: 23623028001095 | AC58: https://drive.google.com/open?id=1sAnOS-klkKNxUHLQQA1nebfrNs7UHF3f | AF58: KKDPS6734N | AG58: https://drive.google.com/open?id=1SefsNnW2N-5RAzKURGcWE46DoH3EFMvZ | AS58: Yes | AT58: Onboarded | AU58: No | AZ58: ankitha.baske@capsdelivery.com | BR58: =Concatenate(BQ58,BP58,BO58,E58,T58) -> JUS VOUS
A59: 46061.736 | B59: 46055 | C59: 0.61458333 | D59: Intro Meeting | E59: BEGUM KI BIRYANI | F59: 100 | G59: 200 | H59: NA | I59: 7000 | J59: Tier-3 ( AOV<200 ) | K59: Zomato | L59: 22 | M59: 22 | N59: 1 | O59: Prop | P59: No | Q59: Active | R59: No | S59: NA | U59: SYED AMEER HUSSIAN | V59: 8121007155 | W59: NA | AA59: Yes | AB59: 23623028000252 | AC59: https://drive.google.com/open?id=1S1WlPojpvf1raedXv-niWA3UjYFTUlk5 | AF59: BJVPS7089G | AG59: https://drive.google.com/open?id=16VMSkJtnx2sth2a93gMBw8bIauhQ4QgY | AS59: Yes | AT59: ONBOARDED | AU59: No | AZ59: ankitha.baske@capsdelivery.com | BR59: =Concatenate(BQ59,BP59,BO59,E59,T59) -> BEGUM KI BIRYANI
A60: 46061.788 | B60: 46058 | C60: 0.67361111 | D60: Intro Meeting | E60: FOOD 4 U | F60: 60 | G60: 150 | H60: NA | I60: 10000 | J60: Tier-3 ( AOV<200 ) | K60: Zomato | L60: 20 | M60: 20 | N60: 1 | O60: Prop | P60: No | Q60: Active | R60: No | S60: NA | U60: MOHD ARSHAD | V60: 8247496273 | W60: NA | AA60: Yes | AB60: 23625030005083 | AC60: https://drive.google.com/open?id=1yf9M7K7UhdTNA3TQu2NOSU6PrAh13spn | AF60: BNUPA9377G | AG60: https://drive.google.com/open?id=1_dVx2u88AJbRK_cdhlcm5w9BOa-NL-qE | AS60: Yes | AT60: ONBOARDED | AU60: No | AZ60: ankitha.baske@capsdelivery.com | BR60: =Concatenate(BQ60,BP60,BO60,E60,T60) -> FOOD 4 U
A61: 46061.792 | B61: 46058 | C61: 0.67361111 | D61: Intro Meeting | E61: TAHARI HOUSE | F61: 80 | G61: 200 | H61: NA | I61: 8000 | J61: Tier-3 ( AOV<200 ) | K61: Zomato | L61: 20 | M61: 20 | N61: 1 | O61: Prop | P61: No | Q61: Active | R61: No | S61: NA | U61: MOHAMMED FEROZ | V61: 7097949648 | W61: ak.8977.ak@gmail.com | AA61: Yes | AB61: 23625030004696 | AC61: https://drive.google.com/open?id=1AlxCOdJ1Za0jZBdQ3zWZHURu3hmd6ii2 | AK61: https://drive.google.com/open?id=1-wjf481GOo4dlMS7Mn0_aN82x0QlqFIb | AL61: 157097949648 | AM61: INDB0001052 | AN61: Indusland Bank | AO61: MOHAMMED FEROZ | AP61: 7097949648 | AS61: Yes | AT61: ONBOARDED | AU61: No | AZ61: ankitha.baske@capsdelivery.com | BR61: =Concatenate(BQ61,BP61,BO61,E61,T61) -> TAHARI HOUSE
A62: 46061.795 | B62: 46058 | C62: 0.67361111 | D62: Intro Meeting | E62: RAHAT RESTURANT | F62: 100 | G62: 200 | H62: NA | I62: 10000 | J62: Tier-3 ( AOV<200 ) | K62: Zomato | L62: 20 | M62: 20 | N62: 1 | O62: Prop | P62: No | Q62: Active | R62: No | S62: NA | U62: MOHAMMED FEROZ | V62: 7097949648 | W62: NA | AA62: Yes | AB62: 13624011000338 | AC62: https://drive.google.com/open?id=1-8lOUY6jgkJa66YVEByy-q1eWlWTl5rK | AS62: Yes | AT62: ONBOARDED | AU62: No | AZ62: ankitha.baske@capsdelivery.com | BR62: =Concatenate(BQ62,BP62,BO62,E62,T62) -> RAHAT RESTURANT
A63: 46061.934 | B63: 46058 | C63: 0.79166667 | D63: Intro Meeting | E63: Bhavani mess | F63: 50 | G63: 250 | H63: They are not using any online platforms currently | J63: Tier-2 (AOV <400) | K63: None | N63: 1 | O63: Prop | P63: Yes | Q63: Active | R63: No | S63: https://maps.app.goo.gl/6hdkrbad7BwbvaWQ6 | U63: Anil | V63: 72868 01930 | W63: Na | AA63: Yes | AS63: Will follow up tomorrow | AT63: The restaurant owner Mr Satyanarayana lives in khammam, will get confirmation from him tomorrow. Mr Anil who takes care of bhavani mess in Hyderabad is very impressed with the pitch and is okay for onboarding. Just need Mr Satyanarayana's permission. | AZ63: sumadhur.mummadi@capsdelivery.com | BA63: Cold Walk-in | BB63: Yes | BR63: =Concatenate(BQ63,BP63,BO63,E63,T63) -> Bhavani mess
A64: 46061.937 | B64: 46058 | C64: 0.625 | D64: Intro Meeting | E64: Kausar cafe,Al nabi cafe | F64: 30 | G64: 100 | H64: NA | J64: Both restaurants are newly opened so no info regarding AOV and POS | N64: 1 | O64: Prop | P64: No | Q64: Not Applied | R64: Not Applied | S64: https://maps.app.goo.gl/9s4KoQNjMUjsr5Kj8 | U64: Mirza Hussain | V64: 96403 07014 | W64: NA | AA64: Yes | AS64: No | AU64: Yes | AV64: Contract Signing | AX64: 46062 | AY64: 0.60416667 | AZ64: sumadhur.mummadi@capsdelivery.com | BA64: Cold Walk-in | BB64: Yes | BR64: =Concatenate(BQ64,BP64,BO64,E64,T64) -> Kausar cafe,Al nabi cafe
A65: 46062.002 | B65: 46059 | C65: 0.75 | D65: Intro Meeting | E65: Madhapuram food court | F65: 50 | G65: 250 | H65: PET POOJA | J65: Tier-2 (AOV <400) | K65: Zomato | L65: 19 | M65: 22 | N65: 1 | O65: Prop | P65: No | Q65: Active | R65: No | S65: https://www.google.com/maps/place/Hunan+Chinese+Cuisine/@17.4478451,78.3885023,17z/data=!3m1!4b1!4m6!3m5!1s0x3bcb91b50352f21f:0xee872dfeab40a154!8m2!3d17.4478451!4d78.3885023!16s%2Fg%2F11vxjzpgh9?hl=en&entry=ttu&g_ep=EgoyMDI2MDIwMS4wIKXMDSoKLDEwMDc5MjA2OUgBUAM%3D | U65: ANIL | V65: 7893713995 | W65: NA | AA65: Yes | AB65: 23625032000080 | AC65: https://drive.google.com/open?id=1DlC2bj1dFOqdVO20DL-nBeSxxMLICMpI | AF65: DEZPM8147A | AG65: https://drive.google.com/open?id=1mShRP-cqmHVFZLU640-JIitYc1Hbdu-w | AO65: MADAPURAM ANIL KUMAR | AP65: 7893713995 | AR65: Madapuram food court | AS65: Yes | AU65: Yes | AV65: Document Collection | AX65: 46062 | AY65: 0.625 | AZ65: moin.khan@capsdelivery.com | BA65: Cold Walk-in | BB65: Yes | BH65: 22 | BJ65: 0.45833333 | BK65: 0 | BL65: 60 | BR65: =Concatenate(BQ65,BP65,BO65,E65,T65) -> Madhapuram food court
A66: 46062.003 | B66: 46059 | C66: 0.79166667 | U66: SUDHAKAR | V66: 9856666589 | W66: NA | AA66: No | AU66: Yes | AV66: Meeting with different POC | AX66: 46062 | AY66: 0.58333333 | AZ66: moin.khan@capsdelivery.com | BA66: Cold Walk-in | BB66: No | BR66: =Concatenate(BQ66,BP66,BO66,E66,T66)
A67: 46062.004 | B67: 46059 | C67: 0.75 | U67: RAVI | V67: 7702070233 | W67: NA | AA67: No | AU67: Yes | AV67: Introduction | AX67: 46062 | AY67: 0.54166667 | AZ67: moin.khan@capsdelivery.com | BA67: Cold Walk-in | BB67: No | BR67: =Concatenate(BQ67,BP67,BO67,E67,T67)
A68: 46062.006 | B68: 46059 | C68: 0.75 | D68: Follow up | T68: godavari restaurant | U68: SATYA | V68: 6281845369 | W68: NA | AA68: No | AU68: Yes | AV68: Negotiation | AX68: 46062 | AY68: 0.58333333 | AZ68: moin.khan@capsdelivery.com | BA68: Cold Walk-in | BB68: Yes | BR68: =Concatenate(BQ68,BP68,BO68,E68,T68) -> godavari restaurant
A69: 46062.007 | B69: 46059 | C69: 0.75 | U69: JYOTHI | V69: 9346811687 | W69: NA | AA69: No | AU69: Yes | AV69: Meeting with different POC | AX69: 46062 | AY69: 0.58333333 | AZ69: moin.khan@capsdelivery.com | BA69: Cold Walk-in | BB69: No | BR69: =Concatenate(BQ69,BP69,BO69,E69,T69)
A70: 46062.015 | B70: 46059 | C70: 0.75 | D70: Intro Meeting | E70: anand bhavan mess | F70: 50 | G70: 300 | H70: PET POOJA | I70: 18000 | J70: Tier-2 (AOV <400) | K70: Swiggy, Zomato | L70: 19 | M70: 22 | N70: 1 | O70: Partnership | P70: Yes | Q70: Active | R70: Yes | S70: https://www.google.com/maps/place/ANAND+BHAVAN+MESS/@17.4471051,78.3854684,17z/data=!3m1!4b1!4m6!3m5!1s0x3bcb910040604355:0x1b5af753bc8c8b9e!8m2!3d17.4471051!4d78.3880433!16s%2Fg%2F11mt5nf89c?hl=en&entry=ttu&g_ep=EgoyMDI2MDIwMS4wIKXMDSoKLDEwMDc5MjA2OUgBUAM%3D | U70: SHANKAR | V70: 7093742666 | W70: anandbhavanmess@gmail.com | AA70: Yes | AB70: 23625032007575 | AC70: https://drive.google.com/open?id=1-Dl1aiT5Ad0HRsUNS4BdokXeybknF0vr | AF70: AOCPJ4808H | AG70: https://drive.google.com/open?id=1AJ6Bfl3fKA7EyjUaT33Q-BEaqLJYLFpE | AK70: https://drive.google.com/open?id=174krwSmWS-7Ns96sjRGj3zQCcClDenc9 | AL70: 018361900006050 | AM70: YESB0000183 | AN70: ANAND BHAVAN MESS | AO70: SHANKAR | AP70: 7093742666 | AQ70: anandbhavanmess@gmail.com | AR70: ANAND BHAVAN MESS | AS70: Yes | AT70: ONBOARDED | AU70: No | AZ70: moin.khan@capsdelivery.com | BA70: Cold Walk-in | BB70: Yes | BH70: 22 | BI70: No | BJ70: 0.45833333 | BK70: 0 | BL70: 60 | BR70: =Concatenate(BQ70,BP70,BO70,E70,T70) -> anand bhavan mess
A71: 46062.017 | B71: 46059 | C71: 0.75 | U71: ANKIT | V71: 9966644448 | W71: NA | AA71: No | AU71: Yes | AV71: Introduction | AX71: 46062 | AY71: 0.54166667 | AZ71: moin.khan@capsdelivery.com | BA71: Cold Walk-in | BB71: No | BR71: =Concatenate(BQ71,BP71,BO71,E71,T71)
A72: 46062.018 | B72: 46059 | C72: 0.75 | U72: SANTOSH | V72: NA | W72: NA | AA72: No | AU72: Yes | AV72: Introduction | AX72: 46062 | AY72: 0.5625 | AZ72: moin.khan@capsdelivery.com | BA72: Cold Walk-in | BB72: No | BR72: =Concatenate(BQ72,BP72,BO72,E72,T72)
A73: 46062.02 | B73: 46059 | C73: 0.75 | D73: Follow up | T73: UCKY RESTAURANT | U73: KHASIM | V73: 9849108337 | W73: NA | AA73: No | AU73: Yes | AV73: Contract Signing | AX73: 46062 | AY73: 0.625 | AZ73: moin.khan@capsdelivery.com | BA73: Scheduled | BR73: =Concatenate(BQ73,BP73,BO73,E73,T73) -> UCKY RESTAURANT
A74: 46062.384 | B74: 46059 | C74: 0.66666667 | D74: Intro Meeting | E74: The smash city | F74: 10 | G74: 200 | H74: own | I74: 1000 | J74: Tier-3 ( AOV<200 ) | K74: Swiggy | L74: 22 | M74: 22 | N74: 1 | O74: Prop | P74: Yes | Q74: Active | R74: Yes | S74: yes | U74: Pranay | V74: 9963967706 | W74: smashcity.bk2025@gmail.com | AA74: Yes | AB74: 23625032006375 | AC74: https://drive.google.com/open?id=1TyQ5VyQoYOXBgO6bKGNQK8FFz5yUt2Nw | AD74: 36DBDPM7611E1ZT | AE74: https://drive.google.com/open?id=16MNvuqRPFC7_QYv133p_s5qg9F-FCQ4f | AF74: DBDPM7611E | AG74: https://drive.google.com/open?id=1bIvEcXpfVNl_DQCS6PvKRh51VxqYyyLn | AK74: https://drive.google.com/open?id=1gCFHksXqJDMO9XNunUEWVv0oVwAAtw9X | AL74: 1850667931 | AM74: KKBK0008392 | AN74: KOTAK MAHINDRA BANK | AO74: PRANAY | AP74: 9963967706 | AQ74: SMASHCITY.BK2025@GMAIL.COM | AR74: SMASH CITY | AS74: Yes | AT74: ON BOARDED | AU74: No | AX74: 46059 | AY74: 0.66666667 | AZ74: chanakya.inugala@capsdelivery.com | BA74: Cold Walk-in | BB74: Yes | BJ74: 0.41666667 | BK74: 0.91666667 | BL74: 40 | BR74: =Concatenate(BQ74,BP74,BO74,E74,T74) -> The smash city
A75: 46062.388 | B75: 46062 | C75: 0.5 | D75: Intro Meeting | E75: Gold sparrow millets | F75: 50 | G75: 100 | H75: Pet pooja | I75: 30000 | J75: Tier-3 ( AOV<200 ) | K75: Swiggy, Zomato | N75: 3 | O75: Partnership | P75: Yes | Q75: Active | R75: Yes | S75: https://share.google/SZFJJlssb5hkmphPA | U75: Ramchanra rao | V75: 8977709421 | W75: Na | AA75: No | AU75: Yes | AV75: Contract Signing | AW75: Na | AX75: 46062 | AY75: 0.5 | AZ75: parthive.maganti@capsdelivery.com | BA75: Scheduled | BL75: 50-60 | BR75: =Concatenate(BQ75,BP75,BO75,E75,T75) -> Gold sparrow millets
A76: 46062.393 | B76: 46059 | C76: 0.70833333 | D76: Intro Meeting | E76: BREW COMMUNE CAFE&BISTRO | F76: 40 | G76: 250 | H76: OWN | I76: 10000 | J76: Tier-3 ( AOV<200 ) | K76: Swiggy, Zomato, Magic Pin | L76: 22 | M76: 22 | N76: 1 | O76: Prop | P76: Yes | Q76: Active | R76: Not Applied | S76: YES | U76: CHALLA TRIVENI | V76: 8333833299 | W76: brewcommunecafe@gmail.com | AA76: Yes | AB76: 13626013000059 | AC76: https://drive.google.com/open?id=1f4MJPvzkVHBffgC4W0BlFcwQrLXPEzPq | AD76: 36BEYPC6487C1Z2 | AE76: https://drive.google.com/open?id=1DvL3nMVvblvTgCQjw2nEz6TTgrlJB-SM | AF76: BEYPC6487C | AG76: https://drive.google.com/open?id=10C5WjBtCBIlv55ac_HFiCjrMwueH5--t | AJ76: https://drive.google.com/open?id=1d5gMIAgwLYoo1XE8r6S6l9xrXBuHC_fD | AK76: https://drive.google.com/open?id=1z18XBbhWksdkjRHgsWjBufUzI3CtoA82 | AL76: 00000044866997013 | AM76: SBIN0014676 | AN76: SBI | AO76: CHALLA TRIVENI | AP76: 8333833299 | AQ76: brewcommunecafe@gmail.com | AR76: BREW COMMUNE CAFE & BISTRO | AS76: Yes | AT76: ONBOARDED | AU76: No | AX76: 46059 | AY76: 0.70833333 | AZ76: chanakya.inugala@capsdelivery.com | BA76: Cold Walk-in | BB76: Yes | BJ76: 0.41666667 | BK76: 0.91666667 | BL76: 20 | BR76: =Concatenate(BQ76,BP76,BO76,E76,T76) -> BREW COMMUNE CAFE&BISTRO
A77: 46062.395 | B77: 46059 | C77: 0.625 | D77: Follow up | T77: NA | U77: NAVEEN REDDY | V77: 9676945646 | W77: CAFEREELS@GMAIL.COM | AA77: No | AU77: Yes | AV77: Introduction | AX77: 46062 | AY77: 0.5 | AZ77: chanakya.inugala@capsdelivery.com | BA77: Cold Walk-in | BB77: Yes | BR77: =Concatenate(BQ77,BP77,BO77,E77,T77) -> NA
A78: 46062.399 | B78: 46059 | C78: 0.75 | D78: Intro Meeting | E78: HOTEL INNER CIRCLE | F78: 50 | G78: 400 | H78: OWN | I78: 50000 | J78: Tier-2 (AOV <400) | K78: Swiggy, Zomato | L78: 22 | M78: 22 | N78: 1 | O78: Prop | P78: Yes | Q78: Active | R78: Yes | S78: YES | U78: IBRAHIM KHAN | V78: 9010924000 | W78: NA | AA78: No | AU78: Yes | AV78: Introduction | AX78: 46062 | AY78: 0.58333333 | AZ78: chanakya.inugala@capsdelivery.com | BA78: Cold Walk-in | BB78: Yes | BL78: 40 | BR78: =Concatenate(BQ78,BP78,BO78,E78,T78) -> HOTEL INNER CIRCLE
A79: 46062.402 | B79: 46059 | C79: 0.54166667 | D79: Intro Meeting | E79: RENAO | F79: 30 | G79: 300 | H79: NA | I79: 10000 | J79: Tier-2 (AOV <400) | K79: Swiggy, Zomato | L79: 22 | M79: 22 | N79: 3 | O79: Prop | P79: Yes | Q79: Active | R79: Yes | S79: NA | U79: ASHRAF ALI | V79: 9701916013 | W79: NA | AA79: No | AU79: Yes | AV79: Meeting with different POC | AX79: 46062 | AY79: 0.625 | AZ79: chanakya.inugala@capsdelivery.com | BA79: Cold Walk-in | BB79: Yes | BL79: 30 | BR79: =Concatenate(BQ79,BP79,BO79,E79,T79) -> RENAO
A80: 46062.417 | B80: 46062 | C80: 0.625 | D80: Follow up | T80: NA | U80: SHEIK NAZEER | V80: 8886904546 | W80: NA | AA80: No | AU80: Yes | AV80: Meeting with different POC | AX80: 46062 | AY80: 0.625 | AZ80: chanakya.inugala@capsdelivery.com | BA80: Cold Walk-in | BB80: Yes | BR80: =Concatenate(BQ80,BP80,BO80,E80,T80) -> NA
A81: 46062.419 | B81: 46057 | C81: 0.50694444 | E81: merajs restraunt | F81: 100 | G81: 400 | H81: na | I81: 150000 | J81: Tier-2 (AOV <400) | K81: None | L81: 20 | M81: 20 | N81: 1 | O81: Prop | P81: No | Q81: Not Applied | R81: Not Applied | S81: na | U81: MOHD UMAR KHAN | V81: 9885199151 | W81: amer786khan@gmail.com | AA81: No | AT81: onboarded | AU81: No | AV81: Introduction | AZ81: madhumitha.sonnakula@capsdelivery.com | BL81: 0 | BR81: =Concatenate(BQ81,BP81,BO81,E81,T81) -> merajs restraunt
A82: 46062.42 | B82: 46058 | C82: 0.67083333 | D82: Intro Meeting | E82: Flavors Of Briyani Cafe | F82: 25 | G82: 200 | H82: na | I82: 8000 | J82: Tier-3 ( AOV<200 ) | K82: Swiggy, Zomato | L82: 22 | M82: 22 | N82: 1 | O82: Prop | P82: No | Q82: Active | R82: No | S82: na | U82: Sai Teja | V82: 9642897117 | W82: flavourbiryanicafe9@gmail.com | AA82: Yes | AB82: 23626030000702 | AC82: https://drive.google.com/open?id=1rHTW-WZBcmBuGCZkK9YDvq-bRkFEbAAL | AF82: BSYPT7188K | AG82: https://drive.google.com/open?id=1sI3WqNOFvKe4niWEHF_25fgwDL5FWJv4 | AL82: 6414081002 | AM82: IDIB000K284 | AN82: Indian Bank | AO82: M SaiTeja | AP82: 9642897117 | AS82: Yes | AT82: Onboarded | AU82: No | AZ82: ankitha.baske@capsdelivery.com | BA82: Cold Walk-in | BB82: Yes | BL82: 50 | BR82: =Concatenate(BQ82,BP82,BO82,E82,T82) -> Flavors Of Briyani Cafe
A83: 46062.423 | B83: 46057 | C83: 0.45833333 | D83: Intro Meeting | E83: lassi corner | F83: 10 | G83: 200 | H83: na | I83: 5000 | J83: Tier-3 ( AOV<200 ) | K83: Swiggy, Zomato | N83: 1 | O83: Prop | P83: No | Q83: Active | R83: Yes | S83: na | U83: ashok thapa | V83: 7995109409 | W83: vishnuthapaaaa@gamil.com | AA83: No | AT83: na | AU83: No | AW83: na | AZ83: madhumitha.sonnakula@capsdelivery.com | BA83: Cold Walk-in | BB83: Yes | BL83: 30 | BR83: =Concatenate(BQ83,BP83,BO83,E83,T83) -> lassi corner
A84: 46062.425 | B84: 46056 | C84: 0.5 | D84: Intro Meeting | E84: Pandu Fast Food Center | F84: 60 | G84: 120 | H84: NA | I84: 7000 | J84: Tier-3 ( AOV<200 ) | K84: Swiggy, Zomato | L84: 22 | M84: 22 | N84: 1 | O84: Prop | P84: No | Q84: Active | R84: No | S84: NA | U84: Sai Kumar Goud | V84: 9030518803 | W84: rebalsaikumargoud@gmail.com | AA84: Yes | AB84: 23621030003744 | AC84: https://drive.google.com/open?id=1fGbSlo6SQePsw9IXCKG5RYAxMZoOHZ-d | AF84: ANSPY4470D | AG84: https://drive.google.com/open?id=18bZYxppjAI2i6dJ5kmCHOmhA6qsOjZuW | AL84: 3269632568 | AM84: CBIN0283883 | AN84: Central Bank Of India | AO84: Sai Kumar Goud | AP84: 9030518803 | AQ84: rebalsaikumargoud@gmail.com | AS84: Yes | AT84: Onboarded | AU84: No | AZ84: ankitha.baske@capsdelivery.com | BA84: Cold Walk-in | BB84: Yes | BL84: 50 | BR84: =Concatenate(BQ84,BP84,BO84,E84,T84) -> Pandu Fast Food Center
A85: 46062.426 | B85: 46057 | C85: 0.41666667 | D85: Intro Meeting | E85: sri udupi grand pure veg | F85: 50 | G85: 200 | H85: na | I85: 15000 | J85: Tier-3 ( AOV<200 ) | K85: Zomato | L85: 22 | M85: 22 | N85: 7 | O85: Prop | P85: No | Q85: Active | R85: Yes | S85: na | U85: manjunath | V85: 8125178544 | W85: bmanjunathkotteri@gmail.com | AA85: No | AT85: na | AU85: No | AV85: Introduction | AZ85: madhumitha.sonnakula@capsdelivery.com | BA85: Cold Walk-in | BB85: Yes | BL85: 70 | BR85: =Concatenate(BQ85,BP85,BO85,E85,T85) -> sri udupi grand pure veg
A86: 46062.506 | B86: 46062 | C86: 0.5 | D86: Intro Meeting | E86: SSR FOOD ZONE | F86: 50 | G86: 150 | H86: Order matic | I86: 15000 | J86: Tier-3 ( AOV<200 ) | K86: Swiggy, Zomato | L86: 25 | M86: 22 | N86: 1 | O86: Prop | P86: No | Q86: Active | R86: Yes | S86: https://maps.app.goo.gl/Azm6uVjLA8CHdEVq5?g_st=ic | U86: Dinesh | V86: 6281821329 | W86: dinesh.pedamallu@gmail.com | AA86: No | AT86: Closed by Ankitha, documents will be submitted by her. | AU86: No | AZ86: manasa.chigurupati@capsdelivery.com | BA86: Cold Walk-in | BB86: Yes | BL86: 10 | BR86: =Concatenate(BQ86,BP86,BO86,E86,T86) -> SSR FOOD ZONE
A87: 46062.518 | B87: 46062 | C87: 0.52083333 | U87: Kanshith | V87: 9347059650 | W87: Mattaparthykanakshith@gmail.com | AA87: No | AU87: Yes | AV87: Document Collection | AW87: Commisions | AX87: 46063 | AY87: 0.52083333 | AZ87: manasa.chigurupati@capsdelivery.com | BA87: Cold Walk-in | BB87: No | BR87: =Concatenate(BQ87,BP87,BO87,E87,T87)
A88: 46062.548 | B88: 46062 | C88: 0.54513889 | D88: Intro Meeting | E88: Mammu’s Kitchen | F88: 60 | G88: 250 | H88: - | J88: Tier-2 (AOV <400) | K88: None | L88: 25 | M88: 20 | N88: 1 | O88: PVT | P88: Yes | Q88: Active | R88: No | S88: - | U88: Prabavathi | V88: 9381245681 | W88: - | AA88: No | AU88: Yes | AV88: Negotiation | AW88: Commisions | AX88: 46069 | AY88: 0.5 | AZ88: manasa.chigurupati@capsdelivery.com | BA88: Cold Walk-in | BB88: Yes | BR88: =Concatenate(BQ88,BP88,BO88,E88,T88) -> Mammu’s Kitchen
A89: 46062.606 | B89: 46062 | C89: 0.58958333 | D89: Intro Meeting | E89: Kshatriya Grand | F89: 60 | G89: 200 | H89: Na | I89: 20000 | J89: Tier-3 ( AOV<200 ) | K89: Swiggy, Zomato | L89: 22 | M89: 22 | N89: 1 | O89: Prop | P89: No | Q89: Active | R89: Yes | S89: https://maps.app.goo.gl/ZRjTitSxKuHU45Vv7?g_st=ic | U89: Karthik | V89: 9642431013 | W89: tkartheek.516@gmail.com | AA89: Yes | AB89: 23625032007840 | AC89: https://drive.google.com/open?id=1oKV_3cQoMNE-A5xCKoHVszsAgIot6crY | AF89: ANNPT1216H | AG89: https://drive.google.com/open?id=1dMfhXyQ5x-FzUs_VFgnZWPWGoRTr7BXk | AK89: https://drive.google.com/open?id=17gc3uKZwnSFjbItrX6qAUmzjxO6L0k0z | AL89: 3212110291 | AM89: KKBK0000560 | AN89: Kotak Mahindra Bank | AO89: Kartheek | AP89: 9642431013 | AS89: Yes | AT89: Onboarded | AU89: No | AZ89: ankitha.baske@capsdelivery.com | BA89: Cold Walk-in | BB89: Yes | BL89: 80 | BR89: =Concatenate(BQ89,BP89,BO89,E89,T89) -> Kshatriya Grand
A90: 46062.621 | B90: 46062 | C90: 0.58333333 | D90: Intro Meeting | E90: Bakeway bakers | F90: 10 | G90: 200 | H90: Not present | I90: 10000 | J90: Tier-3 ( AOV<200 ) | K90: Swiggy, Zomato | N90: 1 | O90: Partnership | P90: Yes | Q90: Active | R90: No | S90: https://maps.app.goo.gl/W2xHqpTu7pXfvcBD6 | U90: K Nagabhushan rao | V90: +91 85010 24577 | W90: bhushankottavalasa@gmail.com | AA90: Yes | AS90: Yes | AT90: Onboarding done | AU90: No | AV90: Contract Signing | AX90: 46062 | AY90: 0.58333333 | AZ90: sumadhur.mummadi@capsdelivery.com | BA90: Cold Walk-in | BB90: Yes | BL90: 20-30 | BR90: =Concatenate(BQ90,BP90,BO90,E90,T90) -> Bakeway bakers
A91: 46062.673 | B91: 46062 | C91: 0.64791667 | D91: Intro Meeting | E91: Golconda Biryani House | F91: 100 | G91: 250 | H91: NA | I91: 30000 | J91: Tier-3 ( AOV<200 ) | K91: Swiggy, Zomato, Magic Pin | L91: 15 | M91: 17 | N91: 1 | O91: Partnership | P91: No | Q91: Not Applied | R91: Not Applied | S91: https://maps.app.goo.gl/PmQrZ6A18zjb25S37?g_st=ic | U91: Prasad | V91: 9761859999 | W91: NA | AA91: No | AU91: Yes | AV91: Negotiation | AW91: We need to share the proposal | AZ91: ankitha.baske@capsdelivery.com | BA91: Cold Walk-in | BB91: Yes | BL91: 60 | BR91: =Concatenate(BQ91,BP91,BO91,E91,T91) -> Golconda Biryani House
A92: 46062.727 | B92: 46062 | C92: 0.70833333 | D92: Intro Meeting | E92: Veeramma Gari Vantillu | F92: 60 | G92: 200 | H92: PetPuja | I92: 6000 | J92: Tier-3 ( AOV<200 ) | K92: Swiggy, Zomato | L92: 19.7 | M92: 18.5 | N92: 1 | O92: Prop | P92: No | Q92: Active | R92: Yes | S92: NA | U92: Suryam | V92: 9849995653 | W92: veerammagarivantillu@gmail.com | AA92: Yes | AB92: 23625032006338 | AC92: https://drive.google.com/open?id=176ECpGpxZDmqD8I_vWbXX5K-YBZRlh3A | AF92: AKEPY8763E | AG92: https://drive.google.com/open?id=1_F3xmRV2zlRSNziROJSeDL0iKC_VNGZt | AH92: 36AKEPY8763E1ZL | AI92: https://drive.google.com/open?id=1yiMZ_9SQgNkHaFczbCDoGLcoQaoiMWqz | AK92: https://drive.google.com/open?id=1dKb9onDSn0QUhvFk10SsnWf6GzlGdEV2 | AL92: 44573150739 | AM92: SBIN0032241 | AN92: State Bank Of India | AO92: Suryam | AP92: 9849995653 | AQ92: veerammagarivantillu@gmail.com | AS92: Yes | AT92: Onboarded | AU92: No | AZ92: ankitha.baske@capsdelivery.com | BA92: Cold Walk-in | BB92: Yes | BL92: 25 | BR92: =Concatenate(BQ92,BP92,BO92,E92,T92) -> Veeramma Gari Vantillu
A93: 46062.92 | B93: 46062 | C93: 0.47916667 | D93: Intro Meeting | E93: Bhojanam Tayyari | F93: 120 | G93: 250 | H93: Pet Pooja | J93: Tier-2 (AOV <400) | K93: Swiggy, Zomato | L93: 25 | M93: 20 | N93: 1 | O93: Partnership | P93: Yes | Q93: Active | R93: Yes | S93: https://www.google.com/maps/dir//Bhojanam+Thali,+1200,+Rd+Number+59,+Jubilee+Hills,+Hyderabad,+Telangana+500033/@17.4358528,78.4072704,11z/data=!4m8!4m7!1m0!1m5!1m1!1s0x3bcb91ff414df91d:0xb3f0fa00e20c4e2d!2m2!1d78.4095133!2d17.4290901?entry=ttu&g_ep=EgoyMDI2MDIwNC4wIKXMDSoKLDEwMDc5MjA2OUgBUAM%3D | U93: Bhoojanam | V93: 7028412666 | W93: Yes | X93: Yes | Y93: 4785863578 | Z93: Yes | AA93: No | AU93: Yes | AV93: Meeting with different POC | AW93: asked for Propsal and Comission I have Pitched is 20++,need to call him tmrw eveng fro Scduling the meeting | AX93: 46063 | AY93: 0.27083333 | AZ93: akhila.narra@capsdelivery.com | BA93: Scheduled | BL93: 50 | BR93: =Concatenate(BQ93,BP93,BO93,E93,T93) -> Bhojanam Tayyari
A94: 46062.925 | B94: 46062 | C94: 0.0625 | D94: Follow up | T94: Mandi@36 | U94: Mandi@69 | V94: 9381522074 | W94: na | AA94: No | AU94: Yes | AV94: Introduction | AW94: Intro meeting need dicuss regarding Commision for all branches | AX94: 46063 | AY94: 0.14583333 | AZ94: akhila.narra@capsdelivery.com | BA94: Scheduled | BR94: =Concatenate(BQ94,BP94,BO94,E94,T94) -> Mandi@36
A95: 46062.927 | B95: 46062 | C95: 0.24305556 | U95: Prabath | V95: 9148628899 | W95: na | AA95: No | AU95: Yes | AV95: Document Collection | AW95: 20++ Comission we Sait it | AX95: 46064 | AY95: 0.1875 | AZ95: akhila.narra@capsdelivery.com | BA95: Cold Walk-in | BB95: No | BR95: =Concatenate(BQ95,BP95,BO95,E95,T95)
A96: 46063.394 | B96: 46063 | C96: 0.75 | D96: Intro Meeting | E96: CAFE REELS | F96: 25 | G96: 250 | H96: NA | I96: 10000 | J96: Tier-3 ( AOV<200 ) | K96: Swiggy, Zomato | L96: 22 | M96: 22 | N96: 1 | O96: Prop | P96: Yes | Q96: Active | R96: Yes | S96: YES | U96: NAVEEN REDDY | V96: 9676945646 | W96: NA | AA96: Yes | AB96: 23624032003894 | AC96: https://drive.google.com/open?id=1FPCiNB0YBRTLIUvuT9773zFtJI3rUXLv | AD96: 36AOWPN9130L1Z4 | AE96: https://drive.google.com/open?id=1lzn9VjNKeaCPDBh4aYrl3n_K7W9Qn8cy | AF96: AOWPN9130L | AG96: https://drive.google.com/open?id=1nTgwZ-m4rPslhVYuqeVe_nRrYljsedOK | AH96: AMEND202553969 | AI96: https://drive.google.com/open?id=1EZX1yqE9A9WyTNlB7ShJMB6qtXLxeZoC | AL96: NA | AS96: Yes | AT96: ON BOARDED | AU96: No | AV96: Introduction | AX96: 46062 | AY96: 0.70833333 | AZ96: chanakya.inugala@capsdelivery.com | BA96: Cold Walk-in | BB96: Yes | BH96: 22 | BJ96: 0.41666667 | BK96: 0.70833333 | BL96: 25 | BM96: SHOP PREMISES BEARING PLOT NO 86,KHANMET,AYYAPPA SOCIETY,RANGA REDDY DIST | BR96: =Concatenate(BQ96,BP96,BO96,E96,T96) -> CAFE REELS
A97: 46063.425 | B97: 46062 | C97: 0.70833333 | D97: Intro Meeting | E97: Veera di chaap | F97: 20 | G97: 200 | H97: n/a | J97: Tier-2 (AOV <400) | K97: Swiggy, Zomato | N97: 1 | O97: Prop | P97: No | Q97: Active | R97: No | S97: Shop 1, House 1-8-153/2, Ground Floor, Circle 29, PG Road, Secunderabad | U97: Karthik | V97: +91 78428 04422 | W97: n/a | AA97: No | AT97: need to get bank details,adhar card and pan card | AU97: No | AV97: Document Collection | AZ97: greeshma.vanneldas@capsdelivery.com | BA97: Scheduled | BR97: =Concatenate(BQ97,BP97,BO97,E97,T97) -> Veera di chaap
A98: 46063.432 | B98: 46062 | C98: 0.75 | D98: Follow up | T98: GODAVARI RESTAURANT | U98: SATYA | V98: +91 6281 845 369 | W98: NA | AA98: No | AU98: Yes | AV98: Contract Signing | AX98: 46063 | AY98: 0.54166667 | AZ98: moin.khan@capsdelivery.com | BA98: Cold Walk-in | BB98: Yes | BR98: =Concatenate(BQ98,BP98,BO98,E98,T98) -> GODAVARI RESTAURANT
A99: 46063.432 | B99: 46062 | C99: 0.70833333 | D99: Intro Meeting | E99: Donut O clock | F99: 10 | G99: 2000 | H99: n/a | J99: Tier-1(AOV>400) | K99: Swiggy, Zomato | N99: 8 | O99: Prop | P99: Yes | Q99: Active | R99: No | S99: 1-8-153⁄1, Ground Floor, Amaan Arcade, Circle 29, PG Road, Secunderabad | U99: Juhi Sanjay Sajnani | V99: 9133847766 | W99: frostbakeryindia@gmail.com | AA99: No | AT99: n/a | AU99: No | AZ99: greeshma.vanneldas@capsdelivery.com | BA99: Scheduled | BR99: =Concatenate(BQ99,BP99,BO99,E99,T99) -> Donut O clock
A100: 46063.433 | B100: 46062 | C100: 0.70833333 | D100: Intro Meeting | E100: kush mandi | F100: 30 | G100: 300 | H100: na | I100: 50000 | J100: Tier-2 (AOV <400) | K100: Swiggy, Zomato | L100: 22 | M100: 22 | N100: 1 | O100: Prop | P100: Yes | Q100: Active | R100: Yes | S100: yes | U100: NA | V100: 9908662728 | W100: NA | AA100: No | AU100: Yes | AV100: Document Collection | AX100: 46065 | AY100: 0.58333333 | AZ100: chanakya.inugala@capsdelivery.com | BA100: Cold Walk-in | BB100: Yes | BL100: 40 | BN100: 1 | BR100: =Concatenate(BQ100,BP100,BO100,E100,T100) -> kush mandi
A101: 46063.433 | B101: 46062 | C101: 0.75 | D101: Follow up | T101: LUCKY RESTAURANT | U101: KHASIM | V101: +91 98491 08337 | W101: NA | AA101: No | AU101: Yes | AV101: Contract Signing | AX101: 46064 | AY101: 0.85416667 | AZ101: moin.khan@capsdelivery.com | BA101: Scheduled | BR101: =Concatenate(BQ101,BP101,BO101,E101,T101) -> LUCKY RESTAURANT
A102: 46063.435 | B102: 46062 | C102: 0.70833333 | D102: Intro Meeting | E102: Tempt chocolates | F102: 10 | G102: 2000 | H102: n/a | J102: Tier-1(AOV>400) | K102: Swiggy, Zomato | N102: 8 | O102: Prop | P102: Yes | Q102: Active | R102: No | S102: 1-8-153⁄1, Ground Floor, Amaan Arcade, Circle 29, PG Road, Secunderabad | U102: Juhi Sanjay Sajnani | V102: 9133847766 | W102: frostbakeryindia@gmail.com | AA102: No | AT102: n/a | AU102: No | AZ102: greeshma.vanneldas@capsdelivery.com | BA102: Scheduled | BR102: =Concatenate(BQ102,BP102,BO102,E102,T102) -> Tempt chocolates
...

Sheet Follow ups

Sheet Detail19-Tier-1(AOV>400)
A1: Timestamp | B1: Date | C1: Time | D1: Type Of Meeting | E1: Restaurant Name Concat | F1: Seating Capacity | G1: AOV | H1: POS | I1: Daily Revenue? | J1: Kind of Restaurant | K1: Restaurant Live on | L1: Claimed Margins (Competition) | M1: Expected Margins (Caps) | N1: No.of Branches? | O1: Type of Ownership | P1: GST | Q1: FSSAI | R1: Labour License | S1: Google Map Business link | T1: Restaurant ID | U1: Name (POC-1) | V1: Contact Number (POC-1) | W1: Email- ID (POC-1) | X1: Name (POC-2) | Y1: Contact Number (POC-2) | Z1: Email- ID (POC-2) | AA1: Do you want to Submit Documents | AB1: FSSAI Number | AC1: FSSAI 2 | AD1: GST Number | AE1: GST 2 | AF1: PAN Number | AG1: PAN Card | AH1: Labour License Number | AI1: Labour License 2 | AJ1: Menu (Image) | AK1: Bank Account Proof | AL1: Account Number | AM1: IFSC | AN1: Name on Bank Account | AO1: Owner Name | AP1: Owner Contact Number | AQ1: Owner Email address | AR1: Legal Entity Name | AS1: Onboarding Done | AT1: Remarks(Comments) | AU1: Follow Up Meeting Required? | AV1: Meeting agenda for follow up | AW1: Points to be prepared | AX1: Meeting Date | AY1: Meeting Time | AZ1: Email address | BA1: Cold Walk/ Scheduled | BB1: POC Available | BC1: Manager Name | BD1: Manager Contact Details | BE1: Manager Email ID | BF1: Manager Contact Number | BG1: Manager Email ID 2 | BH1: Caps Magin % | BI1: Additional 2% Distance Margin | BJ1: Restaurant Open Time | BK1: Restaurant Close Time | BL1: Daily Online Orders | BM1: Restaurant Address | BN1: Cluster | BO1: Name of Restaurant Walk | BP1: Name of Restaurant | BQ1: Name of Ra
A2: 46059.334 | B2: 46058 | C2: 0.66666667 | D2: Intro Meeting | E2: Hamara Adda | F2: 30 | G2: 1 | H2: 1 | I2: 1 | J2: Tier-1(AOV>400) | K2: Swiggy, Zomato | N2: 1 | O2: Didnt meet the client,got the niumber of the owner | P2: Yes | Q2: Active | R2: Not Applied | S2: G-02, Ground Floor, Silicon Towers, Image Gardens Road, Madhapur, Hyderabad | U2: owner | V2: 8712220229 | W2: didnt received | AA2: No | AU2: Yes | AV2: To explain about our platform | AZ2: greeshma.vanneldas@capsdelivery.com
A3: 46059.426 | B3: 46175 | C3: 0.5625 | D3: Intro Meeting | E3: KNOX | F3: 200 | G3: 500 | H3: - | I3: 1 | J3: Tier-1(AOV>400) | K3: Swiggy, Zomato | L3: 22 | M3: 20 | N3: 1 | O3: Prop | P3: Yes | Q3: Active | R3: Yes | S3: NA | U3: Das | V3: 7842264138 | W3: - | AA3: No | AU3: Yes | AV3: Document Collection | AX3: 46059 | AY3: 0.5625 | AZ3: manasa.chigurupati@capsdelivery.com
A4: 46059.431 | B4: 46059 | C4: 0.60416667 | D4: Intro Meeting | E4: Zythum | F4: 300 | G4: 1000 | H4: - | I4: 1 | J4: Tier-1(AOV>400) | K4: Swiggy, Zomato | L4: 22 | M4: 20 | N4: 1 | O4: Prop | P4: Yes | Q4: Active | R4: No | S4: - | U4: Bhargav | V4: 8019447999 | W4: - | AA4: No | AU4: Yes | AV4: Document Collection | AZ4: manasa.chigurupati@capsdelivery.com
A5: 46059.542 | B5: 46059 | C5: 0.45486111 | D5: Intro Meeting | E5: Ohri's Cake Nation | F5: 150 | G5: 600 | H5: Brain power | I5: 15000 | J5: Tier-1(AOV>400) | K5: Swiggy, Zomato | L5: 17 | M5: 10 | N5: 11 | O5: Prop | P5: Yes | Q5: Active | R5: Yes | S5: na | U5: Ravi Kanth | V5: 6309794222 | W5: - | AA5: No | AU5: Yes | AV5: Document Collection | AW5: documents collection | AX5: 46069 | AY5: 0.45833333 | AZ5: manasa.chigurupati@capsdelivery.com
A6: 46059.586 | B6: 46059 | C6: 0.58333333 | D6: Intro Meeting | E6: KNOX | F6: 320 | G6: 450 | H6: pet pooja | I6: 20000 | J6: Tier-1(AOV>400) | K6: Swiggy, Zomato | L6: 20 | M6: 20 | N6: 1 | O6: Prop | P6: Yes | Q6: Active | R6: Yes | S6: - | U6: Jashwanth | V6: 9100007676 | W6: knowclubandkitchen@gmail.com | AA6: No | AU6: Yes | AV6: Document Collection | AW6: commissions & documents signs | AX6: 46064 | AY6: 0.39583333 | AZ6: manasa.chigurupati@capsdelivery.com
A7: 46059.667 | B7: 46059 | C7: 0.66666667 | D7: Intro Meeting | E7: Zythum | F7: 400 | G7: 500 | H7: explorates | I7: 100000 | J7: Tier-1(AOV>400) | K7: Swiggy, Zomato | L7: 20 | M7: 20 | N7: 1 | O7: PVT | P7: Yes | Q7: Active | R7: Yes | S7: - | U7: BHURDHABAN | V7: 8249132908 | W7: - | AA7: No | AU7: Yes | AV7: Negotiation | AW7: Commissions, documents collections, Competrtiors | AX7: 46063 | AY7: 0.70833333 | AZ7: manasa.chigurupati@capsdelivery.com
A8: 46063.526 | B8: 46063 | C8: 0.083333333 | D8: Intro Meeting | E8: Labond | F8: 150 | G8: 500 | H8: NA | I8: 23 | J8: Tier-1(AOV>400) | K8: Swiggy, Zomato | N8: 2 | O8: Partnership | P8: No | Q8: Active | R8: Yes | S8: NA | U8: Pasha | V8: 9032245891 | W8: na | AA8: No | AU8: Yes | AV8: Introduction | AW8: need to call him after 2 pm today | AX8: 46063 | AY8: 0.083333333 | AZ8: akhila.narra@capsdelivery.com | BA8: Cold Walk-in | BB8: Yes | BL8: NA | BN8: Jublii Hills
A9: 46063.528 | B9: 46063 | C9: 0.0625 | D9: Intro Meeting | E9: Chubby Chow | F9: 150 | G9: 500 | H9: na | I9: 23 | J9: Tier-1(AOV>400) | N9: 1 | O9: Prop | P9: Yes | Q9: Active | R9: Yes | S9: http | U9: Rajesh GM | V9: 6300797895 | W9: na | X9: na | AA9: No | AU9: Yes | AV9: Introduction | AW9: Intro meetng we Visted the Outelt Yesterday | AX9: 46064 | AY9: 0.52083333 | AZ9: akhila.narra@capsdelivery.com | BA9: Cold Walk-in | BB9: Yes | BL9: 25 | BN9: Jubliee hills
A10: 46063.602 | B10: 46063 | C10: 0.59722222 | D10: Intro Meeting | E10: Burma Burma | F10: 130 | G10: 1500 | H10: NA | J10: Tier-1(AOV>400) | K10: Swiggy, Zomato | N10: 1 | O10: NA | P10: No | Q10: Not Applied | R10: No | S10: NA | U10: Kajal | V10: 7977765789 | W10: NA | AA10: No | AU10: Yes | AV10: Introduction | AW10: We need to approach Marketing team | AZ10: ankitha.baske@capsdelivery.com | BA10: Cold Walk-in | BB10: Yes | BL10: 30-50
A11: 46063.687 | B11: 46063 | C11: 0.16666667 | D11: Intro Meeting | E11: president dhaba | F11: 250 | G11: 1000 | H11: na | J11: Tier-1(AOV>400) | K11: Swiggy, Zomato | L11: 18 | N11: 4 | O11: Prop | P11: Yes | Q11: Active | R11: Yes | S11: na | U11: vinod | V11: 7337001104 | W11: na | AA11: No | AU11: Yes | AV11: Introduction | AZ11: madhumitha.sonnakula@capsdelivery.com | BA11: Cold Walk-in | BB11: Yes | BN11: jubilee hills
A12: 46063.689 | B12: 46063 | C12: 0.1875 | D12: Intro Meeting | E12: my froyo land | F12: 25 | G12: 400 | H12: na | J12: Tier-1(AOV>400) | K12: Swiggy, Zomato | N12: 1 | O12: Prop | P12: Yes | Q12: Active | R12: Yes | S12: na | U12: kajal | V12: 9172541254 | W12: na | AA12: No | AU12: Yes | AV12: Introduction | AX12: 46064 | AY12: 0.5 | AZ12: madhumitha.sonnakula@capsdelivery.com | BA12: Cold Walk-in | BB12: Yes | BN12: jubilee hills
A13: 46063.707 | B13: 46063 | C13: 0.1875 | D13: Intro Meeting | E13: Rayalaseema Ruchulu | F13: 120 | G13: 600 | H13: Pet pooja | I13: 600000 | J13: Tier-1(AOV>400) | K13: Swiggy, Zomato, Magic Pin | L13: 15 | M13: 12 | N13: 4 | O13: Prop | P13: Yes | Q13: Active | R13: Yes | S13: - | U13: Rajini | V13: 9959020310 | W13: Info@rayalaseemaruchulu.com | AA13: No | AU13: Yes | AV13: Negotiation | AW13: Commisions | AZ13: manasa.chigurupati@capsdelivery.com | BA13: Scheduled | BN13: Hi tech city, lakdikapol, ameerpet, Jubilee hills
A14: 46063.713 | B14: 46063 | C14: 0.70833333 | D14: Intro Meeting | E14: Rayalaseema spice | F14: 80 | G14: 500 | H14: NA | J14: Tier-1(AOV>400) | K14: Swiggy, Zomato | N14: 1 | O14: NA | P14: No | Q14: Not Applied | R14: No | S14: NA | U14: Narsigin Rao | V14: 7075777491 | W14: NA | AA14: No | AU14: Yes | AV14: Introduction | AZ14: ankitha.baske@capsdelivery.com | BA14: Cold Walk-in | BB14: Yes
A15: 46063.716 | B15: 46063 | C15: 0.71388889 | D15: Intro Meeting | E15: Kake di hatti | F15: 120 | G15: 500 | H15: N/a | J15: Tier-1(AOV>400) | K15: Swiggy, Zomato | N15: 1 | O15: N/a | P15: Yes | Q15: Active | R15: No | S15: Na | U15: Prabhakar | V15: 9140523292 | W15: Na | AA15: No | AU15: Yes | AV15: Meeting with different POC | AW15: Owner will be available after 21:00Pm in the restaurant(Kondapur) | AZ15: greeshma.vanneldas@capsdelivery.com | BA15: Cold Walk-in | BB15: Yes
A16: 46063.727 | B16: 46063 | C16: 0.72569444 | D16: Intro Meeting | E16: Vaikuntapuram | F16: 60 | G16: 400 | H16: NA | J16: Tier-1(AOV>400) | K16: Swiggy, Zomato | N16: 1 | O16: NA | P16: Yes | Q16: Active | R16: Yes | S16: NA | U16: Venkatesh | V16: 9392857604 | W16: Na | AA16: No | AU16: Yes | AV16: Meeting with different POC | AW16: Manager will be available after 7 pm | AZ16: greeshma.vanneldas@capsdelivery.com | BA16: Cold Walk-in | BB16: Yes
A17: 46064.554 | B17: 46064 | C17: 0.54444444 | D17: Intro Meeting | E17: Namesthe | F17: 1 | G17: 500 | H17: NA | J17: Tier-1(AOV>400) | N17: 1 | O17: NA | P17: Yes | Q17: Active | R17: Yes | S17: NA | U17: Basawath | V17: 9052253253 | W17: Na | AA17: No | AU17: Yes | AV17: Meeting with different POC | AZ17: ankitha.baske@capsdelivery.com | BA17: Cold Walk-in | BB17: Yes
A18: 46064.909 | B18: 46053 | C18: 0.074305556 | D18: Intro Meeting | E18: fb bakers | F18: 10 | G18: 500 | H18: na | J18: Tier-1(AOV>400) | K18: Swiggy, Zomato | N18: 1 | O18: Prop | P18: Yes | Q18: Active | R18: Yes | S18: na | U18: ashok | V18: 8939369888 | W18: nA | AA18: No | AU18: Yes | AV18: Introduction | AZ18: madhumitha.sonnakula@capsdelivery.com | BA18: Cold Walk-in | BB18: Yes | BN18: mehandipatanam
A19: 46064.91 | B19: 46053 | C19: 0.10416667 | D19: Intro Meeting | E19: MAHARAJA | F19: 1 | G19: 600 | H19: NA | J19: Tier-1(AOV>400) | K19: Swiggy, Zomato | N19: 1 | O19: Prop | P19: Yes | Q19: Active | R19: Yes | S19: NA | U19: UMAR KHAN | V19: 9885199151 | W19: NA | AA19: No | AU19: Yes | AV19: Introduction | AZ19: madhumitha.sonnakula@capsdelivery.com | BA19: Cold Walk-in | BB19: Yes | BN19: MEHANDIPATANAM
A20: 46065.195 | B20: 46064 | C20: 0.66666667 | D20: Intro Meeting | E20: Aaha | F20: 50 | G20: 500 | H20: Na | I20: 50000 | J20: Tier-1(AOV>400) | K20: Swiggy, Zomato | L20: 22 | M20: 19 | N20: 2 | O20: Prop | P20: Yes | Q20: Active | R20: No | S20: Na | U20: Raju | V20: 8688995094 | W20: Na | AA20: No | AU20: Yes | AV20: Meeting with different POC | AX20: 46065 | AY20: 0.625 | AZ20: chanakya.inugala@capsdelivery.com | BA20: Cold Walk-in | BB20: Yes | BL20: 50 | BN20: Manikonda
A21: 46066.523 | B21: 46066 | C21: 0.52152778 | D21: Intro Meeting | E21: Patiala plate | F21: 60 | G21: 500 | H21: Na | J21: Tier-1(AOV>400) | K21: Swiggy, Zomato | N21: 1 | O21: Na | P21: Yes | Q21: Active | R21: Not Applied | S21: 5G Patiala Plate North Indian | U21: Jaffar | V21: 8319942382 | W21: Na | AA21: No | AU21: Yes | AV21: Introduction | AW21: Manager need to discuss with owner | AZ21: greeshma.vanneldas@capsdelivery.com | BA21: Cold Walk-in | BB21: Yes | BP21: Patiala plate
A22: 46066.561 | B22: 46066 | C22: 0.52083333 | D22: Intro Meeting | E22: The spicy venue | F22: 250 | G22: 500 | H22: Na | I22: 70000 | J22: Tier-1(AOV>400) | K22: Swiggy, Zomato | N22: 1 | O22: PVT | P22: Yes | Q22: Active | R22: Yes | S22: https://share.google/NGYbU0jsM5QQzbN2H | U22: Lead | V22: Lead | W22: Lead | AA22: No | AU22: Yes | AV22: Meeting with different POC | AZ22: parthive.maganti@capsdelivery.com | BA22: Scheduled | BN22: Na | BP22: The spicy venue
A23: 46066.563 | B23: 46066 | C23: 0.54166667 | D23: Intro Meeting | E23: Sri Kanya comfort | F23: 200 | G23: 500 | H23: Na | I23: 80000 | J23: Tier-1(AOV>400) | K23: Swiggy, Zomato | N23: 1 | O23: Prop | P23: Yes | Q23: Active | R23: No | S23: https://share.google/Rak1DxkX5m16fu3uV | U23: Lead murali | V23: Lead | W23: Lead | AA23: No | AU23: Yes | AV23: Negotiation | AZ23: parthive.maganti@capsdelivery.com | BA23: Scheduled | BL23: 100 | BP23: Sri Kanya comfort
A24: 46066.566 | B24: 46066 | C24: 0.54166667 | D24: Intro Meeting | E24: Itihaas Restaurant and Banquets | F24: 500 | G24: 500 | H24: Na | I24: 80000 | J24: Tier-1(AOV>400) | K24: Swiggy, Zomato | N24: 1 | O24: Partnership | P24: Yes | Q24: Active | R24: Yes | S24: https://share.google/CHy1tdi4IZ9qchmkI | U24: Lead murali | V24: Lead | W24: lead | AA24: No | AU24: Yes | AV24: Negotiation | AZ24: parthive.maganti@capsdelivery.com | BA24: Scheduled | BL24: 80 | BN24: Na | BP24: Itihaas Restaurant and Banquets
A25: 46066.569 | B25: 46066 | C25: 0.52083333 | D25: Intro Meeting | E25: Gumagumalu | F25: 150 | G25: 350 | H25: Na | J25: Tier-1(AOV>400) | K25: Swiggy, Zomato | N25: 1 | O25: Partnership | P25: Yes | Q25: Active | R25: Yes | S25: https://share.google/M0vWSrt6a1iawTVxb | U25: Lead | V25: Lead | W25: lead | X25: lead | AA25: No | AU25: Yes | AW25: Na | AX25: 46067 | AY25: 0.5 | AZ25: parthive.maganti@capsdelivery.com | BA25: Scheduled | BP25: Gumagumalu
A26: 46066.696 | B26: 46066 | C26: 0.10416667 | D26: Intro Meeting | E26: Kadali kitchen | F26: 90 | G26: 900 | H26: Pet poja | J26: Tier-1(AOV>400) | K26: Swiggy, Zomato | N26: 1 | O26: PVT | P26: Yes | Q26: Active | R26: No | S26: https://maps.google.com/maps/place//data=!4m2!3m1!1s0x3bcb974d964ebe25:0xece3580d587566f?entry=s&sa=X&ved=2ahUKEwjugt--qtaSAxV3TGwGHaIQFDYQ4kB6BAgXEAA&hl=en | U26: Rohan | V26: 9989649223 | W26: Ahsth | AA26: No | AU26: Yes | AV26: Meeting with different POC | AW26: 19++ | AX26: 46069 | AY26: 0.10416667 | AZ26: akhila.narra@capsdelivery.com | BA26: Scheduled | BN26: Jubliee Hills | BP26: Kadali kitchen
A27: 46066.706 | B27: 46066 | C27: 0.20138889 | D27: Intro Meeting | E27: Hyderabad wala | F27: 120 | G27: 500 | H27: Pet pooja | J27: Tier-1(AOV>400) | K27: Swiggy, Zomato | N27: 1 | O27: PVT, Prop | P27: Yes | Q27: Active | R27: Yes | S27: http | U27: Hyder | V27: 8886741212 | W27: Na | AA27: No | AU27: Yes | AV27: Meeting with different POC | AZ27: akhila.narra@capsdelivery.com | BA27: Scheduled | BN27: Banjara hills | BP27: Hyderabad wala
A28: 46069.806 | B28: 46069 | C28: 0.75 | D28: Intro Meeting | E28: Hard Rock CafeHard Rock Cafe | F28: 80 | G28: 800 | H28: Urban Piper | J28: Tier-1(AOV>400) | K28: Swiggy, Zomato | N28: 3 | O28: PVT | P28: Yes | Q28: Active | R28: Not Applied | S28: https://share.google/Dw0aunpNz3KYzSitm | T28: Hard Rock Cafe | U28: T Naveen Kumar | V28: 9985287122 | W28: om.hrchyd@jsmcorp.in | AA28: No | AT28: Asked to share the proposal over the email | AU28: Yes | AV28: Introduction | AX28: 46070 | AZ28: manisha.kumari@capsdelivery.com | BA28: Cold Walk-in | BB28: Yes | BP28: Hard Rock Cafe
A29: 46070.385 | B29: 46070 | C29: 0.27083333 | D29: Intro Meeting | E29: Tiffins and more | F29: 80 | G29: 900 | H29: Pet Pooja | J29: Tier-1(AOV>400) | K29: Swiggy, Zomato | N29: 1 | O29: Prop | P29: Yes | Q29: Active | R29: Yes | S29: http | U29: Arun | V29: 99855 59905 | W29: Na | AA29: No | AT29: Na | AU29: Yes | AV29: Meeting with different POC | AX29: 46072 | AY29: 0.10416667 | AZ29: akhila.narra@capsdelivery.com | BA29: Cold Walk-in | BB29: Yes | BN29: Jubliee Hills | BP29: Tiffins and more
A30: 46070.51 | B30: 46069 | C30: 0.54513889 | D30: Intro Meeting | E30: Cafe Delhi Heights | F30: 98 | G30: 600 | H30: Na | I30: 7200 | J30: Tier-1(AOV>400) | K30: Swiggy, Zomato, Magic Pin | N30: 52 | O30: PVT | P30: Yes | Q30: Active | R30: No | S30: https://www.google.com/maps?gs_lcrp=EgZjaHJvbWUqDQgBEC4YrwEYxwEYgAQyCggAEEUYFhgeGDkyDQgBEC4YrwEYxwEYgAQyBwgCEAAYgAQyBwgDEAAYgAQyBwgEEAAYgAQyCAgFEAAYFhgeMggIBhAAGBYYHjIICAcQABgWGB4yCAgIEAAYFhge0gEJMTc0OTdqMGo3qAIIsAIB8QVsLCl7Jib_JQ&um=1&ie=UTF-8&fb=1&gl=in&sa=X&geocode=KRnXhiy4kcs7MRTcZ3ygvDfN&daddr=Shop+No.+S-16,+Second+Floor,+Level+4,+Inorbit+Mall+Mindspace,+Cyberabad,+Madhapur,+Hyderabad,+Telangana+500081 | U30: Kishan Negi (Head Office POC) | V30: 9818808004 | W30: NA | X30: Rajan (Asst. Rest. Manager) | Y30: 9281054033 | Z30: NA | AA30: No | AT30: Call Mr. Kishan | AU30: Yes | AV30: Negotiation | AW30: Call Mr. Kishan | AX30: 46071 | AY30: 0.75 | AZ30: amit.kaler@capsdelivery.com | BA30: Cold Walk-in | BB30: Yes | BL30: 10 | BN30: Hi-tech city | BP30: Cafe Delhi Heights
A31: 46070.516 | B31: 46069 | C31: 0.54166667 | D31: Intro Meeting | E31: Chutnety's | F31: 150 | G31: 650 | H31: Na | I31: 500000 | J31: Tier-1(AOV>400) | K31: Swiggy, Zomato, Magic Pin | N31: 7 | O31: PVT | P31: Yes | Q31: Active | R31: No | S31: https://www.google.com/maps?sca_esv=d6eb6bac57f34326&sxsrf=ANbL-n4B5OSWpuRwcNbMRnTof1uYTLjeBg:1771311097540&biw=1470&bih=723&uact=5&gs_lp=Egxnd3Mtd2l6LXNlcnAiFWNodXRuZXlzIGlub3JiaXQgbWFsbDILEC4YgAQYxwEYrwEyBRAAGIAEMgYQABgHGB4yBBAAGB4yBBAAGB4yAhAmMgIQJjILEAAYgAQYhgMYigUyCxAAGIAEGIYDGIoFMgUQABjvBTIaEC4YgAQYxwEYrwEYlwUY3AQY3gQY4ATYAQFInwlQAFivB3AAeAGQAQCYAX6gAfgGqgEDMy41uAEDyAEA-AEBmAIGoALYBcICDRAuGIAEGMcBGA0YrwHCAgcQABiABBgNwgIcEC4YgAQYxwEYDRivARiXBRjcBBjeBBjgBNgBAZgDALoGBggBEAEYFJIHAzEuNaAHz0WyBwMxLjW4B9gFwgcFMi00LjLIByWACAA&um=1&ie=UTF-8&fb=1&gl=in&sa=X&geocode=KcOruzNYkcs7MWMzMvunEor6&daddr=Inorbit+Mall+Rd,+Mind+Space,+Vittal+Rao+Nagar,+HITEC+City,+Hyderabad,+Telangana+500081 | U31: Gaffar Khan | V31: 7893734731 | W31: Na | AA31: No | AT31: Call Mr. Gaffar and meet him at 5 pm at Jubliee Hills office | AU31: Yes | AV31: Introduction | AW31: Call and meet Mr. Gaffar | AX31: 46070 | AY31: 0.70833333 | AZ31: amit.kaler@capsdelivery.com | BA31: Cold Walk-in | BB31: Yes | BN31: Hi-Tech City | BP31: Chutnety's
A32: 46070.524 | B32: 46069 | C32: 0.58333333 | D32: Intro Meeting | E32: Foo | F32: 140 | G32: 1500 | H32: NA | I32: 1 | J32: Tier-1(AOV>400) | K32: Swiggy, Zomato | L32: 1 | N32: 2 | O32: PVT | P32: Yes | Q32: Active | R32: Yes | S32: https://www.google.com/maps?sca_esv=d6eb6bac57f34326&sxsrf=ANbL-n4yy65I9ZopH6s6emlSjdlh6FYi8g:1771311529307&biw=1470&bih=723&uact=5&gs_lp=Egxnd3Mtd2l6LXNlcnAiEGZvbyBpbm9yYml0IG1hbGwyCxAuGIAEGMcBGK8BMgUQABiABDIGEAAYBxgeMgYQABgHGB4yBhAAGAcYHjIEEAAYHjILEAAYgAQYhgMYigUyCxAAGIAEGIYDGIoFMgsQABiABBiGAxiKBTILEAAYgAQYhgMYigUyGhAuGIAEGMcBGK8BGJcFGNwEGN4EGOAE2AEBSMEFUABY2ANwAHgBkAEAmAGZAaABlgSqAQMwLjS4AQPIAQD4AQGYAgOgAqoDwgIKEAAYgAQYsQMYDcICExAuGIAEGLEDGMcBGA0YjgUYrwHCAgcQABiABBgNwgIQEC4YgAQYxwEYDRiOBRivAZgDAOIDBRIBMSBAugYGCAEQARgUkgcDMC4zoAeUOrIHAzAuM7gHqgPCBwUyLTIuMcgHEoAIAA&um=1&ie=UTF-8&fb=1&gl=in&sa=X&geocode=KUP5SZoUkcs7MTS3fLj-rgKR&daddr=Level+4,+Inorbit+Mall+Cyberabad,+APIIC+Software+Layout,+Madhapur,+Hyderabad,+Telangana+500081 | U32: Prajitesh (GM) | V32: 7030998709 | W32: NA | X32: Amitava (Entry Manager) | Y32: 9832874225 | AA32: No | AT32: Call Mr. Prajitesh | AU32: Yes | AV32: Introduction | AW32: Call Mr. Prajitesh | AX32: 46071 | AY32: 0.70833333 | AZ32: amit.kaler@capsdelivery.com | BA32: Cold Walk-in | BB32: Yes | BL32: NA | BN32: Hi-Tech City | BP32: Foo
A33: 46070.526 | B33: 46069 | C33: 0.58333333 | D33: Intro Meeting | E33: Popoyes | F33: 1 | G33: 400 | H33: POSBANK | I33: 120000 | J33: Tier-1(AOV>400) | K33: Swiggy, Zomato | N33: 5 | O33: PVT | P33: Yes | Q33: Active | R33: Yes | S33: https://www.google.com/maps?gs_lcrp=EgZjaHJvbWUyBggAEEUYOTIPCAEQLhgNGK8BGMcBGIAEMgkIAhAAGA0YgAQyCQgDEAAYDRiABDIJCAQQABgNGIAEMggIBRAAGBYYHjIICAYQABgWGB4yCAgHEAAYFhgeMggICBAAGBYYHtIBCDgwMDdqMGo0qAIAsAIA&um=1&ie=UTF-8&fb=1&gl=in&sa=X&geocode=KR1HXg5tkcs7MdTqStPsyZvd&daddr=64,+Inorbit+Mall+Rd,+APIIC+Software+Layout,+Madhapur,+Hyderabad,+Telangana+500081 | U33: Mahender (Area Manager) | V33: 9663743265 | W33: NA | X33: Raju Samba | AA33: No | AT33: Call Mr. Mahendra | AU33: Yes | AV33: Introduction | AW33: Call Mr. Mahendra | AX33: 46071 | AY33: 0.58333333 | AZ33: amit.kaler@capsdelivery.com | BA33: Cold Walk-in | BB33: Yes | BL33: 200 | BN33: Hi-Tech City | BP33: Popoyes
A34: 46070.534 | B34: 46069 | C34: 0.58333333 | D34: Intro Meeting | E34: California Burrito | F34: 1 | G34: 300 | H34: NA | I34: 90000 | J34: Tier-1(AOV>400) | K34: Swiggy, Zomato | N34: 33 | O34: PVT | P34: Yes | Q34: Active | R34: Yes | S34: https://www.google.com/maps?gs_lcrp=EgZjaHJvbWUqBwgBECEYoAEyBggAEEUYOTIHCAEQIRigATIHCAIQIRigATIHCAMQIRigATIHCAQQIRigATIHCAUQIRiPAjIHCAYQIRiPAtIBCTE0Mzk2ajBqNKgCALACAA&um=1&ie=UTF-8&fb=1&gl=in&sa=X&geocode=KY0d_WHukcs7Mdgo-dk7ysUX&daddr=L4,+Inorbit+Mall,+Inorbit+Mall+Rd,+Mind+Space,+Kavuri+Hills,+Madhapur,+Hyderabad,+Telangana+500081 | U34: Mr. Amar (Area Manager) | V34: 7002773847 | W34: NA | X34: Charanjit (Shift Manager) | AA34: No | AT34: No food deliveries on Inorbit location due to high demand and small kitchen need to approach for different locations | AU34: Yes | AV34: Introduction | AW34: Call Mr Amar | AX34: 46071 | AY34: 0.54166667 | AZ34: amit.kaler@capsdelivery.com | BA34: Cold Walk-in | BB34: Yes | BL34: 300 | BN34: Hi-Tech City | BP34: California Burrito
A35: 46070.537 | B35: 46069 | C35: 0.54166667 | D35: Intro Meeting | E35: KFC Inorbit Mall | F35: 1 | G35: 500 | H35: NA | I35: 1 | J35: Tier-1(AOV>400) | K35: Swiggy, Zomato | N35: 30 | O35: PVT | P35: Yes | Q35: Active | R35: Yes | S35: https://www.google.com/maps?gs_lcrp=EgZjaHJvbWUyBggAEEUYOTISCAEQLhgNGK8BGMcBGIAEGI4FMgkIAhAAGA0YgAQyCQgDEAAYDRiABDIJCAQQABgNGIAEMgkIBRAAGA0YgAQyCAgGEAAYFhgeMggIBxAAGBYYHjIICAgQABgWGB7SAQgzODUwajBqNKgCALACAA&um=1&ie=UTF-8&fb=1&gl=in&sa=X&geocode=KRmtG-nNk8s7MY6SesYBMWDP&daddr=64,+APIIC+Software+Layout,+Inorbit+Mall+F+%26+B+14B,+Hi+Tech+City,+Madhapur,+Hyderabad,+Telangana+500081 | U35: KSN Murthi (Delivery Manager) | V35: 9398596919 | W35: NA | X35: Ravi Teja (Area Manager) | Y35: 7416690785 | Z35: NA | AA35: No | AT35: KFC coming up with their own delivery app have own delivery partners and third party tie ups for peaks. Need to connect with delivery manager | AU35: Yes | AV35: Introduction | AW35: Call Mr. KSN Murhi | AX35: 46071 | AY35: 0.58333333 | AZ35: amit.kaler@capsdelivery.com | BA35: Cold Walk-in | BB35: Yes | BL35: 1 | BN35: Hi-Tech City | BP35: KFC Inorbit Mall
A36: 46070.542 | B36: 46069 | C36: 0.58333333 | D36: Intro Meeting | E36: Gabru Di Chaap | F36: 1 | G36: 600 | H36: Pet Pooja | I36: 24000 | J36: Tier-1(AOV>400) | K36: Swiggy, Zomato | N36: 9 | O36: PVT | P36: Yes | Q36: Active | R36: Yes | S36: https://www.google.com/maps?sca_esv=d6eb6bac57f34326&sxsrf=ANbL-n7BVT6m7RNWJrGmzVXHAzXMfEDB9w:1771313119547&biw=1470&bih=723&gs_lp=Egxnd3Mtd2l6LXNlcnAiEWdhYnJ1IGRpIGNoYWFwIEluKgIIADILEC4YgAQYxwEYrwEyCxAuGIAEGMcBGK8BMgUQABiABDIFEAAYgAQyBRAAGIAEMgsQLhiABBjHARivATIFEAAYgAQyBRAAGIAEMgYQABgWGB4yBhAAGBYYHjIaEC4YgAQYxwEYrwEYlwUY3AQY3gQY4ATYAQFIzUdQ9gFY-TtwAXgBkAEAmAGUAaABmQOqAQMwLjO4AQPIAQD4AQGYAgWgAtEOwgIKEAAYsAMY1gQYR8ICDRAAGLADGNYEGEcYyQPCAhAQABiABBiwAxiSAxhDGIoFwgIOEAAYgAQYsAMYkgMYigXCAg0QABiABBiwAxhDGIoFwgITEC4YgAQYsAMYQxjIAxiKBdgBAcICHBAuGIAEGLADGEMYxwEYyAMYigUYjgUYrwHYAQHCAhkQLhiABBiwAxjRAxhDGMcBGMgDGIoF2AEBwgIZEC4YgAQYsAMYQxjHARjIAxiKBRivAdgBAcICDhAAGLADGOQCGNYE2AEBwgIKEAAYgAQYQxiKBcICDRAAGIAEGEMYyQMYigXCAggQABiABBiSA8ICDhAuGIAEGMcBGI4FGK8BmAMAiAYBkAYTugYGCAEQARgIkgcHMS4zLjctMaAHkTGyBwMwLjO4B7MDwgcHMC4xLjMuMcgHF4AIAA&um=1&ie=UTF-8&fb=1&gl=in&sa=X&geocode=Kf__jy5Ykcs7MUbczbUEhGV-&daddr=Inorbit+mall,+Food+court,+Mindspace,+HUDA+Techno+Enclave,+HITEC+City,+Hyderabad,+Telangana+500081 | U36: Umar (Area Manager) (Generally Available at Sarascity Mall) | V36: 8374972864 | W36: NA | AA36: No | AT36: Call Mr. Umar | AU36: Yes | AV36: Introduction | AW36: Call Mr. Umar | AX36: 46071 | AY36: 0.58333333 | AZ36: amit.kaler@capsdelivery.com | BA36: Cold Walk-in | BB36: Yes | BL36: 40 | BN36: Hi-Tech City | BP36: Gabru Di Chaap
A37: 46070.549 | B37: 46069 | C37: 0.58333333 | D37: Intro Meeting | E37: AM AHA | F37: 130 | G37: 1200 | H37: NA | J37: Tier-1(AOV>400) | K37: Swiggy, Zomato | N37: 1 | O37: PVT | P37: Yes | Q37: Active | R37: Yes | S37: https://www.google.com/maps?sca_esv=d6eb6bac57f34326&sxsrf=ANbL-n6zMXS_xjfTwnoF_9GIZIWGUolzMg:1771313953825&biw=1470&bih=723&uact=5&gs_lp=Egxnd3Mtd2l6LXNlcnAiD2FtIGFoYSBpbiBvcmJpdDICECYyBRAAGO8FMgUQABjvBTIFEAAY7wUyCBAAGIAEGKIEMgUQABjvBUj7B1CvA1jEBnABeACQAQCYAaIBoAGiA6oBAzAuM7gBA8gBAPgBAZgCBKACtgPCAhAQLhiABBiwAxjHARgNGK8BwgIJEAAYsAMYDRgewgILEAAYsAMYBRgNGB7CAg0QABiwAxgFGAoYDRgewgILEAAYsAMYCBgNGB7CAgYQABgNGB6YAwCIBgGQBgeSBwMxLjOgB8QOsgcDMC4zuAexA8IHBTAuMS4zyAcMgAgA&um=1&ie=UTF-8&fb=1&gl=in&sa=X&geocode=KfVTvJL4kcs7MRjkfwJO-CAP&daddr=4th+Floor,+64,+Inorbit+Mall+Rd,+APIIC+Software+Layout,+Madhapur,+Hyderabad,+Telangana+500081 | U37: Mr. Laxman | V37: 7093369917 | W37: Na | X37: reference given by Miss Sandhya | AA37: No | AT37: Call Mr. Laxman | AU37: Yes | AV37: Introduction | AW37: Call Mr. Laxman | AX37: 46071 | AY37: 0.5 | AZ37: amit.kaler@capsdelivery.com | BA37: Cold Walk-in | BB37: Yes | BN37: Hi-Tech City | BP37: AM AHA
A38: 46070.552 | B38: 46069 | C38: 0.5 | D38: Intro Meeting | E38: Amnesia Sky Bar | F38: 700 | G38: 550 | H38: Breeza (Exporex) | J38: Tier-1(AOV>400) | K38: Swiggy, Zomato | N38: 1 | O38: PVT | P38: Yes | Q38: Active | R38: Yes | S38: https://www.google.com/maps?um=1&ie=UTF-8&fb=1&gl=in&sa=X&geocode=KUF8vUYlkcs7MS0rNCnlKQ5i&daddr=103,+104,+5th+Floor,+Inorbit+Mall,+Software+Units+Layout,+Madhapur,+Hyderabad,+Telangana+500081 | U38: Mr. Pasha | V38: 7731019977 | W38: NA | X38: Mr. Sahoo | Y38: 7731019988 | AA38: No | AT38: Meet after calling Mr. Pasha | AU38: Yes | AV38: Introduction | AW38: Meet Mr, Pasha post 4 pm on Wednesday | AX38: 46071 | AY38: 0.66666667 | AZ38: amit.kaler@capsdelivery.com | BA38: Cold Walk-in | BB38: Yes | BN38: Hi-Tech City | BP38: Amnesia Sky Bar
A39: 46070.556 | B39: 46069 | C39: 0.58333333 | D39: Intro Meeting | E39: Absolute Barbeque | F39: 150 | G39: 1200 | H39: In House | J39: Tier-1(AOV>400) | K39: Swiggy, Zomato | N39: 14 | O39: PVT | P39: Yes | Q39: Active | R39: Yes | S39: https://www.google.com/maps?sca_esv=d6eb6bac57f34326&biw=1470&bih=723&sxsrf=ANbL-n68xkf7rupxCnfQJmGSVa9MS1buSQ:1771314459815&gs_lp=Egxnd3Mtd2l6LXNlcnAiFmFic29sdXRlIGJhcmJlY3VlIGlub3IqAggAMgsQLhiABBjHARivATILEAAYgAQYkQIYigUyBRAAGIAEMgYQABgWGB4yBhAAGBYYHjIGEAAYFhgeMgYQABgWGB4yBhAAGBYYHjIGEAAYFhgeMgIQJjIaEC4YgAQYxwEYrwEYlwUY3AQY3gQY4ATYAQFIzDJQtQRYyidwBHgBkAEAmAG0AaABggmqAQMwLji4AQPIAQD4AQGYAgygAtsJwgIKEAAYsAMY1gQYR8ICDRAAGIAEGLADGEMYigXCAg4QABiwAxjkAhjWBNgBAcICGRAuGIAEGLADGNEDGEMYxwEYyAMYigXYAQHCAhkQLhiABBiwAxhDGMcBGMgDGIoFGK8B2AEBwgIKEAAYgAQYQxiKBcICDhAuGIAEGMcBGI4FGK8BwgIREC4YgAQYkQIYxwEYigUYrwHCAiAQLhiABBiRAhjHARiKBRivARiXBRjcBBjeBBjgBNgBAcICBRAhGKABwgINEC4YgAQYxwEYDRivAcICBxAAGIAEGA3CAggQABgIGA0YHsICCxAAGIAEGIYDGIoFwgIFEAAY7wXCAhwQLhiABBjHARgNGK8BGJcFGNwEGN4EGOAE2AEBmAMAiAYBkAYTugYGCAEQARgJkgcDNC44oAeugAGyBwMwLji4B7wJwgcHMS4wLjkuMsgHQ4AIAA&um=1&ie=UTF-8&fb=1&gl=in&sa=X&geocode=KUUVztpJkcs7MSEwyK3fMx0Z&daddr=T-02+fifth+floor,+Inorbit+Mall,+Software+Units+Layout,+Madhapur,+Hyderabad,+Telangana+500081 | U39: Mr. Suraj (Territory Manager) | V39: 9907958581 | W39: NA | X39: Kabir (Shift Manager) | Y39: 9121165812 | AA39: No | AT39: Doing 12-13 L daily revenue over all branches with Swiggy and Zomato. Maximum sale is of Combo Box : AOV 1200. Ala carte 500 | AU39: Yes | AV39: Introduction | AW39: Call Mr. Suraj | AX39: 46071 | AY39: 0.58333333 | AZ39: amit.kaler@capsdelivery.com | BA39: Cold Walk-in | BB39: Yes | BN39: Hi-Tech City | BP39: Absolute Barbeque
A40: 46070.561 | B40: 46069 | C40: 0.58333333 | D40: Intro Meeting | E40: Game Palacio | F40: 230 | G40: 1500 | H40: Na | J40: Tier-1(AOV>400) | K40: None | N40: 19 | O40: PVT | P40: Yes | Q40: Active | R40: Yes | S40: https://www.google.com/maps/dir//The+Game+Palacio,+Level+5,+Inorbit+Mall+Rd,+near+PVR+Cinema,+Software+Units+Layout,+HITEC+City,+Hyderabad,+Telangana+500081/@17.4391296,78.4859136,15z/data=!4m8!4m7!1m0!1m5!1m1!1s0x3bcb91b9b901e80d:0x5aebc4a84f5dfbba!2m2!1d78.3872005!2d17.4350874?entry=ttu&g_ep=EgoyMDI2MDIxMS4wIKXMDSoASAFQAw%3D%3D | U40: Mr. Reeshav (Business Head) | V40: 9867122223 | W40: reeshav@pjhindia.com | X40: Mr. Jeet | Y40: 8099420329 | AA40: No | AT40: Not available on Swiggy and Zomato looking for onboarding on online delivery platform, 19 outlets Pan India . Mr. Reeshav is the Business Head handle lead with care | AU40: Yes | AV40: Introduction | AW40: Message Mr. Reeshav get appointment, share proposal on Email | AX40: 46071 | AY40: 0.58333333 | AZ40: amit.kaler@capsdelivery.com | BA40: Cold Walk-in | BB40: Yes | BN40: Hi-Tech City | BP40: Game Palacio
A41: 46070.566 | B41: 46070 | C41: 0.51458333 | D41: Intro Meeting | E41: HaldiramsHaldirams | F41: 60 | G41: 500 | H41: NA | J41: Tier-1(AOV>400) | N41: 1 | O41: Prop | P41: Yes | Q41: Active | R41: Not Applied | S41: http// | T41: Haldirams | U41: Sumit bajaj | V41: 8668045147 | W41: sumit.bajaj@haldirams.com | AA41: No | AT41: Asked to share an email AOV - 500 Seating capacity 60 Location- begumpet | AU41: Yes | AV41: Introduction | AZ41: manisha.kumari@capsdelivery.com | BA41: Cold Walk-in | BB41: Yes | BN41: Haldirams | BP41: Haldirams
A42: 46070.574 | B42: 46070 | C42: 0.51944444 | D42: Intro Meeting | E42: Almond HouseAlmond House | F42: 40 | G42: 450 | H42: NA | J42: Tier-1(AOV>400) | N42: 1 | O42: Prop | P42: Yes | Q42: Active | R42: Yes | S42: http// | T42: Almond House | U42: Dinesh | V42: 9967535945 | W42: NA | AA42: No | AT42: Dinesh Sits in Kukatpally branch Asked to share the proposal on email. He will be sharing his email ID shortly | AU42: Yes | AV42: Introduction | AZ42: manisha.kumari@capsdelivery.com | BA42: Cold Walk-in | BB42: Yes | BN42: Almond House | BP42: Almond House
A43: 46070.588 | B43: 46070 | C43: 0.52430556 | D43: Intro Meeting | E43: MezbaanMezbaan | F43: 40 | G43: 500 | H43: NA | J43: Tier-1(AOV>400) | N43: 1 | O43: Prop | P43: Yes | Q43: Active | R43: Yes | S43: http// | T43: Mezbaan | U43: gopal | V43: 9100009426 | W43: NA | AA43: No | AT43: Owner not available today as he is busy in court case. POC will give me a call tomorrow once the owner comes | AU43: Yes | AV43: Introduction | AZ43: manisha.kumari@capsdelivery.com | BA43: Cold Walk-in | BB43: Yes | BN43: Mezbaan | BP43: Mezbaan
A44: 46070.644 | B44: 46070 | C44: 0.058333333 | D44: Intro Meeting | E44: Karachi BakeryKarachi Bakery | F44: 1 | G44: 500 | H44: NA | J44: Tier-1(AOV>400) | N44: 1 | O44: Prop | P44: Yes | Q44: Active | R44: Not Applied | S44: http// | T44: Karachi Bakery | U44: Saif | V44: 7032888705 | W44: Online@karachibakery | AA44: No | AT44: Receptionist asked to visit banjara hills branch as the main POC will be available there | AU44: Yes | AV44: Introduction | AZ44: manisha.kumari@capsdelivery.com | BA44: Cold Walk-in | BB44: Yes | BN44: Karachi Bakery | BP44: Karachi Bakery
A45: 46071.407 | B45: 46070 | C45: 0.625 | D45: Intro Meeting | E45: Mayabazar | F45: 50 | G45: 400 | H45: na | J45: Tier-1(AOV>400) | K45: Zomato | N45: 1 | O45: Partnership | P45: Yes | Q45: Active | R45: Not Applied | S45: Address: Villa 05, Wonder Cherish Villas, Masjid Banda, Telangana 500084 | U45: Triven | V45: 7330991470 | W45: na | AA45: No | AT45: Discussion done with manager,appointment fixed Md tomorrow | AU45: Yes | AV45: Meeting with different POC | AZ45: greeshma.vanneldas@capsdelivery.com | BA45: Cold Walk-in | BB45: Yes | BP45: Mayabazar
A46: 46071.484 | B46: 46071 | C46: 0.47986111 | D46: Intro Meeting | E46: Le Meridien HyderabadLe Meridian | F46: 120 | G46: 1200 | H46: MICROS | I46: 100000 | J46: Tier-1(AOV>400) | K46: Swiggy, Zomato | N46: 4 | O46: PVT | P46: Yes | Q46: Active | R46: Yes | S46: https://share.google/ONj2n2GaI20X3tFea | T46: Le Meridian | U46: Sanjeev Mandal | V46: 733 883 6300 | W46: sanjeev.mandal@marriott.com | AA46: No | AT46: Asked to share the proposal over the email | AU46: Yes | AV46: Introduction | AZ46: manisha.kumari@capsdelivery.com | BA46: Cold Walk-in | BB46: Yes | BL46: 85 | BN46: Le Meridien Hyderabad | BP46: Le Meridien Hyderabad
A47: 46071.649 | B47: 46071 | C47: 0.64236111 | D47: Intro Meeting | E47: ACCORAccor | F47: 200 | G47: 3000 | H47: MICROS | J47: Tier-1(AOV>400) | K47: Swiggy, Zomato | N47: 1 | O47: PVT | P47: Yes | Q47: Active | R47: Yes | S47: http// | T47: Accor | U47: Gyandeep Singh | V47: 88863 31102 | W47: gyandeep.singh@accor.com | AA47: No | AT47: Asked to share the proposal | AU47: Yes | AV47: Introduction | AW47: Proposal | AZ47: manisha.kumari@capsdelivery.com | BA47: Cold Walk-in | BB47: Yes | BN47: ACCOR | BP47: ACCOR
A48: 46071.819 | B48: 46071 | C48: 0.72916667 | D48: Intro Meeting | E48: Raasta | F48: 273 | G48: 500 | H48: NA | J48: Tier-1(AOV>400) | K48: Swiggy, Zomato | N48: 3 | O48: PVT | P48: Yes | Q48: Active | R48: Yes | S48: 17.43391403132923, 78.38254875300429 | U48: Pradeep (GM) | V48: 9493304525 | W48: NA | X48: Mukul (Shift Manager) | Y48: 9010023567 | AA48: No | AT48: Mr. Predeep will be back by Saturday. He will be available in between Lunch and Dinner | AU48: Yes | AV48: Introduction | AW48: NA | AX48: 46074 | AY48: 0.70833333 | AZ48: amit.kaler@capsdelivery.com | BA48: Cold Walk-in | BB48: Yes | BL48: 25 | BN48: Hi-Tech City | BP48: Raasta
A49: 46071.822 | B49: 46071 | C49: 0.75 | D49: Intro Meeting | E49: Flurry | F49: 34 | G49: 800 | H49: NA | J49: Tier-1(AOV>400) | K49: Swiggy, Zomato | N49: 2 | O49: PVT | P49: Yes | Q49: Active | R49: Yes | S49: 17.434247898762155, 78.38196122416875 | U49: Santosh (South Head) | V49: 9840561868 | W49: NA | X49: Ranjit (Shift Manager) | Y49: 9573345190 | Z49: NA | AA49: No | AT49: Follow Up with Mr. Santosh Reqd | AU49: Yes | AV49: Introduction | AX49: 46072 | AY49: 0.5 | AZ49: amit.kaler@capsdelivery.com | BA49: Cold Walk-in | BB49: Yes | BL49: 15 | BN49: Hi-Tech City | BP49: Flurry
A50: 46071.826 | B50: 46071 | C50: 0.75 | D50: Intro Meeting | E50: Cream Centre | F50: 112 | G50: 800 | H50: NA | J50: Tier-1(AOV>400) | K50: Swiggy, Zomato | N50: 2 | O50: PVT | P50: Yes | Q50: Active | R50: Yes | S50: 17.433158540214496, 78.38246986649779 | U50: Mohd Ali (Shift Manger) | V50: 9637475780 | W50: NA | AA50: No | AT50: Walkin required at Begumpet branch as General Manager not available due to his wedding | AU50: Yes | AV50: Introduction | AW50: Need to follow up at Begumpet branch | AX50: 46073 | AY50: 0.5 | AZ50: amit.kaler@capsdelivery.com | BA50: Cold Walk-in | BB50: Yes | BN50: Hi-tech City | BP50: Cream Centre
A51: 46072.424 | B51: 46071 | C51: 0.75 | D51: Intro Meeting | E51: Manam Chocolate | F51: 15 | G51: 400 | H51: Na | J51: Tier-1(AOV>400) | K51: Swiggy, Zomato | N51: 2 | O51: PVT | P51: Yes | Q51: Active | R51: Yes | S51: 17.43324929596664, 78.38234912601712 | U51: Kalim (GM) | V51: 8978747520 | W51: NA | AA51: No | AT51: Call Kalim | AU51: Yes | AV51: Introduction | AW51: Call Mr. Kalim | AX51: 46072 | AY51: 0.5 | AZ51: amit.kaler@capsdelivery.com | BA51: Cold Walk-in | BB51: Yes | BN51: Hi-Tech City | BP51: Manam Chocolate
A52: 46072.822 | B52: 46072 | C52: 0.58333333 | D52: Intro Meeting | E52: Palle vindhu | F52: 50 | G52: 1000 | H52: NA | J52: Tier-1(AOV>400) | K52: Swiggy, Zomato | N52: 3 | O52: Partnership | P52: Yes | Q52: Active | R52: Not Applied | S52: Address: plot no:25, Jayabheri Enclave, Gachibowli, Hyderabad, Telangana 500032 | U52: Vishnu | V52: 9133711711 | W52: na | AA52: No | AT52: Need to speak with other partner for final discussion | AU52: Yes | AV52: Introduction | AZ52: greeshma.vanneldas@capsdelivery.com | BA52: Cold Walk-in | BB52: Yes | BP52: Palle vindhu
A53: 46072.988 | B53: 46071 | C53: 0.72222222 | D53: Intro Meeting | E53: SANGAM DHABA | F53: 50 | G53: 500 | H53: PET POOJA | I53: 75000 | J53: Tier-1(AOV>400) | K53: Zomato | L53: 17 | M53: 22 | N53: 4 | O53: Partnership | P53: Yes | Q53: Active | R53: Yes | S53: 17.398296633261864, 78.48459875214712 | U53: KAILASH | V53: 7207477577 | W53: NA | AA53: No | AT53: ONBOARDED | AU53: Yes | AV53: Document Collection | AW53: ASKED TO COLLECT DOCUMENTS ON MONDAY | AX53: 46076 | AY53: 0.61458333 | AZ53: moin.khan@capsdelivery.com | BA53: Cold Walk-in | BB53: Yes | BL53: 150 | BN53: HIMAYAT NAGAR | BP53: SANGAM DHABA
A54: 46073.66 | B54: 46073 | C54: 0.14583333 | D54: Intro Meeting | E54: Naughty Kudi | F54: 200 | G54: 500 | H54: Petpooja | J54: Tier-1(AOV>400) | N54: 1 | O54: Partnership | P54: Yes | Q54: Active | R54: Yes | S54: https://maps.app.goo.gl/H9SX4U2MU2PjPQZe7 | U54: Ramesh | V54: 8374572520 | W54: Na | X54: Rama | Y54: 9390442627 | AA54: No | AT54: Need a follow up meetings | AU54: Yes | AV54: Introduction | AZ54: anisha.poddar@capsdelivery.com | BA54: Cold Walk-in | BB54: Yes | BP54: Naughty Kudi
A55: 46074.434 | B55: 46071 | C55: 0.084027778 | D55: Intro Meeting | E55: scoops | F55: 20 | G55: 300 | H55: na | J55: Tier-1(AOV>400) | K55: Swiggy, Zomato | N55: 1 | O55: Prop | P55: No | Q55: Active | R55: Yes | S55: na | U55: na | V55: 8688612955 | W55: NA | AA55: No | AT55: NEED TO follow up | AU55: Yes | AZ55: madhumitha.sonnakula@capsdelivery.com | BA55: Cold Walk-in | BB55: Yes | BN55: khairthabad | BP55: scoops
A56: 46074.436 | B56: 46071 | C56: 0.13541667 | D56: Intro Meeting | E56: avani restraunt | F56: 100 | G56: 400 | H56: pet pooja | J56: Tier-1(AOV>400) | K56: Swiggy, Zomato | N56: 1 | O56: Prop | P56: Yes | Q56: Active | R56: Yes | S56: na | U56: vikas | V56: 7207206239 | W56: na | AA56: No | AT56: we need to follow up | AU56: Yes | AV56: Introduction | AZ56: madhumitha.sonnakula@capsdelivery.com | BA56: Cold Walk-in | BB56: Yes | BN56: khairthabad | BP56: avani restraunt
A57: 46074.445 | B57: 46072 | C57: 0.064583333 | D57: Intro Meeting | E57: abhiruchi sagurha foods | F57: 20 | G57: 800 | H57: pet pooja | J57: Tier-1(AOV>400) | N57: 4 | O57: Prop | P57: Yes | Q57: Active | R57: Yes | S57: na | U57: management | V57: 9502201776 | W57: na | AA57: No | AT57: need to follow up | AU57: Yes | AZ57: madhumitha.sonnakula@capsdelivery.com | BA57: Cold Walk-in | BB57: Yes | BN57: narsing | BP57: abhiruchi sagurha foods
A58: 46074.672 | B58: 46074 | C58: 0.041666667 | D58: Intro Meeting | E58: radisson (chillis) | F58: 300 | G58: 5000 | H58: na | J58: Tier-1(AOV>400) | K58: Swiggy, Zomato | N58: 1 | O58: Prop | P58: Yes | Q58: Active | R58: Yes | S58: na | U58: joel nayak | V58: 914067331122 | W58: afbm@rdhyderabad.com | AA58: No | AT58: we need to send them the proposal | AU58: Yes | AV58: Introduction | AZ58: madhumitha.sonnakula@capsdelivery.com | BA58: Cold Walk-in | BB58: Yes | BN58: banjara hills | BP58: radisson (chillis)
A59: 46074.674 | B59: 46074 | C59: 0.070833333 | D59: Intro Meeting | E59: parampara | F59: 25 | G59: 800 | H59: na | J59: Tier-1(AOV>400) | K59: Swiggy, Zomato | N59: 14 | O59: Prop | P59: Yes | Q59: Active | R59: Yes | S59: na | U59: ravi | V59: 8374223982 | W59: na | AA59: No | AT59: we need to follow up | AU59: Yes | AZ59: madhumitha.sonnakula@capsdelivery.com | BA59: Cold Walk-in | BB59: Yes | BN59: banjara hills | BP59: parampara
A60: 46074.701 | B60: 46074 | C60: 0.0625 | D60: Intro Meeting | E60: Seasons Express | F60: 100 | G60: 450 | H60: na | J60: Tier-1(AOV>400) | K60: Swiggy, Zomato | N60: 5 | O60: Prop | P60: Yes | Q60: Active | R60: Yes | S60: na | U60: na | V60: na | W60: na | AA60: No | AT60: Follow up required - P0 lead | AU60: Yes | AV60: Meeting with different POC | AW60: Detailed discussion with manager required as we spoke to cashier at res. | AX60: 46076 | AY60: 0.125 | AZ60: srivani.reddy@capsdelivery.com | BA60: Cold Walk-in | BB60: Yes | BN60: Banjara Hills | BP60: Seasons Express
A61: 46074.704 | B61: 46074 | C61: 0.078472222 | D61: Intro Meeting | E61: Dine Hill | F61: 80 | G61: 500 | H61: na | J61: Tier-1(AOV>400) | K61: Swiggy, Zomato | N61: 1 | O61: Prop | P61: Yes | Q61: Active | R61: Yes | S61: na | U61: Faizal | V61: 6394101620 | W61: na | AA61: No | AT61: Manager informed to meet after ramzan - after 3PM | AU61: Yes | AV61: Meeting with different POC | AW61: details has to be discussed with owner | AX61: 46109 | AY61: 0.125 | AZ61: srivani.reddy@capsdelivery.com | BA61: Cold Walk-in | BB61: Yes | BN61: Banjara Hills | BP61: Dine Hill
A62: 46074.707 | B62: 46074 | C62: 0.092361111 | D62: Intro Meeting | E62: Exotica | F62: 100 | G62: 500 | H62: na | J62: Tier-1(AOV>400) | K62: Swiggy, Zomato | N62: 1 | O62: Partnership | P62: Yes | Q62: Active | R62: Yes | S62: na | U62: na | V62: 9014113139 | W62: kedar@maanhospitality.com | AA62: No | AT62: They asked to share proposal through mail id | AU62: Yes | AV62: Meeting with different POC | AW62: detailed structure discussion | AX62: 46081 | AY62: 0.16666667 | AZ62: srivani.reddy@capsdelivery.com | BA62: Cold Walk-in | BB62: Yes | BN62: Banjara Hills | BP62: Exotica
A63: 46074.742 | B63: 46074 | C63: 0.41666667 | D63: Intro Meeting | E63: Harsha deluxe mess | F63: 100 | G63: 500 | H63: Petpooja | I63: 70000 | J63: Tier-1(AOV>400) | K63: Swiggy, Zomato, Magic Pin | N63: 10 | O63: Partnership | P63: Yes | Q63: Active | R63: Yes | S63: https://share.google/0FAZRMPoXgCw0Fyoq | U63: Pranay | V63: 8341379379 | W63: Na | AA63: No | AT63: Asking to send proposal | AU63: Yes | AV63: Meeting with different POC | AX63: 46078 | AY63: 0.041666667 | AZ63: parthive.maganti@capsdelivery.com | BA63: Cold Walk-in | BB63: Yes | BL63: 120 | BN63: Madhapur | BP63: Harsha deluxe mess
A64: 46074.765 | B64: 46074 | C64: 0.57638889 | D64: Intro Meeting | E64: Kasoori | F64: 200 | G64: 400 | H64: Pet pooja | I64: 5000 | J64: Tier-1(AOV>400) | K64: Swiggy, Zomato | N64: 1 | O64: Prop | P64: No | Q64: Expired | R64: No | S64: KASOORI - North Indian Rooftop Restaurant https://share.google/IjWb4AWnKSOqkj97T | U64: Shekar | V64: 9705659494 | W64: Na | AA64: No | AT64: Na | AU64: Yes | AV64: Negotiation | AX64: 46081 | AY64: 0.41666667 | AZ64: parthive.maganti@capsdelivery.com | BA64: Cold Walk-in | BB64: Yes | BL64: 50000 | BN64: Kondapur | BP64: Kasoori
A65: 46076.535 | B65: 46076 | C65: 0.53263889 | D65: Intro Meeting | E65: Chinese Chinese kitchen | F65: 46 | G65: 400 | H65: Petpooja | J65: Tier-1(AOV>400) | K65: Swiggy, Zomato | N65: 1 | O65: Partnership | P65: Yes | Q65: Active | R65: Not Applied | S65: https://maps.app.goo.gl/k9WJWwkpwA3V2dof7 | U65: Dharma | V65: 9833858958 | W65: Na | AA65: No | AT65: Need to follow up with the owner for onboarding | AU65: Yes | AV65: Introduction | AZ65: anisha.poddar@capsdelivery.com | BA65: Cold Walk-in | BB65: Yes | BL65: 20-30 | BP65: Chinese Chinese kitchen
A66: 46076.741 | B66: 46072 | C66: 0.54166667 | D66: Intro Meeting | E66: Sarovar Portico HotelSarovar Portico Hotel | F66: 200 | G66: 1200 | H66: NA | J66: Tier-1(AOV>400) | K66: Swiggy, Zomato | N66: 2 | O66: PVT | P66: Yes | Q66: Active | R66: Yes | S66: https://share.google/rBQh0y9tZ3jb15iLq | T66: Sarovar Portico Hotel | U66: Abhijay Verma | V66: 9246526606 | W66: gmhpo@sarovarhotels.com | AA66: No | AT66: Proposal email sent | AU66: Yes | AV66: Meeting with different POC | AZ66: manisha.kumari@capsdelivery.com | BA66: Scheduled | BN66: Sarovar Portico Hotel | BP66: Sarovar Portico Hotel
A67: 46076.745 | B67: 46072 | C67: 0.5625 | D67: Intro Meeting | E67: Hotel GreenparkHotel Greenpark & Marigold | F67: 120 | G67: 800 | H67: MICROS | J67: Tier-1(AOV>400) | K67: Swiggy, Zomato | N67: 1 | O67: PVT | P67: Yes | Q67: Active | R67: Yes | S67: https://share.google/oLGEXqY5nrFZoHwwT | T67: Hotel Greenpark & Marigold | U67: NIRANJAN | V67: 9848633190 | W67: fbmgr.hyd@hotelgreenpark.com | AA67: No | AT67: Proposal Email Sent | AU67: Yes | AV67: Meeting with different POC | AZ67: manisha.kumari@capsdelivery.com | BA67: Scheduled | BN67: Hotel Greenpark | BP67: Hotel Greenpark
A68: 46076.838 | B68: 46076 | C68: 0.625 | D68: Intro Meeting | E68: ProstProst | F68: 200 | G68: 800 | H68: NA | J68: Tier-1(AOV>400) | K68: Swiggy, Zomato | N68: 1 | O68: PVT | P68: Yes | Q68: Active | R68: Yes | S68: https://share.google/FQROJgExIdqy3vrwr | T68: Prost | U68: Raju Kumar | V68: 7090567395 | W68: Rajkumar@prost.in | X68: Raj B | Y68: 7376299999 | Z68: Manager@prost.in Exclusive@prost.in | AA68: No | AT68: Asked to meet tomorrow 24/02/2026 at 3PM | AU68: Yes | AV68: Introduction | AX68: 46077 | AY68: 0.625 | AZ68: manisha.kumari@capsdelivery.com | BA68: Cold Walk-in | BB68: Yes | BN68: Prost | BP68: Prost
A69: 46076.842 | B69: 46076 | C69: 0.6875 | D69: Intro Meeting | E69: Paradise BiryaniParadise Biryani | F69: 200 | G69: 600 | H69: pet pooja | J69: Tier-1(AOV>400) | K69: Swiggy, Zomato | N69: 17 | O69: PVT | P69: Yes | Q69: Active | R69: Yes | S69: https://share.google/s5YB6CZB2NHCEXpOl | T69: Paradise Biryani | U69: Rajesh Kulkarni | V69: 98852 14121 | W69: NA | AA69: No | AT69: Tried calling him but he did not answer the call. POC ashish suggested to visit the corporate office between MON - FRI (11:00 - 18:00) | AU69: Yes | AV69: Introduction | AW69: Proposal | AX69: 46077 | AY69: 0.45833333 | AZ69: manisha.kumari@capsdelivery.com | BA69: Cold Walk-in | BB69: Yes | BN69: Paradise Biryani | BP69: Paradise Biryani
A70: 46077.503 | B70: 46076 | C70: 0.66666667 | D70: Intro Meeting | E70: Sweets DudeSweets Dude | F70: 10 | G70: 700 | H70: Pet Pooja | J70: Tier-1(AOV>400) | K70: Swiggy, Zomato | N70: 1 | O70: PVT | P70: Yes | Q70: Active | R70: Yes | S70: http | T70: Sweets Dude | U70: Naveen Owner | V70: 7416022022 | W70: naveen@sweetsdude.in | AA70: No | AT70: proposal sent on mail | AU70: Yes | AV70: Negotiation | AZ70: manisha.kumari@capsdelivery.com | BA70: Cold Walk-in | BB70: Yes | BN70: Sweets Dude | BP70: Sweets Dude
A71: 46077.511 | B71: 46076 | C71: 0.5 | D71: Intro Meeting | E71: Park HyattPark Hyatt | F71: 200 | G71: 1200 | H71: MICROS | J71: Tier-1(AOV>400) | K71: Swiggy, Zomato | N71: 2 | O71: PVT | P71: Yes | Q71: Active | R71: Yes | S71: https://share.google/g8VtPK9T7Lq2eV6HV | T71: Park Hyatt | U71: Avinash Pant | V71: 7767042422 | W71: avinash.pant@hyatt.com | AA71: No | AT71: Proposal Mail sent | AU71: Yes | AV71: Meeting with different POC | AZ71: manisha.kumari@capsdelivery.com | BA71: Cold Walk-in | BB71: Yes | BN71: Park Hyatt | BP71: Park Hyatt
A72: 46077.524 | B72: 46077 | C72: 0.45833333 | D72: Intro Meeting | E72: Cock & Bull HyderabadCock and Bull Hyderabad | F72: 200 | G72: 900 | H72: NA | J72: Tier-1(AOV>400) | K72: Swiggy, Zomato | N72: 2 | O72: PVT | P72: Yes | Q72: Active | R72: Yes | S72: https://share.google/b7w9SqsO3x5h9MKiW | T72: Cock and Bull Hyderabad | U72: Yogesh | V72: 8392898004‬ | W72: Cocknbullhyd@gmail.com | AA72: No | AT72: Proposal sent | AU72: Yes | AV72: Introduction | AZ72: manisha.kumari@capsdelivery.com | BA72: Cold Walk-in | BB72: Yes | BN72: Cock & Bull Hyderabad | BP72: Cock & Bull Hyderabad
A73: 46077.714 | B73: 46077 | C73: 0.50347222 | D73: Intro Meeting | E73: Andhana Brahma | F73: 120 | G73: 300 | H73: NA | J73: Tier-1(AOV>400) | K73: Swiggy, Zomato | N73: 1 | O73: Partnership | P73: Yes | Q73: Active | R73: Not Applied | S73: https://maps.app.goo.gl/FNpYJXFYk9jPzHydA | U73: Surya | V73: 9938380231 | W73: NA | AA73: No | AT73: Meeting with the MD | AU73: Yes | AV73: Introduction | AZ73: anisha.poddar@capsdelivery.com | BA73: Cold Walk-in | BB73: Yes | BP73: Andhana Brahma
A74: 46078.529 | B74: 46078 | C74: 0.52430556 | D74: Intro Meeting | E74: Golden Pavillion | F74: 120 | G74: 600 | H74: Na | J74: Tier-1(AOV>400) | K74: Swiggy, Zomato | N74: 1 | O74: Prop | P74: Yes | Q74: Active | R74: Not Applied | S74: https://maps.app.goo.gl/7ZAKm49VnnqBZjCD7 | U74: Sajjid | V74: 8247031311 | W74: Gpsajju@gmail.com | AA74: No | AT74: Need to follow up with the owner | AU74: Yes | AV74: Negotiation | AZ74: anisha.poddar@capsdelivery.com | BA74: Cold Walk-in | BB74: Yes | BN74: Banjara hills | BP74: Golden Pavillion
A75: 46078.54 | B75: 46077 | C75: 0.60902778 | D75: Intro Meeting | E75: Paradise Food Court | F75: 80 | G75: 600 | H75: NA | J75: Tier-1(AOV>400) | K75: Swiggy, Zomato | N75: 17 | O75: PVT | P75: Yes | Q75: Active | R75: Yes | S75: http | U75: Peddinti Sharan Kumar | V75: 9666229460 | W75: sharan.peddinti@paradisefoodcourt.in | AA75: No | AT75: They have a protocol of onboarding new vendors only after the launch. However they have asked to share the proposal on email | AU75: Yes | AV75: Introduction | AZ75: manisha.kumari@capsdelivery.com | BA75: Cold Walk-in | BB75: Yes | BN75: Paradise Food Court | BP75: Paradise Food Court
A76: 46078.719 | B76: 46078 | C76: 0.125 | D76: Intro Meeting | E76: Kritunga | F76: 250 | G76: 400 | H76: Petpooja | J76: Tier-1(AOV>400) | K76: Swiggy, Zomato | N76: 10 | O76: Partnership | P76: Yes | Q76: Active | R76: Not Applied | S76: https://maps.app.goo.gl/iQh3tM84Cxr7pSrz8 | U76: Josthna | V76: NA | W76: Chakri.kritunga@gmail.com | X76: Chakri | Y76: 7799678883 | Z76: Chakri.kritunga@gmail.com | AA76: No | AT76: Need to do consistent follow ups | AU76: Yes | AZ76: anisha.poddar@capsdelivery.com | BA76: Cold Walk-in | BB76: Yes | BL76: 50 | BN76: Banjara hills | BP76: Kritunga
A77: 46078.911 | B77: 46078 | C77: 0.45625 | D77: Intro Meeting | E77: taaza tiffens | F77: 50 | G77: 300 | H77: pet pooja | J77: Tier-1(AOV>400) | K77: Swiggy, Zomato | N77: 7 | O77: Prop | P77: Yes | Q77: Active | R77: Yes | S77: na | U77: bhagwan | V77: 9441166869 | W77: na | AA77: No | AT77: we need to talk about that on taaza tiffens | AU77: Yes | AV77: Introduction | AX77: 46081 | AY77: 0.41666667 | AZ77: madhumitha.sonnakula@capsdelivery.com | BA77: Cold Walk-in | BB77: Yes | BN77: langara house | BP77: taaza tiffens
A78: 46078.918 | B78: 46078 | C78: 0.090972222 | D78: Intro Meeting | E78: bandhan mithai vatika | F78: 20 | G78: 400 | H78: pet pooja | J78: Tier-1(AOV>400) | K78: Swiggy, Zomato | N78: 2 | O78: Prop | P78: Yes | Q78: Active | R78: Yes | S78: na | U78: kishore | V78: 8328135391 | W78: na | AA78: No | AT78: after 1st march | AU78: Yes | AZ78: madhumitha.sonnakula@capsdelivery.com | BA78: Cold Walk-in | BB78: Yes | BN78: khairthabad | BP78: bandhan mithai vatika
A79: 46078.923 | B79: 46078 | C79: 0.28194444 | D79: Intro Meeting | E79: epic bawarachi tiffen centre | F79: 50 | G79: 450 | H79: na | J79: Tier-1(AOV>400) | K79: Swiggy, Zomato | N79: 1 | O79: Prop | P79: Yes | Q79: Active | R79: Yes | S79: na | U79: krishna roa | V79: 9986881566 | W79: na | AA79: No | AT79: onboarded | AU79: Yes | AZ79: madhumitha.sonnakula@capsdelivery.com | BA79: Cold Walk-in | BB79: Yes | BN79: lanagara house | BP79: epic bawarachi tiffen centre
A80: 46080.666 | B80: 46080 | C80: 0.65625 | D80: Intro Meeting | E80: Mandi Bistro | F80: 100 | G80: 700 | H80: Pet pooja | I80: 30000 | J80: Tier-1(AOV>400) | K80: Swiggy, Zomato | L80: 25 | M80: 22 | N80: 4 | O80: Prop | P80: Yes | Q80: Active | R80: Yes | S80: https://maps.app.goo.gl/z9SkJgocGbESBgAP8?g_st=ic | U80: Mohammed omer | V80: 9381305084 | W80: Na | AA80: No | AT80: Have a meeting on monday | AU80: Yes | AV80: Document Collection | AW80: Explanation | AX80: 46083 | AY80: 0.54166667 | AZ80: manasa.chigurupati@capsdelivery.com | BA80: Cold Walk-in | BB80: Yes | BL80: 30 | BN80: Raidurg | BP80: Mandi Bistro
A81: 46083.388 | B81: 46081 | C81: 0.70833333 | D81: Intro Meeting | E81: Golden Barrel Restaurent and pub | F81: 60 | G81: 1500 | H81: pet pooja | I81: 200000 | J81: Tier-1(AOV>400) | K81: Zomato | L81: 22 | M81: 20 | N81: 1 | O81: Prop | P81: Yes | Q81: Active | R81: Yes | S81: 17.540369703987597, 78.36868222281474 | U81: chary | V81: 9032785954 | W81: na | AA81: No | AT81: will ready to onboard | AU81: Yes | AV81: Document Collection | AZ81: chanakya.inugala@capsdelivery.com | BA81: Cold Walk-in | BB81: Yes | BL81: 100 | BN81: Bachupally | BP81: Golden Barrel Restaurent and pub
A82: 46083.572 | B82: 46083 | C82: 0.5625 | D82: Intro Meeting | E82: Baburao gari biriyani | F82: 15 | G82: 300 | H82: Dotpay | J82: Tier-1(AOV>400) | K82: Swiggy, Zomato | L82: 24 | N82: 8 | O82: Prop | P82: Yes | Q82: Active | R82: Yes | S82: https://maps.google.com/?q=Baburao%20Gari%20Biryani,%20Sri%20Sai%20Chaitanya%20Nilayam,%20Street%20Number%204,%20opposite%20Montessori%20High%20School,%20Vijaya%20Nagar%20Colony,%20Kukatpally,%20Hyderabad,%20Telangana%20500072&ftid=0x3bcb919f96d79569:0xc5f549118c193c7b&entry=gps&shh=CAE&lucs=,94297699,94284481,94231188,94280568,47071704,94266210,94218641,94282134,94286869&g_st=ic | U82: Deepak | V82: 9951343434 | W82: Kakaralad@gmail.com | AA82: No | AT82: Dotpay pos | AU82: Yes | AV82: Document Collection | AZ82: manasa.chigurupati@capsdelivery.com | BA82: Cold Walk-in | BB82: Yes | BN82: Kukatpally | BP82: Baburao gari biriyani
A83: 46083.591 | B83: 46083 | C83: 0.58819444 | D83: Intro Meeting | E83: Athithi Biriyani Ruchulu | F83: 150 | G83: 350 | H83: Pet pooja | I83: 60000 | J83: Tier-1(AOV>400) | K83: Swiggy, Zomato | L83: 25 | M83: 20 | N83: 1 | O83: Partnership | P83: Yes | Q83: Active | R83: Yes | S83: https://maps.app.goo.gl/c9RYPFLsTBfefUWG9?g_st=ic | U83: Sudheer | V83: 8688880266 | W83: Sudheermunna056@gmail.com | AA83: No | AT83: Should come back for onboarding | AU83: Yes | AV83: Document Collection | AW83: Onboarding | AX83: 46085 | AY83: 0.5625 | AZ83: manasa.chigurupati@capsdelivery.com | BA83: Cold Walk-in | BB83: Yes | BL83: 300 | BN83: Kukatpally | BP83: Athithi Biriyani Ruchulu
A84: 46083.752 | B84: 46083 | C84: 0.52083333 | D84: Intro Meeting | E84: Anmol continental | F84: 60 | G84: 700 | H84: Pet pooja | I84: 49000 | J84: Tier-1(AOV>400) | K84: None | M84: 22 | N84: 1 | O84: Partnership | P84: Yes | Q84: Active | R84: Yes | S84: 500063, 5-9-20/A, Secretariat Rd, Saifabad, Khairtabad, Hyderabad, Telangana 500004 | U84: Narayan | V84: 9154999897 | W84: Info@nicehospitality.in | AA84: No | AT84: Asked to send proposal | AU84: Yes | AV84: Introduction | AW84: Asked to send the proposal in email | AX84: 46086 | AY84: 0.54166667 | AZ84: moin.khan@capsdelivery.com | BA84: Cold Walk-in | BB84: Yes | BL84: 70 | BN84: Khairatabad | BP84: Anmol continental
A85: 46085.978 | B85: 46084 | C85: 0.10486111 | D85: Intro Meeting | E85: paradise | F85: 200 | G85: 400 | H85: na | J85: Tier-1(AOV>400) | K85: Swiggy, Zomato | N85: 34 | O85: Prop | P85: Yes | Q85: Active | R85: Yes | S85: na | U85: mr jimmy | V85: na | W85: na | AA85: No | AT85: na | AU85: Yes | AV85: Introduction | AZ85: madhumitha.sonnakula@capsdelivery.com | BA85: Cold Walk-in | BB85: Yes | BN85: khairathabad | BP85: paradise
A86: 46085.979 | B86: 46084 | C86: 0.10833333 | D86: Intro Meeting | E86: pizza hut | F86: 200 | G86: 600 | H86: na | J86: Tier-1(AOV>400) | K86: Swiggy, Zomato | N86: 27 | O86: Prop | P86: Yes | Q86: Active | R86: Yes | S86: na | U86: na | V86: 9652374967 | W86: na | AA86: No | AT86: na | AU86: Yes | AV86: Introduction | AZ86: madhumitha.sonnakula@capsdelivery.com | BA86: Cold Walk-in | BB86: Yes | BN86: khairthabad | BP86: pizza hut
A87: 46085.98 | B87: 46084 | C87: 0.11180556 | D87: Intro Meeting | E87: kfc | F87: 200 | G87: 600 | H87: na | J87: Tier-1(AOV>400) | K87: Swiggy, Zomato | N87: 38 | O87: Prop | P87: Yes | Q87: Active | R87: Yes | S87: na | U87: na | V87: 9398596919 | W87: na | AA87: No | AT87: nz | AU87: Yes | AZ87: madhumitha.sonnakula@capsdelivery.com | BA87: Cold Walk-in | BB87: Yes | BN87: khairthabad | BP87: kfc
A88: 46085.982 | B88: 46084 | C88: 0.11805556 | D88: Intro Meeting | E88: momo street | F88: 300 | G88: 400 | H88: na | J88: Tier-1(AOV>400) | N88: 3 | O88: Prop | P88: Yes | Q88: Active | R88: Yes | S88: na | U88: ankith agarawal | V88: 9100086888 | W88: na | AA88: No | AT88: na | AU88: Yes | AV88: Introduction | AZ88: madhumitha.sonnakula@capsdelivery.com | BA88: Cold Walk-in | BB88: Yes | BN88: khairthabad | BP88: momo street
A89: 46085.984 | B89: 46084 | C89: 0.12152778 | D89: Intro Meeting | E89: pista house | F89: 300 | G89: 400 | H89: no | J89: Tier-1(AOV>400) | K89: Swiggy, Zomato | N89: 23 | O89: Prop | P89: Yes | Q89: Active | R89: Yes | S89: na | U89: laxaman | V89: 9392458705 | W89: na | AA89: No | AT89: ns | AU89: Yes | AZ89: madhumitha.sonnakula@capsdelivery.com | BA89: Cold Walk-in | BB89: Yes | BN89: khaiurthabad | BP89: pista house
A90: 46085.985 | B90: 46084 | C90: 0.125 | D90: Intro Meeting | E90: cafe coffee day | F90: 300 | G90: 200 | H90: na | J90: Tier-1(AOV>400) | N90: 112 | O90: Prop | P90: Yes | Q90: Active | R90: Yes | S90: na | U90: sourav | V90: 7397400542 | W90: na | AA90: No | AT90: na | AU90: Yes | AZ90: madhumitha.sonnakula@capsdelivery.com | BA90: Cold Walk-in | BB90: Yes | BN90: khairthabad | BP90: cafe coffee day
A91: 46085.988 | B91: 46084 | C91: 0.27083333 | D91: Intro Meeting | E91: scandy | F91: 20 | G91: 300 | H91: na | J91: Tier-1(AOV>400) | K91: Swiggy | N91: 12 | O91: Prop | P91: Yes | Q91: Active | R91: Yes | S91: ns | U91: na | V91: na | W91: na | AA91: No | AT91: na | AU91: Yes | AZ91: madhumitha.sonnakula@capsdelivery.com | BA91: Cold Walk-in | BB91: Yes | BN91: madhapur | BP91: scandy
A92: 46085.993 | B92: 46083 | C92: 0.20833333 | D92: Intro Meeting | E92: the eatary hub | F92: 50 | G92: 300 | H92: na | J92: Tier-1(AOV>400) | K92: Swiggy, Zomato | N92: 1 | O92: Prop | P92: No | Q92: Active | R92: Yes | S92: na | U92: anwar | V92: 9030944113 | W92: na | AA92: No | AT92: na | AU92: Yes | AZ92: madhumitha.sonnakula@capsdelivery.com | BA92: Cold Walk-in | BB92: Yes | BN92: khairthabad | BP92: the eatary hub
A93: 46087.801 | B93: 46083 | C93: 0.125 | D93: Intro Meeting | E93: Kamat hotel | F93: 200 | G93: 200 | H93: Na | J93: Tier-1(AOV>400) | K93: Swiggy, Zomato | N93: 1 | O93: Prop | P93: Yes | Q93: Active | R93: No | S93: Na | U93: Na | V93: Na | W93: Na | AA93: No | AT93: Na | AU93: Yes | AZ93: madhumitha.sonnakula@capsdelivery.com | BA93: Cold Walk-in | BB93: Yes | BP93: Kamat hotel
A94: 46091.491 | B94: 46091 | C94: 0.47916667 | D94: Intro Meeting | E94: Chutneys | F94: 80 | G94: 400 | H94: Na | J94: Tier-1(AOV>400) | N94: 10 | O94: Na | P94: Yes | Q94: Active | R94: Yes | S94: Na | U94: Satish | V94: 9949391723 | W94: atlurifoods@gmail.com | AA94: No | AT94: Meeting done in the headoffice,the head Satish asked to share the proposal , forwarded to Charan about the details to share proposal, thursday call back to schedule meeting | AU94: Yes | AZ94: greeshma.vanneldas@capsdelivery.com | BA94: Cold Walk-in | BB94: Yes | BN94: Jubilee hills | BP94: Chutneys
A95: 46091.772 | B95: 46091 | C95: 0.64583333 | D95: Intro Meeting | E95: Minerva | F95: 50 | G95: 400 | H95: Pet pooja | I95: 50000 | J95: Tier-1(AOV>400) | K95: Swiggy, Zomato, Magic Pin | N95: 30 | O95: Partnership | P95: Yes | Q95: Active | R95: Yes | S95: Minerva | U95: Amjed ali | V95: Na | W95: Na | AA95: No | AT95: Need to provide them proposal data | AU95: Yes | AV95: Contract Signing | AX95: 46093 | AZ95: parthive.maganti@capsdelivery.com | BA95: Cold Walk-in | BB95: Yes | BP95: Minerva
A96: 46091.776 | B96: 46091 | C96: 0.625 | D96: Intro Meeting | E96: Iron hill | F96: 100 | G96: 600 | H96: Pet pooja | J96: Tier-1(AOV>400) | K96: Swiggy, Zomato | N96: 20 | O96: Prop | P96: Yes | Q96: Active | R96: Yes | S96: Na | U96: Palesh | V96: Na | W96: Na | AA96: No | AT96: Need to send proposal and arrange meeting | AU96: Yes | AV96: Negotiation | AZ96: parthive.maganti@capsdelivery.com | BA96: Cold Walk-in | BB96: Yes | BN96: Hi tech | BP96: Iron hill
A97: 46092.643 | B97: 46092 | C97: 0.57638889 | D97: Intro Meeting | E97: Salt Indian Restaurant | F97: 80 | G97: 400 | H97: Petpooja | J97: Tier-1(AOV>400) | K97: Swiggy, Zomato | L97: 25 | M97: 18 | N97: 1 | O97: Prop | P97: Yes | Q97: Active | R97: Yes | S97: https://maps.app.goo.gl/bvLLQi92EuhBxDRCA?g_st=ic | U97: Jwala | V97: 8867857222 | W97: NA | AA97: No | AT97: They are busy dealing Gas issues, asked to come back later once the issue is solved, they said they will call later | AU97: Yes | AV97: Introduction | AZ97: manasa.chigurupati@capsdelivery.com | BA97: Cold Walk-in | BB97: Yes | BN97: Raidurg | BP97: Salt Indian Restaurant

Sheet Pivot Table 14

Sheet Visit New

Sheet POS Data
E1: ON BOARDED
E2: POS | F2: COUNTA of Date | G2: %
E3: PET POOJA | F3: 26 | G3: =F3/$F$10 -> 0.60465116
E4: Mobile Application | F4: 4 | G4: =F4/$F$10 -> 0.093023256
E5: Own | F5: 4 | G5: =F5/$F$10 -> 0.093023256
E6: NO POS | F6: 3 | G6: =F6/$F$10 -> 0.069767442
E7: Order matic | F7: 3 | G7: =F7/$F$10 -> 0.069767442
E8: Chef’s Desk | F8: 2 | G8: =F8/$F$10 -> 0.046511628
E9: urban pipers | F9: 1 | G9: =F9/$F$10 -> 0.023255814
E10: GT | F10: =SUM(F3:F9) -> 43 | G10: =F10/$F$10 -> 1
E12: Overall Data
E13: POS | F13: COUNTA of Date | G13: %
E14: Pet poja | F14: 85 | G14: =F14/$F$32 -> 0.69672131
E15: Own | F15: 5 | G15: =F15/$F$32 -> 0.040983607
E16: Brain power | F16: 4 | G16: =F16/$F$32 -> 0.032786885
E17: Mobile | F17: 4 | G17: =F17/$F$32 -> 0.032786885
E18: Not present | F18: 5 | G18: =F18/$F$32 -> 0.040983607
E19: Chef’s Desk | F19: 2 | G19: =F19/$F$32 -> 0.016393443
E20: MICROS | F20: 2 | G20: =F20/$F$32 -> 0.016393443
E21: Order matic | F21: 2 | G21: =F21/$F$32 -> 0.016393443
E22: OrderMatic | F22: 2 | G22: =F22/$F$32 -> 0.016393443
E23: Rista | F23: 2 | G23: =F23/$F$32 -> 0.016393443
E24: urban pipers | F24: 2 | G24: =F24/$F$32 -> 0.016393443
E25: Breeza (Exporex) | F25: 1 | G25: =F25/$F$32 -> 0.0081967213
... E31: Urban Piper | F31: 1 | G31: =F31/$F$32 -> 0.0081967213
E32: Total | F32: =sUM(F14:F31) -> 122

Sheet Data
A1: Date | B1: RM | C1: Restaurant | D1: REMARKS | E1: FOLLOW UP REQD. | F1: Follow up date | G1: Follow up Time | H1: =Form_Responses[[#HEADERS],[Points to be prepared]] -> Points to be prepared | I1: Onboarding Status | J1: Restaurant Category | K1: AOV | L1: Seating Capacity | M1: POC 1 | N1: POC 1 NUMBER | O1: POC 1 EMAIL ID | P1: POC 2 | Q1: POC 2 NUMBER | R1: POC 2 EMAIL ID | S1: =Form_Responses[[#HEADERS],[FSSAI]] -> FSSAI | T1: =Form_Responses[[#HEADERS],[GST]] -> GST | U1: =Form_Responses[[#HEADERS],[PAN Card]] -> PAN Card | V1: =Form_Responses[[#HEADERS],[Labour License]] -> Labour License | W1: =Form_Responses[[#HEADERS],[Menu (Image)]] -> Menu (Image) | X1: =Form_Responses[[#HEADERS],[Bank Account Proof]] -> Bank Account Proof | Y1: FSSAI Status | Z1: GST Status | AA1: PAN Card Status | AB1: Labour License Status | AC1: Menu Status | AD1: Bank Account Proof Status | AE1: =Form_Responses[[#HEADERS],[Name on Bank Account]] -> Name on Bank Account | AF1: =Form_Responses[[#HEADERS],[Owner Name]] -> Owner Name | AG1: =Form_Responses[[#HEADERS],[Owner Contact Number]] -> Owner Contact Number | AH1: =Form_Responses[[#HEADERS],[Owner Email address]] -> Owner Email address | AI1: =Form_Responses[[#HEADERS],[Legal Entity Name]] -> Legal Entity Name
A2: ='Form responses 1'!B4 -> 44577 | B2: ='Form responses 1'!AZ4 -> TEST | C2: ='Form responses 1'!BR4 -> 5823694 | D2: ='Form responses 1'!AT4 | E2: ='Form responses 1'!AU4 -> Yes | F2: ='Form responses 1'!AX4 -> 35098 | G2: ='Form responses 1'!AY4 -> 0.42430556 | H2: ='Form responses 1'!AW4 -> KBUHIH | I2: ='Form responses 1'!AS4 -> Yes | J2: ='Form responses 1'!J4 | K2: ='Form responses 1'!G4 | L2: ='Form responses 1'!F4 | M2: ='Form responses 1'!U4 -> sandeep | N2: ='Form responses 1'!V4 -> 916679555 | O2: ='Form responses 1'!W4 -> parul986@gmail | P2: ='Form responses 1'!X4 -> amit | Q2: ='Form responses 1'!Y4 -> 7896541232 | R2: ='Form responses 1'!Z4 -> parul@gmail | S2: ='Form responses 1'!AC4 -> https://drive.google.com/open?id=1K2GAYdf9j8OoeRQJN7a2rrWNqrJv-Yr8 | T2: ='Form responses 1'!AE4 -> https://drive.google.com/open?id=1Xrc3uPOk64pgUM1gMvRHq-hhYc6pYKJT | U2: ='Form responses 1'!AG4 -> https://drive.google.com/open?id=1P8o5u-wkGayDLIcyTArlaMzpPcBL8IP1 | V2: ='Form responses 1'!AI4 -> https://drive.google.com/open?id=1zOmxq565qkkMqqCAFCaCRWzjb7i60OTF | W2: ='Form responses 1'!AJ4 -> https://drive.google.com/open?id=1qsXvdJuct7_aToPR8ThIMJcmid9TRtyr | X2: ='Form responses 1'!AK4 | Y2: =if(S2>0,1,0) -> 1 | Z2: =if(T2>0,1,0) -> 1 | AA2: =if(U2>0,1,0) -> 1 | AB2: =if(V2>0,1,0) -> 1 | AC2: =if(W2>0,1,0) -> 1 | AD2: =if(X2>0,1,0) -> 0 | AE2: ='Form responses 1'!AN4 -> icici | AF2: ='Form responses 1'!AO4 -> jihughyfu | AG2: ='Form responses 1'!AP4 -> 64946165597 | AH2: ='Form responses 1'!AQ4 -> jhgyfyf2@GMAIL,COM | AI2: ='Form responses 1'!AR4 -> HVTFUGYFYGJH
A3: ='Form responses 1'!B5 -> 46056 | B3: ='Form responses 1'!AZ5 -> manasa.chigurupati@capsdelivery.com | C3: ='Form responses 1'!BR5 -> Bhuvan’s Kitchen | D3: ='Form responses 1'!AT5 -> Res has been onboarded | E3: ='Form responses 1'!AU5 -> No | F3: ='Form responses 1'!AX5 | G3: ='Form responses 1'!AY5 | H3: ='Form responses 1'!AW5 | I3: ='Form responses 1'!AS5 -> Yes | J3: ='Form responses 1'!J5 -> Tier-2 (AOV <400) | K3: ='Form responses 1'!G5 -> 250 | L3: ='Form responses 1'!F5 -> 85 | M3: ='Form responses 1'!U5 -> Rama Rao | N3: ='Form responses 1'!V5 -> 9030611616 | O3: ='Form responses 1'!W5 -> Bhuvan’skitchen25@gmail.com | P3: ='Form responses 1'!X5 | Q3: ='Form responses 1'!Y5 | R3: ='Form responses 1'!Z5 | S3: ='Form responses 1'!AC5 -> https://drive.google.com/open?id=1zQ8cp3_66Bhden1m6eXDLNsshBt8JXb3 | T3: ='Form responses 1'!AE5 | U3: ='Form responses 1'!AG5 | V3: ='Form responses 1'!AI5 | W3: ='Form responses 1'!AJ5 | X3: ='Form responses 1'!AK5 | Y3: =if(S3>0,1,0) -> 1 | Z3: =if(T3>0,1,0) -> 0 | AA3: =if(U3>0,1,0) -> 0 | AB3: =if(V3>0,1,0) -> 0 | AC3: =if(W3>0,1,0) -> 0 | AD3: =if(X3>0,1,0) -> 0 | AE3: ='Form responses 1'!AN5 -> HDFC Bank | AF3: ='Form responses 1'!AO5 -> Rama Rao | AG3: ='Form responses 1'!AP5 -> 9030611616 | AH3: ='Form responses 1'!AQ5 -> bhuvanskitchen25@gmail.com | AI3: ='Form responses 1'!AR5 -> Bhuvan’s Kitchen
A4: ='Form responses 1'!B6 -> 46056 | B4: ='Form responses 1'!AZ6 -> sumadhur.mummadi@capsdelivery.com | C4: ='Form responses 1'!BR6 -> 12345578 | D4: ='Form responses 1'!AT6 | E4: ='Form responses 1'!AU6 -> Yes | F4: ='Form responses 1'!AX6 -> 46057 | G4: ='Form responses 1'!AY6 -> 0.45833333 | H4: ='Form responses 1'!AW6 | I4: ='Form responses 1'!AS6 | J4: ='Form responses 1'!J6 | K4: ='Form responses 1'!G6 | L4: ='Form responses 1'!F6 | M4: ='Form responses 1'!U6 -> Mohammed Amir | N4: ='Form responses 1'!V6 -> 9949814600 | O4: ='Form responses 1'!W6 -> na | P4: ='Form responses 1'!X6 | Q4: ='Form responses 1'!Y6 | R4: ='Form responses 1'!Z6 | S4: ='Form responses 1'!AC6 | T4: ='Form responses 1'!AE6 | U4: ='Form responses 1'!AG6 | V4: ='Form responses 1'!AI6 | W4: ='Form responses 1'!AJ6 | X4: ='Form responses 1'!AK6 | Y4: =if(S4>0,1,0) -> 0 | Z4: =if(T4>0,1,0) -> 0 | AA4: =if(U4>0,1,0) -> 0 | AB4: =if(V4>0,1,0) -> 0 | AC4: =if(W4>0,1,0) -> 0 | AD4: =if(X4>0,1,0) -> 0 | AE4: ='Form responses 1'!AN6 | AF4: ='Form responses 1'!AO6 | AG4: ='Form responses 1'!AP6 | AH4: ='Form responses 1'!AQ6 | AI4: ='Form responses 1'!AR6
A5: ='Form responses 1'!B7 -> 46056 | B5: ='Form responses 1'!AZ7 -> chanakya.inugala@capsdelivery.com | C5: ='Form responses 1'!BR7 -> Bhojanams & Birynis | D5: ='Form responses 1'!AT7 -> PARTNER ON BOARDED | E5: ='Form responses 1'!AU7 -> No | F5: ='Form responses 1'!AX7 -> 46056 | G5: ='Form responses 1'!AY7 -> 0.84722222 | H5: ='Form responses 1'!AW7 | I5: ='Form responses 1'!AS7 -> Yes | J5: ='Form responses 1'!J7 -> Tier-2 (AOV <400) | K5: ='Form responses 1'!G7 -> 500 | L5: ='Form responses 1'!F7 -> 30 | M5: ='Form responses 1'!U7 -> Shesha sai | N5: ='Form responses 1'!V7 -> 9052592437 | O5: ='Form responses 1'!W7 -> sheshasai@gmail.com | P5: ='Form responses 1'!X7 | Q5: ='Form responses 1'!Y7 | R5: ='Form responses 1'!Z7 | S5: ='Form responses 1'!AC7 -> https://drive.google.com/open?id=1jDd9udZkiYFM95E6qDnBXxB9dZAPA3Q6 | T5: ='Form responses 1'!AE7 -> https://drive.google.com/open?id=1wmAzfgRO6AUexNEcncft5vbltGIV8av4 | U5: ='Form responses 1'!AG7 | V5: ='Form responses 1'!AI7 | W5: ='Form responses 1'!AJ7 | X5: ='Form responses 1'!AK7 -> https://drive.google.com/open?id=13qbsLsi98K74BchvdcD_7-swJp4EtkeO | Y5: =if(S5>0,1,0) -> 1 | Z5: =if(T5>0,1,0) -> 1 | AA5: =if(U5>0,1,0) -> 0 | AB5: =if(V5>0,1,0) -> 0 | AC5: =if(W5>0,1,0) -> 0 | AD5: =if(X5>0,1,0) -> 1 | AE5: ='Form responses 1'!AN7 -> IDFC | AF5: ='Form responses 1'!AO7 -> SHESHA SAI | AG5: ='Form responses 1'!AP7 -> 9052592437 | AH5: ='Form responses 1'!AQ7 | AI5: ='Form responses 1'!AR7 -> INVENCES FOODS
A6: ='Form responses 1'!B8 -> 46055 | B6: ='Form responses 1'!AZ8 -> parthive.maganti@capsdelivery.com | C6: ='Form responses 1'!BR8 -> Sunrise Business Hotel | D6: ='Form responses 1'!AT8 -> They got impress with our application take away point | E6: ='Form responses 1'!AU8 -> No | F6: ='Form responses 1'!AX8 -> 46056 | G6: ='Form responses 1'!AY8 -> 0.23958333 | H6: ='Form responses 1'!AW8 | I6: ='Form responses 1'!AS8 -> Yes | J6: ='Form responses 1'!J8 -> Tier-2 (AOV <400) | K6: ='Form responses 1'!G8 -> 300 | L6: ='Form responses 1'!F8 -> 100 | M6: ='Form responses 1'!U8 -> Venkat Lingam | N6: ='Form responses 1'!V8 -> 8989873636 | O6: ='Form responses 1'!W8 -> bowlrise.srnagar@gmail.com | P6: ='Form responses 1'!X8 | Q6: ='Form responses 1'!Y8 | R6: ='Form responses 1'!Z8 | S6: ='Form responses 1'!AC8 -> https://drive.google.com/open?id=1p7jWoaNGA48ZsmXz8piawFvDD6h8MZPo | T6: ='Form responses 1'!AE8 -> https://drive.google.com/open?id=1hZ4_XJa0ar_5viyQyWSwjO63ut7o3QIh | U6: ='Form responses 1'!AG8 -> https://drive.google.com/open?id=11LbxcMTLS62PuKE6EHwzu8WdUemKU5ba | V6: ='Form responses 1'!AI8 | W6: ='Form responses 1'!AJ8 | X6: ='Form responses 1'!AK8 -> https://drive.google.com/open?id=1LV1wXeDgKShlIJHBUn--Sn9J2gR1xgxD | Y6: =if(S6>0,1,0) -> 1 | Z6: =if(T6>0,1,0) -> 1 | AA6: =if(U6>0,1,0) -> 1 | AB6: =if(V6>0,1,0) -> 0 | AC6: =if(W6>0,1,0) -> 0 | AD6: =if(X6>0,1,0) -> 1 | AE6: ='Form responses 1'!AN8 -> ICICI BANK | AF6: ='Form responses 1'!AO8 -> VENKAT LINGAM | AG6: ='Form responses 1'!AP8 -> 8989873636 | AH6: ='Form responses 1'!AQ8 -> BOWLRISE.SRNAGAR@GMAIL.COM | AI6: ='Form responses 1'!AR8 -> AARAV SUNRISE HOSPITALITES
A7: ='Form responses 1'!B9 -> 46056 | B7: ='Form responses 1'!AZ9 -> moin.khan@capsdelivery.com | C7: ='Form responses 1'!BR9 -> ZYROS BIRYANI HOUSE | D7: ='Form responses 1'!AT9 -> ONBOARDED | E7: ='Form responses 1'!AU9 -> No | F7: ='Form responses 1'!AX9 | G7: ='Form responses 1'!AY9 | H7: ='Form responses 1'!AW9 | I7: ='Form responses 1'!AS9 -> Yes | J7: ='Form responses 1'!J9 -> Tier-2 (AOV <400) | K7: ='Form responses 1'!G9 -> 300 | L7: ='Form responses 1'!F9 -> 8 | M7: ='Form responses 1'!U9 -> NATVA SANTOSH KUMAR | N7: ='Form responses 1'!V9 -> 6302181276 | O7: ='Form responses 1'!W9 -> nsantosh086@gmail.com | P7: ='Form responses 1'!X9 -> NA | Q7: ='Form responses 1'!Y9 | R7: ='Form responses 1'!Z9 | S7: ='Form responses 1'!AC9 -> https://drive.google.com/open?id=19PGovlvYadreb67eUHeNKzrktgJO-8bX | T7: ='Form responses 1'!AE9 -> https://drive.google.com/open?id=1xkvSfuIbWsf_ar7Z_3_MFx49cCnJTGSd | U7: ='Form responses 1'!AG9 | V7: ='Form responses 1'!AI9 | W7: ='Form responses 1'!AJ9 -> https://drive.google.com/open?id=1zs5LVtkzfw6Ig4tlx1lPWSn0Lm-7bwoP | X7: ='Form responses 1'!AK9 -> https://drive.google.com/open?id=12sEwp13vy0B0IOgjOaR48di8G3M0dgC6 | Y7: =if(S7>0,1,0) -> 1 | Z7: =if(T7>0,1,0) -> 1 | AA7: =if(U7>0,1,0) -> 0 | AB7: =if(V7>0,1,0) -> 0 | AC7: =if(W7>0,1,0) -> 1 | AD7: =if(X7>0,1,0) -> 1 | AE7: ='Form responses 1'!AN9 | AF7: ='Form responses 1'!AO9 -> NATVA SANTOSH KUMAR | AG7: ='Form responses 1'!AP9 -> 6302181276 | AH7: ='Form responses 1'!AQ9 -> nsantosh086@gmail.com | AI7: ='Form responses 1'!AR9 -> NATVA SANTOSH KUMAR
A8: ='Form responses 1'!B10 -> 46055 | B8: ='Form responses 1'!AZ10 -> nitya.akshara@capsdelivery.com | C8: ='Form responses 1'!BR10 -> Slice of Spice | D8: ='Form responses 1'!AT10 -> Onboarded | E8: ='Form responses 1'!AU10 -> No | F8: ='Form responses 1'!AX10 | G8: ='Form responses 1'!AY10 | H8: ='Form responses 1'!AW10 | I8: ='Form responses 1'!AS10 -> Yes | J8: ='Form responses 1'!J10 -> Tier-1(AOV>400) | K8: ='Form responses 1'!G10 -> 5000 | L8: ='Form responses 1'!F10 -> 150 | M8: ='Form responses 1'!U10 -> Venkat Lingam | N8: ='Form responses 1'!V10 -> 888655996 | O8: ='Form responses 1'!W10 -> bowlrise.srnagar@gmail.com | P8: ='Form responses 1'!X10 | Q8: ='Form responses 1'!Y10 | R8: ='Form responses 1'!Z10 | S8: ='Form responses 1'!AC10 -> https://drive.google.com/open?id=1O-A-ESorVgS21JbM9bD4LsPgYXHMCp0d | T8: ='Form responses 1'!AE10 -> https://drive.google.com/open?id=15R5f8q3so1Ik7UrWJk_3rCjAQY8sBEFO | U8: ='Form responses 1'!AG10 -> https://drive.google.com/open?id=1r4LwvkbszhmmgLl56dsxPyTtENCSry3W | V8: ='Form responses 1'!AI10 | W8: ='Form responses 1'!AJ10 -> https://drive.google.com/open?id=1kddVXBDtmyxBYZuEGyQzheu06kPD2YCr | X8: ='Form responses 1'!AK10 -> https://drive.google.com/open?id=1HMbFf9NKxwpNmJpRUAoeT4JSbWFH_gsM | Y8: =if(S8>0,1,0) -> 1 | Z8: =if(T8>0,1,0) -> 1 | AA8: =if(U8>0,1,0) -> 1 | AB8: =if(V8>0,1,0) -> 0 | AC8: =if(W8>0,1,0) -> 1 | AD8: =if(X8>0,1,0) -> 1 | AE8: ='Form responses 1'!AN10 -> EASTIN HOTELS AND RESORTS | AF8: ='Form responses 1'!AO10 -> VAMSI | AG8: ='Form responses 1'!AP10 -> 9014707850 | AH8: ='Form responses 1'!AQ10 -> info@eastinhotel.com | AI8: ='Form responses 1'!AR10
A9: ='Form responses 1'!B11 -> 46057 | B9: ='Form responses 1'!AZ11 -> moin.khan@capsdelivery.com | C9: ='Form responses 1'!BR11 -> ROLO BAKERS | D9: ='Form responses 1'!AT11 -> ONBOARDED | E9: ='Form responses 1'!AU11 -> No | F9: ='Form responses 1'!AX11 | G9: ='Form responses 1'!AY11 | H9: ='Form responses 1'!AW11 | I9: ='Form responses 1'!AS11 -> Yes | J9: ='Form responses 1'!J11 -> Tier-2 (AOV <400) | K9: ='Form responses 1'!G11 -> 250 | L9: ='Form responses 1'!F11 -> 20 | M9: ='Form responses 1'!U11 -> GM RAGHAVENDRA | N9: ='Form responses 1'!V11 -> 9963968917 | O9: ='Form responses 1'!W11 -> NA | P9: ='Form responses 1'!X11 | Q9: ='Form responses 1'!Y11 | R9: ='Form responses 1'!Z11 | S9: ='Form responses 1'!AC11 -> https://drive.google.com/open?id=16IQXYD4HTTgs7GCdBU6iPTmSXHfWlbQY | T9: ='Form responses 1'!AE11 -> https://drive.google.com/open?id=1QyRpGDX2lP1lX3GoLj4kqxGuQ7cNxZ5q | U9: ='Form responses 1'!AG11 -> https://drive.google.com/open?id=1wLa_Pt-AJbdtSV0NDD93Cgm0a-yocPNO | V9: ='Form responses 1'!AI11 | W9: ='Form responses 1'!AJ11 | X9: ='Form responses 1'!AK11 | Y9: =if(S9>0,1,0) -> 1 | Z9: =if(T9>0,1,0) -> 1 | AA9: =if(U9>0,1,0) -> 1 | AB9: =if(V9>0,1,0) -> 0 | AC9: =if(W9>0,1,0) -> 0 | AD9: =if(X9>0,1,0) -> 0 | AE9: ='Form responses 1'!AN11 | AF9: ='Form responses 1'!AO11 -> GM RAGHAVENDRA | AG9: ='Form responses 1'!AP11 -> 9963968917 | AH9: ='Form responses 1'!AQ11 | AI9: ='Form responses 1'!AR11 -> ROLO ONE BAKERS
A10: ='Form responses 1'!B12 -> 46057 | B10: ='Form responses 1'!AZ12 -> moin.khan@capsdelivery.com | C10: ='Form responses 1'!BR12 -> rayalseema spice restaurant | D10: ='Form responses 1'!AT12 -> ONBOARDED | E10: ='Form responses 1'!AU12 -> No | F10: ='Form responses 1'!AX12 | G10: ='Form responses 1'!AY12 | H10: ='Form responses 1'!AW12 | I10: ='Form responses 1'!AS12 -> Yes | J10: ='Form responses 1'!J12 -> Tier-2 (AOV <400) | K10: ='Form responses 1'!G12 -> 300 | L10: ='Form responses 1'!F12 -> 40 | M10: ='Form responses 1'!U12 -> narapu reddy | N10: ='Form responses 1'!V12 -> 6301782448 | O10: ='Form responses 1'!W12 -> rayalseemaspice@gmail.com | P10: ='Form responses 1'!X12 | Q10: ='Form responses 1'!Y12 | R10: ='Form responses 1'!Z12 | S10: ='Form responses 1'!AC12 -> https://drive.google.com/open?id=12A0pBqsWeMNRgfr4-RewydCYL1MhGFzW | T10: ='Form responses 1'!AE12 -> https://drive.google.com/open?id=1w2-0S2iGSW_hsqhFAKZANxRRUo2t8rGA | U10: ='Form responses 1'!AG12 -> https://drive.google.com/open?id=1pP1p8yHifkOvlMj3fFQXJ-_zZU02HhTR | V10: ='Form responses 1'!AI12 | W10: ='Form responses 1'!AJ12 | X10: ='Form responses 1'!AK12 -> https://drive.google.com/open?id=1B_C4vy9xoX9tPLwjSW2tR-EM6ekXOlYl | Y10: =if(S10>0,1,0) -> 1 | Z10: =if(T10>0,1,0) -> 1 | AA10: =if(U10>0,1,0) -> 1 | AB10: =if(V10>0,1,0) -> 0 | AC10: =if(W10>0,1,0) -> 0 | AD10: =if(X10>0,1,0) -> 1 | AE10: ='Form responses 1'!AN12 -> BANDHAN BANK | AF10: ='Form responses 1'!AO12 -> POKURI PRATHYUSHA | AG10: ='Form responses 1'!AP12 -> 6301782448 | AH10: ='Form responses 1'!AQ12 | AI10: ='Form responses 1'!AR12 -> POKURI PRATHYUSHA
A11: ='Form responses 1'!B13 -> 46057 | B11: ='Form responses 1'!AZ13 -> moin.khan@capsdelivery.com | C11: ='Form responses 1'!BR13 -> alankrutha multicuisine restaurant | D11: ='Form responses 1'!AT13 -> ONBOARDED | E11: ='Form responses 1'!AU13 -> No | F11: ='Form responses 1'!AX13 | G11: ='Form responses 1'!AY13 | H11: ='Form responses 1'!AW13 | I11: ='Form responses 1'!AS13 -> Yes | J11: ='Form responses 1'!J13 -> Tier-2 (AOV <400) | K11: ='Form responses 1'!G13 -> 300 | L11: ='Form responses 1'!F13 -> 20 | M11: ='Form responses 1'!U13 -> AKASH | N11: ='Form responses 1'!V13 -> 8341514984 | O11: ='Form responses 1'!W13 -> cakash121@gmail.com | P11: ='Form responses 1'!X13 | Q11: ='Form responses 1'!Y13 | R11: ='Form responses 1'!Z13 | S11: ='Form responses 1'!AC13 -> https://drive.google.com/open?id=1yUrIaR5y55zD2nSA-kJ0RTpJklMZhyOE | T11: ='Form responses 1'!AE13 | U11: ='Form responses 1'!AG13 -> https://drive.google.com/open?id=1lHnQS6jFD0j-ODzzm6ncc6Fds_MkMTOj | V11: ='Form responses 1'!AI13 | W11: ='Form responses 1'!AJ13 | X11: ='Form responses 1'!AK13 -> https://drive.google.com/open?id=1xJurv609CUKpePCGd0rcMOwYy6MJKEto | Y11: =if(S11>0,1,0) -> 1 | Z11: =if(T11>0,1,0) -> 0 | AA11: =if(U11>0,1,0) -> 1 | AB11: =if(V11>0,1,0) -> 0 | AC11: =if(W11>0,1,0) -> 0 | AD11: =if(X11>0,1,0) -> 1 | AE11: ='Form responses 1'!AN13 -> BANK OF BARODA | AF11: ='Form responses 1'!AO13 -> ALANKRUTHA RESTAURANT | AG11: ='Form responses 1'!AP13 -> 8341514984 | AH11: ='Form responses 1'!AQ13 -> cakash121@gmail.com | AI11: ='Form responses 1'!AR13 -> ALANKRUTHA MULTICUSINE RESTAURANT
A12: ='Form responses 1'!B14 -> 46057 | B12: ='Form responses 1'!AZ14 -> chanakya.inugala@capsdelivery.com | C12: ='Form responses 1'!BR14 -> GUNTUR MESS | D12: ='Form responses 1'!AT14 -> on boarded waiting for documents | E12: ='Form responses 1'!AU14 -> No | F12: ='Form responses 1'!AX14 | G12: ='Form responses 1'!AY14 | H12: ='Form responses 1'!AW14 | I12: ='Form responses 1'!AS14 -> Yes | J12: ='Form responses 1'!J14 -> Tier-3 ( AOV<200 ) | K12: ='Form responses 1'!G14 -> 200 | L12: ='Form responses 1'!F14 -> 20 | M12: ='Form responses 1'!U14 -> SHIVA | N12: ='Form responses 1'!V14 -> 9391167117 | O12: ='Form responses 1'!W14 -> shiva@gmail.com | P12: ='Form responses 1'!X14 | Q12: ='Form responses 1'!Y14 | R12: ='Form responses 1'!Z14 | S12: ='Form responses 1'!AC14 | T12: ='Form responses 1'!AE14 | U12: ='Form responses 1'!AG14 | V12: ='Form responses 1'!AI14 | W12: ='Form responses 1'!AJ14 | X12: ='Form responses 1'!AK14 | Y12: =if(S12>0,1,0) -> 0 | Z12: =if(T12>0,1,0) -> 0 | AA12: =if(U12>0,1,0) -> 0 | AB12: =if(V12>0,1,0) -> 0 | AC12: =if(W12>0,1,0) -> 0 | AD12: =if(X12>0,1,0) -> 0 | AE12: ='Form responses 1'!AN14 | AF12: ='Form responses 1'!AO14 | AG12: ='Form responses 1'!AP14 | AH12: ='Form responses 1'!AQ14 | AI12: ='Form responses 1'!AR14
A13: ='Form responses 1'!B15 -> 46058 | B13: ='Form responses 1'!AZ15 -> chanakya.inugala@capsdelivery.com | C13: ='Form responses 1'!BR15 -> Bihar Dhaba | D13: ='Form responses 1'!AT15 -> onboarded waiting for documets | E13: ='Form responses 1'!AU15 -> No | F13: ='Form responses 1'!AX15 -> 46059 | G13: ='Form responses 1'!AY15 -> 0.625 | H13: ='Form responses 1'!AW15 | I13: ='Form responses 1'!AS15 | J13: ='Form responses 1'!J15 -> Tier-3 ( AOV<200 ) | K13: ='Form responses 1'!G15 -> 200 | L13: ='Form responses 1'!F15 -> 30 | M13: ='Form responses 1'!U15 -> prajwah kumar | N13: ='Form responses 1'!V15 -> 9441674841 | O13: ='Form responses 1'!W15 -> na | P13: ='Form responses 1'!X15 | Q13: ='Form responses 1'!Y15 | R13: ='Form responses 1'!Z15 | S13: ='Form responses 1'!AC15 | T13: ='Form responses 1'!AE15 | U13: ='Form responses 1'!AG15 | V13: ='Form responses 1'!AI15 | W13: ='Form responses 1'!AJ15 | X13: ='Form responses 1'!AK15 | Y13: =if(S13>0,1,0) -> 0 | Z13: =if(T13>0,1,0) -> 0 | AA13: =if(U13>0,1,0) -> 0 | AB13: =if(V13>0,1,0) -> 0 | AC13: =if(W13>0,1,0) -> 0 | AD13: =if(X13>0,1,0) -> 0 | AE13: ='Form responses 1'!AN15 | AF13: ='Form responses 1'!AO15 | AG13: ='Form responses 1'!AP15 | AH13: ='Form responses 1'!AQ15 | AI13: ='Form responses 1'!AR15
... A423: ='Form responses 1'!B425 -> 46069 | B423: ='Form responses 1'!AZ425 -> chanakya.inugala@capsdelivery.com | C423: ='Form responses 1'!BR425 -> Swad of Grandma | D423: ='Form responses 1'!AT425 -> Na | E423: ='Form responses 1'!AU425 -> No | F423: ='Form responses 1'!AX425 | G423: ='Form responses 1'!AY425 | H423: ='Form responses 1'!AW425 | I423: ='Form responses 1'!AS425 | J423: ='Form responses 1'!J425 -> Tier-3 ( AOV<200 ) | K423: ='Form responses 1'!G425 -> 270 | L423: ='Form responses 1'!F425 -> 30 | M423: ='Form responses 1'!U425 -> Amit | N423: ='Form responses 1'!V425 -> 9985489397 | O423: ='Form responses 1'!W425 -> Na | P423: ='Form responses 1'!X425 | Q423: ='Form responses 1'!Y425 | R423: ='Form responses 1'!Z425 | S423: ='Form responses 1'!AC425 | T423: ='Form responses 1'!AE425 | U423: ='Form responses 1'!AG425 | V423: ='Form responses 1'!AI425 | W423: ='Form responses 1'!AJ425 | X423: ='Form responses 1'!AK425 | Y423: =if(S423>0,1,0) -> 0 | Z423: =if(T423>0,1,0) -> 0 | AA423: =if(U423>0,1,0) -> 0 | AB423: =if(V423>0,1,0) -> 0 | AC423: =if(W423>0,1,0) -> 0 | AD423: =if(X423>0,1,0) -> 0 | AE423: ='Form responses 1'!AN425 | AF423: ='Form responses 1'!AO425 | AG423: ='Form responses 1'!AP425 | AH423: ='Form responses 1'!AQ425 | AI423: ='Form responses 1'!AR425
A424: ='Form responses 1'!B473 -> 46069 | B424: ='Form responses 1'!AZ473 -> greeshma.vanneldas@capsdelivery.com | C424: ='Form responses 1'!BR473 -> Hope in a cup | D424: ='Form responses 1'!AT473 -> following up to fix intro meeting | E424: ='Form responses 1'!AU473 -> Yes | F424: ='Form responses 1'!AX473 | G424: ='Form responses 1'!AY473 | H424: ='Form responses 1'!AW473 | I424: ='Form responses 1'!AS473 | J424: ='Form responses 1'!J473 | K424: ='Form responses 1'!G473 | L424: ='Form responses 1'!F473 | M424: ='Form responses 1'!U473 -> Niranjan | N424: ='Form responses 1'!V473 -> 9676367127 | O424: ='Form responses 1'!W473 -> na | P424: ='Form responses 1'!X473 | Q424: ='Form responses 1'!Y473 | R424: ='Form responses 1'!Z473 | S424: ='Form responses 1'!AC473 | T424: ='Form responses 1'!AE473 | U424: ='Form responses 1'!AG473 | V424: ='Form responses 1'!AI473 | W424: ='Form responses 1'!AJ473 | X424: ='Form responses 1'!AK473 | Y424: =if(S424>0,1,0) -> 0 | Z424: =if(T424>0,1,0) -> 0 | AA424: =if(U424>0,1,0) -> 0 | AB424: =if(V424>0,1,0) -> 0 | AC424: =if(W424>0,1,0) -> 0 | AD424: =if(X424>0,1,0) -> 0 | AE424: ='Form responses 1'!AN473 | AF424: ='Form responses 1'!AO473 | AG424: ='Form responses 1'!AP473 | AH424: ='Form responses 1'!AQ473 | AI424: ='Form responses 1'!AR473
A425: ='Form responses 1'!B427 -> 46069 | B425: ='Form responses 1'!AZ427 -> moin.khan@capsdelivery.com | C425: ='Form responses 1'!BR427 -> preeti tiffins | D425: ='Form responses 1'!AT427 | E425: ='Form responses 1'!AU427 -> Yes | F425: ='Form responses 1'!AX427 -> 46070 | G425: ='Form responses 1'!AY427 -> 0.72847222 | H425: ='Form responses 1'!AW427 | I425: ='Form responses 1'!AS427 | J425: ='Form responses 1'!J427 | K425: ='Form responses 1'!G427 | L425: ='Form responses 1'!F427 | M425: ='Form responses 1'!U427 -> megha | N425: ='Form responses 1'!V427 -> 8897622869 | O425: ='Form responses 1'!W427 -> na | P425: ='Form responses 1'!X427 | Q425: ='Form responses 1'!Y427 | R425: ='Form responses 1'!Z427 | S425: ='Form responses 1'!AC427 | T425: ='Form responses 1'!AE427 | U425: ='Form responses 1'!AG427 | V425: ='Form responses 1'!AI427 | W425: ='Form responses 1'!AJ427 | X425: ='Form responses 1'!AK427 | Y425: =if(S425>0,1,0) -> 0 | Z425: =if(T425>0,1,0) -> 0 | AA425: =if(U425>0,1,0) -> 0 | AB425: =if(V425>0,1,0) -> 0 | AC425: =if(W425>0,1,0) -> 0 | AD425: =if(X425>0,1,0) -> 0 | AE425: ='Form responses 1'!AN427 | AF425: ='Form responses 1'!AO427 | AG425: ='Form responses 1'!AP427 | AH425: ='Form responses 1'!AQ427 | AI425: ='Form responses 1'!AR427
A426: ='Form responses 1'!B678 -> 46073 | B426: ='Form responses 1'!AZ678 -> greeshma.vanneldas@capsdelivery.com | C426: ='Form responses 1'!BR678 -> Hotel swaruchiHotel surichi | D426: ='Form responses 1'!AT678 -> He is looking for 12% | E426: ='Form responses 1'!AU678 -> Yes | F426: ='Form responses 1'!AX678 | G426: ='Form responses 1'!AY678 | H426: ='Form responses 1'!AW678 | I426: ='Form responses 1'!AS678 | J426: ='Form responses 1'!J678 | K426: ='Form responses 1'!G678 | L426: ='Form responses 1'!F678 | M426: ='Form responses 1'!U678 -> Ramesh | N426: ='Form responses 1'!V678 -> 7396928999 | O426: ='Form responses 1'!W678 -> Na | P426: ='Form responses 1'!X678 | Q426: ='Form responses 1'!Y678 | R426: ='Form responses 1'!Z678 | S426: ='Form responses 1'!AC678 | T426: ='Form responses 1'!AE678 | U426: ='Form responses 1'!AG678 | V426: ='Form responses 1'!AI678 | W426: ='Form responses 1'!AJ678 | X426: ='Form responses 1'!AK678 | Y426: =if(S426>0,1,0) -> 0 | Z426: =if(T426>0,1,0) -> 0 | AA426: =if(U426>0,1,0) -> 0 | AB426: =if(V426>0,1,0) -> 0 | AC426: =if(W426>0,1,0) -> 0 | AD426: =if(X426>0,1,0) -> 0 | AE426: ='Form responses 1'!AN678 | AF426: ='Form responses 1'!AO1797 | AG426: ='Form responses 1'!AP1797 | AH426: ='Form responses 1'!AQ1797 | AI426: ='Form responses 1'!AR1797
A427: ='Form responses 1'!B429 -> 46070 | B427: ='Form responses 1'!AZ429 -> moin.khan@capsdelivery.com | C427: ='Form responses 1'!BR429 -> fire and ice cream fire and ice ice cream | D427: ='Form responses 1'!AT429 | E427: ='Form responses 1'!AU429 -> Yes | F427: ='Form responses 1'!AX429 -> 46070 | G427: ='Form responses 1'!AY429 -> 0.5625 | H427: ='Form responses 1'!AW429 | I427: ='Form responses 1'!AS429 | J427: ='Form responses 1'!J429 | K427: ='Form responses 1'!G429 | L427: ='Form responses 1'!F429 | M427: ='Form responses 1'!U429 -> azhar | N427: ='Form responses 1'!V429 -> 84649 15054 | O427: ='Form responses 1'!W429 -> na | P427: ='Form responses 1'!X429 | Q427: ='Form responses 1'!Y429 | R427: ='Form responses 1'!Z429 | S427: ='Form responses 1'!AC429 | T427: ='Form responses 1'!AE429 | U427: ='Form responses 1'!AG429 | V427: ='Form responses 1'!AI429 | W427: ='Form responses 1'!AJ429 | X427: ='Form responses 1'!AK429 | Y427: =if(S427>0,1,0) -> 0 | Z427: =if(T427>0,1,0) -> 0 | AA427: =if(U427>0,1,0) -> 0 | AB427: =if(V427>0,1,0) -> 0 | AC427: =if(W427>0,1,0) -> 0 | AD427: =if(X427>0,1,0) -> 0 | AE427: ='Form responses 1'!AN429 | AF427: ='Form responses 1'!AO429 | AG427: ='Form responses 1'!AP429 | AH427: ='Form responses 1'!AQ429 | AI427: ='Form responses 1'!AR429
A428: ='Form responses 1'!B275 -> 46065 | B428: ='Form responses 1'!AZ275 -> greeshma.vanneldas@capsdelivery.com | C428: ='Form responses 1'!BR275 -> Hulchal desserts and bakers | D428: ='Form responses 1'!AT275 | E428: ='Form responses 1'!AU275 -> Yes | F428: ='Form responses 1'!AX275 | G428: ='Form responses 1'!AY275 | H428: ='Form responses 1'!AW275 -> Owner will be available after 18th of these month | I428: ='Form responses 1'!AS275 | J428: ='Form responses 1'!J275 | K428: ='Form responses 1'!G275 | L428: ='Form responses 1'!F275 | M428: ='Form responses 1'!U275 -> Awaiz Ammari | N428: ='Form responses 1'!V275 -> 9000931717 | O428: ='Form responses 1'!W275 -> na | P428: ='Form responses 1'!X275 | Q428: ='Form responses 1'!Y275 | R428: ='Form responses 1'!Z275 | S428: ='Form responses 1'!AC275 | T428: ='Form responses 1'!AE275 | U428: ='Form responses 1'!AG275 | V428: ='Form responses 1'!AI275 | W428: ='Form responses 1'!AJ275 | X428: ='Form responses 1'!AK275 | Y428: =if(S428>0,1,0) -> 0 | Z428: =if(T428>0,1,0) -> 0 | AA428: =if(U428>0,1,0) -> 0 | AB428: =if(V428>0,1,0) -> 0 | AC428: =if(W428>0,1,0) -> 0 | AD428: =if(X428>0,1,0) -> 0 | AE428: ='Form responses 1'!AN275 | AF428: ='Form responses 1'!AO275 | AG428: ='Form responses 1'!AP275 | AH428: ='Form responses 1'!AQ275 | AI428: ='Form responses 1'!AR275
A429: ='Form responses 1'!B431 -> 46069 | B429: ='Form responses 1'!AZ431 -> moin.khan@capsdelivery.com | C429: ='Form responses 1'!BR431 -> minerva sweet | D429: ='Form responses 1'!AT431 | E429: ='Form responses 1'!AU431 -> Yes | F429: ='Form responses 1'!AX431 -> 46070 | G429: ='Form responses 1'!AY431 -> 0.83333333 | H429: ='Form responses 1'!AW431 -> OWNER WILL BE AVAILABLE AFTER 8 | I429: ='Form responses 1'!AS431 | J429: ='Form responses 1'!J431 | K429: ='Form responses 1'!G431 | L429: ='Form responses 1'!F431 | M429: ='Form responses 1'!U431 -> ashish | N429: ='Form responses 1'!V431 -> 7801005204 | O429: ='Form responses 1'!W431 -> NA | P429: ='Form responses 1'!X431 | Q429: ='Form responses 1'!Y431 | R429: ='Form responses 1'!Z431 | S429: ='Form responses 1'!AC431 | T429: ='Form responses 1'!AE431 | U429: ='Form responses 1'!AG431 | V429: ='Form responses 1'!AI431 | W429: ='Form responses 1'!AJ431 | X429: ='Form responses 1'!AK431 | Y429: =if(S429>0,1,0) -> 0 | Z429: =if(T429>0,1,0) -> 0 | AA429: =if(U429>0,1,0) -> 0 | AB429: =if(V429>0,1,0) -> 0 | AC429: =if(W429>0,1,0) -> 0 | AD429: =if(X429>0,1,0) -> 0 | AE429: ='Form responses 1'!AN431 | AF429: ='Form responses 1'!AO431 | AG429: ='Form responses 1'!AP431 | AH429: ='Form responses 1'!AQ431 | AI429: ='Form responses 1'!AR431
A430: ='Form responses 1'!B552 -> 46070 | B430: ='Form responses 1'!AZ552 -> greeshma.vanneldas@capsdelivery.com | C430: ='Form responses 1'!BR552 -> IFC INDIAN FAV CHEFIFC INDIAN FAV CHEF | D430: ='Form responses 1'!AT552 -> discussion done with owner need to think | E430: ='Form responses 1'!AU552 -> Yes | F430: ='Form responses 1'!AX552 | G430: ='Form responses 1'!AY552 | H430: ='Form responses 1'!AW552 | I430: ='Form responses 1'!AS552 | J430: ='Form responses 1'!J552 | K430: ='Form responses 1'!G552 | L430: ='Form responses 1'!F552 | M430: ='Form responses 1'!U552 -> na | N430: ='Form responses 1'!V552 -> POC-70042 40970(Owner) | O430: ='Form responses 1'!W552 -> na | P430: ='Form responses 1'!X552 | Q430: ='Form responses 1'!Y552 | R430: ='Form responses 1'!Z552 | S430: ='Form responses 1'!AC552 | T430: ='Form responses 1'!AE552 | U430: ='Form responses 1'!AG552 | V430: ='Form responses 1'!AI552 | W430: ='Form responses 1'!AJ552 | X430: ='Form responses 1'!AK552 | Y430: =if(S430>0,1,0) -> 0 | Z430: =if(T430>0,1,0) -> 0 | AA430: =if(U430>0,1,0) -> 0 | AB430: =if(V430>0,1,0) -> 0 | AC430: =if(W430>0,1,0) -> 0 | AD430: =if(X430>0,1,0) -> 0 | AE430: ='Form responses 1'!AN552 | AF430: ='Form responses 1'!AO552 | AG430: ='Form responses 1'!AP552 | AH430: ='Form responses 1'!AQ552 | AI430: ='Form responses 1'!AR552
A431: ='Form responses 1'!B541 -> 46070 | B431: ='Form responses 1'!AZ541 -> greeshma.vanneldas@capsdelivery.com | C431: ='Form responses 1'!BR541 -> Just bake | D431: ='Form responses 1'!AT541 -> meeting scheduled tomorrow | E431: ='Form responses 1'!AU541 -> Yes | F431: ='Form responses 1'!AX541 | G431: ='Form responses 1'!AY541 | H431: ='Form responses 1'!AW541 | I431: ='Form responses 1'!AS541 | J431: ='Form responses 1'!J541 -> Tier-2 (AOV <400) | K431: ='Form responses 1'!G541 -> 300 | L431: ='Form responses 1'!F541 -> 15 | M431: ='Form responses 1'!U541 -> Mohan | N431: ='Form responses 1'!V541 -> 9666669210 | O431: ='Form responses 1'!W541 -> na | P431: ='Form responses 1'!X541 | Q431: ='Form responses 1'!Y541 | R431: ='Form responses 1'!Z541 | S431: ='Form responses 1'!AC541 | T431: ='Form responses 1'!AE541 | U431: ='Form responses 1'!AG541 | V431: ='Form responses 1'!AI541 | W431: ='Form responses 1'!AJ541 | X431: ='Form responses 1'!AK541 | Y431: =if(S431>0,1,0) -> 0 | Z431: =if(T431>0,1,0) -> 0 | AA431: =if(U431>0,1,0) -> 0 | AB431: =if(V431>0,1,0) -> 0 | AC431: =if(W431>0,1,0) -> 0 | AD431: =if(X431>0,1,0) -> 0 | AE431: ='Form responses 1'!AN541 | AF431: ='Form responses 1'!AO541 | AG431: ='Form responses 1'!AP541 | AH431: ='Form responses 1'!AQ541 | AI431: ='Form responses 1'!AR541
A432: ='Form responses 1'!B434 -> 46069 | B432: ='Form responses 1'!AZ434 -> ankitha.baske@capsdelivery.com | C432: ='Form responses 1'!BR434 -> Deccan Dhaba | D432: ='Form responses 1'!AT434 | E432: ='Form responses 1'!AU434 -> Yes | F432: ='Form responses 1'!AX434 | G432: ='Form responses 1'!AY434 | H432: ='Form responses 1'!AW434 | I432: ='Form responses 1'!AS434 | J432: ='Form responses 1'!J434 | K432: ='Form responses 1'!G434 | L432: ='Form responses 1'!F434 | M432: ='Form responses 1'!U434 -> NA | N432: ='Form responses 1'!V434 -> NA | O432: ='Form responses 1'!W434 -> NA | P432: ='Form responses 1'!X434 | Q432: ='Form responses 1'!Y434 | R432: ='Form responses 1'!Z434 | S432: ='Form responses 1'!AC434 | T432: ='Form responses 1'!AE434 | U432: ='Form responses 1'!AG434 | V432: ='Form responses 1'!AI434 | W432: ='Form responses 1'!AJ434 | X432: ='Form responses 1'!AK434 | Y432: =if(S432>0,1,0) -> 0 | Z432: =if(T432>0,1,0) -> 0 | AA432: =if(U432>0,1,0) -> 0 | AB432: =if(V432>0,1,0) -> 0 | AC432: =if(W432>0,1,0) -> 0 | AD432: =if(X432>0,1,0) -> 0 | AE432: ='Form responses 1'!AN434 | AF432: ='Form responses 1'!AO434 | AG432: ='Form responses 1'!AP434 | AH432: ='Form responses 1'!AQ434 | AI432: ='Form responses 1'!AR434
A433: ='Form responses 1'!B435 -> 46069 | B433: ='Form responses 1'!AZ435 -> moin.khan@capsdelivery.com | C433: ='Form responses 1'!BR435 -> priyansh fast food | D433: ='Form responses 1'!AT435 | E433: ='Form responses 1'!AU435 -> Yes | F433: ='Form responses 1'!AX435 -> 46070 | G433: ='Form responses 1'!AY435 -> 0.54166667 | H433: ='Form responses 1'!AW435 | I433: ='Form responses 1'!AS435 -> Yes | J433: ='Form responses 1'!J435 -> Tier-2 (AOV <400) | K433: ='Form responses 1'!G435 -> 250 | L433: ='Form responses 1'!F435 -> 30 | M433: ='Form responses 1'!U435 -> VENKETESH | N433: ='Form responses 1'!V435 -> 832 856 8920 | O433: ='Form responses 1'!W435 -> Rathodvenkat62@gmail.com | P433: ='Form responses 1'!X435 | Q433: ='Form responses 1'!Y435 | R433: ='Form responses 1'!Z435 | S433: ='Form responses 1'!AC435 -> https://drive.google.com/open?id=1WyRpq7Y9UlNtgHY06tO1Rf-kj6bCjxqg | T433: ='Form responses 1'!AE435 | U433: ='Form responses 1'!AG435 -> https://drive.google.com/open?id=1a4jrdCpp0mdyelv-EXaW5gTBFvJFBFj8 | V433: ='Form responses 1'!AI435 | W433: ='Form responses 1'!AJ435 | X433: ='Form responses 1'!AK435 | Y433: =if(S433>0,1,0) -> 1 | Z433: =if(T433>0,1,0) -> 0 | AA433: =if(U433>0,1,0) -> 1 | AB433: =if(V433>0,1,0) -> 0 | AC433: =if(W433>0,1,0) -> 0 | AD433: =if(X433>0,1,0) -> 0 | AE433: ='Form responses 1'!AN435 | AF433: ='Form responses 1'!AO435 | AG433: ='Form responses 1'!AP435 | AH433: ='Form responses 1'!AQ435 | AI433: ='Form responses 1'!AR435
A434: ='Form responses 1'!B436 -> 46069 | B434: ='Form responses 1'!AZ436 -> chanakya.inugala@capsdelivery.com | C434: ='Form responses 1'!BR436 -> Sardarji kitchen | D434: ='Form responses 1'!AT436 | E434: ='Form responses 1'!AU436 -> Yes | F434: ='Form responses 1'!AX436 | G434: ='Form responses 1'!AY436 | H434: ='Form responses 1'!AW436 | I434: ='Form responses 1'!AS436 | J434: ='Form responses 1'!J436 -> Tier-2 (AOV <400) | K434: ='Form responses 1'!G436 -> 200 | L434: ='Form responses 1'!F436 -> 30 | M434: ='Form responses 1'!U436 -> Gurvinder Singh | N434: ='Form responses 1'!V436 -> 9642357335 | O434: ='Form responses 1'!W436 -> Na | P434: ='Form responses 1'!X436 | Q434: ='Form responses 1'!Y436 | R434: ='Form responses 1'!Z436 | S434: ='Form responses 1'!AC436 | T434: ='Form responses 1'!AE436 | U434: ='Form responses 1'!AG436 | V434: ='Form responses 1'!AI436 | W434: ='Form responses 1'!AJ436 | X434: ='Form responses 1'!AK436 | Y434: =if(S434>0,1,0) -> 0 | Z434: =if(T434>0,1,0) -> 0 | AA434: =if(U434>0,1,0) -> 0 | AB434: =if(V434>0,1,0) -> 0 | AC434: =if(W434>0,1,0) -> 0 | AD434: =if(X434>0,1,0) -> 0 | AE434: ='Form responses 1'!AN436 | AF434: ='Form responses 1'!AO436 | AG434: ='Form responses 1'!AP436 | AH434: ='Form responses 1'!AQ436 | AI434: ='Form responses 1'!AR436
A435: ='Form responses 1'!B437 -> 46069 | B435: ='Form responses 1'!AZ437 -> moin.khan@capsdelivery.com | C435: ='Form responses 1'!BR437 -> mysore bakery | D435: ='Form responses 1'!AT437 -> ONBOARDED | E435: ='Form responses 1'!AU437 -> No | F435: ='Form responses 1'!AX437 | G435: ='Form responses 1'!AY437 | H435: ='Form responses 1'!AW437 | I435: ='Form responses 1'!AS437 -> Yes | J435: ='Form responses 1'!J437 -> Tier-2 (AOV <400) | K435: ='Form responses 1'!G437 -> 300 | L435: ='Form responses 1'!F437 -> 20 | M435: ='Form responses 1'!U437 -> DINESH | N435: ='Form responses 1'!V437 -> 9885238434 | O435: ='Form responses 1'!W437 -> NA | P435: ='Form responses 1'!X437 | Q435: ='Form responses 1'!Y437 | R435: ='Form responses 1'!Z437 | S435: ='Form responses 1'!AC437 -> https://drive.google.com/open?id=1d95a7vRIcXsPASPsC4bzqOyFhSVR4OSZ | T435: ='Form responses 1'!AE437 | U435: ='Form responses 1'!AG437 -> https://drive.google.com/open?id=1Ob5ZsFBnNcbO1RXlHH9F9alkofaUv9JU | V435: ='Form responses 1'!AI437 | W435: ='Form responses 1'!AJ437 | X435: ='Form responses 1'!AK437 -> https://drive.google.com/open?id=1dxElB3vRZ1tS6RVyXUrVqeRnYh81rGTu | Y435: =if(S435>0,1,0) -> 1 | Z435: =if(T435>0,1,0) -> 0 | AA435: =if(U435>0,1,0) -> 1 | AB435: =if(V435>0,1,0) -> 0 | AC435: =if(W435>0,1,0) -> 0 | AD435: =if(X435>0,1,0) -> 1 | AE435: ='Form responses 1'!AN437 -> C DINESH KUMAR | AF435: ='Form responses 1'!AO437 -> C DINESH KUMAR | AG435: ='Form responses 1'!AP437 | AH435: ='Form responses 1'!AQ437 | AI435: ='Form responses 1'!AR437 -> C DINESH KUMAR
A436: ='Form responses 1'!B438 -> 46069 | B436: ='Form responses 1'!AZ438 -> chanakya.inugala@capsdelivery.com | C436: ='Form responses 1'!BR438 -> Kingston Restaurant | D436: ='Form responses 1'!AT438 | E436: ='Form responses 1'!AU438 -> Yes | F436: ='Form responses 1'!AX438 | G436: ='Form responses 1'!AY438 | H436: ='Form responses 1'!AW438 | I436: ='Form responses 1'!AS438 | J436: ='Form responses 1'!J438 -> Tier-2 (AOV <400) | K436: ='Form responses 1'!G438 -> 300 | L436: ='Form responses 1'!F438 -> 50 | M436: ='Form responses 1'!U438 -> Sultan | N436: ='Form responses 1'!V438 -> Na | O436: ='Form responses 1'!W438 -> Na | P436: ='Form responses 1'!X438 | Q436: ='Form responses 1'!Y438 | R436: ='Form responses 1'!Z438 | S436: ='Form responses 1'!AC438 | T436: ='Form responses 1'!AE438 | U436: ='Form responses 1'!AG438 | V436: ='Form responses 1'!AI438 | W436: ='Form responses 1'!AJ438 | X436: ='Form responses 1'!AK438 | Y436: =if(S436>0,1,0) -> 0 | Z436: =if(T436>0,1,0) -> 0 | AA436: =if(U436>0,1,0) -> 0 | AB436: =if(V436>0,1,0) -> 0 | AC436: =if(W436>0,1,0) -> 0 | AD436: =if(X436>0,1,0) -> 0 | AE436: ='Form responses 1'!AN438 | AF436: ='Form responses 1'!AO438 | AG436: ='Form responses 1'!AP438 | AH436: ='Form responses 1'!AQ438 | AI436: ='Form responses 1'!AR438
A437: ='Form responses 1'!B439 -> 46069 | B437: ='Form responses 1'!AZ439 -> chanakya.inugala@capsdelivery.com | C437: ='Form responses 1'!BR439 -> Akshaya bhojanam | D437: ='Form responses 1'!AT439 | E437: ='Form responses 1'!AU439 -> Yes | F437: ='Form responses 1'!AX439 | G437: ='Form responses 1'!AY439 | H437: ='Form responses 1'!AW439 | I437: ='Form responses 1'!AS439 | J437: ='Form responses 1'!J439 -> Tier-3 ( AOV<200 ) | K437: ='Form responses 1'!G439 -> 200 | L437: ='Form responses 1'!F439 -> 15 | M437: ='Form responses 1'!U439 -> Santhosh | N437: ='Form responses 1'!V439 -> 9790769073 | O437: ='Form responses 1'!W439 -> Na | P437: ='Form responses 1'!X439 | Q437: ='Form responses 1'!Y439 | R437: ='Form responses 1'!Z439 | S437: ='Form responses 1'!AC439 | T437: ='Form responses 1'!AE439 | U437: ='Form responses 1'!AG439 | V437: ='Form responses 1'!AI439 | W437: ='Form responses 1'!AJ439 | X437: ='Form responses 1'!AK439 | Y437: =if(S437>0,1,0) -> 0 | Z437: =if(T437>0,1,0) -> 0 | AA437: =if(U437>0,1,0) -> 0 | AB437: =if(V437>0,1,0) -> 0 | AC437: =if(W437>0,1,0) -> 0 | AD437: =if(X437>0,1,0) -> 0 | AE437: ='Form responses 1'!AN439 | AF437: ='Form responses 1'!AO439 | AG437: ='Form responses 1'!AP439 | AH437: ='Form responses 1'!AQ439 | AI437: ='Form responses 1'!AR439
A438: ='Form responses 1'!B440 -> 46069 | B438: ='Form responses 1'!AZ440 -> moin.khan@capsdelivery.com | C438: ='Form responses 1'!BR440 -> NAWAB CAFETERIANAWAB CAFETERIA | D438: ='Form responses 1'!AT440 | E438: ='Form responses 1'!AU440 -> Yes | F438: ='Form responses 1'!AX440 -> 46070 | G438: ='Form responses 1'!AY440 -> 0.71875 | H438: ='Form responses 1'!AW440 -> ASKED TO COME 5 PM | I438: ='Form responses 1'!AS440 | J438: ='Form responses 1'!J440 | K438: ='Form responses 1'!G440 | L438: ='Form responses 1'!F440 | M438: ='Form responses 1'!U440 -> IRFAN | N438: ='Form responses 1'!V440 -> +91 891 919 3385 | O438: ='Form responses 1'!W440 -> mohammedirfan5731@gmail.com | P438: ='Form responses 1'!X440 | Q438: ='Form responses 1'!Y440 | R438: ='Form responses 1'!Z440 | S438: ='Form responses 1'!AC440 | T438: ='Form responses 1'!AE440 | U438: ='Form responses 1'!AG440 | V438: ='Form responses 1'!AI440 | W438: ='Form responses 1'!AJ440 | X438: ='Form responses 1'!AK440 | Y438: =if(S438>0,1,0) -> 0 | Z438: =if(T438>0,1,0) -> 0 | AA438: =if(U438>0,1,0) -> 0 | AB438: =if(V438>0,1,0) -> 0 | AC438: =if(W438>0,1,0) -> 0 | AD438: =if(X438>0,1,0) -> 0 | AE438: ='Form responses 1'!AN440 | AF438: ='Form responses 1'!AO440 | AG438: ='Form responses 1'!AP440 | AH438: ='Form responses 1'!AQ440 | AI438: ='Form responses 1'!AR440
A439: ='Form responses 1'!B733 -> 46073 | B439: ='Form responses 1'!AZ733 -> greeshma.vanneldas@capsdelivery.com | C439: ='Form responses 1'!BR733 -> Kadak house | D439: ='Form responses 1'!AT733 -> They have 6 outlets,main branch is in jubliee hills kbr park | E439: ='Form responses 1'!AU733 -> Yes | F439: ='Form responses 1'!AX733 | G439: ='Form responses 1'!AY733 | H439: ='Form responses 1'!AW733 | I439: ='Form responses 1'!AS733 | J439: ='Form responses 1'!J733 | K439: ='Form responses 1'!G733 | L439: ='Form responses 1'!F733 | M439: ='Form responses 1'!U733 -> sameer | N439: ='Form responses 1'!V733 -> na | O439: ='Form responses 1'!W733 -> na | P439: ='Form responses 1'!X733 | Q439: ='Form responses 1'!Y733 | R439: ='Form responses 1'!Z733 | S439: ='Form responses 1'!AC733 | T439: ='Form responses 1'!AE733 | U439: ='Form responses 1'!AG733 | V439: ='Form responses 1'!AI733 | W439: ='Form responses 1'!AJ733 | X439: ='Form responses 1'!AK733 | Y439: =if(S439>0,1,0) -> 0 | Z439: =if(T439>0,1,0) -> 0 | AA439: =if(U439>0,1,0) -> 0 | AB439: =if(V439>0,1,0) -> 0 | AC439: =if(W439>0,1,0) -> 0 | AD439: =if(X439>0,1,0) -> 0 | AE439: ='Form responses 1'!AN733 | AF439: ='Form responses 1'!AO1852 | AG439: ='Form responses 1'!AP1852 | AH439: ='Form responses 1'!AQ1852 | AI439: ='Form responses 1'!AR1852
A440: ='Form responses 1'!B442 -> 46069 | B440: ='Form responses 1'!AZ442 -> manisha.kumari@capsdelivery.com | C440: ='Form responses 1'!BR442 -> Hard Rock CafeHard Rock Cafe | D440: ='Form responses 1'!AT442 -> Asked to share the proposal over the email | E440: ='Form responses 1'!AU442 -> Yes | F440: ='Form responses 1'!AX442 -> 46070 | G440: ='Form responses 1'!AY442 | H440: ='Form responses 1'!AW442 | I440: ='Form responses 1'!AS442 | J440: ='Form responses 1'!J442 -> Tier-1(AOV>400) | K440: ='Form responses 1'!G442 -> 800 | L440: ='Form responses 1'!F442 -> 80 | M440: ='Form responses 1'!U442 -> T Naveen Kumar | N440: ='Form responses 1'!V442 -> 9985287122 | O440: ='Form responses 1'!W442 -> om.hrchyd@jsmcorp.in | P440: ='Form responses 1'!X442 | Q440: ='Form responses 1'!Y442 | R440: ='Form responses 1'!Z442 | S440: ='Form responses 1'!AC442 | T440: ='Form responses 1'!AE442 | U440: ='Form responses 1'!AG442 | V440: ='Form responses 1'!AI442 | W440: ='Form responses 1'!AJ442 | X440: ='Form responses 1'!AK442 | Y440: =if(S440>0,1,0) -> 0 | Z440: =if(T440>0,1,0) -> 0 | AA440: =if(U440>0,1,0) -> 0 | AB440: =if(V440>0,1,0) -> 0 | AC440: =if(W440>0,1,0) -> 0 | AD440: =if(X440>0,1,0) -> 0 | AE440: ='Form responses 1'!AN442 | AF440: ='Form responses 1'!AO442 | AG440: ='Form responses 1'!AP442 | AH440: ='Form responses 1'!AQ442 | AI440: ='Form responses 1'!AR442
A441: ='Form responses 1'!B443 -> 46069 | B441: ='Form responses 1'!AZ443 -> sumadhur.mummadi@capsdelivery.com | C441: ='Form responses 1'!BR443 -> Deerga Ayushman bhava Deerga Ayushman bhava | D441: ='Form responses 1'!AT443 -> Onboarding will be done tomorrow | E441: ='Form responses 1'!AU443 -> Yes | F441: ='Form responses 1'!AX443 -> 46070 | G441: ='Form responses 1'!AY443 -> 0.54166667 | H441: ='Form responses 1'!AW443 | I441: ='Form responses 1'!AS443 | J441: ='Form responses 1'!J443 | K441: ='Form responses 1'!G443 | L441: ='Form responses 1'!F443 | M441: ='Form responses 1'!U443 -> Srinivas | N441: ='Form responses 1'!V443 -> +91 96180 84946 | O441: ='Form responses 1'!W443 -> NA | P441: ='Form responses 1'!X443 | Q441: ='Form responses 1'!Y443 | R441: ='Form responses 1'!Z443 | S441: ='Form responses 1'!AC443 | T441: ='Form responses 1'!AE443 | U441: ='Form responses 1'!AG443 | V441: ='Form responses 1'!AI443 | W441: ='Form responses 1'!AJ443 | X441: ='Form responses 1'!AK443 | Y441: =if(S441>0,1,0) -> 0 | Z441: =if(T441>0,1,0) -> 0 | AA441: =if(U441>0,1,0) -> 0 | AB441: =if(V441>0,1,0) -> 0 | AC441: =if(W441>0,1,0) -> 0 | AD441: =if(X441>0,1,0) -> 0 | AE441: ='Form responses 1'!AN443 | AF441: ='Form responses 1'!AO443 | AG441: ='Form responses 1'!AP443 | AH441: ='Form responses 1'!AQ443 | AI441: ='Form responses 1'!AR443
A442: ='Form responses 1'!B444 -> 46069 | B442: ='Form responses 1'!AZ444 -> sumadhur.mummadi@capsdelivery.com | C442: ='Form responses 1'!BR444 -> Simply parottas Simply parottas | D442: ='Form responses 1'!AT444 -> I should call him tomorrow at 1:00 regarding an update from his side | E442: ='Form responses 1'!AU444 -> Yes | F442: ='Form responses 1'!AX444 -> 46070 | G442: ='Form responses 1'!AY444 -> 0.54166667 | H442: ='Form responses 1'!AW444 | I442: ='Form responses 1'!AS444 | J442: ='Form responses 1'!J444 | K442: ='Form responses 1'!G444 | L442: ='Form responses 1'!F444 | M442: ='Form responses 1'!U444 -> Rupesh | N442: ='Form responses 1'!V444 -> 7991231238 | O442: ='Form responses 1'!W444 -> NA | P442: ='Form responses 1'!X444 | Q442: ='Form responses 1'!Y444 | R442: ='Form responses 1'!Z444 | S442: ='Form responses 1'!AC444 | T442: ='Form responses 1'!AE444 | U442: ='Form responses 1'!AG444 | V442: ='Form responses 1'!AI444 | W442: ='Form responses 1'!AJ444 | X442: ='Form responses 1'!AK444 | Y442: =if(S442>0,1,0) -> 0 | Z442: =if(T442>0,1,0) -> 0 | AA442: =if(U442>0,1,0) -> 0 | AB442: =if(V442>0,1,0) -> 0 | AC442: =if(W442>0,1,0) -> 0 | AD442: =if(X442>0,1,0) -> 0 | AE442: ='Form responses 1'!AN444 | AF442: ='Form responses 1'!AO444 | AG442: ='Form responses 1'!AP444 | AH442: ='Form responses 1'!AQ444 | AI442: ='Form responses 1'!AR444
A443: ='Form responses 1'!B445 -> 46069 | B443: ='Form responses 1'!AZ445 -> sumadhur.mummadi@capsdelivery.com | C443: ='Form responses 1'!BR445 -> Hari dosaHari dosa | D443: ='Form responses 1'!AT445 -> He asked for two days time regarding the decision. Will follow him up | E443: ='Form responses 1'!AU445 -> Yes | F443: ='Form responses 1'!AX445 | G443: ='Form responses 1'!AY445 | H443: ='Form responses 1'!AW445 | I443: ='Form responses 1'!AS445 | J443: ='Form responses 1'!J445 | K443: ='Form responses 1'!G445 | L443: ='Form responses 1'!F445 | M443: ='Form responses 1'!U445 -> Hari palve | N443: ='Form responses 1'!V445 -> +917702428848 | O443: ='Form responses 1'!W445 -> NA | P443: ='Form responses 1'!X445 | Q443: ='Form responses 1'!Y445 | R443: ='Form responses 1'!Z445 | S443: ='Form responses 1'!AC445 | T443: ='Form responses 1'!AE445 | U443: ='Form responses 1'!AG445 | V443: ='Form responses 1'!AI445 | W443: ='Form responses 1'!AJ445 | X443: ='Form responses 1'!AK445 | Y443: =if(S443>0,1,0) -> 0 | Z443: =if(T443>0,1,0) -> 0 | AA443: =if(U443>0,1,0) -> 0 | AB443: =if(V443>0,1,0) -> 0 | AC443: =if(W443>0,1,0) -> 0 | AD443: =if(X443>0,1,0) -> 0 | AE443: ='Form responses 1'!AN445 | AF443: ='Form responses 1'!AO445 | AG443: ='Form responses 1'!AP445 | AH443: ='Form responses 1'!AQ445 | AI443: ='Form responses 1'!AR445
A444: ='Form responses 1'!B446 -> 46069 | B444: ='Form responses 1'!AZ446 -> sumadhur.mummadi@capsdelivery.com | C444: ='Form responses 1'!BR446 -> Missamma restaurant Missamma restaurant | D444: ='Form responses 1'!AT446 -> The receptionist asked me to call tomorrow at 11am for checking the availability of the owner | E444: ='Form responses 1'!AU446 -> Yes | F444: ='Form responses 1'!AX446 | G444: ='Form responses 1'!AY446 | H444: ='Form responses 1'!AW446 | I444: ='Form responses 1'!AS446 | J444: ='Form responses 1'!J446 | K444: ='Form responses 1'!G446 | L444: ='Form responses 1'!F446 | M444: ='Form responses 1'!U446 -> NA | N444: ='Form responses 1'!V446 -> 96422 34333 | O444: ='Form responses 1'!W446 -> NA | P444: ='Form responses 1'!X446 | Q444: ='Form responses 1'!Y446 | R444: ='Form responses 1'!Z446 | S444: ='Form responses 1'!AC446 | T444: ='Form responses 1'!AE446 | U444: ='Form responses 1'!AG446 | V444: ='Form responses 1'!AI446 | W444: ='Form responses 1'!AJ446 | X444: ='Form responses 1'!AK446 | Y444: =if(S444>0,1,0) -> 0 | Z444: =if(T444>0,1,0) -> 0 | AA444: =if(U444>0,1,0) -> 0 | AB444: =if(V444>0,1,0) -> 0 | AC444: =if(W444>0,1,0) -> 0 | AD444: =if(X444>0,1,0) -> 0 | AE444: ='Form responses 1'!AN446 | AF444: ='Form responses 1'!AO446 | AG444: ='Form responses 1'!AP446 | AH444: ='Form responses 1'!AQ446 | AI444: ='Form responses 1'!AR446
A445: ='Form responses 1'!B447 -> 46069 | B445: ='Form responses 1'!AZ447 -> sumadhur.mummadi@capsdelivery.com | C445: ='Form responses 1'!BR447 -> Poruginti chepala pulusu Poruginti chepala pulusu | D445: ='Form responses 1'!AT447 -> He has asked for time regarding the decision but he is interested . I will follow up the day after tomorrow | E445: ='Form responses 1'!AU447 -> Yes | F445: ='Form responses 1'!AX447 | G445: ='Form responses 1'!AY447 | H445: ='Form responses 1'!AW447 | I445: ='Form responses 1'!AS447 | J445: ='Form responses 1'!J447 | K445: ='Form responses 1'!G447 | L445: ='Form responses 1'!F447 | M445: ='Form responses 1'!U447 -> Naveen | N445: ='Form responses 1'!V447 -> 90595 55171 | O445: ='Form responses 1'!W447 -> NA | P445: ='Form responses 1'!X447 | Q445: ='Form responses 1'!Y447 | R445: ='Form responses 1'!Z447 | S445: ='Form responses 1'!AC447 | T445: ='Form responses 1'!AE447 | U445: ='Form responses 1'!AG447 | V445: ='Form responses 1'!AI447 | W445: ='Form responses 1'!AJ447 | X445: ='Form responses 1'!AK447 | Y445: =if(S445>0,1,0) -> 0 | Z445: =if(T445>0,1,0) -> 0 | AA445: =if(U445>0,1,0) -> 0 | AB445: =if(V445>0,1,0) -> 0 | AC445: =if(W445>0,1,0) -> 0 | AD445: =if(X445>0,1,0) -> 0 | AE445: ='Form responses 1'!AN447 | AF445: ='Form responses 1'!AO447 | AG445: ='Form responses 1'!AP447 | AH445: ='Form responses 1'!AQ447 | AI445: ='Form responses 1'!AR447
A446: ='Form responses 1'!B448 -> 46069 | B446: ='Form responses 1'!AZ448 -> sumadhur.mummadi@capsdelivery.com | C446: ='Form responses 1'!BR448 -> Rainbow mandi restaurant Rainbow mandi | D446: ='Form responses 1'!AT448 -> They have agreed to onboard next Monday | E446: ='Form responses 1'!AU448 -> No | F446: ='Form responses 1'!AX448 | G446: ='Form responses 1'!AY448 | H446: ='Form responses 1'!AW448 | I446: ='Form responses 1'!AS448 | J446: ='Form responses 1'!J448 | K446: ='Form responses 1'!G448 | L446: ='Form responses 1'!F448 | M446: ='Form responses 1'!U448 -> Divya | N446: ='Form responses 1'!V448 -> 7995243674 | O446: ='Form responses 1'!W448 -> NA | P446: ='Form responses 1'!X448 | Q446: ='Form responses 1'!Y448 | R446: ='Form responses 1'!Z448 | S446: ='Form responses 1'!AC448 | T446: ='Form responses 1'!AE448 | U446: ='Form responses 1'!AG448 | V446: ='Form responses 1'!AI448 | W446: ='Form responses 1'!AJ448 | X446: ='Form responses 1'!AK448 | Y446: =if(S446>0,1,0) -> 0 | Z446: =if(T446>0,1,0) -> 0 | AA446: =if(U446>0,1,0) -> 0 | AB446: =if(V446>0,1,0) -> 0 | AC446: =if(W446>0,1,0) -> 0 | AD446: =if(X446>0,1,0) -> 0 | AE446: ='Form responses 1'!AN448 | AF446: ='Form responses 1'!AO448 | AG446: ='Form responses 1'!AP448 | AH446: ='Form responses 1'!AQ448 | AI446: ='Form responses 1'!AR448
A447: ='Form responses 1'!B449 -> 46069 | B447: ='Form responses 1'!AZ449 -> sumadhur.mummadi@capsdelivery.com | C447: ='Form responses 1'!BR449 -> Ritvikas kitchenRitvikas kitchen | D447: ='Form responses 1'!AT449 -> I should call Mr Surendra owner tomorrow | E447: ='Form responses 1'!AU449 -> Yes | F447: ='Form responses 1'!AX449 | G447: ='Form responses 1'!AY449 | H447: ='Form responses 1'!AW449 | I447: ='Form responses 1'!AS449 | J447: ='Form responses 1'!J449 | K447: ='Form responses 1'!G449 | L447: ='Form responses 1'!F449 | M447: ='Form responses 1'!U449 -> Surendra | N447: ='Form responses 1'!V449 -> +919127893278 | O447: ='Form responses 1'!W449 -> NA | P447: ='Form responses 1'!X449 | Q447: ='Form responses 1'!Y449 | R447: ='Form responses 1'!Z449 | S447: ='Form responses 1'!AC449 | T447: ='Form responses 1'!AE449 | U447: ='Form responses 1'!AG449 | V447: ='Form responses 1'!AI449 | W447: ='Form responses 1'!AJ449 | X447: ='Form responses 1'!AK449 | Y447: =if(S447>0,1,0) -> 0 | Z447: =if(T447>0,1,0) -> 0 | AA447: =if(U447>0,1,0) -> 0 | AB447: =if(V447>0,1,0) -> 0 | AC447: =if(W447>0,1,0) -> 0 | AD447: =if(X447>0,1,0) -> 0 | AE447: ='Form responses 1'!AN449 | AF447: ='Form responses 1'!AO449 | AG447: ='Form responses 1'!AP449 | AH447: ='Form responses 1'!AQ449 | AI447: ='Form responses 1'!AR449
A448: ='Form responses 1'!B450 -> 46069 | B448: ='Form responses 1'!AZ450 -> sumadhur.mummadi@capsdelivery.com | C448: ='Form responses 1'!BR450 -> Raagam foods Raagam foods | D448: ='Form responses 1'!AT450 -> I should call him tomorrow for appointment | E448: ='Form responses 1'!AU450 -> Yes | F448: ='Form responses 1'!AX450 | G448: ='Form responses 1'!AY450 | H448: ='Form responses 1'!AW450 | I448: ='Form responses 1'!AS450 | J448: ='Form responses 1'!J450 | K448: ='Form responses 1'!G450 | L448: ='Form responses 1'!F450 | M448: ='Form responses 1'!U450 -> 9381425752 | N448: ='Form responses 1'!V450 -> NA | O448: ='Form responses 1'!W450 -> NA | P448: ='Form responses 1'!X450 | Q448: ='Form responses 1'!Y450 | R448: ='Form responses 1'!Z450 | S448: ='Form responses 1'!AC450 | T448: ='Form responses 1'!AE450 | U448: ='Form responses 1'!AG450 | V448: ='Form responses 1'!AI450 | W448: ='Form responses 1'!AJ450 | X448: ='Form responses 1'!AK450 | Y448: =if(S448>0,1,0) -> 0 | Z448: =if(T448>0,1,0) -> 0 | AA448: =if(U448>0,1,0) -> 0 | AB448: =if(V448>0,1,0) -> 0 | AC448: =if(W448>0,1,0) -> 0 | AD448: =if(X448>0,1,0) -> 0 | AE448: ='Form responses 1'!AN450 | AF448: ='Form responses 1'!AO450 | AG448: ='Form responses 1'!AP450 | AH448: ='Form responses 1'!AQ450 | AI448: ='Form responses 1'!AR450
A449: ='Form responses 1'!B451 -> 46069 | B449: ='Form responses 1'!AZ451 -> sumadhur.mummadi@capsdelivery.com | C449: ='Form responses 1'!BR451 -> Kings biryani adda Kings biryani adda | D449: ='Form responses 1'!AT451 -> This restaurant's owner has been postponing onboarding from the last 3 days | E449: ='Form responses 1'!AU451 -> Yes | F449: ='Form responses 1'!AX451 -> 46070 | G449: ='Form responses 1'!AY451 -> 0.75 | H449: ='Form responses 1'!AW451 | I449: ='Form responses 1'!AS451 | J449: ='Form responses 1'!J451 | K449: ='Form responses 1'!G451 | L449: ='Form responses 1'!F451 | M449: ='Form responses 1'!U451 -> Mahesh | N449: ='Form responses 1'!V451 -> 87901 30941 | O449: ='Form responses 1'!W451 -> NA | P449: ='Form responses 1'!X451 | Q449: ='Form responses 1'!Y451 | R449: ='Form responses 1'!Z451 | S449: ='Form responses 1'!AC451 | T449: ='Form responses 1'!AE451 | U449: ='Form responses 1'!AG451 | V449: ='Form responses 1'!AI451 | W449: ='Form responses 1'!AJ451 | X449: ='Form responses 1'!AK451 | Y449: =if(S449>0,1,0) -> 0 | Z449: =if(T449>0,1,0) -> 0 | AA449: =if(U449>0,1,0) -> 0 | AB449: =if(V449>0,1,0) -> 0 | AC449: =if(W449>0,1,0) -> 0 | AD449: =if(X449>0,1,0) -> 0 | AE449: ='Form responses 1'!AN451 | AF449: ='Form responses 1'!AO451 | AG449: ='Form responses 1'!AP451 | AH449: ='Form responses 1'!AQ451 | AI449: ='Form responses 1'!AR451
A450: ='Form responses 1'!B452 -> 46069 | B450: ='Form responses 1'!AZ452 -> sumadhur.mummadi@capsdelivery.com | C450: ='Form responses 1'!BR452 -> Emerald food house Emerald food house | D450: ='Form responses 1'!AT452 -> Mr venu has asked me to meet after 4 pm tomorrow | E450: ='Form responses 1'!AU452 -> Yes | F450: ='Form responses 1'!AX452 -> 46070 | G450: ='Form responses 1'!AY452 -> 0.66666667 | H450: ='Form responses 1'!AW452 | I450: ='Form responses 1'!AS452 | J450: ='Form responses 1'!J452 | K450: ='Form responses 1'!G452 | L450: ='Form responses 1'!F452 | M450: ='Form responses 1'!U452 -> Venu | N450: ='Form responses 1'!V452 -> 93461 12262 | O450: ='Form responses 1'!W452 -> NA | P450: ='Form responses 1'!X452 | Q450: ='Form responses 1'!Y452 | R450: ='Form responses 1'!Z452 | S450: ='Form responses 1'!AC452 | T450: ='Form responses 1'!AE452 | U450: ='Form responses 1'!AG452 | V450: ='Form responses 1'!AI452 | W450: ='Form responses 1'!AJ452 | X450: ='Form responses 1'!AK452 | Y450: =if(S450>0,1,0) -> 0 | Z450: =if(T450>0,1,0) -> 0 | AA450: =if(U450>0,1,0) -> 0 | AB450: =if(V450>0,1,0) -> 0 | AC450: =if(W450>0,1,0) -> 0 | AD450: =if(X450>0,1,0) -> 0 | AE450: ='Form responses 1'!AN452 | AF450: ='Form responses 1'!AO452 | AG450: ='Form responses 1'!AP452 | AH450: ='Form responses 1'!AQ452 | AI450: ='Form responses 1'!AR452
A451: ='Form responses 1'!B453 -> 46069 | B451: ='Form responses 1'!AZ453 -> sumadhur.mummadi@capsdelivery.com | C451: ='Form responses 1'!BR453 -> QubzQubz | D451: ='Form responses 1'!AT453 -> He has asked me to call and come tomorrow after 4pm | E451: ='Form responses 1'!AU453 -> Yes | F451: ='Form responses 1'!AX453 -> 46070 | G451: ='Form responses 1'!AY453 -> 0.66666667 | H451: ='Form responses 1'!AW453 | I451: ='Form responses 1'!AS453 | J451: ='Form responses 1'!J453 | K451: ='Form responses 1'!G453 | L451: ='Form responses 1'!F453 | M451: ='Form responses 1'!U453 -> Hemanth | N451: ='Form responses 1'!V453 -> 81425 20056 | O451: ='Form responses 1'!W453 -> NA | P451: ='Form responses 1'!X453 | Q451: ='Form responses 1'!Y453 | R451: ='Form responses 1'!Z453 | S451: ='Form responses 1'!AC453 | T451: ='Form responses 1'!AE453 | U451: ='Form responses 1'!AG453 | V451: ='Form responses 1'!AI453 | W451: ='Form responses 1'!AJ453 | X451: ='Form responses 1'!AK453 | Y451: =if(S451>0,1,0) -> 0 | Z451: =if(T451>0,1,0) -> 0 | AA451: =if(U451>0,1,0) -> 0 | AB451: =if(V451>0,1,0) -> 0 | AC451: =if(W451>0,1,0) -> 0 | AD451: =if(X451>0,1,0) -> 0 | AE451: ='Form responses 1'!AN453 | AF451: ='Form responses 1'!AO453 | AG451: ='Form responses 1'!AP453 | AH451: ='Form responses 1'!AQ453 | AI451: ='Form responses 1'!AR453
... A464: ='Form responses 1'!B466 -> 46069 | B464: ='Form responses 1'!AZ466 -> akhila.narra@capsdelivery.com | C464: ='Form responses 1'!BR466 -> Sri Raghavendra Bhavan | D464: ='Form responses 1'!AT466 -> Na | E464: ='Form responses 1'!AU466 -> Yes | F464: ='Form responses 1'!AX466 -> 46069 | G464: ='Form responses 1'!AY466 -> 0.10416667 | H464: ='Form responses 1'!AW466 -> Intrested to Onboard | I464: ='Form responses 1'!AS466 | J464: ='Form responses 1'!J466 -> Tier-2 (AOV <400) | K464: ='Form responses 1'!G466 -> 270 | L464: ='Form responses 1'!F466 -> 120 | M464: ='Form responses 1'!U466 -> Swamy | N464: ='Form responses 1'!V466 -> 7702942820 | O464: ='Form responses 1'!W466 -> Na | P464: ='Form responses 1'!X466 | Q464: ='Form responses 1'!Y466 | R464: ='Form responses 1'!Z466 | S464: ='Form responses 1'!AC466 | T464: ='Form responses 1'!AE466 | U464: ='Form responses 1'!AG466 | V464: ='Form responses 1'!AI466 | W464: ='Form responses 1'!AJ466 | X464: ='Form responses 1'!AK466 | Y464: =if(S464>0,1,0) -> 0 | Z464: =if(T464>0,1,0) -> 0 | AA464: =if(U464>0,1,0) -> 0 | AB464: =if(V464>0,1,0) -> 0 | AC464: =if(W464>0,1,0) -> 0 | AD464: =if(X464>0,1,0) -> 0 | AE464: ='Form responses 1'!AN466 | AF464: ='Form responses 1'!AO466 | AG464: ='Form responses 1'!AP466 | AH464: ='Form responses 1'!AQ466 | AI464: ='Form responses 1'!AR466
A465: ='Form responses 1'!B685 -> 46073 | B465: ='Form responses 1'!AZ685 -> greeshma.vanneldas@capsdelivery.com | C465: ='Form responses 1'!BR685 -> Kadak house | D465: ='Form responses 1'!AT685 -> The owner will be available in jubliee hills branch they have 6outlets | E465: ='Form responses 1'!AU685 -> Yes | F465: ='Form responses 1'!AX685 | G465: ='Form responses 1'!AY685 | H465: ='Form responses 1'!AW685 | I465: ='Form responses 1'!AS685 | J465: ='Form responses 1'!J685 | K465: ='Form responses 1'!G685 | L465: ='Form responses 1'!F685 | M465: ='Form responses 1'!U685 -> Sameer | N465: ='Form responses 1'!V685 -> Na | O465: ='Form responses 1'!W685 -> Na | P465: ='Form responses 1'!X685 | Q465: ='Form responses 1'!Y685 | R465: ='Form responses 1'!Z685 | S465: ='Form responses 1'!AC685 | T465: ='Form responses 1'!AE685 | U465: ='Form responses 1'!AG685 | V465: ='Form responses 1'!AI685 | W465: ='Form responses 1'!AJ685 | X465: ='Form responses 1'!AK685 | Y465: =if(S465>0,1,0) -> 0 | Z465: =if(T465>0,1,0) -> 0 | AA465: =if(U465>0,1,0) -> 0 | AB465: =if(V465>0,1,0) -> 0 | AC465: =if(W465>0,1,0) -> 0 | AD465: =if(X465>0,1,0) -> 0 | AE465: ='Form responses 1'!AN685 | AF465: ='Form responses 1'!AO1804 | AG465: ='Form responses 1'!AP1804 | AH465: ='Form responses 1'!AQ1804 | AI465: ='Form responses 1'!AR1804
A466: ='Form responses 1'!B661 -> 46071 | B466: ='Form responses 1'!AZ661 -> greeshma.vanneldas@capsdelivery.com | C466: ='Form responses 1'!BR661 -> Kafika | D466: ='Form responses 1'!AT661 -> need to follow up | E466: ='Form responses 1'!AU661 -> Yes | F466: ='Form responses 1'!AX661 | G466: ='Form responses 1'!AY661 | H466: ='Form responses 1'!AW661 | I466: ='Form responses 1'!AS661 | J466: ='Form responses 1'!J661 | K466: ='Form responses 1'!G661 | L466: ='Form responses 1'!F661 | M466: ='Form responses 1'!U661 -> Chakra | N466: ='Form responses 1'!V661 -> 9701959365 | O466: ='Form responses 1'!W661 -> na | P466: ='Form responses 1'!X661 | Q466: ='Form responses 1'!Y661 | R466: ='Form responses 1'!Z661 | S466: ='Form responses 1'!AC661 | T466: ='Form responses 1'!AE661 | U466: ='Form responses 1'!AG661 | V466: ='Form responses 1'!AI661 | W466: ='Form responses 1'!AJ661 | X466: ='Form responses 1'!AK661 | Y466: =if(S466>0,1,0) -> 0 | Z466: =if(T466>0,1,0) -> 0 | AA466: =if(U466>0,1,0) -> 0 | AB466: =if(V466>0,1,0) -> 0 | AC466: =if(W466>0,1,0) -> 0 | AD466: =if(X466>0,1,0) -> 0 | AE466: ='Form responses 1'!AN661 | AF466: ='Form responses 1'!AO1780 | AG466: ='Form responses 1'!AP1780 | AH466: ='Form responses 1'!AQ1780 | AI466: ='Form responses 1'!AR1780
A467: ='Form responses 1'!B139 -> 46063 | B467: ='Form responses 1'!AZ139 -> greeshma.vanneldas@capsdelivery.com | C467: ='Form responses 1'!BR139 -> Kake di hatti | D467: ='Form responses 1'!AT139 | E467: ='Form responses 1'!AU139 -> Yes | F467: ='Form responses 1'!AX139 | G467: ='Form responses 1'!AY139 | H467: ='Form responses 1'!AW139 -> Owner will be available after 21:00Pm in the restaurant(Kondapur) | I467: ='Form responses 1'!AS139 | J467: ='Form responses 1'!J139 -> Tier-1(AOV>400) | K467: ='Form responses 1'!G139 -> 500 | L467: ='Form responses 1'!F139 -> 120 | M467: ='Form responses 1'!U139 -> Prabhakar | N467: ='Form responses 1'!V139 -> 9140523292 | O467: ='Form responses 1'!W139 -> Na | P467: ='Form responses 1'!X139 | Q467: ='Form responses 1'!Y139 | R467: ='Form responses 1'!Z139 | S467: ='Form responses 1'!AC139 | T467: ='Form responses 1'!AE139 | U467: ='Form responses 1'!AG139 | V467: ='Form responses 1'!AI139 | W467: ='Form responses 1'!AJ139 | X467: ='Form responses 1'!AK139 | Y467: =if(S467>0,1,0) -> 0 | Z467: =if(T467>0,1,0) -> 0 | AA467: =if(U467>0,1,0) -> 0 | AB467: =if(V467>0,1,0) -> 0 | AC467: =if(W467>0,1,0) -> 0 | AD467: =if(X467>0,1,0) -> 0 | AE467: ='Form responses 1'!AN139 | AF467: ='Form responses 1'!AO139 | AG467: ='Form responses 1'!AP139 | AH467: ='Form responses 1'!AQ139 | AI467: ='Form responses 1'!AR139
A468: ='Form responses 1'!B470 -> 46069 | B468: ='Form responses 1'!AZ470 -> greeshma.vanneldas@capsdelivery.com | C468: ='Form responses 1'!BR470 -> Palapitta ruchuluPala pitta ruchulu | D468: ='Form responses 1'!AT470 -> Onboarded | E468: ='Form responses 1'!AU470 -> No | F468: ='Form responses 1'!AX470 | G468: ='Form responses 1'!AY470 | H468: ='Form responses 1'!AW470 | I468: ='Form responses 1'!AS470 | J468: ='Form responses 1'!J470 | K468: ='Form responses 1'!G470 | L468: ='Form responses 1'!F470 | M468: ='Form responses 1'!U470 -> Manne hanumanth | N468: ='Form responses 1'!V470 -> 7331139799 | O468: ='Form responses 1'!W470 -> na | P468: ='Form responses 1'!X470 | Q468: ='Form responses 1'!Y470 | R468: ='Form responses 1'!Z470 | S468: ='Form responses 1'!AC470 | T468: ='Form responses 1'!AE470 | U468: ='Form responses 1'!AG470 | V468: ='Form responses 1'!AI470 | W468: ='Form responses 1'!AJ470 | X468: ='Form responses 1'!AK470 | Y468: =if(S468>0,1,0) -> 0 | Z468: =if(T468>0,1,0) -> 0 | AA468: =if(U468>0,1,0) -> 0 | AB468: =if(V468>0,1,0) -> 0 | AC468: =if(W468>0,1,0) -> 0 | AD468: =if(X468>0,1,0) -> 0 | AE468: ='Form responses 1'!AN470 | AF468: ='Form responses 1'!AO470 | AG468: ='Form responses 1'!AP470 | AH468: ='Form responses 1'!AQ470 | AI468: ='Form responses 1'!AR470
A469: ='Form responses 1'!B471 -> 46069 | B469: ='Form responses 1'!AZ471 -> greeshma.vanneldas@capsdelivery.com | C469: ='Form responses 1'!BR471 -> Patnam ruchuluPatnam ruchulu | D469: ='Form responses 1'!AT471 -> Onboarded | E469: ='Form responses 1'!AU471 -> No | F469: ='Form responses 1'!AX471 | G469: ='Form responses 1'!AY471 | H469: ='Form responses 1'!AW471 | I469: ='Form responses 1'!AS471 | J469: ='Form responses 1'!J471 | K469: ='Form responses 1'!G471 | L469: ='Form responses 1'!F471 | M469: ='Form responses 1'!U471 -> Nithesh | N469: ='Form responses 1'!V471 -> 9000464440 | O469: ='Form responses 1'!W471 -> na | P469: ='Form responses 1'!X471 | Q469: ='Form responses 1'!Y471 | R469: ='Form responses 1'!Z471 | S469: ='Form responses 1'!AC471 | T469: ='Form responses 1'!AE471 | U469: ='Form responses 1'!AG471 | V469: ='Form responses 1'!AI471 | W469: ='Form responses 1'!AJ471 | X469: ='Form responses 1'!AK471 | Y469: =if(S469>0,1,0) -> 0 | Z469: =if(T469>0,1,0) -> 0 | AA469: =if(U469>0,1,0) -> 0 | AB469: =if(V469>0,1,0) -> 0 | AC469: =if(W469>0,1,0) -> 0 | AD469: =if(X469>0,1,0) -> 0 | AE469: ='Form responses 1'!AN471 | AF469: ='Form responses 1'!AO471 | AG469: ='Form responses 1'!AP471 | AH469: ='Form responses 1'!AQ471 | AI469: ='Form responses 1'!AR471
A470: ='Form responses 1'!B240 -> 46064 | B470: ='Form responses 1'!AZ240 -> greeshma.vanneldas@capsdelivery.com | C470: ='Form responses 1'!BR240 -> Kanchi cafe | D470: ='Form responses 1'!AT240 | E470: ='Form responses 1'!AU240 -> Yes | F470: ='Form responses 1'!AX240 | G470: ='Form responses 1'!AY240 | H470: ='Form responses 1'!AW240 -> Manager is not available,when I visited the cafe got the contact details,I will follow up | I470: ='Form responses 1'!AS240 | J470: ='Form responses 1'!J240 -> Tier-2 (AOV <400) | K470: ='Form responses 1'!G240 -> 300 | L470: ='Form responses 1'!F240 -> 30 | M470: ='Form responses 1'!U240 -> Dhakshina murthy | N470: ='Form responses 1'!V240 -> 8438457084 | O470: ='Form responses 1'!W240 -> na | P470: ='Form responses 1'!X240 | Q470: ='Form responses 1'!Y240 | R470: ='Form responses 1'!Z240 | S470: ='Form responses 1'!AC240 | T470: ='Form responses 1'!AE240 | U470: ='Form responses 1'!AG240 | V470: ='Form responses 1'!AI240 | W470: ='Form responses 1'!AJ240 | X470: ='Form responses 1'!AK240 | Y470: =if(S470>0,1,0) -> 0 | Z470: =if(T470>0,1,0) -> 0 | AA470: =if(U470>0,1,0) -> 0 | AB470: =if(V470>0,1,0) -> 0 | AC470: =if(W470>0,1,0) -> 0 | AD470: =if(X470>0,1,0) -> 0 | AE470: ='Form responses 1'!AN240 | AF470: ='Form responses 1'!AO240 | AG470: ='Form responses 1'!AP240 | AH470: ='Form responses 1'!AQ240 | AI470: ='Form responses 1'!AR240
A471: ='Form responses 1'!B532 -> 46070 | B471: ='Form responses 1'!AZ532 -> greeshma.vanneldas@capsdelivery.com | C471: ='Form responses 1'!BR532 -> Kings Restaurant and bar | D471: ='Form responses 1'!AT532 -> manager was not available | E471: ='Form responses 1'!AU532 -> Yes | F471: ='Form responses 1'!AX532 | G471: ='Form responses 1'!AY532 | H471: ='Form responses 1'!AW532 | I471: ='Form responses 1'!AS532 | J471: ='Form responses 1'!J532 | K471: ='Form responses 1'!G532 | L471: ='Form responses 1'!F532 | M471: ='Form responses 1'!U532 -> Probin | N471: ='Form responses 1'!V532 -> 9441469962 | O471: ='Form responses 1'!W532 -> na | P471: ='Form responses 1'!X532 | Q471: ='Form responses 1'!Y532 | R471: ='Form responses 1'!Z532 | S471: ='Form responses 1'!AC532 | T471: ='Form responses 1'!AE532 | U471: ='Form responses 1'!AG532 | V471: ='Form responses 1'!AI532 | W471: ='Form responses 1'!AJ532 | X471: ='Form responses 1'!AK532 | Y471: =if(S471>0,1,0) -> 0 | Z471: =if(T471>0,1,0) -> 0 | AA471: =if(U471>0,1,0) -> 0 | AB471: =if(V471>0,1,0) -> 0 | AC471: =if(W471>0,1,0) -> 0 | AD471: =if(X471>0,1,0) -> 0 | AE471: ='Form responses 1'!AN532 | AF471: ='Form responses 1'!AO532 | AG471: ='Form responses 1'!AP532 | AH471: ='Form responses 1'!AQ532 | AI471: ='Form responses 1'!AR532
A472: ='Form responses 1'!B264 -> 46065 | B472: ='Form responses 1'!AZ264 -> greeshma.vanneldas@capsdelivery.com | C472: ='Form responses 1'!BR264 -> Kochin spicesKochinspices | D472: ='Form responses 1'!AT264 | E472: ='Form responses 1'!AU264 -> Yes | F472: ='Form responses 1'!AX264 | G472: ='Form responses 1'!AY264 | H472: ='Form responses 1'!AW264 -> They are 4 partners,discussion done with one partner need to discuss with other partners,200-400 average orders per day in online platforms | I472: ='Form responses 1'!AS264 | J472: ='Form responses 1'!J264 | K472: ='Form responses 1'!G264 | L472: ='Form responses 1'!F264 | M472: ='Form responses 1'!U264 -> Jeff | N472: ='Form responses 1'!V264 -> 9544186712 | O472: ='Form responses 1'!W264 -> na | P472: ='Form responses 1'!X264 | Q472: ='Form responses 1'!Y264 | R472: ='Form responses 1'!Z264 | S472: ='Form responses 1'!AC264 | T472: ='Form responses 1'!AE264 | U472: ='Form responses 1'!AG264 | V472: ='Form responses 1'!AI264 | W472: ='Form responses 1'!AJ264 | X472: ='Form responses 1'!AK264 | Y472: =if(S472>0,1,0) -> 0 | Z472: =if(T472>0,1,0) -> 0 | AA472: =if(U472>0,1,0) -> 0 | AB472: =if(V472>0,1,0) -> 0 | AC472: =if(W472>0,1,0) -> 0 | AD472: =if(X472>0,1,0) -> 0 | AE472: ='Form responses 1'!AN264 | AF472: ='Form responses 1'!AO264 | AG472: ='Form responses 1'!AP264 | AH472: ='Form responses 1'!AQ264 | AI472: ='Form responses 1'!AR264
A473: ='Form responses 1'!B432 -> 46069 | B473: ='Form responses 1'!AZ432 -> greeshma.vanneldas@capsdelivery.com | C473: ='Form responses 1'!BR432 -> Kodi kura chitti gaare | D473: ='Form responses 1'!AT432 | E473: ='Form responses 1'!AU432 -> Yes | F473: ='Form responses 1'!AX432 | G473: ='Form responses 1'!AY432 | H473: ='Form responses 1'!AW432 | I473: ='Form responses 1'!AS432 | J473: ='Form responses 1'!J432 | K473: ='Form responses 1'!G432 | L473: ='Form responses 1'!F432 | M473: ='Form responses 1'!U432 -> Ashish | N473: ='Form responses 1'!V432 -> 8328471182 | O473: ='Form responses 1'!W432 -> na | P473: ='Form responses 1'!X432 | Q473: ='Form responses 1'!Y432 | R473: ='Form responses 1'!Z432 | S473: ='Form responses 1'!AC432 | T473: ='Form responses 1'!AE432 | U473: ='Form responses 1'!AG432 | V473: ='Form responses 1'!AI432 | W473: ='Form responses 1'!AJ432 | X473: ='Form responses 1'!AK432 | Y473: =if(S473>0,1,0) -> 0 | Z473: =if(T473>0,1,0) -> 0 | AA473: =if(U473>0,1,0) -> 0 | AB473: =if(V473>0,1,0) -> 0 | AC473: =if(W473>0,1,0) -> 0 | AD473: =if(X473>0,1,0) -> 0 | AE473: ='Form responses 1'!AN432 | AF473: ='Form responses 1'!AO432 | AG473: ='Form responses 1'!AP432 | AH473: ='Form responses 1'!AQ432 | AI473: ='Form responses 1'!AR432
A474: ='Form responses 1'!B472 -> 46069 | B474: ='Form responses 1'!AZ472 -> greeshma.vanneldas@capsdelivery.com | C474: ='Form responses 1'!BR472 -> Kodi kura chitti gare | D474: ='Form responses 1'!AT472 -> Manager was not available,following up | E474: ='Form responses 1'!AU472 -> Yes | F474: ='Form responses 1'!AX472 | G474: ='Form responses 1'!AY472 | H474: ='Form responses 1'!AW472 | I474: ='Form responses 1'!AS472 | J474: ='Form responses 1'!J472 | K474: ='Form responses 1'!G472 | L474: ='Form responses 1'!F472 | M474: ='Form responses 1'!U472 -> Ashish | N474: ='Form responses 1'!V472 -> 8328471182 | O474: ='Form responses 1'!W472 -> na | P474: ='Form responses 1'!X472 | Q474: ='Form responses 1'!Y472 | R474: ='Form responses 1'!Z472 | S474: ='Form responses 1'!AC472 | T474: ='Form responses 1'!AE472 | U474: ='Form responses 1'!AG472 | V474: ='Form responses 1'!AI472 | W474: ='Form responses 1'!AJ472 | X474: ='Form responses 1'!AK472 | Y474: =if(S474>0,1,0) -> 0 | Z474: =if(T474>0,1,0) -> 0 | AA474: =if(U474>0,1,0) -> 0 | AB474: =if(V474>0,1,0) -> 0 | AC474: =if(W474>0,1,0) -> 0 | AD474: =if(X474>0,1,0) -> 0 | AE474: ='Form responses 1'!AN472 | AF474: ='Form responses 1'!AO472 | AG474: ='Form responses 1'!AP472 | AH474: ='Form responses 1'!AQ472 | AI474: ='Form responses 1'!AR472
A475: ='Form responses 1'!B534 -> 46070 | B475: ='Form responses 1'!AZ534 -> greeshma.vanneldas@capsdelivery.com | C475: ='Form responses 1'!BR534 -> KS Bakers | D475: ='Form responses 1'!AT534 -> Follo up | E475: ='Form responses 1'!AU534 -> Yes | F475: ='Form responses 1'!AX534 | G475: ='Form responses 1'!AY534 | H475: ='Form responses 1'!AW534 | I475: ='Form responses 1'!AS534 | J475: ='Form responses 1'!J534 | K475: ='Form responses 1'!G534 | L475: ='Form responses 1'!F534 | M475: ='Form responses 1'!U534 -> David | N475: ='Form responses 1'!V534 -> 9154819482 | O475: ='Form responses 1'!W534 -> na | P475: ='Form responses 1'!X534 | Q475: ='Form responses 1'!Y534 | R475: ='Form responses 1'!Z534 | S475: ='Form responses 1'!AC534 | T475: ='Form responses 1'!AE534 | U475: ='Form responses 1'!AG534 | V475: ='Form responses 1'!AI534 | W475: ='Form responses 1'!AJ534 | X475: ='Form responses 1'!AK534 | Y475: =if(S475>0,1,0) -> 0 | Z475: =if(T475>0,1,0) -> 0 | AA475: =if(U475>0,1,0) -> 0 | AB475: =if(V475>0,1,0) -> 0 | AC475: =if(W475>0,1,0) -> 0 | AD475: =if(X475>0,1,0) -> 0 | AE475: ='Form responses 1'!AN534 | AF475: ='Form responses 1'!AO534 | AG475: ='Form responses 1'!AP534 | AH475: ='Form responses 1'!AQ534 | AI475: ='Form responses 1'!AR534
A476: ='Form responses 1'!B547 -> 46070 | B476: ='Form responses 1'!AZ547 -> greeshma.vanneldas@capsdelivery.com | C476: ='Form responses 1'!BR547 -> Kulcha kulchaKulcha kulcha | D476: ='Form responses 1'!AT547 -> Meeting fixed with Md | E476: ='Form responses 1'!AU547 -> Yes | F476: ='Form responses 1'!AX547 | G476: ='Form responses 1'!AY547 | H476: ='Form responses 1'!AW547 | I476: ='Form responses 1'!AS547 | J476: ='Form responses 1'!J547 | K476: ='Form responses 1'!G547 | L476: ='Form responses 1'!F547 | M476: ='Form responses 1'!U547 -> Rohith | N476: ='Form responses 1'!V547 -> 9000360723 | O476: ='Form responses 1'!W547 -> na | P476: ='Form responses 1'!X547 | Q476: ='Form responses 1'!Y547 | R476: ='Form responses 1'!Z547 | S476: ='Form responses 1'!AC547 | T476: ='Form responses 1'!AE547 | U476: ='Form responses 1'!AG547 | V476: ='Form responses 1'!AI547 | W476: ='Form responses 1'!AJ547 | X476: ='Form responses 1'!AK547 | Y476: =if(S476>0,1,0) -> 0 | Z476: =if(T476>0,1,0) -> 0 | AA476: =if(U476>0,1,0) -> 0 | AB476: =if(V476>0,1,0) -> 0 | AC476: =if(W476>0,1,0) -> 0 | AD476: =if(X476>0,1,0) -> 0 | AE476: ='Form responses 1'!AN547 | AF476: ='Form responses 1'!AO547 | AG476: ='Form responses 1'!AP547 | AH476: ='Form responses 1'!AQ547 | AI476: ='Form responses 1'!AR547
A477: ='Form responses 1'!B660 -> 46071 | B477: ='Form responses 1'!AZ660 -> greeshma.vanneldas@capsdelivery.com | C477: ='Form responses 1'!BR660 -> Kulcha kulchaKulcha kulcha | D477: ='Form responses 1'!AT660 -> Meeting scheduled on friday | E477: ='Form responses 1'!AU660 -> Yes | F477: ='Form responses 1'!AX660 -> 46073 | G477: ='Form responses 1'!AY660 | H477: ='Form responses 1'!AW660 | I477: ='Form responses 1'!AS660 | J477: ='Form responses 1'!J660 | K477: ='Form responses 1'!G660 | L477: ='Form responses 1'!F660 | M477: ='Form responses 1'!U660 -> sajan | N477: ='Form responses 1'!V660 -> 9030000622 | O477: ='Form responses 1'!W660 -> na | P477: ='Form responses 1'!X660 | Q477: ='Form responses 1'!Y660 | R477: ='Form responses 1'!Z660 | S477: ='Form responses 1'!AC660 | T477: ='Form responses 1'!AE660 | U477: ='Form responses 1'!AG660 | V477: ='Form responses 1'!AI660 | W477: ='Form responses 1'!AJ660 | X477: ='Form responses 1'!AK660 | Y477: =if(S477>0,1,0) -> 0 | Z477: =if(T477>0,1,0) -> 0 | AA477: =if(U477>0,1,0) -> 0 | AB477: =if(V477>0,1,0) -> 0 | AC477: =if(W477>0,1,0) -> 0 | AD477: =if(X477>0,1,0) -> 0 | AE477: ='Form responses 1'!AN660 | AF477: ='Form responses 1'!AO1779 | AG477: ='Form responses 1'!AP1779 | AH477: ='Form responses 1'!AQ1779 | AI477: ='Form responses 1'!AR1779
