Workbook

Sheet Sheet1
A1: Date | B1: Restaurant Name | C1: RM/KAM | D1: Type of Ownership | E1: Address | F1: Signing Authority | G1: Pincode | H1: Locality | I1: Region | J1: Zone | K1: Service fees | L1: Service Fees Bucket | M1: Payment Gateway Charges | N1: Long Distance Charges % | O1: Legal Entity Name | P1: Legal Entity Address | Q1: Contact Person | R1: Phone no. | S1: Email ID | T1: Benficiary name | U1: Bank Name | V1: Account Number | W1: IFSC Code | X1: Account Type | Y1: FSSAI | Z1: GST | AA1: PAN | AB1: CHEQUE | AC1: MENU | AD1: LABOUR LINCENSE | AE1: Drive Link | AF1: Map Co-ordinates | AG1: LOCALITY AREA | AH1: Remarks | AI1: Remarks 2 | AJ1: Column 35 | AK1: Column 36 | AL1: Column 37 | AM1: Column 38 | AN1: Column 39 | AO1: Column 40 | AP1: Column 41 | AQ1: Column 42 | AR1: Column 43
A2: 46054 | B2: Mohammed minhaj uddin(Fancy Ice Cream) | C2: nitya.akshara@capsdelivery.com | D2: Proprietorship | E2: Rs complex vijayanagar colony near anjuman deendar back gate,masab tank,hyd | F2: Mohammed minhaj uddin | G2: 500057 | H2: Masab Tank | I2: =VLOOKUP(H2,Mapping!D:E,2,0) -> masab tank | J2: Zone 1 Mehdipatnam | K2: 0.22 | L2: =if(K2=0,"0",(if(K2<15%,"<15%",if(K2<17%,"<17%",IF(K2<20%,"<20%","20%+"))))) -> 20%+ | M2: 0.018 | O2: Mohammed minhaj uddin | P2: Rs complex vijayanagar colony near anjuman deendar back gate,masab tank,hyd 500057 | Q2: Mohammed minhaj uddin | R2: 9949583785 | S2: minhajsmarty@gmail.com | T2: Mohammed minhaj uddin | U2: Bank of Borada | V2: 75540100010283 | W2: BARBOVJVCHY | X2: Savings Account | Y2: Yes | Z2: No | AA2: Yes | AB2: No | AC2: No | AD2: No | AG2: =VLOOKUP(H:H,'Pivot Table 8'!B:C,2,0) -> #REF!
A3: 46054 | B3: R and B hospitality (Lebanese Grill) | C3: manasa.chigurupati@capsdelivery.com | D3: Partnership | E3: 12-2-825/2, Mehdipatnam | F3: M.A aqeel | G3: 500028 | H3: Mehdipatnam | I3: =VLOOKUP(H3,Mapping!D:E,2,0) -> mehdipatnam | J3: Zone 1 Mehdipatnam | K3: 0.24 | L3: =if(K3=0,"0",(if(K3<15%,"<15%",if(K3<17%,"<17%",IF(K3<20%,"<20%","20%+"))))) -> 20%+ | M3: 0.018 | O3: R and B hospitality | P3: 12-2-825/2, Mehdipatnam | Q3: M.A aqeel | R3: 9618659036 | S3: theoriginalgrill03@gmail.com | T3: not mentioned | U3: not mentioned | V3: not mentioned | W3: not mentioned | X3: No | Y3: No | Z3: No | AA3: No | AB3: No | AC3: No | AD3: NA | AE3: https://drive.google.com/drive/folders/1LEmpLQPhgga4iNmw8DK8oKC7Z9adVo_Z | AG3: =VLOOKUP(H:H,'Pivot Table 8'!B:C,2,0) -> #REF! | AI3: Not Uploaded
A4: 46054 | B4: Rahat Restaurant | C4: ankitha.baske@capsdelivery.com | D4: Proprietorship | E4: 12-2-486,4/7,Tappa Chabutra rd, asif nagar | F4: Mohammed Arshad | G4: 500006 | H4: Mehdipatnam | I4: =VLOOKUP(H4,Mapping!D:E,2,0) -> mehdipatnam | J4: Zone 1 Mehdipatnam | K4: 0.2 | L4: =if(K4=0,"0",(if(K4<15%,"<15%",if(K4<17%,"<17%",IF(K4<20%,"<20%","20%+"))))) -> 20%+ | M4: 0.018 | O4: Rahat Restaurant | P4: 12-2-486,4/7,Tappa Chabutra rd, asif nagar | Q4: Mohammed Arshad | R4: 8686561072 | S4: prinzzarshad@gamil.com | T4: Mohammed Arshad | U4: Airtel Bank | V4: 8686561072 | W4: AIRP0000001 | X4: Current Account | Y4: Yes | Z4: No | AA4: Yes | AB4: Yes | AC4: No | AD4: No | AG4: =VLOOKUP(H:H,'Pivot Table 8'!B:C,2,0) -> #REF! | AH4: switch off
A5: 46055 | B5: Alkemy | C5: manasa.chigurupati@capsdelivery.com | D5: Proprietorship | E5: kismatpur, survey 132,alkemy, 1/2 near prestige royal woods, abhyudaya nagar,dargah khaleejkhan | F5: Naika Amena | G5: 500086 | H5: Kismathpur | I5: =VLOOKUP(H5,Mapping!D:E,2,0) -> Langar Houz | J5: Zone 2 Jubliee hils | K5: 0.22 | L5: =if(K5=0,"0",(if(K5<15%,"<15%",if(K5<17%,"<17%",IF(K5<20%,"<20%","20%+"))))) -> 20%+ | M5: 0.018 | O5: alkemy | P5: survey 132,alkemy, 1/2 near prestige royal woods, abhyudaya nagar,dargah khaleejkhan | Q5: Naika Amena | R5: 8977918331 | S5: alkemy.ind@gmail.com | T5: alkemy | U5: Hdfc bank | V5: 50200096500839 | W5: HDFC0005853 | X5: Current Account | Y5: Yes | Z5: Yes | AA5: Yes | AB5: No | AC5: No | AD5: NA | AE5: https://drive.google.com/drive/folders/1hu60tEHn9OQubLStFBH50kklrc1mSCAQ | AG5: =VLOOKUP(H:H,'Pivot Table 8'!B:C,2,0) -> #REF! | AH5: Checked
A6: 46055 | B6: Begum ki briyani | C6: madhumitha.sonnakula@capsdelivery.com | D6: Proprietorship | E6: Attapur, Hyderabad | F6: Syed Ameer Hussain | G6: 500048 | H6: Attapur | I6: =VLOOKUP(H6,Mapping!D:E,2,0) -> mehdipatnam | J6: Zone 1 Mehdipatnam | K6: 0.22 | L6: =if(K6=0,"0",(if(K6<15%,"<15%",if(K6<17%,"<17%",IF(K6<20%,"<20%","20%+"))))) -> 20%+ | M6: 0.018 | O6: Tahaan foods private limited | P6: syno:32,plot no 7,pillar no 242,suleman nagar,attapur 500031 | Q6: Syed Ameer Hussain | R6: 8121007155 | S6: ameersyed131@gmail.com | T6: Shabana Begum | U6: Kotak mahindra bank | V6: 6049069572 | W6: KKBK0007487 | X6: Savings Account | Y6: Yes | Z6: NA | AA6: Yes | AB6: Yes | AC6: No | AD6: NA | AE6: https://drive.google.com/drive/folders/10dJbKX5ksSDh27Q6F7Vv--1oAZHBxtZz?usp=drive_link | AG6: =VLOOKUP(H:H,'Pivot Table 8'!B:C,2,0) -> #REF! | AH6: number does not exist
A7: 46055 | B7: Jusvous | C7: ankitha.baske@capsdelivery.com | D7: Proprietorship | E7: Attapur, Hyderabad | F7: Shabana Begum | G7: 500048 | H7: Attapur | I7: =VLOOKUP(H7,Mapping!D:E,2,0) -> mehdipatnam | J7: Zone 1 Mehdipatnam | K7: 0.22 | L7: =if(K7=0,"0",(if(K7<15%,"<15%",if(K7<17%,"<17%",IF(K7<20%,"<20%","20%+"))))) -> 20%+ | M7: 0.018 | O7: Jusvous | P7: syno:32,plot no 7,pillar no 242,suleman nagar,attapur 500030 | Q7: Shabana Begum | R7: 9701168269 | S7: shabanaameer131@gmail.com | T7: Shabana Begum | U7: Kotak mahindra bank | V7: 6049069572 | W7: KKBK0007487 | X7: Savings Account | Y7: Yes | Z7: NA | AA7: Yes | AB7: Yes | AC7: Yes | AD7: NA | AE7: https://drive.google.com/drive/folders/1HsJMgJiTpKMJBeM_QGp1o0L2blqry1_p?usp=drive_link | AG7: =VLOOKUP(H:H,'Pivot Table 8'!B:C,2,0) -> #REF!
A8: 46055 | B8: New farmaish Restaurant | C8: ankitha.baske@capsdelivery.com | D8: Proprietorship | E8: Banglaguda plot no 13/a bandlaguda,rahendranagar | F8: Syed Ameer Hussain | G8: 500091 | H8: Bandlaguda | I8: =VLOOKUP(H8,Mapping!D:E,2,0) -> mehdipatnam | J8: Zone 1 Mehdipatnam | K8: 0.22 | L8: =if(K8=0,"0",(if(K8<15%,"<15%",if(K8<17%,"<17%",IF(K8<20%,"<20%","20%+"))))) -> 20%+ | M8: 0.018 | O8: New farmaish Restaurant | P8: Banglaguda plot no 13/a banglaguda,rahendranagar,500091 | Q8: Syed Ameer Hussain | R8: 8121007155 | S8: ameersyed131@gmail.com | T8: Tahaan foods private limited | U8: Axis Bank | V8: 9.2100201e+15 | W8: UTIB0004826 | X8: coperate account | Y8: Yes | Z8: NA | AA8: Yes | AB8: Yes | AC8: No | AD8: NA | AE8: https://drive.google.com/drive/folders/1fCUi5DR9A9LINTfSuXKP6MhAbwgu-JhO?usp=drive_link | AG8: =VLOOKUP(H:H,'Pivot Table 8'!B:C,2,0) -> #REF!
A9: 46055 | B9: Waffle station | C9: manasa.chigurupati@capsdelivery.com | D9: Proprietorship | E9: survey no.37,himayath sagar village bandlaguda jagir muncipal corporation gandipet mandal | F9: Mohd Shoieb | G9: 500091 | H9: Gandipet | I9: =VLOOKUP(H9,Mapping!D:E,2,0) -> Langar Houz | J9: Zone 2 Jubliee hils | K9: 0.2 | L9: =if(K9=0,"0",(if(K9<15%,"<15%",if(K9<17%,"<17%",IF(K9<20%,"<20%","20%+"))))) -> 20%+ | M9: 0.018 | O9: Waffle station | P9: survey no.37,himayath sagar village bondlaguda jagir muncipal corporation gandipet mandal-500091 | Q9: Mohd Shoieb | R9: 9398554461 | S9: mmshoieb786@gmail.com | T9: Mohd Shoieb | U9: State Bank of India | V9: 20308200989 | W9: SBIN0008026 | X9: Savings Account | Y9: No | Z9: No | AA9: Yes | AB9: Yes | AC9: Yes | AD9: NA | AE9: https://drive.google.com/drive/folders/1ulPwAwYgA1k4f0sUZ1XbFUA0_rXx2Rcr | AG9: =VLOOKUP(H:H,'Pivot Table 8'!B:C,2,0) -> #REF! | AH9: Checked
A10: 46056 | B10: Al rawaf home made dishes | C10: madhumitha.sonnakula@capsdelivery.com | D10: Proprietorship | E10: Hakeem shah colony,tolichowki,hyderabad | F10: Asfiya sulthana | G10: 500008 | H10: Tolichowki | I10: =VLOOKUP(H10,Mapping!D:E,2,0) -> tolichowki | J10: Zone 2 Jubliee hils | K10: 0.22 | L10: =if(K10=0,"0",(if(K10<15%,"<15%",if(K10<17%,"<17%",IF(K10<20%,"<20%","20%+"))))) -> 20%+ | M10: 0.018 | O10: Al rawaf home made dishes | P10: Hakeem shah colony,tolichowki,hyderabad | Q10: Mohammed rizwan qureshi | R10: 8121586490 | S10: anasriyanmohammed@gmail.com | T10: Asfiya sulthana | U10: State Bank of India | V10: 42545548670 | W10: SBIN0005095 | X10: Savings Account | Y10: Yes | Z10: No | AA10: Yes | AB10: No | AC10: Yes | AD10: No | AE10: https://drive.google.com/drive/folders/1smCsR9G_YgZE_fKEqCXQq0ImYMzTeQTL | AG10: =VLOOKUP(H:H,'Pivot Table 8'!B:C,2,0) -> #REF!
A11: 46056 | B11: Bhojanams and biryani | C11: chanakya.inugala@capsdelivery.com | D11: Proprietorship | E11: plot no.87,swamy ayyappa society,madhapur,hyd | F11: Katragadda Shesha sai | G11: 500085 | H11: Madhapur | I11: =VLOOKUP(H11,Mapping!D:E,2,0) -> madhapur | J11: Zone 4 Hi-tech City | K11: 0.19 | L11: =if(K11=0,"0",(if(K11<15%,"<15%",if(K11<17%,"<17%",IF(K11<20%,"<20%","20%+"))))) -> <20% | M11: 0.018 | O11: M/s. invences foods Bhojanams and biryani | P11: plot no.87,swamy ayyappa society,madhapur,hyd,500085 | Q11: Katragadda Shesha sai | R11: 9052592437 | S11: sheshasai.katragadda@gmail.com | T11: Invences foods | U11: IDFC Bank | V11: 10192341683 | W11: IDFB0080231 | X11: Current Account | Y11: Yes | Z11: Yes | AA11: Yes | AB11: Yes | AC11: No | AD11: No | AF11: https://www.google.com/maps/place/Bhojanams+%26+Biryanis/@17.4468252,78.3895983,17z/data=!3m1!4b1!4m6!3m5!1s0x3bcb91687dc6785f:0x9d238a8fc18acf44!8m2!3d17.4468201!4d78.3921732!16s%2Fg%2F11fgjxmc9s?entry=ttu&g_ep=EgoyMDI2MDIxMS4wIKXMDSoASAFQAw%3D%3D | AG11: =VLOOKUP(H:H,'Pivot Table 8'!B:C,2,0) -> #REF!
A12: 46056 | B12: Bhuvan's kitchen | C12: manasa.chigurupati@capsdelivery.com | D12: Proprietorship | E12: H.no:6-331192/1/g/3 block-1 ground floor white house,kundanbagh,begumpet | F12: K.Rama Rao | G12: 500082 | H12: Begumpet | I12: =VLOOKUP(H12,Mapping!D:E,2,0) -> ameerpet | J12: Zone 6 Ameerpet | K12: 0.2 | L12: =if(K12=0,"0",(if(K12<15%,"<15%",if(K12<17%,"<17%",IF(K12<20%,"<20%","20%+"))))) -> 20%+ | M12: 0.018 | O12: Bhuvan's kitchen | P12: H.no:6-331192/1/g/3 block-1 ground floor white house,kundanbagh,begumpet,500082 | Q12: K.Rama Rao | R12: 9030611616 | S12: bhuvanskitchen25@gmail.com | T12: Ravindra babu tadiboyina | U12: Hdfc bank | V12: 50200102000231 | W12: HDFC0010090 | X12: Current Account | Y12: Yes | Z12: No | AA12: Yes | AB12: Yes | AC12: No | AD12: NA | AE12: https://drive.google.com/drive/folders/1KNPeVcsMJ0WDp5KH6nSS-MfsJEjo5gEl | AG12: =VLOOKUP(H:H,'Pivot Table 8'!B:C,2,0) -> #REF! | AH12: Checked
A13: 46056 | B13: Biryani N biryani | C13: ankitha.baske@capsdelivery.com | D13: Partnership | E13: 13-6-798/1/1,bapughat langa howz circle,13 hyd | F13: Raguveer | G13: 500008 | H13: Langer houz | I13: =VLOOKUP(H13,Mapping!D:E,2,0) -> Langar Houz | J13: Zone 2 Jubliee hils | K13: 0.22 | L13: =if(K13=0,"0",(if(K13<15%,"<15%",if(K13<17%,"<17%",IF(K13<20%,"<20%","20%+"))))) -> 20%+ | M13: 0.018 | O13: Biryani N biryani | P13: 13-6-798/1/1,bapughat langa howz circle,13 hyd | Q13: Raguveer | R13: 9963122625 | S13: munnoorraghuveer@gmail.com | T13: not mentioned | U13: not mentioned | V13: not mentioned | W13: not mentioned | X13: not mentioned | Y13: Yes | Z13: NA | AA13: Yes | AB13: No | AC13: Yes | AD13: NA | AE13: https://drive.google.com/drive/folders/1YsOVORTRLFpXHAUJiIrmFhshAi8DDIee?usp=drive_link | AG13: =VLOOKUP(H:H,'Pivot Table 8'!B:C,2,0) -> #REF! | AI13: Not Uploaded
A14: 46056 | B14: Bob's biryani | C14: manasa.chigurupati@capsdelivery.com | D14: Proprietorship | E14: 1-8-370and372 abhishek scan center,2nd floor near huda office,begumpet | F14: Paul kumar | G14: 500016 | H14: Begumpet | I14: =VLOOKUP(H14,Mapping!D:E,2,0) -> ameerpet | J14: Zone 6 Ameerpet | K14: 0.2 | L14: =if(K14=0,"0",(if(K14<15%,"<15%",if(K14<17%,"<17%",IF(K14<20%,"<20%","20%+"))))) -> 20%+ | M14: 0.018 | O14: Bob's biryani | P14: 1-8-370and372 abhishek scan center,2nd floor near huda office,begumpet,500016 | Q14: Paul kumar | R14: 9100777133 | S14: bobsbiriyani07@gmail.com | T14: Paul kumar rapaka | U14: Telangana state cooperative apex bank ltd | V14: 991111800000003 | W14: TSAB0000111 | X14: Current Account | Y14: Yes | Z14: NA | AA14: Yes | AB14: Yes | AC14: Yes | AD14: NA | AE14: https://drive.google.com/drive/folders/16PzSygeOLaXCa7wt2mKHTfEYFJ3Y9ChJ | AG14: =VLOOKUP(H:H,'Pivot Table 8'!B:C,2,0) -> #REF!
A15: 46056 | B15: Eastin hotels | C15: parthive.maganti@capsdelivery.com | D15: Partnership | E15: 2-52/1/3 hitech city rd,phase 2,kaveri hills madhapur,hyd | F15: Bargava.B | G15: 500081 | H15: Madhapur | I15: =VLOOKUP(H15,Mapping!D:E,2,0) -> madhapur | J15: Zone 4 Hi-tech City | K15: 0.15 | L15: =if(K15=0,"0",(if(K15<15%,"<15%",if(K15<17%,"<17%",IF(K15<20%,"<20%","20%+"))))) -> <17% | M15: 0.018 | O15: Eastin hotels | P15: 1-65-f,survey no.6,madhpur,gutlala begumpet,hyderabad,500081 | Q15: vamsi | R15: 9177285333 | S15: info@easrinhotels.in | T15: Eastin hotels and resorts | U15: ICICI BANK | V15: 112005003328 | W15: ICIC0001120 | X15: Current Account | Y15: Yes | Z15: Yes | AA15: Yes | AB15: Yes | AC15: Yes | AD15: No | AE15: Eastin Hotel | AF15: https://maps.app.goo.gl/7kDCtkQs6d4Hwruc8?g_st=iw | AG15: =VLOOKUP(H:H,'Pivot Table 8'!B:C,2,0) -> #REF! | AH15: checked
A16: 46056 | B16: Ns bakers | C16: akhila.narra@capsdelivery.com | D16: Proprietorship | E16: H.no:7-1-455/23/12,Ameerpet gurudwara road, telangana, | F16: Gardas saritha | G16: 500016 | H16: Ameerpet | I16: =VLOOKUP(H16,Mapping!D:E,2,0) -> panjagutta | J16: Zone 6 Ameerpet | K16: 0.22 | L16: =if(K16=0,"0",(if(K16<15%,"<15%",if(K16<17%,"<17%",IF(K16<20%,"<20%","20%+"))))) -> 20%+ | M16: 0.018 | O16: Ns bakers,Gardas saritha | P16: H.no:7-1-455/23/12,Ameerpet gurudwara road | Q16: Gardas saritha | R16: 9985000567 | S16: gardasnagesh34@gmail.com | T16: Gardas saritha | U16: State Bank of India | V16: 20297710024 | W16: SBIN0010676 | X16: Savings Account | AG16: =VLOOKUP(H:H,'Pivot Table 8'!B:C,2,0) -> #REF!
A17: 46056 | B17: Om Vaishnav Enterprise | C17: manasa.chigurupati@capsdelivery.com | D17: Proprietorship | E17: bus shelter stall,bus bay premises on sp road,opp anand theater and piller non1292, sindhi colony,begumpet | F17: Kuna Vaishnav | G17: 500003 | H17: Begumpet | I17: =VLOOKUP(H17,Mapping!D:E,2,0) -> ameerpet | J17: Zone 6 Ameerpet | K17: 0.22 | L17: =if(K17=0,"0",(if(K17<15%,"<15%",if(K17<17%,"<17%",IF(K17<20%,"<20%","20%+"))))) -> 20%+ | M17: 0.018 | O17: Om Vaishnav Enterprise | P17: bus shelter stall,bus bay premises on sp road,opp anand theater and piller non1292, sindhi colony,begumpet ,500003 | Q17: Kuna Vaishnav | R17: 9014176534 | S17: kunavyshnav@gmail.com | T17: Om Vaishnav Enterprise | U17: Yes Bank | V17: 100126900000171 | W17: YESB0001001 | X17: Current Account | Y17: Yes | Z17: Yes | AA17: Yes | AB17: Yes | AC17: Yes | AD17: NA | AE17: https://drive.google.com/drive/folders/1Bcpf2nTkRm8vyXXW6mpna2LwmGTtAnVJ | AG17: =VLOOKUP(H:H,'Pivot Table 8'!B:C,2,0) -> #REF! | AH17: Checked
A18: 46056 | B18: Pandu fast food center | C18: ankitha.baske@capsdelivery.com | D18: Proprietorship | E18: B41/f5 shop no.3 ps nagar,vijay nagar | F18: Yelgani sai kumar goud | G18: 500057 | H18: Mehdipatnam | I18: =VLOOKUP(H18,Mapping!D:E,2,0) -> mehdipatnam | J18: Zone 1 Mehdipatnam | K18: 0.22 | L18: =if(K18=0,"0",(if(K18<15%,"<15%",if(K18<17%,"<17%",IF(K18<20%,"<20%","20%+"))))) -> 20%+ | M18: 0.018 | O18: Yelgani sai kumar goud | P18: D.no: b41/f5 shop no.3 ps nagar,500057 | Q18: Yelgani sai kumar | R18: 9030518803 | S18: rebalsaikumargoud@gmail.com | T18: Yelgani sai kumar goud | U18: Centeal bank of india | V18: 3269632568 | W18: CBIN0283883 | X18: Savings Account | Y18: Yes | Z18: NA | AA18: Yes | AB18: No | AC18: Yes | AD18: NA | AE18: https://drive.google.com/drive/folders/16Pqgac9j1zbGysD70GA0bsI2nEml5nxG?usp=drive_link | AG18: =VLOOKUP(H:H,'Pivot Table 8'!B:C,2,0) -> #REF!
A19: 46056 | B19: Sunrise | C19: parthive.maganti@capsdelivery.com | D19: Proprietorship | E19: H.no:325/2rt,sanjeev reddy nagar,umeshchandra statue | F19: veeram reddy seetharam reddy | G19: 500038 | H19: S.R Nagar | I19: =VLOOKUP(H19,Mapping!D:E,2,0) -> panjagutta | J19: Zone 6 Ameerpet | K19: 0.17 | L19: =if(K19=0,"0",(if(K19<15%,"<15%",if(K19<17%,"<17%",IF(K19<20%,"<20%","20%+"))))) -> <20% | M19: 0.018 | O19: Sunrise | P19: H.no:325/2rt,sanjeev reddy nagar,umeshchandra statue road,s.r nagar hyd 500038 | Q19: veeram reddy seetharam reddy | R19: 8989873636 | S19: bowlrise.srnagaar@gmail.com | T19: For aarav sunrise hospitalitfes | U19: ICICI BANK | V19: 803705000004 | W19: ICIC0008037 | X19: Current Account | Y19: Yes | Z19: Yes | AA19: Yes | AB19: Yes | AC19: Yes | AD19: No | AE19: Sunrise Hotel | AF19: Sunrise Business Hotel | AG19: =VLOOKUP(H:H,'Pivot Table 8'!B:C,2,0) -> #REF! | AH19: checked
A20: 46056 | B20: Vaarahi fast food and tiffins | C20: greeshma.vanneldas@capsdelivery.com | D20: Proprietorship | E20: plot no.111,60ft road swamy ayyappa society,megha hills,khanamet,madhapur,hyd | F20: Divvela sri mahalakshmi | G20: 500081 | H20: Madhapur | I20: =VLOOKUP(H20,Mapping!D:E,2,0) -> madhapur | J20: Zone 4 Hi-tech City | K20: 0.22 | L20: =if(K20=0,"0",(if(K20<15%,"<15%",if(K20<17%,"<17%",IF(K20<20%,"<20%","20%+"))))) -> 20%+ | M20: 0.018 | O20: not mentioned | P20: plot no.111,60ft road swamy ayyappa society,megha hills,khanamet,madhapur,hyd | Q20: Prashanth | R20: 8555825704 | S20: not mentioned | T20: not mentioned | U20: not mentioned | V20: not mentioned | W20: not mentioned | X20: not mentioned | Y20: No | Z20: No | AA20: No | AB20: No | AC20: No | AD20: NA | AG20: =VLOOKUP(H:H,'Pivot Table 8'!B:C,2,0) -> #REF! | AH20: Today by EOD
A21: 46056 | B21: Zyras Biryani house | C21: moin.khan@capsdelivery.com | D21: Proprietorship | E21: plot no.03-805,shop no.2 ground floor M and M elite home,sri swamy ayyappa co-op Hs madhapur,hyd | F21: Natva Santosh kumar | G21: 500081 | H21: Madhapur | I21: =VLOOKUP(H21,Mapping!D:E,2,0) -> madhapur | J21: Zone 4 Hi-tech City | K21: 0.18 | L21: =if(K21=0,"0",(if(K21<15%,"<15%",if(K21<17%,"<17%",IF(K21<20%,"<20%","20%+"))))) -> <20% | M21: 0.018 | O21: Natva Santosh kumar | P21: plot no.03-805,shop no.2 ground floor M and M elite home,sri swamy ayyappa co-op Hs madhapur,hyd,500081 | Q21: Natva Santosh kumar | R21: 6302181276 | S21: nsantosh086@gmail.com | T21: Zyras Biryani house | U21: kotak mahindra bank | V21: 6450935473 | W21: KKBK0000561 | X21: Current Account | Y21: Yes | Z21: Yes | AA21: Yes | AB21: Yes | AC21: Yes | AD21: No | AE21: https://drive.google.com/drive/folders/1UCJPJOZGe8jeYMBocwtl6TwiAGnpIlby?usp=sharing | AG21: =VLOOKUP(H:H,'Pivot Table 8'!B:C,2,0) -> #REF!
A22: 46057 | B22: Alankrutha multi cuisine Restaurant | C22: moin.khan@capsdelivery.com | D22: proprietorship | E22: plot no-1206,madhapur,kondukur,rangareddy,telangana | F22: chatne akash | G22: 500081 | H22: Madhapur | I22: =VLOOKUP(H22,Mapping!D:E,2,0) -> madhapur | J22: Zone 4 Hi-tech City | K22: 0.2 | L22: =if(K22=0,"0",(if(K22<15%,"<15%",if(K22<17%,"<17%",IF(K22<20%,"<20%","20%+"))))) -> 20%+ | M22: 0.018 | O22: chatne akash | P22: plot no-1206,madhapur,kondukur,rangareddy,telangana,500081 | Q22: chatne akash | R22: 8341514984 | S22: cakash121@gmail.com | T22: Alankrutha multi cuisine Restaurant | U22: Bank of Borada | V22: 65980200001283 | W22: BARBODBMDHP | X22: Current Account | Y22: Yes | Z22: No | AA22: Yes | AB22: Yes | AC22: No | AD22: No | AE22: https://drive.google.com/drive/folders/1vjzFqzXaDbk0UgQjX9vk9TtWw7QA1ZRo?usp=drive_link | AG22: =VLOOKUP(H:H,'Pivot Table 8'!B:C,2,0) -> #REF!
A23: 46057 | B23: Alnkarutha multicusine Restaurant | C23: moin.khan@capsdelivery.com | D23: Proprietorship | E23: plot no.1206,madhapur,kandukur,rangareddy, telangana | F23: Chatne akash | G23: 500081 | H23: Madhapur | I23: =VLOOKUP(H23,Mapping!D:E,2,0) -> madhapur | J23: Zone 4 Hi-tech City | K23: 0.2 | L23: =if(K23=0,"0",(if(K23<15%,"<15%",if(K23<17%,"<17%",IF(K23<20%,"<20%","20%+"))))) -> 20%+ | M23: 0.018 | O23: Chatne akash | P23: plot no.1206,madhapur,kandukur,rangareddy, telangana-500081 | Q23: Chatne akash | R23: 8341514984 | S23: cakash121@gmail.com | T23: Alnkarutha multicusine Restaurant | U23: Bank of Borada | V23: 65980200001283 | W23: BARBODBMDHP | X23: Current Account | Y23: Yes | Z23: No | AA23: Yes | AB23: Yes | AC23: No | AD23: No | AE23: https://drive.google.com/drive/folders/1vjzFqzXaDbk0UgQjX9vk9TtWw7QA1ZRo?usp=drive_link | AG23: =VLOOKUP(H:H,'Pivot Table 8'!B:C,2,0) -> #REF!
A24: 46057 | B24: Ankapur Military Hotel Madhapur | C24: nitya.akshara@capsdelivery.com | I24: =VLOOKUP(H24,Mapping!D:E,2,0) -> #N/A | L24: =if(K24=0,"0",(if(K24<15%,"<15%",if(K24<17%,"<17%",IF(K24<20%,"<20%","20%+"))))) -> 0 | Y24: No | Z24: No | AA24: No | AB24: No | AC24: No | AD24: No | AG24: =VLOOKUP(H:H,'Pivot Table 8'!B:C,2,0) -> #REF! | AH24: Merchant asked to visit directly & explain the details.
A25: 46057 | B25: Ankapur village a military hotel | C25: nitya.akshara@capsdelivery.com | D25: LLP | E25: 1-98/2,durgam chervu,inorbit mall rd, hyd | F25: Ankapur village hotels llp | G25: 500081 | H25: Madhapur | I25: =VLOOKUP(H25,Mapping!D:E,2,0) -> madhapur | J25: Zone 4 Hi-tech City | K25: 0.15 | L25: =if(K25=0,"0",(if(K25<15%,"<15%",if(K25<17%,"<17%",IF(K25<20%,"<20%","20%+"))))) -> <17% | M25: 0.018 | O25: Ankapur village hotels llp | P25: H.no:1-89/2/1/21,plot no-10,21,21/a,21/a, sy no.37,38,39,40,46,47 to 49,inorbit mall road, madhapur | Q25: Venudhar reddy malakapalli | R25: 9642883377 | S25: venudharr@gmail.com | T25: Avhllp sambal | U25: Hdfc bank | V25: 50200029920971 | W25: HDFC0003739 | X25: Current Account | Y25: No | Z25: No | AA25: No | AB25: No | AC25: No | AD25: No | AG25: =VLOOKUP(H:H,'Pivot Table 8'!B:C,2,0) -> #REF! | AH25: Merchant asked to visit directly & explain the details.
A26: 46057 | B26: Ankapur village-a military hotel (kokapet) | C26: nitya.akshara@capsdelivery.com | D26: LLP | E26: osman sagar, kokapet gandipet, hyd,telangana | F26: Ankapur village hotels llp | G26: 500075 | H26: Gandipet | I26: =VLOOKUP(H26,Mapping!D:E,2,0) -> Langar Houz | J26: Zone 2 Jubliee hils | K26: 0.15 | L26: =if(K26=0,"0",(if(K26<15%,"<15%",if(K26<17%,"<17%",IF(K26<20%,"<20%","20%+"))))) -> <17% | M26: 0.018 | O26: A unit of Ankapur village hotels llp | P26: s.v no.167/1,madhuri sadan osman nagar road,opp ocean park kokapet hyd | Q26: Venudhar reddy | R26: 8121040277 | S26: not mentioned | T26: Avhllp kokapet | U26: Hdfc bank | V26: 50200093208670 | W26: HDFC0000021 | X26: Current Account | Y26: No | Z26: No | AA26: No | AB26: No | AC26: No | AD26: No | AG26: =VLOOKUP(H:H,'Pivot Table 8'!B:C,2,0) -> #REF! | AH26: Merchant asked to visit directly & explain the details.
A27: 46057 | B27: Govindas cafe | C27: madhumitha.sonnakula@capsdelivery.com | D27: Trust(company) | E27: plot no.220,mushak mahal residential, attapur,hyd | F27: Sachinandan hari das | G27: 500048 | H27: Attapur | I27: =VLOOKUP(H27,Mapping!D:E,2,0) -> mehdipatnam | J27: Zone 1 Mehdipatnam | K27: 0.21 | L27: =if(K27=0,"0",(if(K27<15%,"<15%",if(K27<17%,"<17%",IF(K27<20%,"<20%","20%+"))))) -> 20%+ | M27: 0.018 | O27: Govindas cafe | P27: plot no.220,mushak mahal residential complex huda,attapur,hyd | Q27: Sachinandan hari das | R27: 9392038004 | S27: admin.govindasatiskconattapur.com | T27: iskcon-Govindas | U27: Axis Bank | V27: 924010053814296 | W27: UTIB0004826 | X27: Current Account | Y27: Yes | Z27: Yes | AA27: Yes | AB27: Yes | AC27: Yes | AD27: No | AE27: https://drive.google.com/drive/folders/1dSwEyifkPxUG9QNgXPEPSPe9Wz37Yjpx | AG27: =VLOOKUP(H:H,'Pivot Table 8'!B:C,2,0) -> #REF!
A28: 46057 | B28: Guntur Mess | C28: greeshma.vanneldas@capsdelivery.com | D28: proprietorship | E28: manikonda, ayyappa society | F28: Siva Rama Krishna | G28: 500081 | H28: Manikonda | I28: =VLOOKUP(H28,Mapping!D:E,2,0) -> manikonda | J28: Zone 3 Raidurg | K28: 0.22 | L28: =if(K28=0,"0",(if(K28<15%,"<15%",if(K28<17%,"<17%",IF(K28<20%,"<20%","20%+"))))) -> 20%+ | M28: 0.018 | O28: not mentioned | P28: not mentioned | Q28: Siva Rama Krishna | R28: 9391167117 | S28: shivakandavelli@gmail.com | T28: Kandavelli Siva Rama Krishna | U28: Unioun bank of india | V28: 135610011001804 | W28: UBIN0813567 | X28: Savings Account | Y28: No | Z28: No | AA28: No | AB28: No | AC28: No | AD28: NA | AG28: =VLOOKUP(H:H,'Pivot Table 8'!B:C,2,0) -> #REF! | AH28: Today bt eod
A29: 46057 | B29: Lassi corner | C29: madhumitha.sonnakula@capsdelivery.com | D29: Proprietorship | E29: plot no 7,syno 17 ground floor R.R district 500047 | F29: Ashok thapa,Vishu thapa | G29: 500047 | H29: Gandipet | I29: =VLOOKUP(H29,Mapping!D:E,2,0) -> Langar Houz | J29: Zone 2 Jubliee hils | L29: =if(K29=0,"0",(if(K29<15%,"<15%",if(K29<17%,"<17%",IF(K29<20%,"<20%","20%+"))))) -> 0 | M29: 0.018 | O29: Lassi corner | P29: plot no 7 ground floor,gandamguda 500045 | Q29: Ashok thapa | R29: 7995109409 | S29: vishnuthapaa@gmail.com | T29: not mentioned | U29: not mentioned | V29: not mentioned | W29: not mentioned | X29: not mentioned | Y29: Yes | Z29: No | AA29: Yes | AB29: No | AC29: No | AD29: No | AG29: =VLOOKUP(H:H,'Pivot Table 8'!B:C,2,0) -> #REF!
A30: 46057 | B30: Lassi corner | C30: nitya.akshara@capsdelivery.com | D30: LLP | E30: h.no:1-98/6a/14,plot no 42 road no.3, patrikanagar hitech city,madhapur, hitech city | F30: venudhar reddy | G30: 500075 | H30: Madhapur | I30: =VLOOKUP(H30,Mapping!D:E,2,0) -> madhapur | J30: Zone 4 Hi-tech City | K30: 0.15 | L30: =if(K30=0,"0",(if(K30<15%,"<15%",if(K30<17%,"<17%",IF(K30<20%,"<20%","20%+"))))) -> <17% | M30: 0.018 | O30: Ankapur village-A military hotel | P30: h.no:1-98/6a/14,plot no 42 road no.3, patrikanagar hitech city,madhapur, hitech city | Q30: venudhar reddy | R30: 7995854986 | S30: venudharr@gmail.com | T30: Avhllp military hotel | U30: Hdfc bank | V30: 50200029918240 | W30: HDFC0003739 | X30: Current Account | Y30: No | Z30: No | AA30: No | AB30: No | AC30: No | AD30: No | AG30: =VLOOKUP(H:H,'Pivot Table 8'!B:C,2,0) -> #REF! | AH30: Merchant asked to visit directly & explain the details.
A31: 46057 | B31: Namaste the Indian kitchen | C31: greeshma.vanneldas@capsdelivery.com | D31: Partnership | E31: plot no. 501,sy no.11/14.11/15,11/16,khanamet village ayyappa society,htd | F31: not mentioned | G31: 500084 | H31: Madhapur | I31: =VLOOKUP(H31,Mapping!D:E,2,0) -> madhapur | J31: Zone 4 Hi-tech City | K31: 0.2 | L31: =if(K31=0,"0",(if(K31<15%,"<15%",if(K31<17%,"<17%",IF(K31<20%,"<20%","20%+"))))) -> 20%+ | M31: 0.018 | O31: V6 ventures LLP | P31: Bulding no/Flat no, sy no.64, mindspace road, madhapur | Q31: Raghav | R31: 9972901941 | S31: V6 venturesllp@gmail.com | T31: V6 ventures LLP | U31: ICICI BANK | V31: 4005030744 | W31: ICIC0000040 | X31: Current Account | Y31: Yes | Z31: Yes | AA31: Yes | AB31: Yes | AC31: Yes | AD31: NA | AG31: =VLOOKUP(H:H,'Pivot Table 8'!B:C,2,0) -> #REF! | AH31: Anexure Missing
A32: 46057 | B32: Rayalaseema spice Restaurant | C32: moin.khan@capsdelivery.com | D32: Proprietorship | E32: plot no.1208,g1andg2,ground floor,ayyappa society,madhapur,hyd,telangan | F32: Pokuri prathyusha | G32: 500081 | H32: Madhapur | I32: =VLOOKUP(H32,Mapping!D:E,2,0) -> madhapur | J32: Zone 4 Hi-tech City | K32: 0.18 | L32: =if(K32=0,"0",(if(K32<15%,"<15%",if(K32<17%,"<17%",IF(K32<20%,"<20%","20%+"))))) -> <20% | M32: 0.018 | O32: Pokuri prathyusha | P32: plot no.1208,g1andg2,ground floor,ayyappa society,madhapur,hyd,telangan,500081 | Q32: Narupu reddy | R32: 6301782448 | S32: rayalaseemaspicefamilyvetaura@gmail.com | T32: Rayalaseema spice Restaurant | U32: Bandhan Bank | V32: 20100061259823 | W32: BDBL0002722 | X32: Current Account | Y32: No | Z32: No | AA32: Yes | AB32: No | AC32: No | AD32: No | AE32: https://drive.google.com/drive/folders/1O9zT56Qjx_Fn-1HXs44MbW70lNaEY6eu?usp=sharing | AG32: =VLOOKUP(H:H,'Pivot Table 8'!B:C,2,0) -> #REF! | AH32: not answering calls
A33: 46057 | B33: Rolo one Bakers | C33: moin.khan@capsdelivery.com | D33: Partnership | E33: p.no.4(a),1-89/8/4, madhapur ,hyd,telangana | F33: Ragavendra Gm | G33: 500081 | H33: Madhapur | I33: =VLOOKUP(H33,Mapping!D:E,2,0) -> madhapur | J33: Zone 4 Hi-tech City | K33: 0.17 | L33: =if(K33=0,"0",(if(K33<15%,"<15%",if(K33<17%,"<17%",IF(K33<20%,"<20%","20%+"))))) -> <20% | M33: 0.018 | O33: Rolo one Bakers | P33: p.no.4(a),1-89/8/4, madhapur ,hyd,telangana,500081 | Q33: Ragavendra Gm | R33: 9963968917 | S33: raghavs2606@yahoo.com | T33: Muni Ragavendra gandavadi | U33: Central Bank Of India | V33: 5684056323 | W33: CBIN0280814 | X33: Current Account | Y33: Yes | Z33: Yes | AA33: Yes | AB33: Yes | AC33: No | AD33: No | AE33: https://drive.google.com/drive/folders/1fMxi-4kuAYVRCumBpHT0cJ0OQJGZKWP9?usp=sharing | AG33: =VLOOKUP(H:H,'Pivot Table 8'!B:C,2,0) -> #REF!
A34: 46057 | B34: Shree balaji tiffin center | C34: ankitha.baske@capsdelivery.com | D34: Proprietorship | E34: 4-17-12,hitech city santosh residency,beside farmaish Restaurant,gandamguda,hyd | F34: B.Raja yashwanth kumar | G34: 500081 | H34: Gandamguda | I34: =VLOOKUP(H34,Mapping!D:E,2,0) -> mehdipatnam | J34: Zone 1 Mehdipatnam | K34: 0.22 | L34: =if(K34=0,"0",(if(K34<15%,"<15%",if(K34<17%,"<17%",IF(K34<20%,"<20%","20%+"))))) -> 20%+ | M34: 0.018 | O34: Shree balaji tiffin center | P34: 4-17-12,hitech city santosh residency,hyd | Q34: B.Raja yashwanth kumar | R34: 9705812524 | S34: yeshwanth.bugude@gmail.com | T34: B.Raja yashwanth kumar | U34: Bank of Borada | V34: 80980100003622 | W34: BARBOVJBUND | X34: Savings Account | Y34: Yes | Z34: NA | AA34: Yes | AB34: Yes | AC34: Yes | AD34: NA | AG34: =VLOOKUP(H:H,'Pivot Table 8'!B:C,2,0) -> #REF!
A35: 46057 | B35: Shri balaji family dhaba | C35: ankitha.baske@capsdelivery.com | D35: Proprietorship | E35: Gudi malkapur,12-2-417/46/9,sharada nagar colony gudimalk | F35: Bidhaniyasoni | G35: 500028 | H35: Gudimalkapur | I35: =VLOOKUP(H35,Mapping!D:E,2,0) -> masab tank | J35: Zone 1 Mehdipatnam | K35: 0.22 | L35: =if(K35=0,"0",(if(K35<15%,"<15%",if(K35<17%,"<17%",IF(K35<20%,"<20%","20%+"))))) -> 20%+ | M35: 0.018 | O35: Shri balaji family dhaba | P35: 12-2-417/46/9,sharada nagar colony gudimalk,500028 | Q35: Rihaan | R35: 04023536061 | S35: bighaniyasony@gmail.com | T35: B.soni | U35: DCB bank | V35: ;02711500006880 | W35: DCBL0000027 | X35: Savings Account | Y35: Yes | Z35: NA | AA35: Yes | AB35: Yes | AC35: Yes | AD35: Yes | AG35: =VLOOKUP(H:H,'Pivot Table 8'!B:C,2,0) -> #REF!
A36: 46057 | B36: Sri Udupi grand pure veg | C36: madhumitha.sonnakula@capsdelivery.com | D36: proprietorship | E36: Gudimalkapur, hyderabad 13-6-460/112, mahesh nagar gudimalkapur | F36: Manjunath | G36: 500028 | H36: Gudimalkapur | I36: =VLOOKUP(H36,Mapping!D:E,2,0) -> masab tank | J36: Zone 1 Mehdipatnam | K36: 0.22 | L36: =if(K36=0,"0",(if(K36<15%,"<15%",if(K36<17%,"<17%",IF(K36<20%,"<20%","20%+"))))) -> 20%+ | M36: 0.018 | O36: Sri Udupi grand pure veg | P36: 13-6-460/112, mahesh nagar gudimalkapur | Q36: Manjunath | R36: 9032944860 | S36: bmanjunathkotteri@gmail.com | T36: Bailu Manjunath | U36: City union bank ltd | V36: 500101013048225 | W36: CIUB0000386 | X36: Savings Account | Y36: Yes | Z36: No | AA36: Yes | AB36: Yes | AC36: Yes | AD36: No | AE36: https://drive.google.com/drive/folders/1feNNzyCdx3sxbzFyqJhVyFJNTvoq8k2G | AG36: =VLOOKUP(H:H,'Pivot Table 8'!B:C,2,0) -> #REF!
A37: 46057 | B37: Vidhusekhara pizzeria | C37: greeshma.vanneldas@capsdelivery.com | D37: Pvt ltd | E37: plot no.o1,first floor survey no,12 kondapur village serlingampally circle | F37: Madyapaga Ravindra | G37: 500019 | H37: Kondapur | I37: =VLOOKUP(H37,Mapping!D:E,2,0) -> Kondapur | J37: Zone 5 Kukatpally | K37: 0.22 | L37: =if(K37=0,"0",(if(K37<15%,"<15%",if(K37<17%,"<17%",IF(K37<20%,"<20%","20%+"))))) -> 20%+ | M37: 0.018 | O37: Vidhusekhara pizzeria private limited | P37: plot no.o1,first floor survey no,12 kondapur village serlingampally circle,500019 | Q37: Grandi sravan kumar | R37: 7347337323 | S37: vidhusekharapizzeria@gmail.com | T37: Vidhusekhara pizzeria private limited | U37: Unioun bank of india | V37: 226711010000044 | W37: UBIN0822671 | X37: Current Account | Y37: Yes | Z37: Yes | AA37: Yes | AB37: Yes | AC37: Yes | AD37: NA | AG37: KONDAPUR | AH37: just menu pending will receive today
A38: 46057 | B38: Vrindaas kitchen | C38: greeshma.vanneldas@capsdelivery.com | D38: Proprietorship | E38: shopon plot no.2a in sy no 2a in sy no.12, situated at 500084 | F38: Abhilash Thota | G38: 500084 | H38: Kondapur | I38: =VLOOKUP(H38,Mapping!D:E,2,0) -> Kondapur | J38: Zone 5 Kukatpally | K38: 0.22 | L38: =if(K38=0,"0",(if(K38<15%,"<15%",if(K38<17%,"<17%",IF(K38<20%,"<20%","20%+"))))) -> 20%+ | M38: 0.018 | O38: Vrindaas kitchen | P38: shopon plot no.2a in sy no 2a in sy no.12, situated at 500084 | Q38: Abhilash Thota | R38: 7416814310 | S38: abhigupta143@gmail.com | T38: Thota abhilash | U38: RBL Bank | V38: 309005434613 | W38: RATN000208 | X38: Savings Account | Y38: Yes | Z38: No | AA38: Yes | AB38: Yes | AC38: Yes | AD38: NA | AG38: KONDAPUR | AH38: All done
A39: 46058 | B39: Ahladha kitchen | C39: greeshma.vanneldas@capsdelivery.com | D39: Partnership | E39: plot no 68,shop no 5,Ayyappa society main road,madhapur,serlingampally circle no20 hyd | F39: Penubua kula sai | G39: 500081 | H39: Madhapur | I39: =VLOOKUP(H39,Mapping!D:E,2,0) -> madhapur | J39: Zone 4 Hi-tech City | K39: 0.2 | L39: =if(K39=0,"0",(if(K39<15%,"<15%",if(K39<17%,"<17%",IF(K39<20%,"<20%","20%+"))))) -> 20%+ | M39: 0.018 | O39: Ahladha kitchen | P39: plot no-68 shop no-5 ayyappa socity circle-20 hyd,500081 | Q39: naveen | R39: 9849975158 | S39: ahladha2025@gmail.com | T39: Ahladha kitchen | U39: Induslnd Bank | V39: 259849975158 | W39: INDB0001805 | X39: not mentioned | Y39: Yes | Z39: Yes | AA39: Yes | AB39: Yes | AC39: No | AD39: Yes | AG39: =VLOOKUP(H:H,'Pivot Table 8'!B:C,2,0) -> #REF! | AH39: menu pending
A40: 46058 | B40: Flavours of biryani cafe | C40: madhumitha.sonnakula@capsdelivery.com | D40: Proprietorship | E40: 6-1-964,shop no 2, khairthabad circel, no.17 | F40: Mangalarapu sai teja | G40: 500004 | H40: Khairathabad | I40: =VLOOKUP(H40,Mapping!D:E,2,0) -> Khairathabad | J40: Zone 1 Mehdipatnam | K40: 0.22 | L40: =if(K40=0,"0",(if(K40<15%,"<15%",if(K40<17%,"<17%",IF(K40<20%,"<20%","20%+"))))) -> 20%+ | M40: 0.018 | O40: Mangalarapu sai teja | P40: 6-1-964,shop no 2, khairthabad circel, no.17,hyderabad telangana500004 | Q40: Mangalarapu sai teja | R40: 9642897117 | S40: flavourbiryanicafe@gmail.com | T40: M. sai teja | U40: Indian bank | V40: 6414081002 | W40: IDIB000k284 | X40: Savings Account | Y40: Yes | Z40: No | AA40: Yes | AB40: Yes | AC40: Yes | AD40: No | AE40: https://drive.google.com/drive/folders/1XNX_PCNBMLG34jK7wyR_ALjgQ6bEz51m | AG40: =VLOOKUP(H:H,'Pivot Table 8'!B:C,2,0) -> #REF!
A41: 46058 | B41: Food 4 U (Rahath) | C41: madhumitha.sonnakula@capsdelivery.com | D41: Proprietorship | E41: 12-1-486/b/4 krishan nagar | F41: Mohd Arshad | G41: 500006 | H41: Asif nagar | I41: =VLOOKUP(H41,Mapping!D:E,2,0) -> mehdipatnam | J41: Zone 1 Mehdipatnam | K41: 0.2 | L41: =if(K41=0,"0",(if(K41<15%,"<15%",if(K41<17%,"<17%",IF(K41<20%,"<20%","20%+"))))) -> 20%+ | M41: 0.018 | O41: Mohd Arshad | P41: 12-1-486/b/4 krishan nagar, 500006 | Q41: Mohd Arshad | R41: 8686561072 | S41: prinzzarshad@gamil.com | T41: Mohammed Arshad | U41: Airtel Bank | V41: 8686561072 | W41: AIRP0000001 | X41: Current Account | Y41: Yes | Z41: No | AA41: Yes | AB41: Yes | AC41: No | AD41: No | AE41: https://drive.google.com/drive/folders/1WEpYZjSzuc3cu3dsjnK0dhwMDIyFdwMG | AG41: =VLOOKUP(H:H,'Pivot Table 8'!B:C,2,0) -> #REF!
A42: 46058 | B42: Hunan chinese cuisine | C42: moin.khan@capsdelivery.com | D42: Proprietorship | E42: jap hind gandhi road near ayyappa society hyd telangana | F42: Rai shankar | G42: 500081 | H42: Madhapur | I42: =VLOOKUP(H42,Mapping!D:E,2,0) -> madhapur | J42: Zone 4 Hi-tech City | K42: 0.2 | L42: =if(K42=0,"0",(if(K42<15%,"<15%",if(K42<17%,"<17%",IF(K42<20%,"<20%","20%+"))))) -> 20%+ | M42: 0.018 | O42: Hunan Chinese Cuisine | P42: Jai Hind Gandhi Rd, near Ayyappa Society, VIP Hills, Silicon Valley, Madhapur, Hyderabad, Telangana 500081, Chandanagar circle No 21, Hyderabad, Telangana - 500081 | Q42: ravi | R42: 7396735758 | S42: thehunanspice@gamil.com | T42: Hunan chinese cuisine | U42: kotak mahindra bank | V42: 1548257253 | W42: KKBK0007466 | X42: not mentioned | Y42: Yes | Z42: No | AA42: Yes | AB42: Yes | AC42: No | AD42: No | AE42: https://drive.google.com/drive/folders/1s9cQYCodLGci_eu5hOKUMbv1xL8syNuT?usp=sharing | AG42: =VLOOKUP(H:H,'Pivot Table 8'!B:C,2,0) -> #REF! | AI42: Not Uploaded
A43: 46058 | B43: krishna teeram | C43: greeshma.vanneldas@capsdelivery.com | D43: Partnership | E43: Ground flooor, plot no 84 sy no.11 swamy apyyappa housing society khanamet,hyd | F43: Krishna teeram | G43: 500081 | H43: Madhapur | I43: =VLOOKUP(H43,Mapping!D:E,2,0) -> madhapur | J43: Zone 4 Hi-tech City | K43: 0.18 | L43: =if(K43=0,"0",(if(K43<15%,"<15%",if(K43<17%,"<17%",IF(K43<20%,"<20%","20%+"))))) -> <20% | M43: 0.018 | O43: Krishna teeram | P43: Plot no-84,sy no 11 swamy ayyappa housing society khanamet, hyd 500081 | Q43: suresh | R43: 9985609966 | S43: krishnateeram2025@gmail.com | T43: not mentioned | U43: not mentioned | V43: not mentioned | W43: not mentioned | X43: not mentioned | Y43: Yes | Z43: NA | AA43: No | AB43: No | AC43: No | AD43: NA | AG43: =VLOOKUP(H:H,'Pivot Table 8'!B:C,2,0) -> #REF! | AH43: Bank details and menu pending
A44: 46058 | B44: lucky Multicusine Restaurant madhapur | C44: moin.khan@capsdelivery.com | D44: Proprietorship | E44: sy no. 54,58,59 plot no 1,part gb guttala begumpet madhapur road | F44: Md mansoor | G44: 500081 | H44: Madhapur | I44: =VLOOKUP(H44,Mapping!D:E,2,0) -> madhapur | J44: Zone 4 Hi-tech City | K44: 0.15 | L44: =if(K44=0,"0",(if(K44<15%,"<15%",if(K44<17%,"<17%",IF(K44<20%,"<20%","20%+"))))) -> <17% | M44: 0.018 | O44: lucky Multicusine Restaurant | P44: sy no. 54,58,59 plot no 1,part gb guttala begumpet madhapur road | Q44: Md mansoor | R44: 9676213874 | S44: y96822534@gamil.com | T44: Lucky multi cuisine Restaurant | U44: Hdfc bank | V44: 50200064899781 | W44: HDFC0004277 | X44: Current Account | Y44: Yes | Z44: Yes | AA44: Yes | AB44: Yes | AC44: No | AD44: No | AE44: https://drive.google.com/drive/folders/103H3SyeCFb1aeW4_nmJsLx1A-k8jd-yJ?usp=sharing | AG44: =VLOOKUP(H:H,'Pivot Table 8'!B:C,2,0) -> #REF!
A45: 46058 | B45: rahat Restaurant | C45: manasa.chigurupati@capsdelivery.com | D45: Proprietorship | E45: 12-1-486/b/4/1,kishan nagar, tappachabutra road,hyd | F45: Mohammed feroz | G45: 500006 | H45: Asif nagar | I45: =VLOOKUP(H45,Mapping!D:E,2,0) -> mehdipatnam | J45: Zone 1 Mehdipatnam | K45: 0.2 | L45: =if(K45=0,"0",(if(K45<15%,"<15%",if(K45<17%,"<17%",IF(K45<20%,"<20%","20%+"))))) -> 20%+ | M45: 0.018 | O45: Rahat Restaurant | P45: 12-1-486/b/4/1,kishan nagar, tappachabutra road,hyd 500006 | Q45: mohammed feroz | R45: 7097949648 | S45: ak.8977.ak@gmail.com | T45: mohammed froz | U45: Induslnd Bank | V45: 157097949648 | W45: INDB0001052 | X45: Savings Account | Y45: No | Z45: No | AA45: No | AB45: No | AC45: No | AD45: NA | AG45: =VLOOKUP(H:H,'Pivot Table 8'!B:C,2,0) -> #REF!
A46: 46058 | B46: Tahari house (rahaat fast food) | C46: madhumitha.sonnakula@capsdelivery.com | D46: Proprietorship | E46: 12-1-486/b/2/5 krishan nagar,Tappachabuta | F46: Mohanmed feroz | G46: 500006 | H46: Asif nagar | I46: =VLOOKUP(H46,Mapping!D:E,2,0) -> mehdipatnam | J46: Zone 1 Mehdipatnam | K46: 0.2 | L46: =if(K46=0,"0",(if(K46<15%,"<15%",if(K46<17%,"<17%",IF(K46<20%,"<20%","20%+"))))) -> 20%+ | M46: 0.018 | O46: Tahari house | P46: 12-1-486/b/2/5 krishan nagar | Q46: Mohanmed feroz | R46: 7097949648 | S46: ak.8977.ak@gmail.com | T46: Mohanmed feroz | U46: Induslnd Bank | V46: 157097949648 | W46: INDB0001052 | X46: Savings Account | Y46: Yes | Z46: No | AA46: Yes | AB46: Yes | AC46: No | AD46: No | AE46: https://drive.google.com/drive/folders/1jLPstIiQGwHXYF9SbDs4WLQgUwAvIFMx | AG46: =VLOOKUP(H:H,'Pivot Table 8'!B:C,2,0) -> #REF!
A47: 46058 | B47: vijay durga pre veg tiffin and meals | C47: parthive.maganti@capsdelivery.com | D47: Proprietorship | E47: H.no:1-90/7/b/173,plot no.5,madhapur,selingampally circle no.20,hyd, telangana | F47: karempudi vijava durga | G47: 500081 | H47: Madhapur | I47: =VLOOKUP(H47,Mapping!D:E,2,0) -> madhapur | J47: Zone 4 Hi-tech City | K47: 0.17 | L47: =if(K47=0,"0",(if(K47<15%,"<15%",if(K47<17%,"<17%",IF(K47<20%,"<20%","20%+"))))) -> <20% | M47: 0.018 | O47: not mentioned | P47: H.no:1-90/7/b/173,plot no.5,madhapur,selingampally circle no.20,hyd, telangana,500081 | Q47: karempudi vijava durga | R47: 6303274660 | S47: vijayvijju8096@gmail.com | T47: kolli tirunala ravindra | U47: kotak mahindra bank | V47: 3049366762 | W47: KKBK0007466 | X47: Savings Account | Y47: Yes | Z47: No | AA47: Yes | AB47: No | AC47: Yes | AD47: No | AF47: https://maps.app.goo.gl/MJ7UedzFq2PJ6SB88 | AG47: =VLOOKUP(H:H,'Pivot Table 8'!B:C,2,0) -> #REF!
A48: 46059 | B48: Almas multi cusine Restaurant | C48: akhila.narra@capsdelivery.com | D48: not mentioned | E48: not mentioned | F48: SR Nagar | G48: 500038 | H48: SR Nagar | I48: =VLOOKUP(H48,Mapping!D:E,2,0) -> ameerpet | J48: Zone 6 Ameerpet | K48: 0.17 | L48: =if(K48=0,"0",(if(K48<15%,"<15%",if(K48<17%,"<17%",IF(K48<20%,"<20%","20%+"))))) -> <20% | M48: 0.018 | O48: not mentioned | P48: not mentioned | Q48: not mentioned | R48: not mentioned | S48: not mentioned | T48: not mentioned | U48: not mentioned | V48: not mentioned | W48: not mentioned | X48: not mentioned | AG48: =VLOOKUP(H:H,'Pivot Table 8'!B:C,2,0) -> #REF!
A49: 46059 | B49: Anand Bhavan mess | C49: moin.khan@capsdelivery.com | D49: Partnership | E49: H.no:1-98/9/3/74/2,R L raidurg,jai hind enclave,seasons pool, madhapur,hyd | F49: Juturi Rama seshagiri | G49: 500081 | H49: Madhapur | I49: =VLOOKUP(H49,Mapping!D:E,2,0) -> madhapur | J49: Zone 4 Hi-tech City | K49: 0.2 | L49: =if(K49=0,"0",(if(K49<15%,"<15%",if(K49<17%,"<17%",IF(K49<20%,"<20%","20%+"))))) -> 20%+ | M49: 0.018 | O49: Juturi Rama seshagiri | P49: H.no:1-98/9/3/74/2,R L raidurg,jai hind enclave,seasons pool, madhapur,hyd,500081 | Q49: V. Shankar | R49: 7093762666 | S49: anandbhavanmess@gmail.com | T49: Anand Bhavan mess | U49: Yes Bank | V49: 18361900006050 | W49: YESB0000183 | X49: Current Account | Y49: Yes | Z49: No | AA49: Yes | AB49: Yes | AC49: No | AD49: No | AE49: https://drive.google.com/drive/folders/1tbQKo0BRhM1KMeFlCGTLyg8pB7WVsxpT?usp=sharing | AF49: 17.447125553953608, 78.38804061226678 | AG49: =VLOOKUP(H:H,'Pivot Table 8'!B:C,2,0) -> #REF!
A50: 46059 | B50: Brew commune cafe and bistro | C50: chanakya.inugala@capsdelivery.com | D50: Proprietorship | E50: shop no 7 first floor,plot no 2-56/11/53/a survey no 11/6 telangana | F50: Challa Triveni | G50: 500081 | H50: Madhapur | I50: =VLOOKUP(H50,Mapping!D:E,2,0) -> madhapur | J50: Zone 4 Hi-tech City | K50: 0.2 | L50: =if(K50=0,"0",(if(K50<15%,"<15%",if(K50<17%,"<17%",IF(K50<20%,"<20%","20%+"))))) -> 20%+ | M50: 0.018 | O50: Challa Triveni | P50: first floor,plot no 2-56/11/53/a survey no 11/6,100ft road, near by meridian school,telangana | Q50: Triveni | R50: 8333833299 | S50: brewcommunecafe@gmail.com | T50: Brew commune cafe and bistro | U50: State Bank of India | V50: 44866997013 | W50: SBIN0014676 | X50: Current Account | Y50: Yes | Z50: Yes | AA50: Yes | AB50: No | AC50: No | AG50: =VLOOKUP(H:H,'Pivot Table 8'!B:C,2,0) -> #REF!
A51: 46059 | B51: Kissme mandi | C51: chanakya.inugala@capsdelivery.com | D51: not mentioned | E51: DROPPED | F51: not mentioned | G51: not mentioned | H51: Madhapur | I51: =VLOOKUP(H51,Mapping!D:E,2,0) -> madhapur | J51: =VLOOKUP(I51,Mapping!A:B,2,0) -> Zone 4 Hi-tech City | K51: 0.22 | L51: =if(K51=0,"0",(if(K51<15%,"<15%",if(K51<17%,"<17%",IF(K51<20%,"<20%","20%+"))))) -> 20%+ | M51: 0.018 | O51: not mentioned | P51: not mentioned | Q51: not mentioned | R51: not mentioned | S51: not mentioned | T51: not mentioned | U51: not mentioned | V51: not mentioned | W51: not mentioned | X51: not mentioned | Z51: No | AA51: No | AB51: No | AC51: No | AD51: No
A52: 46059 | B52: Madapuram Restaurant | C52: greeshma.vanneldas@capsdelivery.com | D52: Proprietorship | E52: D.no:2-46/1,plot no 33/a megha hills cahndanagar circle,hyd,Telangana | F52: Madapuram anil kumar | G52: 500081 | H52: Chandanagar | I52: =VLOOKUP(H52,Mapping!D:E,2,0) -> miyapur | J52: Zone 5 Kukatpally | K52: 0.2 | L52: =if(K52=0,"0",(if(K52<15%,"<15%",if(K52<17%,"<17%",IF(K52<20%,"<20%","20%+"))))) -> 20%+ | M52: 0.018 | O52: not mentioned | P52: D.no:2-46/1,plot no 33/a megha hills cahndanagar circle,hyd,Telangana,500081 | Q52: Madapuram anil kumar | R52: 7893713995 | S52: danil madapuram@gmail.com | T52: not mentioned | U52: not mentioned | V52: not mentioned | W52: not mentioned | X52: not mentioned | Y52: Yes | Z52: NA | AA52: No | AB52: No | AC52: No | AD52: NA | AE52: https://drive.google.com/drive/folders/1UWFy24j0VbJy49ZBFd7Md1mSffwvmJFM?usp=sharing | AG52: =VLOOKUP(H:H,'Pivot Table 8'!B:C,2,0) -> #REF! | AH52: Its under renovation,need 4 days of time | AI52: Not Uploaded
A53: 46059 | B53: Meraj's Restaurant | C53: madhumitha.sonnakula@capsdelivery.com | D53: Proprietorship | E53: x road, royal colony,mehidpatnam | F53: Mohammed umar khan | G53: 500028 | H53: Mehdipatnam | I53: =VLOOKUP(H53,Mapping!D:E,2,0) -> mehdipatnam | J53: Zone 1 Mehdipatnam | K53: 0.2 | L53: =if(K53=0,"0",(if(K53<15%,"<15%",if(K53<17%,"<17%",IF(K53<20%,"<20%","20%+"))))) -> 20%+ | M53: 0.018 | O53: Meraj's Restaurant | P53: x road, royal colony,mehidpatnam,500028 | Q53: mohd umar khan | R53: 9885199151 | S53: amer786khan@gmil.com | T53: Meraj's Restaurant | U53: Canara bank | V53: 120038671615 | W53: CNRB0013007 | X53: Current Account | Y53: No | Z53: No | AA53: Yes | AB53: Yes | AC53: Yes | AD53: No | AE53: https://drive.google.com/drive/folders/1ZhgTUeICe7C_yN0M6r9sIqQsX2RirxEj | AG53: =VLOOKUP(H:H,'Pivot Table 8'!B:C,2,0) -> #REF!
A54: 46059 | B54: Naseeb cafe | C54: madhumitha.sonnakula@capsdelivery.com | D54: Proprietorship | E54: 13-1-1234,salum nasseb complex a/1,tappa | F54: Mohammed Quddus hussain | G54: 500006 | H54: Asif nagar | I54: =VLOOKUP(H54,Mapping!D:E,2,0) -> mehdipatnam | J54: Zone 1 Mehdipatnam | K54: 0.22 | L54: =if(K54=0,"0",(if(K54<15%,"<15%",if(K54<17%,"<17%",IF(K54<20%,"<20%","20%+"))))) -> 20%+ | M54: 0.018 | O54: Naseeb cafe | P54: 13-1-1234,salum nasseb complex,500006 | Q54: Quddus hussain | R54: 9182466676 | S54: khuddushussain7@gmail.com | T54: Mohammed Quddus hussain | U54: State Bank of India | V54: 37947443400 | W54: SBIN0005322 | X54: Savings Account | Y54: Yes | Z54: Yes | AA54: Yes | AB54: Yes | AC54: Yes | AD54: Yes | AE54: https://drive.google.com/drive/folders/1r91rV1Plcx98BlVs7U95ATjl8nVQIxPT | AG54: =VLOOKUP(H:H,'Pivot Table 8'!B:C,2,0) -> #REF!
A55: 46059 | B55: Sri balaji family Dhaba | C55: ankitha.baske@capsdelivery.com | D55: Proprietorship | E55: 12-2-417/46/9,sharada nagarn colony gudimalk | F55: Bidhaniyasoni | G55: 500028 | H55: Gudimalkapur | I55: =VLOOKUP(H55,Mapping!D:E,2,0) -> masab tank | J55: Zone 1 Mehdipatnam | K55: 0.22 | L55: =if(K55=0,"0",(if(K55<15%,"<15%",if(K55<17%,"<17%",IF(K55<20%,"<20%","20%+"))))) -> 20%+ | M55: 0.018 | O55: Sri balaji family Dhaba | P55: 12-2-417/46/9,sharada nagarn colony gudimalkpur 500028 | Q55: Rihaan | R55: 4023536061 | S55: bidhaniyasony@gmail.com | T55: B.soni | U55: DCB bank | V55: 2711500006880 | W55: DCBL0000027 | X55: Savings Account | Y55: Yes | Z55: NA | AA55: Yes | AB55: Yes | AC55: Yes | AD55: NA | AE55: https://drive.google.com/drive/folders/13RR--Sp7G4RzGdjYpim1KYichrJ67D1q?usp=drive_link | AG55: =VLOOKUP(H:H,'Pivot Table 8'!B:C,2,0) -> #REF!
A56: 46059 | B56: The burger kitchen | C56: chanakya.inugala@capsdelivery.com | D56: Proprietorship | E56: plot no 51 khanamet,attapur,chandanagar,circle no2 hyd | G56: 500084 | H56: Attapur | I56: =VLOOKUP(H56,Mapping!D:E,2,0) -> mehdipatnam | J56: Zone 1 Mehdipatnam | K56: 0.2 | L56: =if(K56=0,"0",(if(K56<15%,"<15%",if(K56<17%,"<17%",IF(K56<20%,"<20%","20%+"))))) -> 20%+ | M56: 0.018 | O56: Smash city | P56: plot no 51 khanamet,attapur,chandanagar,circle no2 hyd,500084 | Q56: Pranay kumar | R56: 9963967706 | S56: smashcity.bk2025@gmail.com | T56: Pranay kumar | U56: kotak mahindra bank | V56: 33311501023101 | W56: NFSC000033 | X56: Current Account | AG56: =VLOOKUP(H:H,'Pivot Table 8'!B:C,2,0) -> #REF!
A57: 46059 | B57: Babu Gari Ruchulu and curry point | C57: parthive.maganti@capsdelivery.com | D57: not mentioned | E57: not mentioned | F57: not mentioned | G57: not mentioned | H57: not mentioned | I57: not mentioned | J57: not mentioned | K57: 0.22 | L57: =if(K57=0,"0",(if(K57<15%,"<15%",if(K57<17%,"<17%",IF(K57<20%,"<20%","20%+"))))) -> 20%+ | M57: 0.018 | O57: not mentioned | P57: not mentioned | Q57: not mentioned | R57: not mentioned | S57: not mentioned | T57: not mentioned | U57: not mentioned | V57: not mentioned | W57: not mentioned | X57: not mentioned
A58: 46060 | B58: Lakshmi's United kitchen | C58: parthive.maganti@capsdelivery.com | D58: Partnership | E58: 100feet road, madhapur | F58: not mentioned | G58: 500081 | H58: Madhapur | I58: =VLOOKUP(H58,Mapping!D:E,2,0) -> madhapur | J58: Zone 4 Hi-tech City | K58: 0.17 | L58: =if(K58=0,"0",(if(K58<15%,"<15%",if(K58<17%,"<17%",IF(K58<20%,"<20%","20%+"))))) -> <20% | M58: 0.018 | O58: V J food partners | P58: H.no:27-3/26, shiva sai nagar-11-bairaguda,hyd,500091 | Q58: vidya sagar kadali | R58: 709504025 | S58: vjfoodprenures@gmail.com | T58: VJ food prenures | U58: Hdfc bank | V58: 50200069149286 | W58: HDFC0003949 | X58: Current Account | Y58: Yes | Z58: Yes | AA58: Yes | AB58: Yes | AC58: Yes | AD58: No | AE58: Lakshmi's United Kitchen | AF58: Lakshmi's United Kitchen | AG58: =VLOOKUP(H:H,'Pivot Table 8'!B:C,2,0) -> #REF! | AH58: checked
A59: 46062 | B59: Bakeway Bakers | C59: sumadhur.mummadi@capsdelivery.com | D59: Partnership | E59: 7-1-455/12 opposite Bata showroom, Balkampet road,Ameerpet Hyd | F59: K. Naga Bhushan Rao | G59: 500016 | H59: Ameerpet | I59: =VLOOKUP(H59,Mapping!D:E,2,0) -> panjagutta | J59: Zone 6 Ameerpet | K59: 0.22 | L59: =if(K59=0,"0",(if(K59<15%,"<15%",if(K59<17%,"<17%",IF(K59<20%,"<20%","20%+"))))) -> 20%+ | M59: 0.018 | O59: Bakeway Bakers | P59: 7-1-455/12 opposite Bata showroom, Balkampet road,Ameerpet Hyd | Q59: K. Naga Bhushan Rao | R59: 8501024577 | S59: bhushankotta valasa@gmail.com | T59: K. Naga Bhushan Rao | U59: Hdfc bank | V59: 50200047092427 | W59: HDFC0001627 | X59: Current Account | Y59: Yes | Z59: Yes | AA59: Yes | AB59: Yes | AC59: Yes | AD59: Yes | AE59: https://drive.google.com/drive/folders/12SN4-iTB989RjZFQ6mgf4CcnuRI5Bjgs | AF59: 17°26'12.6"N 78°26'53.5"E | AG59: =VLOOKUP(H:H,'Pivot Table 8'!B:C,2,0) -> #REF!
A60: 46062 | B60: C'est la vie bakes and cakes (pure veg) | C60: madhumitha.sonnakula@capsdelivery.com | D60: Proprietorship | E60: 138/1,flat no 45 sham apt,secunderabad 138/1,flat no 45 shama apt sindi colony pg road | F60: Juhi sanjay sajnani | G60: 500003 | H60: secunderabad | I60: =VLOOKUP(H60,Mapping!D:E,2,0) -> begumpet | J60: Zone 6 Ameerpet | K60: 0.21 | L60: =if(K60=0,"0",(if(K60<15%,"<15%",if(K60<17%,"<17%",IF(K60<20%,"<20%","20%+"))))) -> 20%+ | M60: 0.018 | O60: Juhi sanjay sajnani | P60: 138/1,flat no 45 shama apt sindi colony pg road 500005 | Q60: Juhi sanjay sajnani | R60: 9133847766 | S60: frostbakery@gmail.com | T60: frost bakery | U60: Axis Bank | V60: 923020067557565 | W60: UTIB0003484 | X60: Current Account | Y60: Yes | Z60: Yes | AA60: Yes | AB60: No | AC60: Yes | AD60: No | AE60: https://drive.google.com/drive/folders/1qqDAuHRUNSZORJNHvCtEG8P1NW_AwUL7 | AG60: =VLOOKUP(H:H,'Pivot Table 8'!B:C,2,0) -> #REF!
A61: 46062 | B61: Cafe Reels | C61: chanakya.inugala@capsdelivery.com | D61: Proprietorship | E61: floor no:ground floor,building no.1,d.no:1-98/90c beside durgamma temple,ayyappa society road | F61: not mentioned | G61: 500081 | H61: Madhapur | I61: =VLOOKUP(H61,Mapping!D:E,2,0) -> madhapur | J61: Zone 4 Hi-tech City | K61: 0.2 | L61: =if(K61=0,"0",(if(K61<15%,"<15%",if(K61<17%,"<17%",IF(K61<20%,"<20%","20%+"))))) -> 20%+ | M61: 0.018 | O61: not mentioned | P61: Building no/flat no.1-98/90c,beside durgamma temple,ayyappa society road,madhapur | Q61: Naveen reddy | R61: 9676945646 | S61: not mentioned | T61: not mentioned | U61: not mentioned | V61: not mentioned | W61: not mentioned | X61: not mentioned | Y61: Yes | Z61: No | AA61: Yes | AB61: No | AC61: No | AD61: No | AG61: =VLOOKUP(H:H,'Pivot Table 8'!B:C,2,0) -> #REF!
A62: 46062 | B62: Donut O' clock (pure veg) | C62: greeshma.vanneldas@capsdelivery.com | D62: Proprietorship | E62: 138/1,flat no 45 sham apt,secunderabad 138/1,flat no 45 shama apt sindi colony pg road | F62: Juhi sanjay sajnani | G62: 500003 | H62: secunderabad | I62: =VLOOKUP(H62,Mapping!D:E,2,0) -> begumpet | J62: Zone 6 Ameerpet | K62: 0.21 | L62: =if(K62=0,"0",(if(K62<15%,"<15%",if(K62<17%,"<17%",IF(K62<20%,"<20%","20%+"))))) -> 20%+ | M62: 0.018 | O62: Juhi sanjay sajnani | P62: 138/1,flat no 45 shama apt sindi colony pg road 500007 | Q62: Juhi sanjay sajnani | R62: 9133847766 | S62: frostbakery@gmail.com | T62: frost bakery | U62: Axis Bank | V62: 923020067557565 | W62: UTIB0003484 | X62: Current Account | Y62: Yes | Z62: Yes | AA62: Yes | AB62: No | AC62: No | AD62: No | AE62: https://drive.google.com/drive/folders/1qqDAuHRUNSZORJNHvCtEG8P1NW_AwUL10 | AG62: =VLOOKUP(H:H,'Pivot Table 8'!B:C,2,0) -> #REF!
A63: 46062 | B63: Frost Bake Studio (pure veg) | C63: madhumitha.sonnakula@capsdelivery.com | D63: Proprietorship | E63: secunderbad circle 138/1,flat no 45 sham apt,secunderabad | F63: Juhi sanjay sajnani | G63: 500003 | H63: secunderabad | I63: =VLOOKUP(H63,Mapping!D:E,2,0) -> begumpet | J63: Zone 6 Ameerpet | K63: 0.21 | L63: =if(K63=0,"0",(if(K63<15%,"<15%",if(K63<17%,"<17%",IF(K63<20%,"<20%","20%+"))))) -> 20%+ | M63: 0.018 | O63: Juhi sanjay sajnani | P63: 138/1,flat no 45 shama apt sindi colony pg road | Q63: Juhi sanjay sajnani | R63: 9133847766 | S63: frostbakeryindia@gmail.com | T63: Juhi sanjay sajnani | U63: Axis Bank | V63: 923020067557565 | W63: UTIB0003484 | X63: Current Account | Y63: Yes | Z63: Yes | AA63: Yes | AB63: No | AC63: Yes | AD63: No | AE63: https://drive.google.com/drive/folders/1qqDAuHRUNSZORJNHvCtEG8P1NW_AwUL10 | AG63: =VLOOKUP(H:H,'Pivot Table 8'!B:C,2,0) -> #REF!
A64: 46062 | B64: Frost Bakery (pure veg) | C64: madhumitha.sonnakula@capsdelivery.com | D64: Proprietorship | E64: 138/1,flat no 45 sham apt,secunderabad 138/1,flat no 45 shama apt sindi colony pg road 500003 | F64: Juhi sanjay sajnani | G64: 500003 | H64: Begumpet | I64: =VLOOKUP(H64,Mapping!D:E,2,0) -> ameerpet | J64: Zone 6 Ameerpet | K64: 0.21 | L64: =if(K64=0,"0",(if(K64<15%,"<15%",if(K64<17%,"<17%",IF(K64<20%,"<20%","20%+"))))) -> 20%+ | M64: 0.018 | O64: Juhi sanjay sajnani | P64: 138/1,flat no 45 shama apt sindi colony pg road 500003 | Q64: Juhi sanjay sajnani | R64: 9133847766 | S64: frostbakery@gmail.com | T64: frost bakery | U64: Axis Bank | V64: 923020067557565 | W64: UTIB0003484 | X64: Current Account | Y64: Yes | Z64: Yes | AA64: Yes | AB64: No | AC64: Yes | AD64: No | AE64: https://drive.google.com/drive/folders/1qqDAuHRUNSZORJNHvCtEG8P1NW_AwUL7 | AG64: =VLOOKUP(H:H,'Pivot Table 8'!B:C,2,0) -> #REF!
A65: 46062 | B65: Gupshup Bistro | C65: madhumitha.sonnakula@capsdelivery.com | D65: Proprietorship | E65: H.no:1-8-125/1/ g-2, shop no.2 , shop no.3 Aman arcade pg road, secundarabad, no. 129, hyderabad telangana | F65: Sonal mohit mehta | G65: 500003 | H65: secunderabad | I65: =VLOOKUP(H65,Mapping!D:E,2,0) -> begumpet | J65: Zone 6 Ameerpet | K65: 0.18 | L65: =if(K65=0,"0",(if(K65<15%,"<15%",if(K65<17%,"<17%",IF(K65<20%,"<20%","20%+"))))) -> <20% | M65: 0.018 | O65: Gupshup Bistro | P65: H.NO: 1-8-125/1/G-2, SHOP NO. 2, AMAN ARCADE, P.G ROAD, SECUNDERABAD,Secunderabad Circle No.29, Hyderabad,Telangana - 500003 | Q65: Sonal mohit mehta | R65: 9603939777 | S65: gupshupbistro@gmail.com | T65: Gupshup Bistro | U65: kotak mahindra bank | V65: 9448450312 | W65: KKBK0007515 | X65: Current Account | Y65: Yes | Z65: Yes | AA65: Yes | AB65: No | AC65: Yes | AD65: No | AE65: https://drive.google.com/drive/folders/1K6pBmqU93pqRUCSJpntmoI1L3BMw5xgl | AG65: =VLOOKUP(H:H,'Pivot Table 8'!B:C,2,0) -> #REF!
A66: 46062 | B66: Just so wow cakes | C66: madhumitha.sonnakula@capsdelivery.com | D66: Proprietorship | E66: 138/1,flat no 45 sham apt,secunderabad 138/1,flat no 45 shama apt sindi colony pg road | F66: Juhi sanjay sajnani | G66: 500003 | H66: secunderabad | I66: =VLOOKUP(H66,Mapping!D:E,2,0) -> begumpet | J66: Zone 6 Ameerpet | K66: 0.21 | L66: =if(K66=0,"0",(if(K66<15%,"<15%",if(K66<17%,"<17%",IF(K66<20%,"<20%","20%+"))))) -> 20%+ | M66: 0.018 | O66: Juhi sanjay sajnani | P66: 138/1,flat no 45 shama apt sindi colony pg road 500004 | Q66: Juhi sanjay sajnani | R66: 9133847766 | S66: frostbakery@gmail.com | T66: frost bakery | U66: Axis Bank | V66: 923020067557565 | W66: UTIB0003484 | X66: Current Account | Y66: Yes | Z66: Yes | AA66: Yes | AB66: No | AC66: Yes | AD66: No | AE66: https://drive.google.com/drive/folders/1qqDAuHRUNSZORJNHvCtEG8P1NW_AwUL7 | AG66: =VLOOKUP(H:H,'Pivot Table 8'!B:C,2,0) -> #REF!
A67: 46062 | B67: Kshatriya Grand | C67: ankitha.baske@capsdelivery.com | D67: Proprietorship | E67: H.no: 4/1 Mig, ground floor , kphb colony, kukatpally,hyd | F67: Karthik | G67: 500072 | H67: Kukatpally | I67: =VLOOKUP(H67,Mapping!D:E,2,0) -> kukatpally | J67: Zone 5 Kukatpally | K67: 0.22 | L67: =if(K67=0,"0",(if(K67<15%,"<15%",if(K67<17%,"<17%",IF(K67<20%,"<20%","20%+"))))) -> 20%+ | M67: 0.018 | O67: Kshatriya Grand | P67: H.no: 4/1 Mig, ground floor , kphb colony, kukatpally,hyd-5000072 | Q67: Karthik | R67: 9642431013 | S67: tkartheek.516@gmail.com | T67: Therala kartheek | U67: kotak mahindra bank | V67: 3212110291 | W67: KKBK0000560 | X67: Savings Account | Y67: Yes | Z67: NA | AA67: Yes | AB67: Yes | AC67: Yes | AD67: Yes | AE67: https://drive.google.com/drive/folders/15_T7Ws4Hj0dUpZmHv1fPfcXjqwgZ3bqF?usp=drive_link | AG67: =VLOOKUP(H:H,'Pivot Table 8'!B:C,2,0) -> #REF!
A68: 46062 | B68: La boulangerie (pure veg) | C68: madhumitha.sonnakula@capsdelivery.com | D68: Proprietorship | E68: 138/1,flat no 45, sham apts, secunderabad,sindhi colony pg road | F68: Juhi sanjay sajnani | G68: 500003 | H68: secunderabad | I68: =VLOOKUP(H68,Mapping!D:E,2,0) -> begumpet | J68: Zone 6 Ameerpet | K68: 0.21 | L68: =if(K68=0,"0",(if(K68<15%,"<15%",if(K68<17%,"<17%",IF(K68<20%,"<20%","20%+"))))) -> 20%+ | M68: 0.018 | O68: Juhi sanjay sajnani | P68: 138/1,flat no 45,secunderabad 500003 | Q68: Juhi sanjay sajnani | R68: 9133847766 | S68: frostbakery@gmail.com | T68: frost bakery | U68: Axis Bank | V68: 923020067557565 | W68: UTIB0003484 | X68: Current Account | Y68: Yes | Z68: Yes | AA68: Yes | AB68: No | AC68: Yes | AD68: No | AE68: https://drive.google.com/drive/folders/1qqDAuHRUNSZORJNHvCtEG8P1NW_AwUL10 | AG68: =VLOOKUP(H:H,'Pivot Table 8'!B:C,2,0) -> #REF!
A69: 46062 | B69: Mokshi kitchen | C69: parthive.maganti@capsdelivery.com | D69: Proprietorship | E69: plot no.2/a,whitefeilds,kondapur,serlingampally circle no 20,hyd | F69: K.Rajesh | G69: 500084 | H69: Serilingampally | I69: =VLOOKUP(H69,Mapping!D:E,2,0) -> Sherilingampally | J69: Zone 5 Kukatpally | K69: paper missing | L69: =if(K69=0,"0",(if(K69<15%,"<15%",if(K69<17%,"<17%",IF(K69<20%,"<20%","20%+"))))) -> 20%+ | M69: 0.018 | N69: papper missing | O69: MOKSHI KITCHEN // KETHINENI RAJESH | P69: plot no.2/a,whitefeilds,kondapur,serlingampally circle no 20,hyd,500084 | Q69: Kethineni Rajesh | R69: 7306445599 | S69: not mentioned | T69: sambasiva rao kethineni | U69: State Bank of India | V69: 20264573793 | W69: SBIN0014170 | X69: Savings Account | Y69: Yes | Z69: No | AA69: No | AB69: NA | AC69: Yes | AD69: No | AE69: Mokshi Kitchen | AF69: https://maps.app.goo.gl/Sq2bCzb7zN1sfzjj8 | AG69: =VLOOKUP(H:H,'Pivot Table 8'!B:C,2,0) -> #REF! | AH69: did not lift the call
A70: 46062 | B70: North indian hub | C70: parthive.maganti@capsdelivery.com | D70: Proprietorship | E70: sutter no.3, plot no .2a sy no.12,kondapur serlingampally circle no.20 hyd | F70: Ashish kumar | G70: 500084 | H70: Kondapur | I70: =VLOOKUP(H70,Mapping!D:E,2,0) -> Kondapur | J70: Zone 5 Kukatpally | K70: 0.17 | L70: =if(K70=0,"0",(if(K70<15%,"<15%",if(K70<17%,"<17%",IF(K70<20%,"<20%","20%+"))))) -> <20% | M70: 0.018 | O70: North indian hub | P70: sutter no.3, plot no .2a sy no.12,kondapur serlingampally circle no.20 hyd,500084 | Q70: Ashish kumar | R70: 9398556461 | S70: not mentioned | T70: Ashish kumar | U70: Bandhan Bank | V70: 50200018292136 | W70: BDBL0001160 | X70: Savings Account | Y70: Yes | Z70: Yes | AA70: Yes | AB70: Yes | AC70: No | AD70: No | AE70: North Indian Hub | AF70: https://maps.app.goo.gl/Sq2bCzb7zN1sfzjj8 | AG70: KONDAPUR | AH70: will share it with parthive
A71: 46062 | B71: Rivora | C71: manasa.chigurupati@capsdelivery.com | D71: Partnership | E71: Gokul plots no.397and 492,VR Colony,beside vijetha super market,kphb | F71: Vamshi krishna | G71: 500085 | H71: KBHP | I71: KPHP | J71: Zone 5 Kukatpally | K71: 0.2 | L71: =if(K71=0,"0",(if(K71<15%,"<15%",if(K71<17%,"<17%",IF(K71<20%,"<20%","20%+"))))) -> 20%+ | M71: 0.018 | O71: Rivora | P71: Gokul plots no.397and 492,VR Colony,beside vijetha super market,kphb,500085 | Q71: Vamshi krishna | R71: 9959357179 | S71: vasmshikrishnamarch20@gmail.com | T71: not mentioned | U71: not mentioned | V71: not mentioned | W71: not mentioned | X71: not mentioned | Y71: No | Z71: No | AA71: Yes | AB71: Yes | AC71: No | AD71: No | AE71: https://drive.google.com/drive/folders/1kjGHv9fx_gvyji9Qe3xnW2P5yjNLNsOr | AG71: =VLOOKUP(H:H,'Pivot Table 8'!B:C,2,0) -> #REF! | AI71: Not Uploaded
A72: 46062 | B72: Say cheese patisserie (pure veg) | C72: madhumitha.sonnakula@capsdelivery.com | D72: Proprietorship | E72: 138/1,flat no 45 sham apt,secunderabad 138/1,flat no 45 shama apt sindi colony pg road | F72: Juhi sanjay sajnani | G72: 500003 | H72: secunderabad | I72: =VLOOKUP(H72,Mapping!D:E,2,0) -> begumpet | J72: Zone 6 Ameerpet | K72: 0.21 | L72: =if(K72=0,"0",(if(K72<15%,"<15%",if(K72<17%,"<17%",IF(K72<20%,"<20%","20%+"))))) -> 20%+ | M72: 0.018 | O72: Juhi sanjay sajnani | P72: 138/1,flat no 45 shama apt sindi colony pg road 500007 | Q72: Juhi sanjay sajnani | R72: 9133847766 | S72: frostbakery@gmail.com | T72: frost bakery | U72: Axis Bank | V72: 923020067557565 | W72: UTIB0003484 | X72: Current Account | Y72: Yes | Z72: Yes | AA72: Yes | AB72: No | AC72: Yes | AD72: No | AE72: https://drive.google.com/drive/folders/1qqDAuHRUNSZORJNHvCtEG8P1NW_AwUL9 | AG72: =VLOOKUP(H:H,'Pivot Table 8'!B:C,2,0) -> #REF!
A73: 46062 | B73: Sri sai ram food zone | C73: manasa.chigurupati@capsdelivery.com | D73: Proprietorship | E73: Mig-64 dharmareddy colony phase-1 kphb colony kukatpally,moosapet circle no.23, | F73: Dinesh | G73: 500072 | H73: Kukatpally | I73: =VLOOKUP(H73,Mapping!D:E,2,0) -> kukatpally | J73: Zone 5 Kukatpally | K73: 0.22 | L73: =if(K73=0,"0",(if(K73<15%,"<15%",if(K73<17%,"<17%",IF(K73<20%,"<20%","20%+"))))) -> 20%+ | M73: 0.018 | O73: Sri sai ram food zone | P73: Mig-64 dharmareddy colony phase-1 kphb colony kukatpally | Q73: Dinesh | R73: 6281821329 | S73: dinesg.pedamallu@gmail.com | T73: Pedamallu dinesh sai | U73: IDBI Bank | V73: 1.510104e+15 | W73: IBKL0001510 | X73: Savings Account | Y73: Yes | Z73: No | AA73: Yes | AB73: Yes | AC73: No | AD73: No | AE73: https://drive.google.com/drive/folders/16gfbzzZAYHYsCWvtHbZJvY-ryyLeZfvh | AG73: =VLOOKUP(H:H,'Pivot Table 8'!B:C,2,0) -> #REF!
A74: 46062 | B74: Tempt Chocolates | C74: greeshma.vanneldas@capsdelivery.com | D74: Proprietorship | E74: 138/1,flat no 45 sham apt,secunderabad 138/1,flat no 45 shama apt sindi colony pg road | F74: Juhi sanjay sajnani | G74: 500003 | H74: secunderabad | I74: =VLOOKUP(H74,Mapping!D:E,2,0) -> begumpet | J74: Zone 6 Ameerpet | K74: 0.21 | L74: =if(K74=0,"0",(if(K74<15%,"<15%",if(K74<17%,"<17%",IF(K74<20%,"<20%","20%+"))))) -> 20%+ | M74: 0.018 | O74: Juhi sanjay sajnani | P74: 138/1,flat no 45 shama apt sindi colony pg road 500006 | Q74: Juhi sanjay sajnani | R74: 9133847766 | S74: frostbakery@gmail.com | T74: frost bakery | U74: Axis Bank | V74: 923020067557565 | W74: UTIB0003484 | X74: Current Account | Y74: Yes | Z74: Yes | AA74: Yes | AB74: No | AC74: No | AD74: No | AE74: https://drive.google.com/drive/folders/1qqDAuHRUNSZORJNHvCtEG8P1NW_AwUL8 | AG74: =VLOOKUP(H:H,'Pivot Table 8'!B:C,2,0) -> #REF!
A75: 46062 | B75: The good sparrow | C75: parthive.maganti@capsdelivery.com | D75: Partnership | E75: sy no.274(a) aparnahills park, commerical buildings behind gangaram lake, chanda nagar | F75: Ramchandra rao | G75: 500026 | H75: Chandanagar | I75: =VLOOKUP(H75,Mapping!D:E,2,0) -> miyapur | J75: Zone 5 Kukatpally | K75: 0.17 | L75: =if(K75=0,"0",(if(K75<15%,"<15%",if(K75<17%,"<17%",IF(K75<20%,"<20%","20%+"))))) -> <20% | M75: 0.018 | O75: Good sparrow millets private limited | P75: 2nd floor, 2-12-66 using B,kalyanamandapam west maredpally | Q75: Ramchandra rao | R75: 8977709421 | S75: info@thegoodsparrow.com | T75: Good sparrow foods private limited | U75: ICICI BANK | V75: 111605002567 | W75: ICIC0001116 | X75: Current Account | Y75: Yes | Z75: Yes | AA75: Yes | AB75: Yes | AC75: Yes | AD75: No | AE75: The Good Sparrow 1 | AF75: The Good Sparrow (Millet Tiffins) | AG75: =VLOOKUP(H:H,'Pivot Table 8'!B:C,2,0) -> #REF! | AH75: did not lift the call
A76: 46062 | B76: The good sparrow | C76: parthive.maganti@capsdelivery.com | D76: Partnership | E76: Jsr mall,vidia colony,madeenaguda,near allywn x road,miyapur | F76: Ramchandra rao | G76: 500050 | H76: Miyapur | I76: =VLOOKUP(H76,Mapping!D:E,2,0) -> miyapur | J76: Zone 5 Kukatpally | K76: 0.17 | L76: =if(K76=0,"0",(if(K76<15%,"<15%",if(K76<17%,"<17%",IF(K76<20%,"<20%","20%+"))))) -> <20% | M76: 0.018 | O76: Good sparrow millets private limited | P76: 2nd floor,2-12-66,using kalyanamadapam, west marredpally | Q76: Ramchandra rao | R76: 8977709421 | S76: info@thegoodsparrow.in | T76: not mentioned | U76: ICICI BANK | V76: 111605002567 | W76: ICIC0001116 | X76: Current Account | Y76: Yes | Z76: Yes | AA76: Yes | AB76: Yes | AC76: Yes | AD76: No | AE76: The Good Sparrow 2 | AF76: The Good Sparrow (Millet Tiffins) | AG76: =VLOOKUP(H:H,'Pivot Table 8'!B:C,2,0) -> #REF! | AH76: did not lift the call
A77: 46062 | B77: The good sparrow | C77: parthive.maganti@capsdelivery.com | D77: Partnership | E77: 1-55/196 and 199A botanical garden road,serilingampally circle co 20 | F77: Ramchandra rao | G77: 500082 | H77: Serilingampally | I77: =VLOOKUP(H77,Mapping!D:E,2,0) -> Sherilingampally | J77: Zone 5 Kukatpally | K77: 0.17 | L77: =if(K77=0,"0",(if(K77<15%,"<15%",if(K77<17%,"<17%",IF(K77<20%,"<20%","20%+"))))) -> <20% | M77: 0.018 | O77: Good sparrow millets private limited | P77: 2nd floor,2-12-66,west maredpally | Q77: Ramchandra rao | R77: 8977709421 | S77: info@thegoodsparrow.in | T77: Good sparrow foods private limited | U77: ICICI BANK | V77: 111605002567 | W77: ICIC0001116 | X77: Current Account | Y77: Yes | Z77: Yes | AA77: Yes | AB77: Yes | AC77: Yes | AD77: No | AE77: The Good Sparrow 3 | AF77: The Good Sparrow (Millet Tiffins) | AG77: =VLOOKUP(H:H,'Pivot Table 8'!B:C,2,0) -> #REF! | AH77: did not lift the call
A78: 46062 | B78: Times Green Energy India Limited | C78: madhumitha.sonnakula@capsdelivery.com | D78: Proprietorship | E78: somajiguda, jumaaldinne laxmi,shop no 7, H.no 6-3-650 | F78: Yashwanth | G78: 500082 | H78: Somajiguda | I78: =VLOOKUP(H78,Mapping!D:E,2,0) -> panjagutta | J78: Zone 6 Ameerpet | K78: 0.22 | L78: =if(K78=0,"0",(if(K78<15%,"<15%",if(K78<17%,"<17%",IF(K78<20%,"<20%","20%+"))))) -> 20%+ | M78: 0.018 | O78: Times green enugy india limited | P78: no 7, H.no 6-3-650, 500082 | Q78: G.Yashwanth meher | R78: 7702632033 | S78: yashwanthmeher@gmail.com | T78: Times green enugy india limited | U78: State Bank of India | V78: 62364741647 | W78: SBIN0020684 | X78: Current Account | Y78: Yes | Z78: Yes | AA78: Yes | AB78: Yes | AC78: Yes | AD78: No | AE78: https://drive.google.com/drive/folders/1E4Ykj6WozePtfLrLIk_S1m_2LpR40ZCm | AG78: =VLOOKUP(H:H,'Pivot Table 8'!B:C,2,0) -> #REF!
A79: 46062 | B79: Veera Di chaap | C79: madhumitha.sonnakula@capsdelivery.com | D79: Proprietorship | E79: H.no: 1-8-153/2, shop no-1 ground floor pg road, paradise, secunderbad | F79: Veera Di chaap | G79: 500003 | H79: secunderabad | I79: =VLOOKUP(H79,Mapping!D:E,2,0) -> begumpet | J79: Zone 6 Ameerpet | K79: 0.22 | L79: =if(K79=0,"0",(if(K79<15%,"<15%",if(K79<17%,"<17%",IF(K79<20%,"<20%","20%+"))))) -> 20%+ | M79: 0.018 | O79: Veera Di chaap | P79: H.no: 1-8-153/2, shop no-1 ground floor pg road, paradise, secunderbad,500003 | Q79: Karthik | R79: 7842804422 | S79: veeradichaap1@gmail.com | T79: not mentioned | U79: IDFC first bank | V79: 10085657065 | W79: IDFB0080205 | X79: not mentioned | Y79: Yes | Z79: No | AA79: Yes | AB79: Yes | AC79: Yes | AD79: No | AE79: https://drive.google.com/drive/folders/1xZcfj_aVWNi54pSCdPOTDkp-TusuAqYC | AG79: =VLOOKUP(H:H,'Pivot Table 8'!B:C,2,0) -> #REF!
A80: 46062 | B80: Veeramma gari vantillu | C80: ankitha.baske@capsdelivery.com | D80: Proprietorship | E80: plot no.11-12,block-f2, sainnath enclave, venkatramana colony, gokul plots, kphb, kukatpally | F80: Yarlagadda Suryam | G80: 500085 | H80: Kukatpally | I80: =VLOOKUP(H80,Mapping!D:E,2,0) -> kukatpally | J80: Zone 5 Kukatpally | K80: 0.185 | L80: =if(K80=0,"0",(if(K80<15%,"<15%",if(K80<17%,"<17%",IF(K80<20%,"<20%","20%+"))))) -> <20% | M80: 0.018 | O80: Veeramma gari vantillu | P80: Kukatpally | Q80: suryam | R80: 9849995653 | S80: veerammagarivantillu@gmail.com | T80: Veeramma gari vantillu | U80: State Bank of India | V80: 44573150739 | W80: SBIN0032241 | X80: Current Account | Y80: Yes | Z80: Yes | AA80: Yes | AB80: Yes | AC80: Yes | AD80: No | AE80: https://drive.google.com/drive/folders/1VOBUtu-z39SH2yaFZY4oZPcdzzygkse8?usp=drive_link | AG80: =VLOOKUP(H:H,'Pivot Table 8'!B:C,2,0) -> #REF!
A81: 46063 | B81: New York Slice pizza | C81: nitya.akshara@capsdelivery.com | D81: Partnership | E81: sai gayathri towers finacial district Nanakramguda,Telangana | G81: 500032 | H81: Nanakramguda | I81: =VLOOKUP(H81,Mapping!D:E,2,0) -> nanakramguda | J81: Zone 3 Raidurg | K81: 0.15 | L81: =if(K81=0,"0",(if(K81<15%,"<15%",if(K81<17%,"<17%",IF(K81<20%,"<20%","20%+"))))) -> <17% | M81: 0.018 | O81: Sri sai and co. | P81: sai gayathri towers finacial district Nanakramguda,Telangana 500033 | Q81: Venudhar reddy malakapalli | R81: 9100112336 | S81: venudharr@gmail.com | T81: Sri sai and co. | U81: State Bank of India | V81: 9748601141 | W81: SBIN0018047 | X81: Current Account | Y81: Yes | Z81: Yes | AA81: Yes | AB81: Yes | AC81: No | AD81: No | AE81: https://drive.google.com/drive/folders/1Pxy8lK7igSsskr30ZhKGFIpPz7wV_jBt | AG81: =VLOOKUP(H:H,'Pivot Table 8'!B:C,2,0) -> #REF!
A82: 46063 | B82: Soy & Sesame | C82: nitya.akshara@capsdelivery.com | D82: Partnership | E82: sai gayathri towers finacial district Nanakramguda,Telangana | G82: 500032 | H82: Nanakramguda | I82: =VLOOKUP(H82,Mapping!D:E,2,0) -> nanakramguda | J82: Zone 3 Raidurg | K82: 0.15 | L82: =if(K82=0,"0",(if(K82<15%,"<15%",if(K82<17%,"<17%",IF(K82<20%,"<20%","20%+"))))) -> <17% | M82: 0.018 | O82: Sri sai and co. | P82: sai gayathri towers finacial district Nanakramguda,Telangana 500032 | Q82: Venudhar reddy malakapalli | R82: 9100112336 | S82: venudharr@gmail.com | T82: Sri sai and co. | U82: Hdfc bank | V82: 50200037904604 | W82: HDFC0004299 | X82: Current Account | Y82: Yes | Z82: Yes | AA82: Yes | AB82: Yes | AC82: No | AD82: No | AE82: https://drive.google.com/drive/folders/1tqp8TfFW2_AiRzRoXvlt4cRRsEyGUaRx | AG82: =VLOOKUP(H:H,'Pivot Table 8'!B:C,2,0) -> #REF!
A83: 46063 | B83: The Emperor | C83: nitya.akshara@capsdelivery.com | D83: Proprietorship | E83: 10-4-3,afia plaxa,near NMDC-vijay nagar colony,masab tank,hyd,telangana | F83: Not mentioned | G83: 500028 | H83: Masab Tank | I83: =VLOOKUP(H83,Mapping!D:E,2,0) -> masab tank | J83: Zone 1 Mehdipatnam | K83: 0.2 | L83: =if(K83=0,"0",(if(K83<15%,"<15%",if(K83<17%,"<17%",IF(K83<20%,"<20%","20%+"))))) -> 20%+ | M83: 0.018 | O83: Not mentioned | P83: Not mentioned | Q83: Not mentioned | R83: Not mentioned | S83: Not mentioned | T83: Not mentioned | U83: Not mentioned | V83: Not mentioned | W83: Not mentioned | X83: Not mentioned | Y83: No | Z83: No | AA83: No | AB83: No | AC83: No | AD83: No | AG83: =VLOOKUP(H:H,'Pivot Table 8'!B:C,2,0) -> #REF! | AH83: No Contact Info
A84: 46063 | B84: Thinnu mama | C84: chanakya.inugala@capsdelivery.com | D84: not mentioned | E84: DROPPED | F84: not mentioned | G84: not mentioned | H84: Manikonda | I84: =VLOOKUP(H84,Mapping!D:E,2,0) -> manikonda | J84: =VLOOKUP(I84,Mapping!A:B,2,0) -> Zone 3 Raidurg | K84: not mentioned | L84: =if(K84=0,"0",(if(K84<15%,"<15%",if(K84<17%,"<17%",IF(K84<20%,"<20%","20%+"))))) -> 20%+ | M84: 0.018 | O84: not mentioned | P84: not mentioned | Q84: not mentioned | R84: not mentioned | S84: not mentioned | T84: not mentioned | U84: not mentioned | V84: not mentioned | W84: not mentioned | X84: not mentioned | Y84: No | Z84: No | AA84: No | AB84: No | AC84: No | AD84: No
A85: 46064 | B85: Anu archana kitchen | C85: chanakya.inugala@capsdelivery.com | D85: Proprietorship | E85: h.no:8-1-284/ou/152,ou colony,shaikpet,jubilee hills circle no.18,hyd,telangana | F85: Medikonda kondaiah | G85: 500033 | H85: shaikpet | I85: =VLOOKUP(H85,Mapping!D:E,2,0) -> shaikpet | J85: Zone 3 Raidurg | K85: 0.2 | L85: =if(K85=0,"0",(if(K85<15%,"<15%",if(K85<17%,"<17%",IF(K85<20%,"<20%","20%+"))))) -> 20%+ | M85: 0.018 | O85: Anu archana kitchen | P85: h.no:8-1-284/ou/152,ou colony,shaikpet,jubliee hills | Q85: Medikonda kondaiah | R85: 9989071021 | S85: not mentioned | T85: Anu archana kitchen | U85: South Indian bank | V85: ;0597073000000451 | W85: SIBL0000591 | X85: Current Account | Y85: Yes | Z85: Yes | AA85: Yes | AB85: No | AC85: No | AD85: No | AE85: Anu Archana kitchen | AF85: https://www.google.com/maps/place/Anu+Archana+Kitchen/@17.4083423,78.3904879,17z/data=!3m1!4b1!4m6!3m5!1s0x3bcb97000c2a71c3:0xf15817e8716a38db!8m2!3d17.4083372!4d78.3930628!16s%2Fg%2F11xr_gtynz?entry=ttu&g_ep=EgoyMDI2MDIxMS4wIKXMDSoASAFQAw%3D%3D | AG85: =VLOOKUP(H:H,'Pivot Table 8'!B:C,2,0) -> #REF!
A86: 46064 | B86: Brew and bloom heaven coffee shop | C86: sumadhur.mummadi@capsdelivery.com | D86: Proprietorship | E86: sri sai arcade,beside prince biryani point,khairatabad circle no.17 hyd | F86: Konda stella mary | G86: 500016 | H86: Khairathabad | I86: =VLOOKUP(H86,Mapping!D:E,2,0) -> Khairathabad | J86: Zone 1 Mehdipatnam | K86: 0.2 | L86: =if(K86=0,"0",(if(K86<15%,"<15%",if(K86<17%,"<17%",IF(K86<20%,"<20%","20%+"))))) -> 20%+ | M86: 0.018 | O86: Brew and bloom heaven coffee shop | P86: sri sai arcade,beside prince biryani point,khairatabad circle no.17 hyd,500016 | Q86: Deepak kumar | R86: 9966591281 | S86: dhanyasideepakvarma@gmail.com | T86: Brew and bloom heaven coffee shop | U86: State Bank of India | V86: 44662846419 | W86: SBI003257 | X86: Current Account | Y86: Yes | Z86: No | AA86: Yes | AB86: No | AC86: Yes | AD86: No | AE86: https://drive.google.com/drive/folders/1E9-9yixpt3TDMvd6hro7csptgS61njEI | AF86: 17.437127,78.447463 | AG86: =VLOOKUP(H:H,'Pivot Table 8'!B:C,2,0) -> #REF!
A87: 46064 | B87: Laxmi addikecharla | C87: manasa.chigurupati@capsdelivery.com | D87: Proprietorship | E87: flat no.5 1st floor block no-6 municipal no;15-31-21-6/5,kphb colony,hyd | F87: Laxmi addikecharla | G87: 500072 | H87: Kukatpally | I87: =VLOOKUP(H87,Mapping!D:E,2,0) -> kukatpally | J87: Zone 5 Kukatpally | K87: 0.16 | L87: =if(K87=0,"0",(if(K87<15%,"<15%",if(K87<17%,"<17%",IF(K87<20%,"<20%","20%+"))))) -> <17% | M87: 0.018 | O87: Laxmi addikecharla | P87: flat no.5 1st floor block no-6 municipal no;15-31-21-6/5,kphb colony,hyd,500072 | Q87: omkar.A | R87: 7032735002 | S87: addomkar@gmail.com | T87: chinthamani pulaous | U87: The Gayatri Co-operative urban bank ltd | V87: 104110021001175 | W87: HDFCOCTGCUB | X87: Current Account | Y87: Yes | Z87: Yes | AA87: Yes | AB87: Yes | AC87: Yes | AD87: NA | AE87: https://drive.google.com/drive/folders/17e5ZoJ64peB0BjuARtUdrR5R8zWWHQuI | AG87: =VLOOKUP(H:H,'Pivot Table 8'!B:C,2,0) -> #REF! | AH87: Checked
A88: 46064 | B88: lucky Multicusine Restaurant | C88: moin.khan@capsdelivery.com | D88: Partnership | E88: Door no.6-3-1089/f/3/3 somajiguda,hyd,telangana | F88: Khasim | G88: 500082 | H88: Somajiguda | I88: =VLOOKUP(H88,Mapping!D:E,2,0) -> panjagutta | J88: Zone 6 Ameerpet | K88: 0.15 | L88: =if(K88=0,"0",(if(K88<15%,"<15%",if(K88<17%,"<17%",IF(K88<20%,"<20%","20%+"))))) -> <17% | M88: 0.018 | O88: lucky Multicusine Restaurant | P88: Door no.6-3-1089/f/3/3 somajiguda,hyd,telangana,500082 | Q88: Khasim | R88: 9849108337 | S88: not mentioned | T88: not mentioned | U88: Hdfc bank | V88: 50200037070986 | W88: HDFC000512 | X88: Current Account | Y88: Yes | Z88: No | AA88: Yes | AB88: Yes | AC88: No | AD88: No | AE88: https://drive.google.com/drive/folders/1f4awwnmjkQ5VpEsLZr8FHC4T73B6cs-e?usp=sharing | AG88: =VLOOKUP(H:H,'Pivot Table 8'!B:C,2,0) -> #REF!
A89: 46064 | B89: Manasa kitchen swagrha sweets | C89: ankitha.baske@capsdelivery.com | D89: Proprietorship | E89: H.no:15-31-2L-1-5/275/3,lig-5/2,phase-3,kphb colony,kukatpally,hyd | F89: Sudheer kumar | G89: 500072 | H89: Kukatpally | I89: =VLOOKUP(H89,Mapping!D:E,2,0) -> kukatpally | J89: Zone 5 Kukatpally | K89: 0.22 | L89: =if(K89=0,"0",(if(K89<15%,"<15%",if(K89<17%,"<17%",IF(K89<20%,"<20%","20%+"))))) -> 20%+ | M89: 0.018 | O89: Manasa kitchen and swagrha sweets | P89: kukatpally,hyd,500072 | Q89: Sudheer kumar | R89: 8185802329 | S89: sudheer2409@gmail.com | T89: Gogineni v j sudheer kumar | U89: ICICI BANK | V89: ;000101558510 | W89: ICIC0000001 | X89: Savings Account | Y89: Yes | Z89: NA | AA89: Yes | AB89: Yes | AC89: Yes | AD89: Yes | AE89: https://drive.google.com/drive/folders/1z0sETsfH5F3Pi2AvC3G2RfzWuQW8x-4d?usp=drive_link | AG89: =VLOOKUP(H:H,'Pivot Table 8'!B:C,2,0) -> #REF!
A90: 46064 | B90: MM cake factory and bakers | C90: manasa.chigurupati@capsdelivery.com | D90: Proprietorship | E90: opposite metro pillar no 833 beside vikings cricket, sangeet nagar,kukatpally,hyd | F90: Musthakin | G90: 500072 | H90: Kukatpally | I90: =VLOOKUP(H90,Mapping!D:E,2,0) -> kukatpally | J90: Zone 5 Kukatpally | K90: 0.2 | L90: =if(K90=0,"0",(if(K90<15%,"<15%",if(K90<17%,"<17%",IF(K90<20%,"<20%","20%+"))))) -> 20%+ | M90: 0.018 | O90: MM cake factory and bakers | P90: opposite metro pillar no 833 beside vikings cricket, sangeet nagar,kukatpally,hyd,500072 | Q90: Musthakin | R90: 9963317579 | S90: mmbakers8052@gmail.com | T90: MM cake factory and bakers | U90: kotak mahindra bank | V90: 4650956984 | W90: KKBK0007535 | X90: Current Account | Y90: Yes | Z90: No | AA90: Yes | AB90: Yes | AC90: No | AD90: NA | AE90: https://drive.google.com/drive/folders/1KkZU6RKi0QkgkyOtEjtz_QuS0voG0ou5 | AG90: =VLOOKUP(H:H,'Pivot Table 8'!B:C,2,0) -> #REF!
A91: 46064 | B91: Pooja Dine Inn | C91: akhila.narra@capsdelivery.com | D91: Proprietorship | E91: H.no:1-8-155/A 1st floor, pg road, secunderabad,begumpet circle no.30 Hyd, telangana | F91: Pooja Karthik | G91: 500016 | H91: Begumpet | I91: =VLOOKUP(H91,Mapping!D:E,2,0) -> ameerpet | J91: Zone 6 Ameerpet | K91: 0.19 | L91: =if(K91=0,"0",(if(K91<15%,"<15%",if(K91<17%,"<17%",IF(K91<20%,"<20%","20%+"))))) -> <20% | M91: 0.018 | O91: Pooja Karthik | P91: H.no:1-8-155/A 1st floor, pg road, secunderabad,begumpet circle no.30 Hyd, telangana,500016 | Q91: Pooja Karthik | R91: 9160602527 | S91: poojasdinein@gmail.com | T91: For Poojas dine IN | U91: Indian Overseas Bank | V91: 20002000002527 | W91: IOBA0000200 | X91: Current Account | AG91: =VLOOKUP(H:H,'Pivot Table 8'!B:C,2,0) -> #REF!
A92: 46064 | B92: subham grand multicusine family Restaurant | C92: moin.khan@capsdelivery.com | D92: Proprietorship | E92: H.no:6-3-902/2and3,first floor,raj bhavan road,somajiguda,hyd,telangana | F92: sudarsan nayak | G92: 500082 | H92: Somajiguda | I92: =VLOOKUP(H92,Mapping!D:E,2,0) -> panjagutta | J92: Zone 6 Ameerpet | K92: 0.19 | L92: =if(K92=0,"0",(if(K92<15%,"<15%",if(K92<17%,"<17%",IF(K92<20%,"<20%","20%+"))))) -> <20% | M92: 0.018 | O92: subham grand multicusine family Restaurant | P92: H.no:6-3-902/2and3,first floor,raj bhavan road,somajiguda,hyd,telangana,500082 | Q92: sudarsan nayak | R92: 8008623545 | S92: hsgsubhamgrand@gmail.com | T92: not mentioned | U92: Axis Bank | V92: 924020006428812 | W92: UTIB0003305 | X92: Current Account | Y92: Yes | Z92: Yes | AA92: Yes | AB92: Yes | AC92: No | AD92: Yes | AE92: https://drive.google.com/drive/folders/1lwnoJfXa3KkWswaN1pg1EuD4LTJyD5En?usp=sharing | AG92: =VLOOKUP(H:H,'Pivot Table 8'!B:C,2,0) -> #REF!
A93: 46065 | B93: Al saba Restaurant | C93: parthive.maganti@capsdelivery.com | D93: Partnership | E93: h.no:8-3-222/c/1/12,ground floor,madhura nagar,yousufnagar,hyd,telangana | F93: K. Shiv kumar | G93: 500045 | H93: Madhura nagar | I93: =VLOOKUP(H93,Mapping!D:E,2,0) -> ameerpet | J93: Zone 6 Ameerpet | K93: 0.17 | L93: =if(K93=0,"0",(if(K93<15%,"<15%",if(K93<17%,"<17%",IF(K93<20%,"<20%","20%+"))))) -> <20% | M93: 0.018 | O93: Al saba Restaurant | P93: h.no:8-3-222/c/1/12,ground floor,madhura nagar,voulanfguda circle no.19 | Q93: shivam | R93: 9392458574 | S93: not mentioned | T93: Al saba Restaurant | U93: Hdfc Bank | V93: 50200116850493 | W93: HDFC0000642 | X93: Current Account | Y93: Yes | Z93: Yes | AA93: Yes | AB93: Yes | AC93: Yes | AD93: No | AE93: Al-saba Restaurant | AF93: Al Saba Cafe | AG93: =VLOOKUP(H:H,'Pivot Table 8'!B:C,2,0) -> #REF!
A94: 46065 | B94: Amma chethi ruchulu | C94: parthive.maganti@capsdelivery.com | D94: Proprietorship | E94: 8-3-6333/82/1,ali nagar, tawwal nagar,yella reddy,hyd,telangana | F94: not mentioned | G94: 500073 | H94: Yellareddy guda | I94: =VLOOKUP(H94,Mapping!D:E,2,0) -> ameerpet | J94: Zone 6 Ameerpet | K94: 0.15 | L94: =if(K94=0,"0",(if(K94<15%,"<15%",if(K94<17%,"<17%",IF(K94<20%,"<20%","20%+"))))) -> <17% | M94: 0.018 | O94: Amma chethi ruchulu | P94: Yellareddy guda | Q94: arun | R94: 9652222583 | S94: arukhaflavours@gmail.com | T94: arukha flavours | U94: Yes Bank | V94: 147601900001351 | W94: YESB0001476 | X94: Current Account | Y94: Yes | Z94: No | AA94: Yes | AB94: Yes | AC94: Yes | AD94: No | AE94: Amma Chethi Ruchulu | AF94: ARUKHAFLAVORS | AG94: =VLOOKUP(H:H,'Pivot Table 8'!B:C,2,0) -> #REF!
A95: 46065 | B95: Andhra kitchens | C95: parthive.maganti@capsdelivery.com | D95: Proprietorship | E95: 8-3/633/82/1,ali nagar,tawak kal, vellareddy guda,khairthabad circle no.17 hyd | F95: not mentioned | G95: 500073 | H95: Khairathabad | I95: =VLOOKUP(H95,Mapping!D:E,2,0) -> Khairathabad | J95: Zone 1 Mehdipatnam | K95: 0.15 | L95: =if(K95=0,"0",(if(K95<15%,"<15%",if(K95<17%,"<17%",IF(K95<20%,"<20%","20%+"))))) -> <17% | M95: 0.018 | O95: Andhra kitchens | P95: ali nagar,khairthabad circle no.17 | Q95: Arun | R95: 9652222583 | S95: arukhaflavours@gmail.com | T95: arukha flavours | U95: Yes Bank | V95: 147661900001351 | W95: YESB0001476 | X95: Current Account | Y95: Yes | Z95: No | AA95: Yes | AB95: Yes | AC95: Yes | AD95: No | AE95: Andhra Kitchens | AF95: ARUKHAFLAVORS | AG95: =VLOOKUP(H:H,'Pivot Table 8'!B:C,2,0) -> #REF!
A96: 46065 | B96: Arm coffee place | C96: manasa.chigurupati@capsdelivery.com | D96: Proprietorship | E96: plot no:11and12,sai nath enclave,gokul plots venkata ramana colony kphb,kukatpally | F96: M.Sanjeev reddy | G96: 500085 | H96: Kukatpally | I96: =VLOOKUP(H96,Mapping!D:E,2,0) -> kukatpally | J96: Zone 5 Kukatpally | K96: 0.2 | L96: =if(K96=0,"0",(if(K96<15%,"<15%",if(K96<17%,"<17%",IF(K96<20%,"<20%","20%+"))))) -> 20%+ | M96: 0.018 | O96: Arm coffee place | P96: plot no:11and12,sai nath enclave,gokul plots venkata ramana colony kphb,kukatpally 500085 | Q96: M.Sanjeev reddy | R96: 8125125635 | S96: jaimaanukanda7@gmail.com | T96: Arm coffee place | U96: the Gayatri Co-operative urban bank ltd | V96: 104110021001527 | W96: HDFCOCTGCUB | X96: Current Account | Y96: Yes | Z96: No | AA96: Yes | AB96: Yes | AC96: Yes | AD96: NA | AE96: https://drive.google.com/drive/folders/1qqGSu3p0OVLxVrQcgpXnUrmht0w0OURK | AG96: =VLOOKUP(H:H,'Pivot Table 8'!B:C,2,0) -> #REF!
A97: 46065 | B97: Arukha flavours | C97: parthive.maganti@capsdelivery.com | D97: Proprietorship | E97: 8-3-6333/82/1,ali nagar, tawwal nagar,yella reddy,hyd,telangana | F97: Arukha flavours/Arun | G97: 500073 | H97: SRINAGAR COLONY | I97: =VLOOKUP(H97,Mapping!D:E,2,0) -> yousufguda | J97: Zone 6 Ameerpet | K97: 0.15 | L97: =if(K97=0,"0",(if(K97<15%,"<15%",if(K97<17%,"<17%",IF(K97<20%,"<20%","20%+"))))) -> <17% | M97: 0.018 | O97: Arukha flavours | P97: Ali nagar,yellareddy,madhura nagar | Q97: arun | R97: 9652222583 | S97: arukhaflavours@gmail.com | T97: arukha flavours | U97: Yes Bank | V97: 147601900001351 | W97: YESB0001476 | X97: Current Account | Y97: Yes | Z97: No | AA97: Yes | AB97: Yes | AC97: Yes | AD97: No | AE97: Arukha Flavours | AF97: ARUKHAFLAVORS | AG97: =VLOOKUP(H:H,'Pivot Table 8'!B:C,2,0) -> #REF!
A98: 46065 | B98: Bunty biryanis | C98: parthive.maganti@capsdelivery.com | D98: Proprietorship | E98: 8-3-6333/82/1,ali nagar, tawwal nagar,yella reddy,hyd,telangana | F98: not mentioned | G98: 500073 | H98: Ali Nagar | I98: =VLOOKUP(H98,Mapping!D:E,2,0) -> ameerpet | J98: Zone 6 Ameerpet | K98: 0.15 | L98: =if(K98=0,"0",(if(K98<15%,"<15%",if(K98<17%,"<17%",IF(K98<20%,"<20%","20%+"))))) -> <17% | M98: 0.018 | O98: Bunty biryani | P98: Madhura nagar | Q98: arun | R98: 9652222583 | S98: arukhaflavours@gmail.com | T98: arukha flavours | U98: Yes Bank | V98: 147601900001351 | W98: YESB0001476 | X98: Current Account | Y98: Yes | Z98: No | AA98: Yes | AB98: Yes | AC98: Yes | AD98: No | AE98: Bunty Biryani's | AF98: ARUKHAFLAVORS | AG98: =VLOOKUP(H:H,'Pivot Table 8'!B:C,2,0) -> #REF!
A99: 46065 | B99: Eden Ice Treats | C99: sumadhur.mummadi@capsdelivery.com | D99: Partnership | E99: shop no.5, Manjira plaza,opposite Aadithya trade centre,near maithrivanam road,srinivas nagar,ameerpet,hyd,telangana | F99: Enoch Chowdary | G99: 500038 | H99: Ameerpet | I99: =VLOOKUP(H99,Mapping!D:E,2,0) -> panjagutta | J99: Zone 6 Ameerpet | K99: 0.2 | L99: =if(K99=0,"0",(if(K99<15%,"<15%",if(K99<17%,"<17%",IF(K99<20%,"<20%","20%+"))))) -> 20%+ | M99: 0.018 | O99: Eden Ice Treats | P99: shop no.5, Manjira plaza,opposite Aadithya trade centre,near maithrivanam road,srinivas nagar,ameerpet,hyd,telangana,500038 | Q99: Enoch Chowdary | R99: 9550930115 | S99: contact.edenindustries@gmail.com | T99: Eden industries | U99: Hdfc Bank | V99: 50200117226947 | W99: HDFC0001627 | X99: Current Account | Y99: Yes | Z99: Yes | AA99: Yes | AB99: No | AC99: No | AD99: No | AE99: https://drive.google.com/drive/folders/1KuOUXuC2qGOX8IivMWfrHVjxheMyFa1a | AF99: 17.437412,78.446691 | AG99: =VLOOKUP(H:H,'Pivot Table 8'!B:C,2,0) -> #REF!
A100: 46065 | B100: G Hitech Bawarchi food court | C100: moin.khan@capsdelivery.com | D100: Proprietorship | E100: 1-21/1 Madhapur,hyd,circle no.20,serlingampally | F100: not mentioned | G100: 500081 | H100: Serilingampally | I100: =VLOOKUP(H100,Mapping!D:E,2,0) -> Sherilingampally | J100: Zone 5 Kukatpally | K100: 0.12 | L100: =if(K100=0,"0",(if(K100<15%,"<15%",if(K100<17%,"<17%",IF(K100<20%,"<20%","20%+"))))) -> <15% | M100: 0.018 | O100: Hitech bawarchi food court | P100: h.no:12,17,opp indian oil petrol pump,madhapur | Q100: Mohammed ilyas | R100: 9618291465 | S100: mohdilyas13@gmail.com | T100: G Hitech Bawarchi food court | U100: Axis bank | V100: 917020033027897 | W100: UTIN0001628 | X100: Current Account | Y100: Yes | Z100: Yes | AA100: Yes | AB100: Yes | AC100: No | AD100: No | AE100: https://drive.google.com/drive/folders/14dWR2loYkBJGSKHxp4kTMqsqOOtdr2sa?usp=sharing | AG100: =VLOOKUP(H:H,'Pivot Table 8'!B:C,2,0) -> #REF!
...

Sheet whatsapp
A1: Date | B1: Restaurant name | C1: location | D1: poc name | E1: contact no. | F1: person went | G1: comment | H1: Follow up date | I1: Follow up time | J1: Google links | K1: Column 11 | L1: Column 12 | M1: Column 13 | N1: Column 14 | O1: Column 15 | P1: Column 16 | Q1: Column 17 | R1: Column 18 | S1: Column 19 | T1: Column 20 | U1: Column 21 | V1: Column 22 | W1: Column 23 | X1: Column 24 | Y1: Column 25 | Z1: Column 26
A2: 46062 | B2: Beyniaz shawarm | C2: Ameerpet | D2: tarun | E2: 7981194980 | F2: sumadhur | G2: Today 4pm
A3: 46062 | B3: Pachakattu dosa | D3: mukesh | E3: 7992492924 | F3: moin.khan@capsdelivery.com | G3: Tommorow
A4: 46062 | B4: cake factory | C4: Ameerpet | E4: 8712274005 | F4: sumadhur | G4: owner will get back
A5: 46062 | B5: SSR FOOD zone | F5: ankitha.baske@capsdelivery.com | G5: onboarded
A6: 46062 | B6: 1000 Biryani | C6: Somajiguda | F6: madhumitha.sonnakula@capsdelivery.com | G6: onboarded
A7: 46062 | B7: Pondy parottas | F7: manasa.chigurupati@capsdelivery.com | G7: owner available after 2pm
A8: 46062 | B8: Roti Ruchulu | C8: Kukatpally | F8: ankitha.baske@capsdelivery.com | G8: Discuss with the partner
A9: 46062 | B9: Bojam taiyaru | F9: madhumitha.sonnakula@capsdelivery.com | G9: intersted will get back to us tomorrow by 6pm
A10: 46062 | B10: Vela bites | D10: Akhil Reddy | E10: 9059810130 | F10: chanakya.inugala@capsdelivery.com | G10: meet on wednesday for onboarding
A11: 46062 | B11: Bowls and Bites | C11: Kukatpally | F11: ankitha.baske@capsdelivery.com | G11: owner will be available after 2 to 3 hours
A12: 46062 | B12: Hari Balaji Dhaba | C12: Ameerpet | E12: 9985559231 | F12: sumadhur | G12: owner will get back
A13: 46062 | B13: Pappanam | D13: Sai Krishna | F13: chanakya.inugala@capsdelivery.com | G13: meet tomorrow sai krishna
A14: 46062 | B14: Grand Spicy Bawarchi | D14: Muqeeb | E14: 970526974 | F14: moin.khan@capsdelivery.com | G14: owner not available
A15: 46062 | B15: The Good Sparrow Millests food | C15: Kondapur/miyapur/Chandanagar | F15: parthive.maganti@capsdelivery.com | G15: onboarded 3 oulets
A16: 46062 | B16: Babai Hotel | D16: Dinesh reddy | F16: chanakya.inugala@capsdelivery.com | G16: he will meet after a week
A17: 46062 | B17: Abhiruchi Biryani | F17: manasa.chigurupati@capsdelivery.com | G17: will be onboarding tommorow
A18: 46062 | B18: Kshatriya Grand | C18: Kukatpally | F18: ankitha.baske@capsdelivery.com | G18: onboarded
A19: 46062 | B19: Mehfil Restaurant | D19: Anil | E19: 8121020121 | F19: moin.khan@capsdelivery.com | G19: will be available on wednesday
A20: 46062 | B20: Bakeway Bakers | C20: Ameerpet | F20: sumadhur | G20: onboarded
A21: 46062 | B21: mandi@36 arabian kitchen | F21: madhumitha.sonnakula@capsdelivery.com | G21: meet owner at banjara hills in evenig times
A22: 46062 | B22: Darbar Family | F22: manasa.chigurupati@capsdelivery.com | G22: owner will available tomorrow at 12pm
A23: 46062 | B23: The Bougainvillea | C23: Jubliee Hills | F23: akhila.narra@capsdelivery.com | G23: intersted he need a trail run once with our app
A24: 46062 | B24: Toppa | F24: madhumitha.sonnakula@capsdelivery.com | G24: manager wiil be available after 4pm
A25: 46062 | B25: The Hole In The Wall Cafe | F25: madhumitha.sonnakula@capsdelivery.com | G25: we can meet tomorrow
A26: 46062 | B26: Kshatriya Grand | C26: Kukatpally | F26: ankitha.baske@capsdelivery.com | G26: he needs lesser cpmmission than 17%
A27: 46062 | B27: Concu | E27: 9985800031 | F27: madhumitha.sonnakula@capsdelivery.com | G27: they will get back to us as they want detailed in everthing
A28: 46062 | B28: Brown Bear | C28: Kukatpally | D28: Manoj | E28: 7077577025 | F28: ankitha.baske@capsdelivery.com | G28: he will talk with MD and get back tomorrow
A29: 46062 | B29: 99 Pancake | F29: madhumitha.sonnakula@capsdelivery.com | G29: interstead get back tomorrow
A30: 46062 | B30: Rivora the cafe | C30: kukatpally | F30: manasa.chigurupati@capsdelivery.com | G30: onboarded
A31: 46062 | B31: Nasir | E31: 8886904546 | F31: chanakya.inugala@capsdelivery.com | G31: as documents not available in this branch going to onboard tomorrow
A32: 46062 | B32: Coffee Place | F32: manasa.chigurupati@capsdelivery.com | G32: interseted get back tomorrow
A33: 46062 | B33: Veeramagearu vantillu | F33: ankitha.baske@capsdelivery.com | G33: onboarded
A34: 46062 | B34: Bhadrakali hotel | C34: Ameerpet | E34: 9949256290 | F34: sumadhur | G34: owner will get back tomorrow
A35: 46062 | B35: Mokshi kitchen | C35: Kondapur | F35: parthive.maganti@capsdelivery.com | G35: onboarded
A36: 46062 | B36: North indian hub only veg | C36: Kondapur | F36: parthive.maganti@capsdelivery.com | G36: onboarded
A37: 46062 | B37: Kavya Tiffins | F37: akhila.narra@capsdelivery.com | G37: tomorrow morning will be onboarded
A38: 46062 | B38: Heart cup coffee | C38: Kondapur | F38: parthive.maganti@capsdelivery.com | G38: meeting fixed at 6pm
A39: 46062 | B39: Deccan chillis | C39: Ameerpet | F39: sumadhur | G39: meeting tomorrow with the owner
A40: 46062 | B40: Lassi Store | C40: Ameerpet | F40: sumadhur | G40: the owner is free after 8pm
A41: 46062 | B41: Aanandobrahma | C41: Ameerpet | F41: sumadhur | G41: the owner is free after 7pm
A42: 46062 | B42: kush mandi | E42: 9908662728 | F42: chanakya.inugala@capsdelivery.com | G42: will onboarded by thursday
A43: 46062 | B43: kadak house | D43: zaki | F43: moin.khan@capsdelivery.com | G43: owner not available
A44: 46062 | B44: Frost Bakery | F44: madhumitha.sonnakula@capsdelivery.com | G44: onboarded
A45: 46062 | B45: Frsot Bake Studio | F45: madhumitha.sonnakula@capsdelivery.com | G45: onboarded
A46: 46062 | B46: Just So wow cakes | F46: madhumitha.sonnakula@capsdelivery.com | G46: onboarded
A47: 46062 | B47: Donut O'clock | F47: akhila.narra@capsdelivery.com | G47: onboarded
A48: 46062 | B48: C'est la vie bakes and cakes | F48: akhila.narra@capsdelivery.com | G48: onboarded
A49: 46062 | B49: Tempt Chocolates | F49: greeshma.vanneldas@capsdelivery.com | G49: onboarded
A50: 46062 | B50: Say Cheese Patisserie | F50: greeshma.vanneldas@capsdelivery.com | G50: onboarded
A51: 46062 | B51: La Boulangerie | F51: greeshma.vanneldas@capsdelivery.com | G51: onboarded
A52: 46062 | B52: Veera di chaap | F52: greeshma.vanneldas@capsdelivery.com | G52: onboarded
A53: 46062 | B53: Gupshup bistro | F53: madhumitha.sonnakula@capsdelivery.com | G53: onboarded
A54: 46062 | B54: Pakwan Grand | D54: Khasim | F54: moin.khan@capsdelivery.com | G54: owner will be onboard after the app
A55: 46062 | B55: Cafe reels | D55: Naveen reddy | E55: 9676945646 | F55: chanakya.inugala@capsdelivery.com | G55: onboarded
A56: 46062 | B56: I love Godavari | D56: Satya | E56: 6281845369 | F56: moin.khan@capsdelivery.com | G56: owner not available asked to come tomorrow
A57: 46062 | B57: Lucky Restaurant | D57: Khasim | E57: 9849108337 | F57: moin.khan@capsdelivery.com | G57: onboarded
A58: 46063 | B58: Sandarshini udipi pure veg | C58: Mehdipatnam | D58: Mahesh | E58: 6302529570 | F58: moin.khan@capsdelivery.com | G58: Not available asked to come tomorrow
A59: 46063 | B59: Cafe nandhini veg deluxe | C59: Hitech-city | D59: Rohith | F59: greeshma.vanneldas@capsdelivery.com | G59: He has 12 outlets the owner is not available once he come back will arrange meeting ,got the manager number to follow up
A60: 46063 | B60: Good Flipping Burgers | F60: chanakya.inugala@capsdelivery.com | G60: Head office in mumbai Area manager is in kondapur have to meet him in kondapur
A61: 46063 | B61: Cream Stone | D61: Anji | F61: akhila.narra@capsdelivery.com | G61: owner is not available today so we scheduled a meeting after 11pm
A62: 46063 | B62: Scoops | D62: Anji | F62: akhila.narra@capsdelivery.com | G62: owner is not available today so we scheduled a meeting after 11pm
A63: 46063 | B63: Froops | D63: Anji | F63: akhila.narra@capsdelivery.com | G63: owner is not available today so we scheduled a meeting after 11pm
A64: 46063 | B64: Sarvi Restaurant | C64: Mehdipatnam | D64: Danial | E64: 6303246535 | F64: moin.khan@capsdelivery.com | G64: Asked to call at 5pm and check whether the owner is available or not
A65: 46063 | B65: 500Foodies club | D65: uma(owner) | E65: 8985607723 | F65: ankitha.baske@capsdelivery.com | G65: owner will be available after 1 hour
A66: 46063 | B66: Habibi Mandi | D66: Chandu | E66: 9398881323 | F66: greeshma.vanneldas@capsdelivery.com | G66: manager will be available after 3pm
A67: 46063 | B67: Krimmy Thickshakes | D67: Zakil(owner) | E67: 9493932004 | F67: ankitha.baske@capsdelivery.com | G67: Has 7 outlets owner available at 3:30pm
A68: 46063 | B68: Tipsy Topsy Bakers | D68: Zunaid | E68: 8885294412 | F68: nitya.akshara@capsdelivery.com | G68: call after 3
A69: 46063 | B69: New aritaku bhojanam | C69: Ameerpet | F69: sumadhur | G69: The owner said to approch after the product lauch
A70: 46063 | B70: Brundavan pure veg | C70: Ameerpet | D70: shankara vara prasad | E70: 9381887842 | F70: sumadhur | G70: main branch is in sr nagar can meet the owner there between 4-6pm
A71: 46063 | B71: Mozo pizza | D71: Abhishek | E71: 9045779674 | F71: chanakya.inugala@capsdelivery.com | G71: head office in mumbai Area manager is in kondapur have to meet him in kondapur
A72: 46063 | B72: Chubby cho | D72: Rajesh | E72: 6300797895 | F72: madhumitha.sonnakula@capsdelivery.com | G72: can meet the decision maker directly tomorrow
A73: 46063 | B73: Maraheb mandi | C73: Ameerpet | E73: 9014249702 | F73: sumadhur | G73: can meet the owner after 2pm
A74: 46063 | B74: Arabian nights mandi | C74: Ameerpet | F74: sumadhur | G74: can meet the owner after 6pm
A75: 46063 | B75: Punhabi affair | D75: santosh | E75: 9032515133 | F75: ankitha.baske@capsdelivery.com | G75: has 3 outlets owner will be available after 10 days
A76: 46063 | B76: yum yum tree | D76: sadhaam(manager) | E76: 7739656963 | F76: greeshma.vanneldas@capsdelivery.com | G76: manager will be available after 8pm and has 7 outlets
A77: 46063 | B77: mandi king | D77: Ashwaq | E77: 8985909898 | F77: chanakya.inugala@capsdelivery.com | G77: meet him in mehdipatnam branch
A78: 46063 | B78: mekong | C78: Ameerpet | E78: 9951122214 | F78: sumadhur | G78: asked to call back after 3:30pm for the manager's availabilty
A79: 46063 | B79: Sithara | D79: Arvind Chowdary(owner) | F79: nitya.akshara@capsdelivery.com | G79: Had a word with him him asked to call back after 10 days due to renovation
A80: 46063 | B80: Aqeeq Restaurant | C80: mehdipatnam | D80: majid | E80: 9581749555 | F80: moin.khan@capsdelivery.com | G80: owner not available today asked to come wednesday
A81: 46063 | B81: vasireddy swagruha foods | D81: upendra | E81: 9949429494 | F81: chanakya.inugala@capsdelivery.com | G81: call again later busy
A82: 46063 | B82: Belgian waffle | D82: manoj and area manager (Avinash) | E82: 7977757237 | F82: nitya.akshara@capsdelivery.com | G82: call not answered
A83: 46063 | B83: Reddy Brothers | E83: 8096999908 | F83: chanakya.inugala@capsdelivery.com | G83: meet afrer 8pm before call and coem
A84: 46063 | B84: Hiyya the chronic mandi | D84: swathi(manager) | E84: 7396422628 | F84: greeshma.vanneldas@capsdelivery.com | G84: Manager will discuss with the owner, for the follow up i will call tomorrow
A85: 46063 | B85: Vellanki foods | C85: Ameerpet | F85: sumadhur | G85: Any discussion should be done in kondapur main branch
A86: 46063 | B86: Pragathi sweets and savouries | D86: chandrashekar | E86: 9676583099 | F86: chanakya.inugala@capsdelivery.com | G86: Head office in kukatpally have to visit directly
A87: 46063 | B87: Tinnu mawa | F87: nitya.akshara@capsdelivery.com | G87: ready to onboarded by 4-5 in the evening need his brothers signature
A88: 46063 | B88: Biryanis and more | C88: Ameerpet | F88: sumadhur | G88: All decision are taken at Gachibowli branch. They told to talk to their marketing manager santhosh
A89: 46063 | B89: Toscano | D89: Bala | E89: 9986998503 | F89: greeshma.vanneldas@capsdelivery.com | G89: Owner is in Banglore
A90: 46063 | B90: Navarasa | D90: Naveen | E90: 9866402028 | F90: chanakya.inugala@capsdelivery.com | G90: He will call at 5pm now he is occupied with some work
A91: 46063 | B91: Frozen Bottles | E91: 6281162645 | F91: nitya.akshara@capsdelivery.com | G91: call not answered
A92: 46063 | B92: Brurma Restaurant | D92: kajal | E92: 7977765789 | F92: ankitha.baske@capsdelivery.com | G92: Discussed with the manager he shared our info with the marketing team once they get back manager will approch us
A93: 46063 | B93: Hard rock cafe | C93: Hitech city | D93: Ali firoz | E93: 9769343996 | F93: greeshma.vanneldas@capsdelivery.com | G93: Discussed with manager, he is intersted but he need the proposal to sent on email with clear points about or platform and commission and the offers so that he can discuss with his higher officilals for approval
A94: 46063 | B94: Itlu Bobbatlu | F94: madhumitha.sonnakula@capsdelivery.com | G94: we are onboarding tomorrow
A95: 46063 | B95: Gabru Di chaap | D95: Fayz | F95: ankitha.baske@capsdelivery.com | G95: He will talk with the Marketing Team and inform tomorrow as he has 9 outlets
A96: 46063 | B96: Wow momo | D96: srinu | E96: 9959160354 | F96: greeshma.vanneldas@capsdelivery.com | G96: After 5 he will available in the outlet as he has 35+outlets in hyd
A97: 46063 | B97: wow chicken | F97: ankitha.baske@capsdelivery.com | G97: manager will be available after 7pm they are not ready to give phone number or email id as they has 500+outlets
A98: 46063 | B98: Monday premium | C98: Madhapur | F98: parthive.maganti@capsdelivery.com | G98: Onboarded
A99: 46063 | B99: Shahi Rasoi family Restaurant | D99: sahil | E99: 9392055514 | F99: moin.khan@capsdelivery.com | G99: owner will be available on friday as he is out of station
A100: 46063 | B100: Donne biryani house | D100: Rajshekhar(owner) | E100: 9059435788 | F100: manasa.chigurupati@capsdelivery.com | G100: has 8 outlerts owner will be available
...

Sheet Pivot Table 28
A34: Region | B34: COUNTA of Region
A35: ameerpet | B35: 18
A36: banjara hills | B36: 3
A37: begumpet | B37: 10
A38: Borabanda | B38: 1
A39: gachibowli | B39: 20
A40: hafeezpet | B40: 12
A41: Hitech-City | B41: 19
A42: Hyderabad | B42: 2
A43: Jubliee hills | B43: 12
A44: Khairathabad | B44: 14
A45: Kondapur | B45: 40
A46: KPHP | B46: 3
... A62: yousufguda | B62: 28
A63: #N/A | B63: 4
B64: 0

Sheet Pivot Table 27

Sheet Mapping
A1: Location | B1: Zone | H1: Zone | I1: Region | J1: Onboarding Done
A2: Khairathabad | B2: Zone 1 Mehdipatnam | D2: locality | E2: Location | F2: Zone | H2: Mehipatnam Zone 1 | I2: Khairathabad | J2: =iferror(VLOOKUP(I2,'Pivot Table 11'!B:C,2,0),0) -> 17
A3: Masab Tank | B3: Zone 1 Mehdipatnam | D3: secunderabad | E3: begumpet | F3: Hyderabad | I3: Masab Tank | J3: =iferror(VLOOKUP(I3,'Pivot Table 11'!B:C,2,0),0) -> 6
A4: Mehdipatnam | B4: Zone 1 Mehdipatnam | D4: Hyderabad | E4: Hyderabad | F4: Hyderabad | I4: Mehdipatnam | J4: =iferror(VLOOKUP(I4,'Pivot Table 11'!B:C,2,0),0) -> 39
A5: Banjara Hills | B5: Zone 1 Mehdipatnam | D5: not mentioned | E5: not mentioned | F5: NA | I5: Banjara Hills | J5: =iferror(VLOOKUP(I5,'Pivot Table 11'!B:C,2,0),0) -> 3
A6: Tolichowki | B6: Zone 2 Jubliee hils | D6: Secundrabad | E6: Secundrabad | F6: Secundrabad | H6: Jubilee Hills Zone 2 | I6: Tolichowki | J6: =iferror(VLOOKUP(I6,'Pivot Table 11'!B:C,2,0),0) -> 4
A7: Langar Houz | B7: Zone 2 Jubliee hils | D7: secundrabad | E7: Secundrabad | F7: Secundrabad | I7: Langar Houz | J7: =iferror(VLOOKUP(I7,'Pivot Table 11'!B:C,2,0),0) -> 16
A8: Hakimpet | B8: Zone 2 Jubliee hils | D8: Banglaguda | E8: mehdipatnam | F8: =VLOOKUP(E8,A:B,2,0) -> Zone 1 Mehdipatnam | I8: Hakimpet | J8: =iferror(VLOOKUP(I8,'Pivot Table 11'!B:C,2,0),0) -> 0
A9: Jubilee Hills | B9: Zone 2 Jubliee hils | D9: Attapur | E9: mehdipatnam | F9: =VLOOKUP(E9,A:B,2,0) -> Zone 1 Mehdipatnam | I9: Jubilee Hills | J9: =iferror(VLOOKUP(I9,'Pivot Table 11'!B:C,2,0),0) -> 0
A10: Shaikpet | B10: Zone 3 Raidurg | D10: khairathabad | E10: masab tank | F10: =VLOOKUP(E10,A:B,2,0) -> Zone 1 Mehdipatnam | H10: Raidurg Zone 3 | I10: Shaikpet | J10: =iferror(VLOOKUP(I10,'Pivot Table 11'!B:C,2,0),0) -> 3
A11: Manikonda | B11: Zone 3 Raidurg | D11: Mehdipatnam | E11: mehdipatnam | F11: =VLOOKUP(E11,A:B,2,0) -> Zone 1 Mehdipatnam | I11: Manikonda | J11: =iferror(VLOOKUP(I11,'Pivot Table 11'!B:C,2,0),0) -> 34
A12: Raidurg | B12: Zone 3 Raidurg | D12: Asif nagar | E12: mehdipatnam | F12: =VLOOKUP(E12,A:B,2,0) -> Zone 1 Mehdipatnam | I12: Raidurg | J12: =iferror(VLOOKUP(I12,'Pivot Table 11'!B:C,2,0),0) -> 2
A13: Narsingi | B13: Zone 3 Raidurg | D13: Gudimalkapur | E13: masab tank | F13: =VLOOKUP(E13,A:B,2,0) -> Zone 1 Mehdipatnam | I13: Narsingi | J13: =iferror(VLOOKUP(I13,'Pivot Table 11'!B:C,2,0),0) -> 0
A14: Nanakramguda | B14: Zone 3 Raidurg | D14: Khairathabad | E14: Khairathabad | F14: =VLOOKUP(E14,A:B,2,0) -> Zone 1 Mehdipatnam | I14: Nanakramguda | J14: =iferror(VLOOKUP(I14,'Pivot Table 11'!B:C,2,0),0) -> 10
A15: Madhapur | B15: Zone 4 Hi-tech City | D15: Masab Tank | E15: masab tank | F15: =VLOOKUP(E15,A:B,2,0) -> Zone 1 Mehdipatnam | H15: HI-Tech Zone 4 | I15: Madhapur | J15: =iferror(VLOOKUP(I15,'Pivot Table 11'!B:C,2,0),0) -> 45
A16: Gachibowli | B16: Zone 4 Hi-tech City | D16: Banjara Hills | E16: banjara hills | F16: =VLOOKUP(E16,A:B,2,0) -> Zone 1 Mehdipatnam | I16: Gachibowli | J16: =iferror(VLOOKUP(I16,'Pivot Table 11'!B:C,2,0),0) -> 20
A17: Hitech-City | B17: Zone 4 Hi-tech City | D17: Gandamguda | E17: mehdipatnam | F17: =VLOOKUP(E17,A:B,2,0) -> Zone 1 Mehdipatnam | I17: Hitech-City | J17: =iferror(VLOOKUP(I17,'Pivot Table 11'!B:C,2,0),0) -> 19
A18: Sherilingampally | B18: Zone 5 Kukatpally | D18: Himayahnagar | E18: Khairathabad | F18: =VLOOKUP(E18,A:B,2,0) -> Zone 1 Mehdipatnam | H18: Kukatpally Zone 5 | I18: Sherilingampally | J18: =iferror(VLOOKUP(I18,'Pivot Table 11'!B:C,2,0),0) -> 8
A19: Hafeezpet | B19: Zone 5 Kukatpally | D19: Lakdikapool | E19: masab tank | F19: =VLOOKUP(E19,A:B,2,0) -> Zone 1 Mehdipatnam | I19: Hafeezpet | J19: =iferror(VLOOKUP(I19,'Pivot Table 11'!B:C,2,0),0) -> 12
A20: kukatpally | B20: Zone 5 Kukatpally | D20: Tappa | E20: mehdipatnam | F20: =VLOOKUP(E20,A:B,2,0) -> Zone 1 Mehdipatnam | I20: kukatpally | J20: =iferror(VLOOKUP(I20,'Pivot Table 11'!B:C,2,0),0) -> 89
A21: Kondapur | B21: Zone 5 Kukatpally | D21: Bandlaguda | E21: mehdipatnam | F21: =VLOOKUP(E21,A:B,2,0) -> Zone 1 Mehdipatnam | I21: Kondapur | J21: =iferror(VLOOKUP(I21,'Pivot Table 11'!B:C,2,0),0) -> 40
A22: Miyapur | B22: Zone 5 Kukatpally | D22: Kismatpur | E22: mehdipatnam | F22: =VLOOKUP(E22,A:B,2,0) -> Zone 1 Mehdipatnam | I22: Miyapur | J22: =iferror(VLOOKUP(I22,'Pivot Table 11'!B:C,2,0),0) -> 65
A23: Moosapet | B23: Zone 6 Ameerpet | D23: Gandipet | E23: Langar Houz | F23: =VLOOKUP(E23,A:B,2,0) -> Zone 2 Jubliee hils | H23: Ameerpet Zone 6 | I23: Moosapet | J23: =iferror(VLOOKUP(I23,'Pivot Table 11'!B:C,2,0),0) -> 0
A24: Ameerpet | B24: Zone 6 Ameerpet | D24: Kismathpur | E24: Langar Houz | F24: =VLOOKUP(E24,A:B,2,0) -> Zone 2 Jubliee hils | I24: Ameerpet | J24: =iferror(VLOOKUP(I24,'Pivot Table 11'!B:C,2,0),0) -> 18
A25: Panjagutta | B25: Zone 6 Ameerpet | D25: Langer houz | E25: Langar Houz | F25: =VLOOKUP(E25,A:B,2,0) -> Zone 2 Jubliee hils | I25: Panjagutta | J25: =iferror(VLOOKUP(I25,'Pivot Table 11'!B:C,2,0),0) -> 1
A26: Yousufguda | B26: Zone 6 Ameerpet | D26: Tolichowki | E26: tolichowki | F26: =VLOOKUP(E26,A:B,2,0) -> Zone 2 Jubliee hils | I26: Yousufguda | J26: =iferror(VLOOKUP(I26,'Pivot Table 11'!B:C,2,0),0) -> 28
A27: Erragada | B27: Zone 6 Ameerpet | D27: Manikonda | E27: manikonda | F27: =VLOOKUP(E27,A:B,2,0) -> Zone 3 Raidurg | I27: Erragada | J27: =iferror(VLOOKUP(I27,'Pivot Table 11'!B:C,2,0),0) -> 0
A28: Borabonda | B28: Zone 6 Ameerpet | D28: Nanakramguda | E28: nanakramguda | F28: =VLOOKUP(E28,A:B,2,0) -> Zone 3 Raidurg | I28: Borabonda | J28: =iferror(VLOOKUP(I28,'Pivot Table 11'!B:C,2,0),0) -> 0
D29: shaikpet | E29: shaikpet | F29: =VLOOKUP(E29,A:B,2,0) -> Zone 3 Raidurg | J29: =sum(J2:J28) -> 479
D30: Narsingi | E30: Nanakramguda | F30: =VLOOKUP(E30,A:B,2,0) -> Zone 3 Raidurg
D31: Madhapur | E31: madhapur | F31: =VLOOKUP(E31,A:B,2,0) -> Zone 4 Hi-tech City
D32: Gachibowli | E32: gachibowli | F32: =VLOOKUP(E32,A:B,2,0) -> Zone 4 Hi-tech City
D33: Hitech city | E33: Hitech-City | F33: =VLOOKUP(E33,A:B,2,0) -> Zone 4 Hi-tech City
D34: Kothaguda | E34: Hitech-City | F34: =VLOOKUP(E34,A:B,2,0) -> Zone 4 Hi-tech City
D35: Kukatpally | E35: kukatpally | F35: =VLOOKUP(E35,A:B,2,0) -> Zone 5 Kukatpally
D36: Miyapur | E36: miyapur | F36: =VLOOKUP(E36,A:B,2,0) -> Zone 5 Kukatpally
D37: Chandanagar | E37: miyapur | F37: =VLOOKUP(E37,A:B,2,0) -> Zone 5 Kukatpally
D38: serlingampally | E38: hafeezpet | F38: =VLOOKUP(E38,A:B,2,0) -> Zone 5 Kukatpally
D39: Hafeezpet | E39: kukatpally | F39: =VLOOKUP(E39,A:B,2,0) -> Zone 5 Kukatpally
D40: KPHB | E40: miyapur | F40: =VLOOKUP(E40,A:B,2,0) -> Zone 5 Kukatpally
D41: Ameenapur | E41: miyapur | F41: =VLOOKUP(E41,A:B,2,0) -> Zone 5 Kukatpally
... D58: Yellareddy guda | E58: ameerpet | F58: =VLOOKUP(E58,A:B,2,0) -> Zone 6 Ameerpet

Sheet Pivot Table 25
B403: COUNTA of Address
A404: Grand Total | B404: 548
A405: not mentioned | B405: 34
A406: Ragiv gandhi nagar,langarhouz,hyderabad,telangana | B406: 14
A407: H.no:2-106/9/1,krisat colony,phase-4,gangaram chandanagar | B407: 9
A408: plot no.103 KSR, Enclave beside ayyappa swamy temple,chandanagar | B408: 7
A409: will- Mallipaathi po -malipathi, 210-C Sri Ram Kondapur | B409: 6
A410: 138/1,flat no 45 sham apt,secunderabad 138/1,flat no 45 shama apt sindi colony pg road | B410: 5
A411: h.no:8-3-229/D175,ventatagiri,yousufguda,hyd,telangana | B411: 5
A412: High tension,line rd,raghavendra colony,kondapur,telangana | B412: 5
A413: plot no.13,sipa paradise,pragathi nagar | B413: 5
A414: plot no.410,raja reshwara nagar,kondapur,serlingampally | B414: 5
A415: sy no.38,39,40,khanmet village,serlingampally circle no.20,hyd | B415: 5
... A800: Yadagiri nagar rd,Jawahar nagar,yousfguda,khairthabad circle no.17,hyd | B800: 1
B801: 0

Sheet Pivot Table 24
B477: COUNTA of Restaurant Name
A478: Grand Total | B478: 500
A479: Aroma Cafe | B479: 4
A480: Sreeja's home foods | B480: 4
A481: D and D caterers | B481: 3
A482: Dosarani Chethivanta | B482: 3
A483: New Chanti mess | B483: 3
A484: P.K Food court | B484: 3
A485: Sangam family dhaba | B485: 3
A486: Sri shakambhari Restaurant | B486: 3
A487: Tealogy cafe | B487: 3
A488: The good sparrow | B488: 3
A489: Chai kaburlu | B489: 2
... A941: Zyras Biryani house | B941: 1
B942: 0

Sheet Pivot Table 22

Sheet Pivot Table 23
B1390: COUNTA of Restaurant name
B1391: 0
A1392: 7 sauces | B1392: 1
A1393: A1 bawarchi | B1393: 1
A1394: A1 hotel | B1394: 1
A1395: Aha Bhojanam | B1395: 1
A1396: Aha Dakshin | B1396: 1
A1397: Al saba Restaurant | B1397: 1
A1398: Anandobhrahma | B1398: 1
A1399: Andhra bhavan | B1399: 1
A1400: AR Raghavendra tiffins and meals | B1400: 1
A1401: Audio Cup | B1401: 1
A1402: B.Bichareddy Pure ghee sweets & cookies | B1402: 1
A1403: Bakers harvest | B1403: 1
... A2776: Grand Total | B2776: 1506

Sheet Pivot Table 21

Sheet total
E2: Date | F2: COUNTA of Date
F3: 0
E4: 46054 | F4: 3
E5: 46055 | F5: 5
E6: 46056 | F6: 12
E7: 46057 | F7: 16
E8: 46058 | F8: 9
E9: 46059 | F9: 8
E10: 46060 | F10: 1
E11: 46062 | F11: 22
E12: 46063 | F12: 3
E13: 46064 | F13: 8
E14: 46065 | F14: 16
E15: 46066 | F15: 19
... E27: 46079 | F27: 15
E28: Grand Total | F28: 356
C33: Date | E33: 46054 | F33: 46055 | G33: 46056 | H33: 46057 | I33: 46058 | J33: 46059 | K33: 46060 | L33: 46062 | M33: 46063 | N33: 46064 | O33: 46065 | P33: 46066 | Q33: 46067 | R33: 46069 | S33: 46070 | T33: 46071 | U33: 46072 | V33: 46073 | W33: 46074 | X33: 46075 | Y33: 46076 | Z33: 46077 | AA33: 46078 | AB33: 46079 | AC33: Grand Total
C34: COUNTA of Date | D34: 0 | E34: 3 | F34: 5 | G34: 12 | H34: 16 | I34: 9 | J34: 8 | K34: 1 | L34: 22 | M34: 3 | N34: 8 | O34: 16 | P34: 19 | Q34: 4 | R34: 24 | S34: 15 | T34: 25 | U34: 27 | V34: 17 | W34: 9 | X34: 1 | Y34: 22 | Z34: 19 | AA34: 56 | AB34: 15 | AC34: 356

Sheet Pivot Table 16
B45: Region | C45: COUNTA of Region | E45: Zone 4 Hi-tech City | F45: gachibowli | G45: 18
C46: 0 | F46: Hitech-City | G46: 12
B47: Borabanda | C47: 1 | F47: madhapur | G47: 35
B48: Hyderabad | C48: 1 | E48: Zone 4 Hi-tech City Total | G48: 65
A49: Total | C49: 2 | E49: Zone 5 Kukatpally | F49: hafeezpet | G49: 2
A50: Zone 1 Mehdipatnam | B50: banjara hills | C50: 2 | F50: Kondapur | G50: 20
B51: Hyderabad | C51: 1 | F51: KPHP | G51: 3
B52: Khairathabad | C52: 10 | F52: kukatpally | G52: 48
B53: Langar Houz | C53: 16 | F53: miyapur | G53: 22
B54: masab tank | C54: 6 | F54: panjagutta | G54: 1
B55: mehdipatnam | C55: 35 | F55: Sherilingampally | G55: 8
A56: Zone 1 Mehdipatnam Total | C56: 70 | E56: Zone 5 Kukatpally Total | G56: 104
A57: Zone 2 Jubliee hils | B57: Jubliee hills | C57: 3 | E57: Zone 6 Ameerpet | F57: ameerpet | G57: 16
B58: Langar Houz | C58: 18 | F58: begumpet | G58: 9
B59: tolichowki | C59: 4 | F59: panjagutta | G59: 15
A60: Zone 2 Jubliee hils Total | C60: 25 | F60: yousufguda | G60: 23
A61: Zone 3 Raidurg | B61: manikonda | C61: 28 | E61: Zone 6 Ameerpet Total | G61: 63
B62: nanakramguda | C62: 9 | E62: #N/A | F62: Hyderabad | G62: 1
B63: shaikpet | C63: 3 | E63: #N/A Total | G63: 1
A64: Zone 3 Raidurg Total | C64: 40 | E64: Grand Total | G64: 370

Sheet Sheet13

Sheet Sheet11
A2: Zone | B2: Region | C2: COUNTA of Region | E2: Zone 4 Hi-tech City | F2: gachibowli | G2: 18
C3: 0 | F3: Hitech-City | G3: 12
B4: Borabanda | C4: 1 | F4: madhapur | G4: 35
B5: Hyderabad | C5: 1 | E5: Zone 4 Hi-tech City Total | G5: 65
A6: Total | C6: 2 | E6: Zone 5 Kukatpally | F6: hafeezpet | G6: 2
A7: Zone 1 Mehdipatnam | B7: banjara hills | C7: 2 | F7: Kondapur | G7: 20
B8: Hyderabad | C8: 1 | F8: KPHP | G8: 3
B9: Khairathabad | C9: 10 | F9: kukatpally | G9: 48
B10: Langar Houz | C10: 16 | F10: miyapur | G10: 22
B11: masab tank | C11: 6 | F11: panjagutta | G11: 1
B12: mehdipatnam | C12: 35 | F12: Sherilingampally | G12: 8
A13: Zone 1 Mehdipatnam Total | C13: 70 | E13: Zone 5 Kukatpally Total | G13: 104
A14: Zone 2 Jubliee hils | B14: Jubliee hills | C14: 3 | E14: Zone 6 Ameerpet | F14: ameerpet | G14: 16
B15: Langar Houz | C15: 18 | F15: begumpet | G15: 9
B16: tolichowki | C16: 4 | F16: panjagutta | G16: 15
A17: Zone 2 Jubliee hils Total | C17: 25 | F17: yousufguda | G17: 23
A18: Zone 3 Raidurg | B18: manikonda | C18: 28 | E18: Zone 6 Ameerpet Total | G18: 63
B19: nanakramguda | C19: 9 | E19: #N/A | F19: Hyderabad | G19: 1
B20: shaikpet | C20: 3 | E20: #N/A Total | G20: 1
A21: Zone 3 Raidurg Total | C21: 40 | E21: Grand Total | G21: 370

Sheet Pivot Table 13

Sheet Sheet10
A1: RM/KAM | C1: 46076 | G1: KAM | H1: RM/ KAM Name | I1: Onboarding done on 23rd | J1: Contract received | K1: Pending Contracts
B2: 0 | G2: manasa.chigurupati@capsdelivery.com | H2: chanakya.inugala@capsdelivery.com | I2: 0 | J2: =VLOOKUP(H2,A:C,3,0) | K2: =I2-J2 -> 0
B3: 0 | G3: manisha.kumari@capsdelivery.com | H3: parthive.maganti@capsdelivery.com | I3: 12 | J3: =VLOOKUP(H3,A:C,3,0) -> 12 | K3: =I3-J3 -> 0
A4: akhila.narra@capsdelivery.com | G4: manisha.kumari@capsdelivery.com | H4: sumadhur.mummadi@capsdelivery.com | I4: 2 | J4: =VLOOKUP(H4,A:C,3,0) -> 1 | K4: =I4-J4 -> 1
A5: ankitha.baske@capsdelivery.com | C5: 2 | G5: anisha.poddar@capsdelivery.com | H5: greeshma.vanneldas@capsdelivery.com | J5: =VLOOKUP(H5,A:C,3,0) | K5: =I5-J5 -> 0
A6: chanakya.inugala@capsdelivery.com | G6: akhila.narra@capsdelivery.com | H6: madhumitha.sonnakula@capsdelivery.com | I6: 0 | J6: =VLOOKUP(H6,A:C,3,0) | K6: =I6-J6 -> 0
A7: greeshma.vanneldas@capsdelivery.com | G7: akhila.narra@capsdelivery.com | H7: akhila.narra@capsdelivery.com | I7: 0 | J7: =VLOOKUP(H7,A:C,3,0) | K7: =I7-J7 -> 0
A8: madhumitha.sonnakula@capsdelivery.com | G8: manisha.kumari@capsdelivery.com | H8: anisha.poddar@capsdelivery.com | J8: 0 | K8: =I8-J8 -> 0
A9: manasa.chigurupati@capsdelivery.com | G9: manisha.kumari@capsdelivery.com | H9: Srivani.reddy@capsdelivery.com | I9: 2 | J9: =VLOOKUP(H9,A:C,3,0) | K9: =I9-J9 -> 2
A10: moin.khan@capsdelivery.com | G10: manasa.chigurupati@capsdelivery.com | H10: manasa.chigurupati@capsdelivery.com | I10: 0 | J10: =VLOOKUP(H10,A:C,3,0) | K10: =I10-J10 -> 0
A11: nitya.akshara@capsdelivery.com | C11: 3 | G11: manasa.chigurupati@capsdelivery.com | H11: ankitha.baske@capsdelivery.com | I11: 2 | J11: =VLOOKUP(H11,A:C,3,0) -> 2 | K11: =I11-J11 -> 0
A12: parthive.maganti@capsdelivery.com | C12: 12 | G12: akhila.narra@capsdelivery.com | H12: moin.khan@capsdelivery.com | I12: 2 | J12: =VLOOKUP(H12,A:C,3,0) | K12: =I12-J12 -> 2
A13: Srivani.reddy@capsdelivery.com | G13: amit.kaler@capsdelivery.com | H13: manisha.kumari@capsdelivery.com | I13: 0 | J13: 0 | K13: =I13-J13 -> 0
A14: sumadhur.mummadi@capsdelivery.com | C14: 1 | G14: manasa.chigurupati@capsdelivery.com | H14: nitya.akshara@capsdelivery.com | I14: 3 | J14: =VLOOKUP(H14,A:C,3,0) -> 3 | K14: =I14-J14 -> 0
A15: Grand Total | B15: 0 | C15: 18 | I15: =sUM(I3:I14) -> 23 | J15: =sUM(J3:J14) -> 18 | K15: =sUM(K3:K14) -> 5

Sheet Pivot Table 11

Sheet Detail12-Zone 4 Hi-tech City-Hi
A1: Date | B1: Restaurant Name | C1: RM/KAM | D1: Type of Ownership | E1: Address | F1: Signing Authority | G1: Pincode | H1: Locality | I1: Region | J1: Zone
A2: 46072 | B2: Punjabi Chaska | C2: greeshma.vanneldas@capsdelivery.com | D2: Proprietorship | E2: h.no 1-90/c/8, inside sri krishna food court, hudo techno enclave, opp LP tower, vittalrao nagar, hitech city | F2: Angad Singh | G2: 500081 | H2: Hitech city | I2: Hitech-City | J2: Zone 4 Hi-tech City
A3: 46073 | B3: Mickey's Tiffin | C3: parthive.maganti@capsdelivery.com | D3: Partnership | E3: Plot No. 279 27/a, khanamet village, Hi-tech city. Seringampally near SSR on the way drive in , Seringampally | F3: not mentioned | G3: 500081 | H3: HItech City | I3: Hitech-City | J3: Zone 4 Hi-tech City
A4: 46073 | B4: Sravanti Biryani | C4: parthive.maganti@capsdelivery.com | D4: Proprietorship | E4: HNO No. 2-41/11/10/11, G3, Sri sai shanti residency prashanth nagar, kothaguda circle | F4: Manoj Reddy | G4: 500084 | H4: Kothaguda | I4: Hitech-City | J4: Zone 4 Hi-tech City
A5: 46073 | B5: Sravanti Fast Food | C5: parthive.maganti@capsdelivery.com | D5: Proprietorship | E5: Door No, 2-41/11/10/, G3, Sri sai residancy prashanth nagar, kothaguda circle | F5: Manoj Reddy | G5: 500084 | H5: Kothaguda | I5: Hitech-City | J5: Zone 4 Hi-tech City
A6: 46073 | B6: Sravanti Mess | C6: parthive.maganti@capsdelivery.com | D6: Proprietorship | E6: Door No, 2-41/11/10/, G3, Sri sai residancy prashanth nagar, kothaguda | F6: Manoj Reddy | G6: 500084 | H6: Kothaguda | I6: Hitech-City | J6: Zone 4 Hi-tech City
A7: 46073 | B7: Sravanti Tiffins | C7: parthive.maganti@capsdelivery.com | D7: Proprietorship | E7: Door No, 2-41/11/10/, G3, Sri sai residancy prashanth nagar, kothaguda circle | F7: Manoj Reddy | G7: 500084 | H7: Kothaguda | I7: Hitech-City | J7: Zone 4 Hi-tech City
A8: 46074 | B8: Snacking Cafe Private limited | C8: parthive.maganti@capsdelivery.com | D8: Proprietorship | E8: RHS-R6-UE, Near Nift college, Hitech city metro chanda nagar Circle No 21, HYD | F8: not mentioned | G8: 500081 | H8: Hitech City | I8: Hitech-City | J8: Zone 4 Hi-tech City
A9: 46074 | B9: Sravanam 4am Biryani | C9: parthive.maganti@capsdelivery.com | D9: Proprietorship | E9: Plot No. 35, khampet , Hitech city, Chandanagar circle No. 21, Hyderbad | F9: not mentioned | G9: 500019 | H9: HItech City | I9: Hitech-City | J9: Zone 4 Hi-tech City
A10: 46074 | B10: Sravanam 4am kuska | C10: parthive.maganti@capsdelivery.com | D10: partnership | E10: plot no.35,khanmet,chandanagar circle no.21 | F10: not mentioned | G10: 500019 | H10: Hitech City | I10: Hitech-City | J10: Zone 4 Hi-tech City
A11: 46077 | B11: Avacado on wheels | C11: parthive.maganti@capsdelivery.com | D11: proprietorship | E11: shop no.1,patrika nagar,SLR guest house,selingampally circle no.20,hyd | F11: not mentioned | G11: 500081 | H11: Hitech City | I11: Hitech-City | J11: Zone 4 Hi-tech City
A12: 46077 | B12: Charcoal sahwarma | C12: parthive.maganti@capsdelivery.com | D12: Proprietorship | E12: shop no.1,patrika nagar,SLR guest house,selingampally circle no.20,hyd | F12: not mentioned | G12: 500081 | H12: Hitech City | I12: Hitech-City | J12: Zone 4 Hi-tech City
A13: 46077 | B13: Oh My Momo's | C13: parthive.maganti@capsdelivery.com | D13: proprietorship | E13: shop no.1,patrika nagar,SLR guest house,selingampally circle no.20,hyd | F13: not mentioned | G13: 500081 | H13: Hitech City | I13: Hitech-City | J13: Zone 4 Hi-tech City
... A20: 46091 | B20: Sri Venkateshwara Hospitality | C20: parthive.maganti@capsdelivery.com | D20: proprietorship | E20: 2-91/14/8,whitefeilds,kondapur,hitech city,serlingampally circle no.20,telangana | F20: not mentioned | G20: 500084 | H20: Hitech City | I20: Hitech-City | J20: Zone 4 Hi-tech City

Sheet Visits

Sheet Agreement Collected

Sheet Detail9-10022026
A1: Date | B1: Name of Restaurant | C1: RM/ KAM | D1: Type of enity | E1: Address | F1: Authorized signatory | G1: locality | H1: Zone | I1: Service Fee in % | J1: Service Fees Bucket | K1: Payment Gateway Charges | L1: Long Distance Charges | M1: legal entity name | N1: legal entity address | O1: contact person | P1: phone number | Q1: Email | R1: Benficiary name | S1: Bank name | T1: Account number | U1: IFSC code | V1: Account type | W1: FSSAI | X1: GST | Y1: PAN | Z1: CHEQUE | AA1: MENU | AB1: LABOUR LICENCE | AC1: Drive Link | AD1: Map Co-ordinates | AE1: Column 3 | AF1: Column 4 | AG1: Column 5 | AH1: Column 6 | AI1: Column 7 | AJ1: Column 8 | AK1: Column 9 | AL1: Column 10 | AM1: Column 11 | AN1: Column 12 | AO1: Column 13 | AP1: Column 14
A2: 46063 | B2: Sri sai and co. | C2: nitya.akshara@capsdelivery.com | D2: Partnership | E2: sai gayathri towers finacial district Nanakramguda,Telangana 500032 | G2: Financial District | H2: Zone 3 Raidurg | I2: 0.15 | J2: <17% | K2: 0.018 | M2: Sri sai and co. | N2: sai gayathri towers finacial district Nanakramguda,Telangana 500032 | O2: Venudhar reddy malakapalli | P2: 9100112336 | Q2: venudharr@gmail.com | R2: Sri sai and co. | S2: Hdfc bank | T2: 50200037904604 | U2: HDFC0004299 | V2: Current account
A3: 46063 | B3: Sri sai and co. | C3: nitya.akshara@capsdelivery.com | D3: Partnership | E3: sai gayathri towers finacial district Nanakramguda,Telangana 500033 | G3: Nanakramguda | H3: Zone 3 Raidurg | I3: 0.15 | J3: <17% | K3: 0.018 | M3: Sri sai and co. | N3: sai gayathri towers finacial district Nanakramguda,Telangana 500033 | O3: Venudhar reddy malakapalli | P3: 9100112336 | Q3: venudharr@gmail.com | R3: Sri sai and co. | S3: State Bank of India | T3: 9748601141 | U3: SBIN0018047 | V3: Current account
A4: 46063 | B4: The Emperor | C4: nitya.akshara@capsdelivery.com | D4: Proprietorship | E4: 10-4-3,afia plaxa,near NMDC-vijay nagar colony,masab tank,hyd,telangana | F4: Not mentioned | G4: Masab Tank | H4: Zone 1 Mehdipatnam | I4: 0.2 | J4: 20%+ | K4: 0.018 | M4: Not mentioned | N4: Not mentioned | O4: Not mentioned | P4: Not mentioned | Q4: Not mentioned | R4: Not mentioned | S4: Not mentioned | T4: Not mentioned | U4: Not mentioned | V4: Not mentioned

Sheet Detail8-05022026
A1: Date | B1: Name of Restaurant | C1: RM/ KAM | D1: Type of enity | E1: Address | F1: Authorized signatory | G1: locality | H1: Zone | I1: Service Fee in % | J1: Service Fees Bucket | K1: Payment Gateway Charges | L1: Long Distance Charges | M1: legal entity name | N1: legal entity address | O1: contact person | P1: phone number | Q1: Email | R1: Benficiary name | S1: Bank name | T1: Account number | U1: IFSC code | V1: Account type | W1: FSSAI | X1: GST | Y1: PAN | Z1: CHEQUE | AA1: MENU | AB1: LABOUR LICENCE | AC1: Drive Link | AD1: Map Co-ordinates | AE1: Column 3 | AF1: Column 4 | AG1: Column 5 | AH1: Column 6 | AI1: Column 7 | AJ1: Column 8 | AK1: Column 9 | AL1: Column 10 | AM1: Column 11 | AN1: Column 12 | AO1: Column 13 | AP1: Column 14
A2: 46058 | B2: Ahladha kitchen | C2: greeshma.vanneldas@capsdelivery.com | D2: Partnership | E2: plot no 68,shop no 5,Ayyappa society main road,madhapur,serlingampally circle no20 hyd 500081 | F2: Penubua kula sai | G2: Madhapur | H2: Zone 4 Hi-tech City | I2: 0.2 | J2: 20%+ | K2: 0.018 | M2: Ahladha kitchen | N2: plot no-68 shop no-5 ayyappa socity circle-20 hyd,500081 | O2: naveen | P2: 9849975158 | Q2: ahladha2025@gmail.com | R2: Ahladha kitchen | S2: Induslnd Bank | T2: 259849975158 | U2: INDB0001805 | V2: not mentioned
A3: 46058 | B3: Flavours of biryani cafe | C3: madhumitha.sonnakula@capsdelivery.com | D3: Proprietorship | E3: 6-1-964,shop no 2, khairthabad circel, no.17,500004 | F3: Mangalarapu sai teja | G3: khairthabad | H3: Zone 1 Mehdipatnam | I3: 0.22 | J3: 20%+ | K3: 0.018 | M3: Mangalarapu sai teja | N3: 6-1-964,shop no 2, khairthabad circel, no.17,hyderabad telangana500004 | O3: Mangalarapu sai teja | P3: 9642897117 | Q3: flavourbiryanicafe@gmail.com | R3: M. sai teja | S3: Indian bank | T3: 6414081002 | U3: IDIB000k284 | V3: Saving account
A4: 46058 | B4: Food 4 U (Rahath) | C4: madhumitha.sonnakula@capsdelivery.com | D4: Proprietorship | E4: 12-1-486/b/4 krishan nagar, 500006 | F4: Mohd Arshad | G4: Asif nagar | H4: Zone 1 Mehdipatnam | I4: 0.2 | J4: 20%+ | K4: 0.018 | M4: Mohd Arshad | N4: 12-1-486/b/4 krishan nagar, 500006 | O4: Mohd Arshad | P4: 8686561072 | Q4: prinzzarshad@gamil.com | R4: Mohammed Arshad | S4: Airtel Bank | T4: 8686561072 | U4: AIRP0000001 | V4: Current account
A5: 46058 | B5: hunan chinese cisine | C5: moin.khan@capsdelivery.com | D5: Proprietorship | E5: jap hind gandhi road near ayyappa society hyd telangana 500081 | F5: Rai shankar | G5: Madhapur | H5: Zone 4 Hi-tech City | I5: 0.2 | J5: 20%+ | K5: 0.018 | M5: not mentioned | N5: not mentioned | O5: ravi | P5: 7396735758 | Q5: thehunanspice@gamil.com | R5: Hunan chinese cuisine | S5: not mentioned | T5: 1548257253 | U5: KKBK0007466 | V5: not mentioned
A6: 46058 | B6: krishna teeram | C6: greeshma.vanneldas@capsdelivery.com | D6: Partnership | E6: Ground flooor, plot no 84 sy no.11 swamy apyyappa housing society khanamet,hyd,500081 | F6: Krishna teeram | G6: Madhapur | H6: Zone 4 Hi-tech City | I6: 0.18 | J6: <20% | K6: 0.018 | M6: Krishna teeram | N6: Plot no-84,sy no 11 swamy ayyappa housing society khanamet, hyd 500081 | O6: suresh | P6: 9985609966 | Q6: krishnateeram2025@gmail.com | R6: not mentioned | S6: not mentioned | T6: not mentioned | U6: not mentioned | V6: not mentioned
A7: 46058 | B7: lucky Multicusine Restaurant | C7: moin.khan@capsdelivery.com | D7: Proprietorship | E7: sy no. 54,58,59 plot no 1,part gb guttala begumpet madhapur road | F7: Md mansoor | G7: Madhapur | H7: Zone 4 Hi-tech City | I7: 0.15 | J7: <17% | K7: 0.018 | M7: lucky Multicusine Restaurant | N7: sy no. 54,58,59 plot no 1,part gb guttala begumpet madhapur road | O7: Md mansoor | P7: 9676213874 | Q7: y96822534@gamil.com | R7: Lucky multi cuisine Restaurant | S7: Hdfc bank | T7: 50200064899781 | U7: HDFC0004277 | V7: Current account
A8: 46058 | B8: rahat Restaurant | C8: manasa.chigurupati@capsdelivery.com | D8: Proprietorship | E8: 12-1-486/b/4/1,kishan nagar, tappachabutra road,hyd 500006 | F8: Mohammed feroz | G8: Asif nagar | H8: Zone 1 Mehdipatnam | I8: 0.2 | J8: 20%+ | K8: 0.018 | M8: Rahat Restaurant | N8: 12-1-486/b/4/1,kishan nagar, tappachabutra road,hyd 500006 | O8: mohammed feroz | P8: 7097949648 | Q8: ak.8977.ak@gmail.com | R8: mohammed froz | S8: Induslnd Bank | T8: 157097949648 | U8: INDB0001052 | V8: Saving account
A9: 46058 | B9: Tahari house (rahaat fast food) | C9: madhumitha.sonnakula@capsdelivery.com | D9: Proprietorship | E9: 12-1-486/b/2/5 krishan nagar,Tappachabuta | F9: Mohanmed feroz | G9: asif nagar | H9: Zone 1 Mehdipatnam | I9: 0.2 | J9: 20%+ | K9: 0.018 | M9: Tahari house | N9: 12-1-486/b/2/5 krishan nagar | O9: Mohanmed feroz | P9: 7097949648 | Q9: ak.8977.ak@gmail.com | R9: Mohanmed feroz | S9: Induslnd Bank | T9: 157097949648 | U9: INDB0001052 | V9: Saving account
A10: 46058 | B10: vijay durga pre veg tiffin and meals | C10: parthive.maganti@capsdelivery.com | D10: Proprietorship | E10: H.no:1-90/7/b/173,plot no.5,madhapur,selingampally circle no.20,hyd, telangana,500081 | F10: karempudi vijava durga | G10: Madhapur | H10: Zone 4 Hi-tech City | I10: 0.17 | J10: <20% | K10: 0.018 | M10: not mentioned | N10: H.no:1-90/7/b/173,plot no.5,madhapur,selingampally circle no.20,hyd, telangana,500081 | O10: karempudi vijava durga | P10: 6303274660 | Q10: vijayvijju8096@gmail.com | R10: kolli tirunala ravindra | S10: kotak mahindra bank | T10: 3049366762 | U10: KKBK0007466 | V10: Saving account
B15: Bihari Dhaba | C15: chanakya

Sheet Detail7-13022026
A1: Date | B1: Name of Restaurant | C1: RM/ KAM | D1: Type of enity | E1: Address | F1: Authorized signatory | G1: locality | H1: Zone | I1: Service Fee in % | J1: Service Fees Bucket | K1: Payment Gateway Charges | L1: Long Distance Charges | M1: legal entity name | N1: legal entity address | O1: contact person | P1: phone number | Q1: Email | R1: Benficiary name | S1: Bank name | T1: Account number | U1: IFSC code | V1: Account type | W1: FSSAI | X1: GST | Y1: PAN | Z1: CHEQUE | AA1: MENU | AB1: LABOUR LICENCE | AC1: Drive Link | AD1: Map Co-ordinates | AE1: Column 3 | AF1: Column 4 | AG1: Column 5 | AH1: Column 6 | AI1: Column 7 | AJ1: Column 8 | AK1: Column 9 | AL1: Column 10 | AM1: Column 11 | AN1: Column 12 | AO1: Column 13 | AP1: Column 14
A2: 46066 | B2: Al shawrma bites | C2: nitya.akshara@capsdelivery.com | D2: Partnership | E2: Manikonda,nanakramguda,selingampally circle no.20,hyd,telangana | F2: not mentioned | G2: Manikonda | H2: Zone 3 Raidurg | I2: 0.2 | J2: 20%+ | K2: 0.018 | M2: Al shawrma bites | N2: plot no.1 road no.27,alkapur twp,manikonda | O2: Syed ali | P2: 7995150934 | Q2: alshawrmabites@gamil.com | R2: Syed ali | S2: Yes Bank | T2: ;047761900002984 | U2: YES80000477 | V2: Current account
A3: 46066 | B3: Amogha cafe and Restaurant | C3: ankitha.baske@capsdelivery.com | D3: Partnership | E3: H.no:2-23-310/83C ground floor,Addagutta society,pragthi road kukatpally,hyd,500085 | F3: Prasad | G3: kukatpally | H3: Zone 5 Kukatpally | I3: 0.18 | J3: <20% | K3: 0.018 | M3: Amogha cafe and Restaurant | N3: Kukatpally | O3: Prasad | P3: 8317636360 | Q3: amoghcafe1@gmail.com | R3: not mentioned | S3: not mentioned | T3: not mentioned | U3: not mentioned | V3: not mentioned
A4: 46066 | B4: Bamma Tiffins | C4: chanakya.inugala@capsdelivery.com | D4: Proprietorship | E4: 7-18-25/27/101,plot no.25,26,27,Alkapur,Ranga Reddy,Telangana,500089 | F4: Naveen | G4: Madhapur | H4: Zone 4 Hi-tech City | I4: 0.19 | J4: <20% | K4: 0.018 | M4: Naveen | N4: H.no:7-18-25/27/101, plot no.25,26,27,alkapur | O4: Naveen reddy | P4: 9885215007 | Q4: not mentioned | R4: not mentioned | S4: not mentioned | T4: not mentioned | U4: not mentioned | V4: not mentioned
A5: 46066 | B5: Bulliabbai kodi palau | C5: parthive.maganti@capsdelivery.com | D5: Partnership | E5: kavya deluxe apartment,lata enclave,madhuranagar,hyderabad,500073 | F5: not mentioned | G5: madhura nagar | H5: Zone 6 Ameerpet | I5: 0.17 | J5: <20% | K5: 0.018 | M5: Bulliabbai kodi palau | N5: shop no.8-3-22/16A and 16/B,madhura nagar | O5: Venkata reddy | P5: 9493989362 | Q5: bulliabbhai@gmail.com | R5: Bulliabbai kodi palau | S5: Indian bank | T5: 8150356795 | U5: IDIB000H601 | V5: Current account
A6: 46066 | B6: Delhi Muradaladi Biryani | C6: nitya.akshara@capsdelivery.com | D6: Proprietorship | E6: plot no.242,bayuth colony,pippalaguda,manikonda,Rajendra nagar,rangareddy | F6: not mentioned | G6: Manikonda | H6: Zone 3 Raidurg | I6: 0.2 | J6: 20%+ | K6: 0.018 | M6: Delhi Muradaladi Biryani | N6: plot no.242,bayuth colony,pippalaguda,manikonda` | O6: Alam | P6: 9911911949 | Q6: royalgaming51945@gmail.com | R6: Imtiaz alam | S6: Bank of Borada | T6: 15710100039717 | U6: BARBOSUARXX | V6: Saving account
A7: 46066 | B7: Hanuman Juice and salad | C7: sumadhur.mummadi@capsdelivery.com | D7: Proprietorship | E7: H.no:B/22,23,24,vengal rao nagar,khairtabad circle no.17,hyd.telangana,500038 | F7: D.Venkata ramana | G7: khairthabad | H7: Zone 1 Mehdipatnam | I7: 0.2 | J7: 20%+ | K7: 0.018 | M7: Hanuman Juice and salad | N7: H.no:B/22,23,24,vengal rao nagar,khairtabad circle no.17,hyd.telangana,500038 | O7: Venkata ramana | P7: 9885552731 | Q7: hjjuicesalad@gmail.com | R7: Hanuman Juice and salad | S7: Indian Overseas Bank | T7: 169602000000386 | U7: IOBA0001696 | V7: Current account | W7: Yes | X7: No | Y7: Yes | Z7: Yes | AA7: No | AB7: No | AC7: https://drive.google.com/drive/folders/1iGkq5x63L9MzLTFtbpSSdoRb2Z16w-QN | AD7: 17.440225,78.439709
A8: 46066 | B8: Hitech Bawarchi food zone | C8: greeshma.vanneldas@capsdelivery.com | D8: Proprietorship | E8: MIG-154,gachibowli,selingampally circle-20,hyderabad,telangana,500081 | F8: Paper missing | G8: Gachibowli | H8: Zone 3 Raidurg | I8: 0.12 | J8: <15% | K8: 0.018 | M8: Hitech Bawarchi food zone | N8: MIG-154,gachibowli,selingampally circle-20,hyderabad,telangana,500081 | O8: Mohammed Ishaq | P8: 8247569561 | Q8: ishaq.1963@yahoo.com | R8: Mohammed ishaq | S8: Canara Bank | T8: ;0798101023882 | U8: CNRB0013051 | V8: Saving account
A9: 46066 | B9: Hitech Biryani house | C9: greeshma.vanneldas@capsdelivery.com | D9: Proprietorship | E9: MIG-154,gachibowli,selingampally circle-20,hyderabad,telangana,500081 | F9: Mohammed Ishaq | G9: Gachibowli | H9: Zone 3 Raidurg | I9: 0.12 | J9: <15% | K9: 0.018 | M9: Mohammed Ishaq | N9: MIG-154,gachibowli,selingampally circle-20,hyderabad,telangana,500081 | O9: Mohammed Ishaq | P9: 8247569561 | Q9: ishaq.1963@yahoo.com | R9: Mohammed ishaq | S9: Canara Bank | T9: ;0798101023882 | U9: CNRB0013051 | V9: Saving account
A10: 46066 | B10: Kaaram the Authntic telangana spice kitchne | C10: greeshma.vanneldas@capsdelivery.com | D10: Proprietorship | E10: plot no.64,opp HP petrol pump,peeramchervu,Gandhamguda,Bandlaguda jagir,hyd,500086 | F10: Srikanth | G10: Banglaguda | H10: Zone 1 Mehdipatnam | I10: 25% including GST | J10: 20%+ | K10: 0.018 | M10: Kaaram the Authntic telangana spice kitchne | N10: plot no.64,opp HP petrol pump,peeramchervu,Gandhamguda,Bandlaguda jagir,hyd,500086 | O10: Srikanth | P10: 9912699903 | Q10: kaaramthspicekitchen@gmail.com | R10: not mentioned | S10: not mentioned | T10: not mentioned | U10: not mentioned | V10: Current account
A11: 46066 | B11: Mother's kitchen | C11: manasa.chigurupati@capsdelivery.com | D11: Proprietorship | E11: H.no:1-59/8/2, nandi co-operative society,miyapur,serlingampally ranga reddy district hyd 500049 | F11: Velagapudi meghana | G11: Miyapur | H11: Zone 5 Kukatpally | I11: 0.21 | J11: 20%+ | K11: 0.018 | M11: Mother's kitchen | N11: H.no:1-59/8/2, nandi co-operative society,miyapur,serlingampally ranga reddy district hyd 500049 | O11: Ravi Kumar | P11: 9177960195 | Q11: velagapudi6@gmail.com | R11: V.Meghana | S11: Hdfc bank | T11: 50100015071650 | U11: HDFC0001021 | V11: Saving account
A12: 46066 | B12: New Udupi sri krishna grand | C12: madhumitha.sonnakula@capsdelivery.com | D12: Proprietorship | E12: H.no:4-28 plot no.28,dwauak nagar colony,banglaguda jagir,rajendra nagar,500086 | F12: Ravikanth Rao | G12: Hyderabad | H12: Zone 1 Mehdipatnam | I12: 25% including GST | J12: 20%+ | K12: 0.018 | M12: New Udupi sri krishna grand | N12: H.no:4-28 plot no.28,dwauak nagar colony,banglaguda jagir,rajendra nagar,500086 | O12: Nallari Ravi | P12: 9490840633 | Q12: ravikanthnalari@gmail.com | R12: Nallari Ravikanth rao | S12: State Bank of India | T12: 62092826288 | U12: SBIN0020121 | V12: Saving account | W12: Yes | X12: No | Y12: Yes | Z12: No | AA12: No | AB12: No | AC12: https://drive.google.com/drive/folders/1q5m_oIPtx_q6EBqzQVHbpbGSahH2dFcx
A13: 46066 | B13: Sri Aadhya Delicious | C13: ankitha.baske@capsdelivery.com | D13: Proprietorship | E13: plot no.82/c road no.3,shutter no.1,Addaguta society,kukatpally,500072,hyd | F13: Manikanta Reddy | G13: kukatpally | H13: Zone 5 Kukatpally | I13: 0.22 | J13: 20%+ | K13: 0.018 | M13: Sri Aadhya Delicious | N13: Kukatpally | O13: Manikanta Reddy | P13: 83339336696 | Q13: saimanikantareddy8172@gmail.com | R13: Peram sai manikanta reddy | S13: Hdfc bank | T13: 50100504584589 | U13: HDFC0001624 | V13: Saving account
A14: 46066 | B14: Sri Bhimanaram Thali/Tangella Ravali | C14: sumadhur.mummadi@capsdelivery.com | D14: Proprietorship | E14: 51/b vengal rao nagar,hyd,yousufguda circel no.19,hyd,telangana,500045 | F14: T.Ravali | G14: SR Nagar | H14: Zone 6 Ameerpet | I14: 0.2 | J14: 20%+ | K14: 0.018 | M14: Sri Bhimanaram Thali/Tangella Ravali | N14: 51/b vengal rao nagar,hyd,yousufguda circel no.19,hyd,telangana,500045 | O14: Satish | P14: 7066346634 | Q14: sribhimavaramthali@gmail.com | R14: Sri Bhimanaram Thali/Tangella Ravali | S14: Equitas small business bank | T14: 20003005621 | U14: ESFB0005004 | V14: Current account | W14: Yes | X14: No | Y14: Yes | Z14: Yes | AA14: No | AB14: Yes | AC14: https://drive.google.com/drive/folders/14gLod5g9ejIgDgoScB7Vcn_7rb662Fqr | AD14: 17.441117,78.439259
A15: 46066 | B15: SS.Bawarchi | C15: moin.khan@capsdelivery.com | D15: Proprietorship | E15: Gandiprt no.75,76,77,dwauaka nagar main road,500086 | F15: Prashanth Singh | G15: Hyderabad | H15: Zone 3 Raidurg | I15: 0.22 | J15: 20%+ | K15: 0.018 | M15: SS.Bawarchi | N15: plot no.75,76,77,dwauaka nagar | O15: Prashanth Singh | P15: 9032000555 | Q15: prashanthhaakur6@gmail.com | R15: Thakur Prasanth singh | S15: ICICI Bank | T15: 393101500870 | U15: not mentioned | V15: Saving account | W15: Yes | X15: No | Y15: Yes | Z15: Yes | AA15: No | AB15: No
A16: 46066 | B16: Vindhu maharaj | C16: manasa.chigurupati@capsdelivery.com | D16: Proprietorship | E16: h.no:1-59/8/2, nandi co-operative society,miyapur,serlingampally ranga reddy district hyd 500049 | F16: V.Ravi Kumar | G16: Miyapur | H16: Zone 5 Kukatpally | I16: 0.21 | J16: 20%+ | K16: 0.018 | M16: Vindhu maharaj | N16: 1-59/8/2, nandi co-operative society,miyapur,serlingampally ranga reddy district hyd 500049 | O16: V.Ravi Kumar | P16: 9177960195 | Q16: velagapudi6@gmail.com | R16: V.Ravi Kumar | S16: State Bank of India | T16: 43288896643 | U16: SBIN0017744 | V16: Saving account
A17: 46066 | B17: Vinnin Cabin Cafe | C17: greeshma.vanneldas@capsdelivery.com | D17: Proprietorship | E17: H.no:2-27/7,vinayak nagar,gachibowlli,hyd,telagana,500032 | F17: Aripelli VInesh | G17: Gachibowli | H17: Zone 3 Raidurg | I17: 0.22 | J17: 20%+ | K17: 0.018 | M17: Vinnin Cabin Cafe | N17: H.no:2-27/7,vinayak nagar,gachibowlli,hyd,telagana,500032 | O17: Aripelli VInesh | P17: 8374628209 | Q17: avinesh363@gmail.com | R17: Aripelli VInesh | S17: UCO bank | T17: 21100110041208 | U17: UCBA0002110 | V17: Saving account
A18: 46066 | B18: Zeeshan Restaurant | C18: madhumitha.sonnakula@capsdelivery.com | D18: Proprietorship | E18: Rajendra nagar,hyderabad,1-224,kistmathpur,rajendra nagar | F18: Tokala mahendra reddy | G18: Hyderabad | H18: Zone 1 Mehdipatnam | I18: 0.23 | J18: 20%+ | K18: 0.018 | M18: Zeeshan Restaurant | N18: Hyderabad | O18: Mahendra reddy | P18: 9490701464 | Q18: humaenterprises1982@gmail.com | R18: Huma Enterprises | S18: Indian overseas Bank | T18: 157002000000978 | U18: IOBA0001571 | V18: Current account | W18: Yes | X18: Yes | Y18: Yes | Z18: Yes | AA18: No | AB18: No | AC18: https://drive.google.com/drive/folders/1U13VSi8AdHY1-kfcRQSIsNhtOFIIlglH
B20: Oye Punjabi | C20: chanakya
B21: Paruchuri foods | C21: Parthiv
B22: Vibe Yard | C22: Sandeep
A23: 1 | B23: Mother's Kitchen | C23: Manasa
B24: Shahi Nawabi Kitchen | C24: Parthiv | D24: 46074
A25: 1 | B25: Buli raju Kodi palav | C25: Parthiv
B26: Alkapuri Bawarchi
